Workbook
Name AsOfDate: Control!$B$5
Name MaterialThreshold: Control!$B$9
Name NegotiationsPerBuyer: Control!$B$7
Name QueueRowsShown: Control!$B$8
Name SourceFolder: Control!$B$6
Name WinFrom: Calc!$C$4
Name WinTo: Calc!$C$5
Name xlTop5: Calc!$C$46
Name xlWindowAll: Calc!$C$47

Sheet README
A1: LUMEN OPTICS MANUFACTURING -- PHOTONICS SPEND SCORECARD
A3: Lumen Optics Manufacturing is a fictional photonics manufacturer. Every figure in this workbook is synthetic, generated by the SQL scripts in the sql\ folder of this project. No confidential data is used and no claim is made about any production system.
A5: THE QUESTION THIS ANSWERS
A6: Our purchase prices are flat or falling and every variance report is green -- so why is material cost per ACCEPTED unit rising, and which supplier-part combinations should sourcing renegotiate first?
A8: WHY PRICE VARIANCE CANNOT ANSWER IT
A9: Photonic components follow learning curves: unit prices decline as volumes rise and processes mature. Purchase price variance compares what was paid against what was AGREED, so a supplier who renews flat every year scores zero variance forever while quietly keeping everything the curve was supposed to hand back. Erosion capture measures that gap; price variance is structurally blind to it.
A11: SHEETS
A12: Dashboard The scorecard, the erosion position and the category cut. Every number is a formula over the extract.
A13: Renegotiation Queue Which supplier-part pair to open first, with the action and the annual value. Filters re-rank the list.
A14: Vendor Scorecard Cost index against the best available on the same parts, plus quality, delivery and compliance.
A15: Validation Each headline figure computed twice -- once in SQL, once in Excel -- and reconciled.
A16: Control Every parameter the workbook obeys.
... A27: Erosion is measured from the FIRST OBSERVED PRICE, so it detects a failure to erode, not whether the opening price was fair. A part bought badly in 2023 and eroded perfectly since will look healthy here. Answering that needs a should-cost build-up from materials and process, which is a different exercise with different inputs.

Sheet Dashboard
A1: LUMEN OPTICS MANUFACTURING -- PHOTONICS SPEND SCORECARD
A2: ="Twelve months to "&TEXT(AsOfDate,"d mmmm yyyy")&" | Fictional company, synthetic data, no production system." -> Twelve months to 31 December 2025 | Fictional company, synthetic data, no production system.
A4: THE QUESTION
A5: Our purchase prices are flat or falling and every variance report is green -- so why is material cost per ACCEPTED unit rising, and which supplier-part combinations should sourcing renegotiate first?
A7: SPEND -- recomputed in Excel from the purchase-order extract | E7: PRICE EROSION -- what the learning curve should have handed back
A8: Extended price (12 months) | C8: =SUMIFS(tPO[ExtendedPrice],tPO[OrderDate],">"&WinFrom,tPO[OrderDate],"<="&WinTo) -> 48586387 | E8: Vendor-part pairs assessed | G8: =COUNTA(tErosion[PartNumber]) -> 185
A9: Landed cost (12 months) | C9: =SUMIFS(tPO[LandedCost],tPO[OrderDate],">"&WinFrom,tPO[OrderDate],"<="&WinTo) -> 49474786 | E9: Spend-weighted erosion capture % | G9: =SUMPRODUCT(tErosion[ErosionCapturePct],tErosion[TTMSpend])/SUM(tErosion[TTMSpend]) -> 29.499101
A10: Freight | C10: =SUMIFS(tPO[FreightAmount],tPO[OrderDate],">"&WinFrom,tPO[OrderDate],"<="&WinTo) -> 779056.82 | E10: Annual opportunity (gross) | G10: =SUMIF(tErosion[AnnualOpportunity],">0") -> 4047608.7 | H10: Gross, not netted: a supplier already beating the curve is not a savings source and cannot fund another supplier's shortfall.
A11: Expedite fees | C11: =SUMIFS(tPO[ExpediteFee],tPO[OrderDate],">"&WinFrom,tPO[OrderDate],"<="&WinTo) -> 109342.24 | E11: Pairs already ahead of the curve | G11: =COUNTIF(tErosion[AnnualOpportunity],"<0") -> 19
A12: Off-contract spend | C12: =SUMIFS(tPO[ExtendedPrice],tPO[OrderDate],">"&WinFrom,tPO[OrderDate],"<="&WinTo,tPO[IsOnContract],0) -> 13161620 | E12: Value where already ahead | G12: =SUMIF(tErosion[AnnualOpportunity],"<0") -> -249428.64
A13: Single-source spend | C13: =SUMIFS(tPO[ExtendedPrice],tPO[OrderDate],">"&WinFrom,tPO[OrderDate],"<="&WinTo,tPO[IsSingleSource],1) -> 13201040 | E13: Pairs capturing under 20% | G13: =COUNTIFS(tErosion[ErosionCapturePct],"<20") -> 61
A14: Units received | C14: =SUMIFS(tPO[QtyReceived],tPO[OrderDate],">"&WinFrom,tPO[OrderDate],"<="&WinTo) -> 560046 | E14: Spend on those pairs | G14: =SUMIFS(tErosion[TTMSpend],tErosion[ErosionCapturePct],"<20") -> 17495221
A15: Units accepted | C15: =SUMIFS(tPO[QtyAccepted],tPO[OrderDate],">"&WinFrom,tPO[OrderDate],"<="&WinTo) -> 555083
A16: Value of rejected material | C16: =SUMIFS(tPO[RejectedValue],tPO[OrderDate],">"&WinFrom,tPO[OrderDate],"<="&WinTo) -> 498840.71
A18: SCORECARD -- status computed against the target table, not typed in
A19: Metric | B19: Value | C19: Target | D19: Warning | E19: Status | F19: Variance | G19: What it means
A20: Erosion capture % | B20: =$G$9 -> 29.499101 | C20: =INDEX(tTargets[TargetValue],MATCH("ErosionCapturePct",tTargets[MetricName],0)) -> 80 | D20: =INDEX(tTargets[WarningValue],MATCH("ErosionCapturePct",tTargets[MetricName],0)) -> 60 | E20: =IF(B20>=C20,"Green",IF(B20>=D20,"Amber","Red")) -> Red | F20: =C20-B20 -> 50.500899 | G20: Share of the expected category erosion actually realised. No price-variance report can see this gap.
A21: Maverick spend % | B21: =100*$C$12/$C$8 -> 27.08911 | C21: =INDEX(tTargets[TargetValue],MATCH("MaverickSpendPct",tTargets[MetricName],0)) -> 5 | D21: =INDEX(tTargets[WarningValue],MATCH("MaverickSpendPct",tTargets[MetricName],0)) -> 12 | E21: =IF(B21<=C21,"Green",IF(B21<=D21,"Amber","Red")) -> Red | F21: =B21-C21 -> 22.08911 | G21: Spend with no agreement in force. There is nothing to negotiate against until it is on contract.
A22: Purchase price variance % | B22: =100*SUMIFS(tPO[PPVAmount],tPO[OrderDate],">"&WinFrom,tPO[OrderDate],"<="&WinTo)/SUMIFS(tPO[ContractedExtended],tPO[OrderDate],">"&WinFrom,tPO[OrderDate],"<="&WinTo) -> -0.18902298 | C22: =INDEX(tTargets[TargetValue],MATCH("PPVPct",tTargets[MetricName],0)) -> 0 | D22: =INDEX(tTargets[WarningValue],MATCH("PPVPct",tTargets[MetricName],0)) -> 2 | E22: =IF(B22<=C22,"Green",IF(B22<=D22,"Amber","Red")) -> Green | F22: =B22-C22 -> -0.18902298 | G22: A supplier who renews flat scores zero here forever. Read it beside erosion capture, never alone.
A23: Acceptance rate % | B23: =100*$C$15/$C$14 -> 99.113823 | C23: =INDEX(tTargets[TargetValue],MATCH("AcceptanceRatePct",tTargets[MetricName],0)) -> 98 | D23: =INDEX(tTargets[WarningValue],MATCH("AcceptanceRatePct",tTargets[MetricName],0)) -> 95 | E23: =IF(B23>=C23,"Green",IF(B23>=D23,"Amber","Red")) -> Green | F23: =C23-B23 -> -1.1138228 | G23: Portfolio figure. Check the vendor-category cut before concluding anything.
A24: On-time delivery % | B24: =100*COUNTIFS(tPO[IsOnTime],1,tPO[OrderDate],">"&WinFrom,tPO[OrderDate],"<="&WinTo)/COUNTIFS(tPO[IsOnTime],">=0",tPO[OrderDate],">"&WinFrom,tPO[OrderDate],"<="&WinTo) -> 80.622837 | C24: =INDEX(tTargets[TargetValue],MATCH("OnTimeDeliveryPct",tTargets[MetricName],0)) -> 95 | D24: =INDEX(tTargets[WarningValue],MATCH("OnTimeDeliveryPct",tTargets[MetricName],0)) -> 90 | E24: =IF(B24>=C24,"Green",IF(B24>=D24,"Amber","Red")) -> Red | F24: =C24-B24 -> 14.377163 | G24: Receipts on or before the promised date.
A25: Expedite spend % | B25: =100*$C$11/$C$8 -> 0.22504707 | C25: =INDEX(tTargets[TargetValue],MATCH("ExpediteSpendPct",tTargets[MetricName],0)) -> 1 | D25: =INDEX(tTargets[WarningValue],MATCH("ExpediteSpendPct",tTargets[MetricName],0)) -> 3 | E25: =IF(B25<=C25,"Green",IF(B25<=D25,"Amber","Red")) -> Green | F25: =B25-C25 -> -0.77495293 | G25: Caused by planning, not by the supplier. Negotiable only by fixing the plan.
A26: Single-source spend % | B26: =100*$C$13/$C$8 -> 27.170244 | C26: =INDEX(tTargets[TargetValue],MATCH("SingleSourceSpendPct",tTargets[MetricName],0)) -> 20 | D26: =INDEX(tTargets[WarningValue],MATCH("SingleSourceSpendPct",tTargets[MetricName],0)) -> 35 | E26: =IF(B26<=C26,"Green",IF(B26<=D26,"Amber","Red")) -> Amber | F26: =B26-C26 -> 7.1702436 | G26: Where the largest erosion gaps sit and the least leverage exists.
A27: Top-5 vendor share % | B27: =100*xlTop5/xlWindowAll -> 27.198155 | C27: =INDEX(tTargets[TargetValue],MATCH("Top5VendorSharePct",tTargets[MetricName],0)) -> 50 | D27: =INDEX(tTargets[WarningValue],MATCH("Top5VendorSharePct",tTargets[MetricName],0)) -> 70 | E27: =IF(B27<=C27,"Green",IF(B27<=D27,"Amber","Red")) -> Green | F27: =B27-C27 -> -22.801845 | G27: Concentration of spend in the five largest suppliers.
A29: BY CATEGORY -- spend, benchmark and what was actually captured
A30: Category | B30: Spend (12m) | C30: Share % | D30: Benchmark erosion % | E30: Captured % | F30: Opportunity | G30: Maverick %
A31: =IFERROR(INDEX(tBenchmark[Category],1),"") -> Fibre Connector | B31: =IF($A31="","",SUMIFS(tPO[ExtendedPrice],tPO[OrderDate],">"&WinFrom,tPO[OrderDate],"<="&WinTo,tPO[Category],$A31)) -> 2929738.1 | C31: =IF($A31="","",100*B31/$C$8) -> 6.0299566 | D31: =IFERROR(INDEX(tBenchmark[AnnualErosionPct],1),"") -> 7 | E31: =IF($A31="","",IFERROR(SUMPRODUCT((tErosion[Category]=$A31)*tErosion[ErosionCapturePct]*tErosion[TTMSpend])/SUMPRODUCT((tErosion[Category]=$A31)*tErosion[TTMSpend]),"")) -> 28.839434 | F31: =IF($A31="","",SUMIFS(tErosion[AnnualOpportunity],tErosion[Category],$A31,tErosion[AnnualOpportunity],">0")) -> 359521.71 | G31: =IF($A31="","",IFERROR(100*SUMIFS(tPO[ExtendedPrice],tPO[OrderDate],">"&WinFrom,tPO[OrderDate],"<="&WinTo,tPO[Category],$A31,tPO[IsOnContract],0)/SUMIFS(tPO[ExtendedPrice],tPO[OrderDate],">"&WinFrom,tPO[OrderDate],"<="&WinTo,tPO[Category],$A31),"")) -> 10.011915
A32: =IFERROR(INDEX(tBenchmark[Category],2),"") -> Laser Diode | B32: =IF($A32="","",SUMIFS(tPO[ExtendedPrice],tPO[OrderDate],">"&WinFrom,tPO[OrderDate],"<="&WinTo,tPO[Category],$A32)) -> 10615765 | C32: =IF($A32="","",100*B32/$C$8) -> 21.849257 | D32: =IFERROR(INDEX(tBenchmark[AnnualErosionPct],2),"") -> 8 | E32: =IF($A32="","",IFERROR(SUMPRODUCT((tErosion[Category]=$A32)*tErosion[ErosionCapturePct]*tErosion[TTMSpend])/SUMPRODUCT((tErosion[Category]=$A32)*tErosion[TTMSpend]),"")) -> 42.984473 | F32: =IF($A32="","",SUMIFS(tErosion[AnnualOpportunity],tErosion[Category],$A32,tErosion[AnnualOpportunity],">0")) -> 1189602.5 | G32: =IF($A32="","",IFERROR(100*SUMIFS(tPO[ExtendedPrice],tPO[OrderDate],">"&WinFrom,tPO[OrderDate],"<="&WinTo,tPO[Category],$A32,tPO[IsOnContract],0)/SUMIFS(tPO[ExtendedPrice],tPO[OrderDate],">"&WinFrom,tPO[OrderDate],"<="&WinTo,tPO[Category],$A32),"")) -> 28.031512
A33: =IFERROR(INDEX(tBenchmark[Category],3),"") -> Lens Assembly | B33: =IF($A33="","",SUMIFS(tPO[ExtendedPrice],tPO[OrderDate],">"&WinFrom,tPO[OrderDate],"<="&WinTo,tPO[Category],$A33)) -> 5521842.9 | C33: =IF($A33="","",100*B33/$C$8) -> 11.365 | D33: =IFERROR(INDEX(tBenchmark[AnnualErosionPct],3),"") -> 3 | E33: =IF($A33="","",IFERROR(SUMPRODUCT((tErosion[Category]=$A33)*tErosion[ErosionCapturePct]*tErosion[TTMSpend])/SUMPRODUCT((tErosion[Category]=$A33)*tErosion[TTMSpend]),"")) -> -14.074411 | F33: =IF($A33="","",SUMIFS(tErosion[AnnualOpportunity],tErosion[Category],$A33,tErosion[AnnualOpportunity],">0")) -> 429596.73 | G33: =IF($A33="","",IFERROR(100*SUMIFS(tPO[ExtendedPrice],tPO[OrderDate],">"&WinFrom,tPO[OrderDate],"<="&WinTo,tPO[Category],$A33,tPO[IsOnContract],0)/SUMIFS(tPO[ExtendedPrice],tPO[OrderDate],">"&WinFrom,tPO[OrderDate],"<="&WinTo,tPO[Category],$A33),"")) -> 40.204204
A34: =IFERROR(INDEX(tBenchmark[Category],4),"") -> Optical Coating | B34: =IF($A34="","",SUMIFS(tPO[ExtendedPrice],tPO[OrderDate],">"&WinFrom,tPO[OrderDate],"<="&WinTo,tPO[Category],$A34)) -> 4144023.4 | C34: =IF($A34="","",100*B34/$C$8) -> 8.5291862 | D34: =IFERROR(INDEX(tBenchmark[AnnualErosionPct],4),"") -> 5 | E34: =IF($A34="","",IFERROR(SUMPRODUCT((tErosion[Category]=$A34)*tErosion[ErosionCapturePct]*tErosion[TTMSpend])/SUMPRODUCT((tErosion[Category]=$A34)*tErosion[TTMSpend]),"")) -> 43.097375 | F34: =IF($A34="","",SUMIFS(tErosion[AnnualOpportunity],tErosion[Category],$A34,tErosion[AnnualOpportunity],">0")) -> 259236 | G34: =IF($A34="","",IFERROR(100*SUMIFS(tPO[ExtendedPrice],tPO[OrderDate],">"&WinFrom,tPO[OrderDate],"<="&WinTo,tPO[Category],$A34,tPO[IsOnContract],0)/SUMIFS(tPO[ExtendedPrice],tPO[OrderDate],">"&WinFrom,tPO[OrderDate],"<="&WinTo,tPO[Category],$A34),"")) -> 22.588663
A35: =IFERROR(INDEX(tBenchmark[Category],5),"") -> Optical Fibre | B35: =IF($A35="","",SUMIFS(tPO[ExtendedPrice],tPO[OrderDate],">"&WinFrom,tPO[OrderDate],"<="&WinTo,tPO[Category],$A35)) -> 11843666 | C35: =IF($A35="","",100*B35/$C$8) -> 24.376511 | D35: =IFERROR(INDEX(tBenchmark[AnnualErosionPct],5),"") -> 4 | E35: =IF($A35="","",IFERROR(SUMPRODUCT((tErosion[Category]=$A35)*tErosion[ErosionCapturePct]*tErosion[TTMSpend])/SUMPRODUCT((tErosion[Category]=$A35)*tErosion[TTMSpend]),"")) -> 43.885711 | F35: =IF($A35="","",SUMIFS(tErosion[AnnualOpportunity],tErosion[Category],$A35,tErosion[AnnualOpportunity],">0")) -> 715059.09 | G35: =IF($A35="","",IFERROR(100*SUMIFS(tPO[ExtendedPrice],tPO[OrderDate],">"&WinFrom,tPO[OrderDate],"<="&WinTo,tPO[Category],$A35,tPO[IsOnContract],0)/SUMIFS(tPO[ExtendedPrice],tPO[OrderDate],">"&WinFrom,tPO[OrderDate],"<="&WinTo,tPO[Category],$A35),"")) -> 18.361652
A36: =IFERROR(INDEX(tBenchmark[Category],6),"") -> Photodetector | B36: =IF($A36="","",SUMIFS(tPO[ExtendedPrice],tPO[OrderDate],">"&WinFrom,tPO[OrderDate],"<="&WinTo,tPO[Category],$A36)) -> 6260935.7 | C36: =IF($A36="","",100*B36/$C$8) -> 12.886193 | D36: =IFERROR(INDEX(tBenchmark[AnnualErosionPct],6),"") -> 6.5 | E36: =IF($A36="","",IFERROR(SUMPRODUCT((tErosion[Category]=$A36)*tErosion[ErosionCapturePct]*tErosion[TTMSpend])/SUMPRODUCT((tErosion[Category]=$A36)*tErosion[TTMSpend]),"")) -> 30.426866 | F36: =IF($A36="","",SUMIFS(tErosion[AnnualOpportunity],tErosion[Category],$A36,tErosion[AnnualOpportunity],">0")) -> 619420.28 | G36: =IF($A36="","",IFERROR(100*SUMIFS(tPO[ExtendedPrice],tPO[OrderDate],">"&WinFrom,tPO[OrderDate],"<="&WinTo,tPO[Category],$A36,tPO[IsOnContract],0)/SUMIFS(tPO[ExtendedPrice],tPO[OrderDate],">"&WinFrom,tPO[OrderDate],"<="&WinTo,tPO[Category],$A36),"")) -> 40.060673
A37: =IFERROR(INDEX(tBenchmark[Category],7),"") -> Precision Mount | B37: =IF($A37="","",SUMIFS(tPO[ExtendedPrice],tPO[OrderDate],">"&WinFrom,tPO[OrderDate],"<="&WinTo,tPO[Category],$A37)) -> 3429103.1 | C37: =IF($A37="","",100*B37/$C$8) -> 7.0577447 | D37: =IFERROR(INDEX(tBenchmark[AnnualErosionPct],7),"") -> 2 | E37: =IF($A37="","",IFERROR(SUMPRODUCT((tErosion[Category]=$A37)*tErosion[ErosionCapturePct]*tErosion[TTMSpend])/SUMPRODUCT((tErosion[Category]=$A37)*tErosion[TTMSpend]),"")) -> -20.831331 | F37: =IF($A37="","",SUMIFS(tErosion[AnnualOpportunity],tErosion[Category],$A37,tErosion[AnnualOpportunity],">0")) -> 189051.85 | G37: =IF($A37="","",IFERROR(100*SUMIFS(tPO[ExtendedPrice],tPO[OrderDate],">"&WinFrom,tPO[OrderDate],"<="&WinTo,tPO[Category],$A37,tPO[IsOnContract],0)/SUMIFS(tPO[ExtendedPrice],tPO[OrderDate],">"&WinFrom,tPO[OrderDate],"<="&WinTo,tPO[Category],$A37),"")) -> 26.112233
A38: =IFERROR(INDEX(tBenchmark[Category],8),"") -> Thermal Control | B38: =IF($A38="","",SUMIFS(tPO[ExtendedPrice],tPO[OrderDate],">"&WinFrom,tPO[OrderDate],"<="&WinTo,tPO[Category],$A38)) -> 3841313 | C38: =IF($A38="","",100*B38/$C$8) -> 7.9061508 | D38: =IFERROR(INDEX(tBenchmark[AnnualErosionPct],8),"") -> 5.5 | E38: =IF($A38="","",IFERROR(SUMPRODUCT((tErosion[Category]=$A38)*tErosion[ErosionCapturePct]*tErosion[TTMSpend])/SUMPRODUCT((tErosion[Category]=$A38)*tErosion[TTMSpend]),"")) -> 38.547711 | F38: =IF($A38="","",SUMIFS(tErosion[AnnualOpportunity],tErosion[Category],$A38,tErosion[AnnualOpportunity],">0")) -> 286120.51 | G38: =IF($A38="","",IFERROR(100*SUMIFS(tPO[ExtendedPrice],tPO[OrderDate],">"&WinFrom,tPO[OrderDate],"<="&WinTo,tPO[Category],$A38,tPO[IsOnContract],0)/SUMIFS(tPO[ExtendedPrice],tPO[OrderDate],">"&WinFrom,tPO[OrderDate],"<="&WinTo,tPO[Category],$A38),"")) -> 30.150219
A39: TOTAL | B39: =SUM(B31:B38) -> 48586387 | C39: =SUM(C31:C38) -> 100 | F39: =SUM(F31:F38) -> 4047608.7

Sheet Renegotiation Queue
A1: RENEGOTIATION QUEUE
A2: Which supplier-part combination to renegotiate first. Ranked by annual opportunity; the ACTION is decided by leverage, because the biggest gaps sit where there is least of it.
B4: Category manager | C4: (All) | F4: Pairs matching | H4: =SUM(Calc!$B$52:$B$236) -> 43
B5: Action | C5: (All) | F5: Annual opportunity in scope | H5: =SUMPRODUCT(Calc!$B$52:$B$236,tQueue[AnnualOpportunity]) -> 2673946.2
B6: Category | C6: (All) | F6: Spend in scope (12m) | H6: =SUMPRODUCT(Calc!$B$52:$B$236,tQueue[TTMSpend]) -> 18583467
B7: This quarter only | C7: Yes | F7: ="Showing top "&MIN(QueueRowsShown,H4)&" of "&H4 -> Showing top 25 of 43
A9: # | B9: Part | C9: Category | D9: Vendor | E9: Manager | F9: Sources | G9: Bench % | H9: Actual % | I9: Capture % | J9: Gap / unit | K9: TTM spend | L9: Opportunity | M9: Leverage | N9: Action | O9: What to do
A10: =IF(1>MIN(QueueRowsShown,$H$4),"",1) -> 1 | B10: =IFERROR(INDEX(tQueue[PartNumber],MATCH(1,Calc!$C$52:$C$236,0)),"") -> LOM-0104 | C10: =IFERROR(INDEX(tQueue[Category],MATCH(1,Calc!$C$52:$C$236,0)),"") -> Laser Diode | D10: =IFERROR(INDEX(tQueue[VendorID],MATCH(1,Calc!$C$52:$C$236,0)),"") -> VEN-003 | E10: =IFERROR(INDEX(tQueue[BuyerName],MATCH(1,Calc!$C$52:$C$236,0)),"") -> Adaeze Okonkwo | F10: =IFERROR(INDEX(tQueue[QualifiedSupplierCount],MATCH(1,Calc!$C$52:$C$236,0)),"") -> 2 | G10: =IFERROR(INDEX(tQueue[BenchmarkErosionPct],MATCH(1,Calc!$C$52:$C$236,0)),"") -> 8 | H10: =IFERROR(INDEX(tQueue[ActualErosionPct],MATCH(1,Calc!$C$52:$C$236,0)),"") -> -4.474 | I10: =IFERROR(INDEX(tQueue[ErosionCapturePct],MATCH(1,Calc!$C$52:$C$236,0)),"") -> -55.93 | J10: =IFERROR(INDEX(tQueue[ErosionGapPerUnit],MATCH(1,Calc!$C$52:$C$236,0)),"") -> 180.3505 | K10: =IFERROR(INDEX(tQueue[TTMSpend],MATCH(1,Calc!$C$52:$C$236,0)),"") -> 714564.24 | L10: =IFERROR(INDEX(tQueue[AnnualOpportunity],MATCH(1,Calc!$C$52:$C$236,0)),"") -> 199828.4 | M10: =IFERROR(INDEX(tQueue[LeverageScore],MATCH(1,Calc!$C$52:$C$236,0)),"") -> 59 | N10: =IFERROR(INDEX(tQueue[ActionCode],MATCH(1,Calc!$C$52:$C$236,0)),"") -> PUT_ON_CONTRACT | O10: =IFERROR(INDEX(tQueue[RecommendedAction],MATCH(1,Calc!$C$52:$C$236,0)),"") -> Most of this spend has no agreement in force. Put it under contract before attempting to negotiate a price against nothing.
A11: =IF(2>MIN(QueueRowsShown,$H$4),"",2) -> 2 | B11: =IFERROR(INDEX(tQueue[PartNumber],MATCH(2,Calc!$C$52:$C$236,0)),"") -> LOM-0128 | C11: =IFERROR(INDEX(tQueue[Category],MATCH(2,Calc!$C$52:$C$236,0)),"") -> Laser Diode | D11: =IFERROR(INDEX(tQueue[VendorID],MATCH(2,Calc!$C$52:$C$236,0)),"") -> VEN-015 | E11: =IFERROR(INDEX(tQueue[BuyerName],MATCH(2,Calc!$C$52:$C$236,0)),"") -> Adaeze Okonkwo | F11: =IFERROR(INDEX(tQueue[QualifiedSupplierCount],MATCH(2,Calc!$C$52:$C$236,0)),"") -> 2 | G11: =IFERROR(INDEX(tQueue[BenchmarkErosionPct],MATCH(2,Calc!$C$52:$C$236,0)),"") -> 8 | H11: =IFERROR(INDEX(tQueue[ActualErosionPct],MATCH(2,Calc!$C$52:$C$236,0)),"") -> 0.738 | I11: =IFERROR(INDEX(tQueue[ErosionCapturePct],MATCH(2,Calc!$C$52:$C$236,0)),"") -> 9.23 | J11: =IFERROR(INDEX(tQueue[ErosionGapPerUnit],MATCH(2,Calc!$C$52:$C$236,0)),"") -> 150.6214 | K11: =IFERROR(INDEX(tQueue[TTMSpend],MATCH(2,Calc!$C$52:$C$236,0)),"") -> 997643.82 | L11: =IFERROR(INDEX(tQueue[AnnualOpportunity],MATCH(2,Calc!$C$52:$C$236,0)),"") -> 179088.8 | M11: =IFERROR(INDEX(tQueue[LeverageScore],MATCH(2,Calc!$C$52:$C$236,0)),"") -> 35 | N11: =IFERROR(INDEX(tQueue[ActionCode],MATCH(2,Calc!$C$52:$C$236,0)),"") -> RENEGOTIATE | O11: =IFERROR(INDEX(tQueue[RecommendedAction],MATCH(2,Calc!$C$52:$C$236,0)),"") -> Renegotiate. A qualified alternative exists, though Lumen is under 8% of this supplier's revenue: leverage is weak, but the gap is large enough to justify the meeting. Open with the category erosion benchmark.
A12: =IF(3>MIN(QueueRowsShown,$H$4),"",3) -> 3 | B12: =IFERROR(INDEX(tQueue[PartNumber],MATCH(3,Calc!$C$52:$C$236,0)),"") -> LOM-0096 | C12: =IFERROR(INDEX(tQueue[Category],MATCH(3,Calc!$C$52:$C$236,0)),"") -> Laser Diode | D12: =IFERROR(INDEX(tQueue[VendorID],MATCH(3,Calc!$C$52:$C$236,0)),"") -> VEN-011 | E12: =IFERROR(INDEX(tQueue[BuyerName],MATCH(3,Calc!$C$52:$C$236,0)),"") -> Adaeze Okonkwo | F12: =IFERROR(INDEX(tQueue[QualifiedSupplierCount],MATCH(3,Calc!$C$52:$C$236,0)),"") -> 1 | G12: =IFERROR(INDEX(tQueue[BenchmarkErosionPct],MATCH(3,Calc!$C$52:$C$236,0)),"") -> 8 | H12: =IFERROR(INDEX(tQueue[ActualErosionPct],MATCH(3,Calc!$C$52:$C$236,0)),"") -> -2.262 | I12: =IFERROR(INDEX(tQueue[ErosionCapturePct],MATCH(3,Calc!$C$52:$C$236,0)),"") -> -28.28 | J12: =IFERROR(INDEX(tQueue[ErosionGapPerUnit],MATCH(3,Calc!$C$52:$C$236,0)),"") -> 116.1129 | K12: =IFERROR(INDEX(tQueue[TTMSpend],MATCH(3,Calc!$C$52:$C$236,0)),"") -> 686912.99 | L12: =IFERROR(INDEX(tQueue[AnnualOpportunity],MATCH(3,Calc!$C$52:$C$236,0)),"") -> 176607.69 | M12: =IFERROR(INDEX(tQueue[LeverageScore],MATCH(3,Calc!$C$52:$C$236,0)),"") -> 37 | N12: =IFERROR(INDEX(tQueue[ActionCode],MATCH(3,Calc!$C$52:$C$236,0)),"") -> PUT_ON_CONTRACT | O12: =IFERROR(INDEX(tQueue[RecommendedAction],MATCH(3,Calc!$C$52:$C$236,0)),"") -> Most of this spend has no agreement in force. Put it under contract before attempting to negotiate a price against nothing.
A13: =IF(4>MIN(QueueRowsShown,$H$4),"",4) -> 4 | B13: =IFERROR(INDEX(tQueue[PartNumber],MATCH(4,Calc!$C$52:$C$236,0)),"") -> LOM-0048 | C13: =IFERROR(INDEX(tQueue[Category],MATCH(4,Calc!$C$52:$C$236,0)),"") -> Laser Diode | D13: =IFERROR(INDEX(tQueue[VendorID],MATCH(4,Calc!$C$52:$C$236,0)),"") -> VEN-008 | E13: =IFERROR(INDEX(tQueue[BuyerName],MATCH(4,Calc!$C$52:$C$236,0)),"") -> Adaeze Okonkwo | F13: =IFERROR(INDEX(tQueue[QualifiedSupplierCount],MATCH(4,Calc!$C$52:$C$236,0)),"") -> 3 | G13: =IFERROR(INDEX(tQueue[BenchmarkErosionPct],MATCH(4,Calc!$C$52:$C$236,0)),"") -> 8 | H13: =IFERROR(INDEX(tQueue[ActualErosionPct],MATCH(4,Calc!$C$52:$C$236,0)),"") -> 2.202 | I13: =IFERROR(INDEX(tQueue[ErosionCapturePct],MATCH(4,Calc!$C$52:$C$236,0)),"") -> 27.53 | J13: =IFERROR(INDEX(tQueue[ErosionGapPerUnit],MATCH(4,Calc!$C$52:$C$236,0)),"") -> 113.5144 | K13: =IFERROR(INDEX(tQueue[TTMSpend],MATCH(4,Calc!$C$52:$C$236,0)),"") -> 988567.39 | L13: =IFERROR(INDEX(tQueue[AnnualOpportunity],MATCH(4,Calc!$C$52:$C$236,0)),"") -> 154039.04 | M13: =IFERROR(INDEX(tQueue[LeverageScore],MATCH(4,Calc!$C$52:$C$236,0)),"") -> 70 | N13: =IFERROR(INDEX(tQueue[ActionCode],MATCH(4,Calc!$C$52:$C$236,0)),"") -> RENEGOTIATE | O13: =IFERROR(INDEX(tQueue[RecommendedAction],MATCH(4,Calc!$C$52:$C$236,0)),"") -> Renegotiate. A qualified alternative exists, though Lumen is under 8% of this supplier's revenue. Open with the category erosion benchmark.
A14: =IF(5>MIN(QueueRowsShown,$H$4),"",5) -> 5 | B14: =IFERROR(INDEX(tQueue[PartNumber],MATCH(5,Calc!$C$52:$C$236,0)),"") -> LOM-0057 | C14: =IFERROR(INDEX(tQueue[Category],MATCH(5,Calc!$C$52:$C$236,0)),"") -> Photodetector | D14: =IFERROR(INDEX(tQueue[VendorID],MATCH(5,Calc!$C$52:$C$236,0)),"") -> VEN-005 | E14: =IFERROR(INDEX(tQueue[BuyerName],MATCH(5,Calc!$C$52:$C$236,0)),"") -> Rafael Duarte | F14: =IFERROR(INDEX(tQueue[QualifiedSupplierCount],MATCH(5,Calc!$C$52:$C$236,0)),"") -> 1 | G14: =IFERROR(INDEX(tQueue[BenchmarkErosionPct],MATCH(5,Calc!$C$52:$C$236,0)),"") -> 6.5 | H14: =IFERROR(INDEX(tQueue[ActualErosionPct],MATCH(5,Calc!$C$52:$C$236,0)),"") -> -3.504 | I14: =IFERROR(INDEX(tQueue[ErosionCapturePct],MATCH(5,Calc!$C$52:$C$236,0)),"") -> -53.91 | J14: =IFERROR(INDEX(tQueue[ErosionGapPerUnit],MATCH(5,Calc!$C$52:$C$236,0)),"") -> 120.4996 | K14: =IFERROR(INDEX(tQueue[TTMSpend],MATCH(5,Calc!$C$52:$C$236,0)),"") -> 436614.97 | L14: =IFERROR(INDEX(tQueue[AnnualOpportunity],MATCH(5,Calc!$C$52:$C$236,0)),"") -> 105437.11 | M14: =IFERROR(INDEX(tQueue[LeverageScore],MATCH(5,Calc!$C$52:$C$236,0)),"") -> 37 | N14: =IFERROR(INDEX(tQueue[ActionCode],MATCH(5,Calc!$C$52:$C$236,0)),"") -> PUT_ON_CONTRACT | O14: =IFERROR(INDEX(tQueue[RecommendedAction],MATCH(5,Calc!$C$52:$C$236,0)),"") -> Most of this spend has no agreement in force. Put it under contract before attempting to negotiate a price against nothing.
A15: =IF(6>MIN(QueueRowsShown,$H$4),"",6) -> 6 | B15: =IFERROR(INDEX(tQueue[PartNumber],MATCH(6,Calc!$C$52:$C$236,0)),"") -> LOM-0082 | C15: =IFERROR(INDEX(tQueue[Category],MATCH(6,Calc!$C$52:$C$236,0)),"") -> Optical Fibre | D15: =IFERROR(INDEX(tQueue[VendorID],MATCH(6,Calc!$C$52:$C$236,0)),"") -> VEN-032 | E15: =IFERROR(INDEX(tQueue[BuyerName],MATCH(6,Calc!$C$52:$C$236,0)),"") -> Mei-Ling Chow | F15: =IFERROR(INDEX(tQueue[QualifiedSupplierCount],MATCH(6,Calc!$C$52:$C$236,0)),"") -> 1 | G15: =IFERROR(INDEX(tQueue[BenchmarkErosionPct],MATCH(6,Calc!$C$52:$C$236,0)),"") -> 4 | H15: =IFERROR(INDEX(tQueue[ActualErosionPct],MATCH(6,Calc!$C$52:$C$236,0)),"") -> 0.016 | I15: =IFERROR(INDEX(tQueue[ErosionCapturePct],MATCH(6,Calc!$C$52:$C$236,0)),"") -> 0.4 | J15: =IFERROR(INDEX(tQueue[ErosionGapPerUnit],MATCH(6,Calc!$C$52:$C$236,0)),"") -> 4.4279 | K15: =IFERROR(INDEX(tQueue[TTMSpend],MATCH(6,Calc!$C$52:$C$236,0)),"") -> 1026650.2 | L15: =IFERROR(INDEX(tQueue[AnnualOpportunity],MATCH(6,Calc!$C$52:$C$236,0)),"") -> 104353.4 | M15: =IFERROR(INDEX(tQueue[LeverageScore],MATCH(6,Calc!$C$52:$C$236,0)),"") -> 60 | N15: =IFERROR(INDEX(tQueue[ActionCode],MATCH(6,Calc!$C$52:$C$236,0)),"") -> RENEGOTIATE | O15: =IFERROR(INDEX(tQueue[RecommendedAction],MATCH(6,Calc!$C$52:$C$236,0)),"") -> Renegotiate. No second supplier is qualified, but Lumen is at least 8% of this supplier's revenue. Open with the category erosion benchmark.
A16: =IF(7>MIN(QueueRowsShown,$H$4),"",7) -> 7 | B16: =IFERROR(INDEX(tQueue[PartNumber],MATCH(7,Calc!$C$52:$C$236,0)),"") -> LOM-0024 | C16: =IFERROR(INDEX(tQueue[Category],MATCH(7,Calc!$C$52:$C$236,0)),"") -> Laser Diode | D16: =IFERROR(INDEX(tQueue[VendorID],MATCH(7,Calc!$C$52:$C$236,0)),"") -> VEN-019 | E16: =IFERROR(INDEX(tQueue[BuyerName],MATCH(7,Calc!$C$52:$C$236,0)),"") -> Rafael Duarte | F16: =IFERROR(INDEX(tQueue[QualifiedSupplierCount],MATCH(7,Calc!$C$52:$C$236,0)),"") -> 1 | G16: =IFERROR(INDEX(tQueue[BenchmarkErosionPct],MATCH(7,Calc!$C$52:$C$236,0)),"") -> 8 | H16: =IFERROR(INDEX(tQueue[ActualErosionPct],MATCH(7,Calc!$C$52:$C$236,0)),"") -> -0.976 | I16: =IFERROR(INDEX(tQueue[ErosionCapturePct],MATCH(7,Calc!$C$52:$C$236,0)),"") -> -12.2 | J16: =IFERROR(INDEX(tQueue[ErosionGapPerUnit],MATCH(7,Calc!$C$52:$C$236,0)),"") -> 98.9079 | K16: =IFERROR(INDEX(tQueue[TTMSpend],MATCH(7,Calc!$C$52:$C$236,0)),"") -> 454797.44 | L16: =IFERROR(INDEX(tQueue[AnnualOpportunity],MATCH(7,Calc!$C$52:$C$236,0)),"") -> 101479.51 | M16: =IFERROR(INDEX(tQueue[LeverageScore],MATCH(7,Calc!$C$52:$C$236,0)),"") -> 60 | N16: =IFERROR(INDEX(tQueue[ActionCode],MATCH(7,Calc!$C$52:$C$236,0)),"") -> RENEGOTIATE | O16: =IFERROR(INDEX(tQueue[RecommendedAction],MATCH(7,Calc!$C$52:$C$236,0)),"") -> Renegotiate. No second supplier is qualified, but Lumen is at least 8% of this supplier's revenue. Open with the category erosion benchmark.
A17: =IF(8>MIN(QueueRowsShown,$H$4),"",8) -> 8 | B17: =IFERROR(INDEX(tQueue[PartNumber],MATCH(8,Calc!$C$52:$C$236,0)),"") -> LOM-0130 | C17: =IFERROR(INDEX(tQueue[Category],MATCH(8,Calc!$C$52:$C$236,0)),"") -> Optical Fibre | D17: =IFERROR(INDEX(tQueue[VendorID],MATCH(8,Calc!$C$52:$C$236,0)),"") -> VEN-008 | E17: =IFERROR(INDEX(tQueue[BuyerName],MATCH(8,Calc!$C$52:$C$236,0)),"") -> Mei-Ling Chow | F17: =IFERROR(INDEX(tQueue[QualifiedSupplierCount],MATCH(8,Calc!$C$52:$C$236,0)),"") -> 1 | G17: =IFERROR(INDEX(tQueue[BenchmarkErosionPct],MATCH(8,Calc!$C$52:$C$236,0)),"") -> 4 | H17: =IFERROR(INDEX(tQueue[ActualErosionPct],MATCH(8,Calc!$C$52:$C$236,0)),"") -> -1.56 | I17: =IFERROR(INDEX(tQueue[ErosionCapturePct],MATCH(8,Calc!$C$52:$C$236,0)),"") -> -39 | J17: =IFERROR(INDEX(tQueue[ErosionGapPerUnit],MATCH(8,Calc!$C$52:$C$236,0)),"") -> 5.7597 | K17: =IFERROR(INDEX(tQueue[TTMSpend],MATCH(8,Calc!$C$52:$C$236,0)),"") -> 694927.1 | L17: =IFERROR(INDEX(tQueue[AnnualOpportunity],MATCH(8,Calc!$C$52:$C$236,0)),"") -> 96439.91 | M17: =IFERROR(INDEX(tQueue[LeverageScore],MATCH(8,Calc!$C$52:$C$236,0)),"") -> 27 | N17: =IFERROR(INDEX(tQueue[ActionCode],MATCH(8,Calc!$C$52:$C$236,0)),"") -> DUAL_SOURCE | O17: =IFERROR(INDEX(tQueue[RecommendedAction],MATCH(8,Calc!$C$52:$C$236,0)),"") -> Sole source with real money at stake and a reachable requalification. Qualify a second supplier, then reopen the price.
A18: =IF(9>MIN(QueueRowsShown,$H$4),"",9) -> 9 | B18: =IFERROR(INDEX(tQueue[PartNumber],MATCH(9,Calc!$C$52:$C$236,0)),"") -> LOM-0009 | C18: =IFERROR(INDEX(tQueue[Category],MATCH(9,Calc!$C$52:$C$236,0)),"") -> Photodetector | D18: =IFERROR(INDEX(tQueue[VendorID],MATCH(9,Calc!$C$52:$C$236,0)),"") -> VEN-020 | E18: =IFERROR(INDEX(tQueue[BuyerName],MATCH(9,Calc!$C$52:$C$236,0)),"") -> Adaeze Okonkwo | F18: =IFERROR(INDEX(tQueue[QualifiedSupplierCount],MATCH(9,Calc!$C$52:$C$236,0)),"") -> 3 | G18: =IFERROR(INDEX(tQueue[BenchmarkErosionPct],MATCH(9,Calc!$C$52:$C$236,0)),"") -> 6.5 | H18: =IFERROR(INDEX(tQueue[ActualErosionPct],MATCH(9,Calc!$C$52:$C$236,0)),"") -> 0.026 | I18: =IFERROR(INDEX(tQueue[ErosionCapturePct],MATCH(9,Calc!$C$52:$C$236,0)),"") -> 0.4 | J18: =IFERROR(INDEX(tQueue[ErosionGapPerUnit],MATCH(9,Calc!$C$52:$C$236,0)),"") -> 72.682 | K18: =IFERROR(INDEX(tQueue[TTMSpend],MATCH(9,Calc!$C$52:$C$236,0)),"") -> 557683.88 | L18: =IFERROR(INDEX(tQueue[AnnualOpportunity],MATCH(9,Calc!$C$52:$C$236,0)),"") -> 93977.83 | M18: =IFERROR(INDEX(tQueue[LeverageScore],MATCH(9,Calc!$C$52:$C$236,0)),"") -> 79 | N18: =IFERROR(INDEX(tQueue[ActionCode],MATCH(9,Calc!$C$52:$C$236,0)),"") -> RENEGOTIATE | O18: =IFERROR(INDEX(tQueue[RecommendedAction],MATCH(9,Calc!$C$52:$C$236,0)),"") -> Renegotiate. A qualified alternative exists, and Lumen is at least 8% of this supplier's revenue. Open with the category erosion benchmark.
A19: =IF(10>MIN(QueueRowsShown,$H$4),"",10) -> 10 | B19: =IFERROR(INDEX(tQueue[PartNumber],MATCH(10,Calc!$C$52:$C$236,0)),"") -> LOM-0106 | C19: =IFERROR(INDEX(tQueue[Category],MATCH(10,Calc!$C$52:$C$236,0)),"") -> Optical Fibre | D19: =IFERROR(INDEX(tQueue[VendorID],MATCH(10,Calc!$C$52:$C$236,0)),"") -> VEN-010 | E19: =IFERROR(INDEX(tQueue[BuyerName],MATCH(10,Calc!$C$52:$C$236,0)),"") -> Johan Lindberg | F19: =IFERROR(INDEX(tQueue[QualifiedSupplierCount],MATCH(10,Calc!$C$52:$C$236,0)),"") -> 1 | G19: =IFERROR(INDEX(tQueue[BenchmarkErosionPct],MATCH(10,Calc!$C$52:$C$236,0)),"") -> 4 | H19: =IFERROR(INDEX(tQueue[ActualErosionPct],MATCH(10,Calc!$C$52:$C$236,0)),"") -> 0.732 | I19: =IFERROR(INDEX(tQueue[ErosionCapturePct],MATCH(10,Calc!$C$52:$C$236,0)),"") -> 18.3 | J19: =IFERROR(INDEX(tQueue[ErosionGapPerUnit],MATCH(10,Calc!$C$52:$C$236,0)),"") -> 4.3014 | K19: =IFERROR(INDEX(tQueue[TTMSpend],MATCH(10,Calc!$C$52:$C$236,0)),"") -> 1096526.6 | L19: =IFERROR(INDEX(tQueue[AnnualOpportunity],MATCH(10,Calc!$C$52:$C$236,0)),"") -> 90892.88 | M19: =IFERROR(INDEX(tQueue[LeverageScore],MATCH(10,Calc!$C$52:$C$236,0)),"") -> 27 | N19: =IFERROR(INDEX(tQueue[ActionCode],MATCH(10,Calc!$C$52:$C$236,0)),"") -> DUAL_SOURCE | O19: =IFERROR(INDEX(tQueue[RecommendedAction],MATCH(10,Calc!$C$52:$C$236,0)),"") -> Sole source with real money at stake and a reachable requalification. Qualify a second supplier, then reopen the price.
A20: =IF(11>MIN(QueueRowsShown,$H$4),"",11) -> 11 | B20: =IFERROR(INDEX(tQueue[PartNumber],MATCH(11,Calc!$C$52:$C$236,0)),"") -> LOM-0120 | C20: =IFERROR(INDEX(tQueue[Category],MATCH(11,Calc!$C$52:$C$236,0)),"") -> Laser Diode | D20: =IFERROR(INDEX(tQueue[VendorID],MATCH(11,Calc!$C$52:$C$236,0)),"") -> VEN-016 | E20: =IFERROR(INDEX(tQueue[BuyerName],MATCH(11,Calc!$C$52:$C$236,0)),"") -> Adaeze Okonkwo | F20: =IFERROR(INDEX(tQueue[QualifiedSupplierCount],MATCH(11,Calc!$C$52:$C$236,0)),"") -> 3 | G20: =IFERROR(INDEX(tQueue[BenchmarkErosionPct],MATCH(11,Calc!$C$52:$C$236,0)),"") -> 8 | H20: =IFERROR(INDEX(tQueue[ActualErosionPct],MATCH(11,Calc!$C$52:$C$236,0)),"") -> 2.505 | I20: =IFERROR(INDEX(tQueue[ErosionCapturePct],MATCH(11,Calc!$C$52:$C$236,0)),"") -> 31.31 | J20: =IFERROR(INDEX(tQueue[ErosionGapPerUnit],MATCH(11,Calc!$C$52:$C$236,0)),"") -> 126.6776 | K20: =IFERROR(INDEX(tQueue[TTMSpend],MATCH(11,Calc!$C$52:$C$236,0)),"") -> 646871.89 | L20: =IFERROR(INDEX(tQueue[AnnualOpportunity],MATCH(11,Calc!$C$52:$C$236,0)),"") -> 85507.38 | M20: =IFERROR(INDEX(tQueue[LeverageScore],MATCH(11,Calc!$C$52:$C$236,0)),"") -> 77 | N20: =IFERROR(INDEX(tQueue[ActionCode],MATCH(11,Calc!$C$52:$C$236,0)),"") -> RENEGOTIATE | O20: =IFERROR(INDEX(tQueue[RecommendedAction],MATCH(11,Calc!$C$52:$C$236,0)),"") -> Renegotiate. A qualified alternative exists, though Lumen is under 8% of this supplier's revenue. Open with the category erosion benchmark.
A21: =IF(12>MIN(QueueRowsShown,$H$4),"",12) -> 12 | B21: =IFERROR(INDEX(tQueue[PartNumber],MATCH(12,Calc!$C$52:$C$236,0)),"") -> LOM-0123 | C21: =IFERROR(INDEX(tQueue[Category],MATCH(12,Calc!$C$52:$C$236,0)),"") -> Lens Assembly | D21: =IFERROR(INDEX(tQueue[VendorID],MATCH(12,Calc!$C$52:$C$236,0)),"") -> VEN-008 | E21: =IFERROR(INDEX(tQueue[BuyerName],MATCH(12,Calc!$C$52:$C$236,0)),"") -> Mei-Ling Chow | F21: =IFERROR(INDEX(tQueue[QualifiedSupplierCount],MATCH(12,Calc!$C$52:$C$236,0)),"") -> 3 | G21: =IFERROR(INDEX(tQueue[BenchmarkErosionPct],MATCH(12,Calc!$C$52:$C$236,0)),"") -> 3 | H21: =IFERROR(INDEX(tQueue[ActualErosionPct],MATCH(12,Calc!$C$52:$C$236,0)),"") -> -5.388 | I21: =IFERROR(INDEX(tQueue[ErosionCapturePct],MATCH(12,Calc!$C$52:$C$236,0)),"") -> -179.6 | J21: =IFERROR(INDEX(tQueue[ErosionGapPerUnit],MATCH(12,Calc!$C$52:$C$236,0)),"") -> 50.417 | K21: =IFERROR(INDEX(tQueue[TTMSpend],MATCH(12,Calc!$C$52:$C$236,0)),"") -> 410583.38 | L21: =IFERROR(INDEX(tQueue[AnnualOpportunity],MATCH(12,Calc!$C$52:$C$236,0)),"") -> 78045.54 | M21: =IFERROR(INDEX(tQueue[LeverageScore],MATCH(12,Calc!$C$52:$C$236,0)),"") -> 61 | N21: =IFERROR(INDEX(tQueue[ActionCode],MATCH(12,Calc!$C$52:$C$236,0)),"") -> PUT_ON_CONTRACT | O21: =IFERROR(INDEX(tQueue[RecommendedAction],MATCH(12,Calc!$C$52:$C$236,0)),"") -> Most of this spend has no agreement in force. Put it under contract before attempting to negotiate a price against nothing.
A22: =IF(13>MIN(QueueRowsShown,$H$4),"",13) -> 13 | B22: =IFERROR(INDEX(tQueue[PartNumber],MATCH(13,Calc!$C$52:$C$236,0)),"") -> LOM-0134 | C22: =IFERROR(INDEX(tQueue[Category],MATCH(13,Calc!$C$52:$C$236,0)),"") -> Fibre Connector | D22: =IFERROR(INDEX(tQueue[VendorID],MATCH(13,Calc!$C$52:$C$236,0)),"") -> VEN-010 | E22: =IFERROR(INDEX(tQueue[BuyerName],MATCH(13,Calc!$C$52:$C$236,0)),"") -> Johan Lindberg | F22: =IFERROR(INDEX(tQueue[QualifiedSupplierCount],MATCH(13,Calc!$C$52:$C$236,0)),"") -> 1 | G22: =IFERROR(INDEX(tQueue[BenchmarkErosionPct],MATCH(13,Calc!$C$52:$C$236,0)),"") -> 7 | H22: =IFERROR(INDEX(tQueue[ActualErosionPct],MATCH(13,Calc!$C$52:$C$236,0)),"") -> -0.256 | I22: =IFERROR(INDEX(tQueue[ErosionCapturePct],MATCH(13,Calc!$C$52:$C$236,0)),"") -> -3.66 | J22: =IFERROR(INDEX(tQueue[ErosionGapPerUnit],MATCH(13,Calc!$C$52:$C$236,0)),"") -> 7.5997 | K22: =IFERROR(INDEX(tQueue[TTMSpend],MATCH(13,Calc!$C$52:$C$236,0)),"") -> 375755.12 | L22: =IFERROR(INDEX(tQueue[AnnualOpportunity],MATCH(13,Calc!$C$52:$C$236,0)),"") -> 72706.7 | M22: =IFERROR(INDEX(tQueue[LeverageScore],MATCH(13,Calc!$C$52:$C$236,0)),"") -> 27 | N22: =IFERROR(INDEX(tQueue[ActionCode],MATCH(13,Calc!$C$52:$C$236,0)),"") -> DUAL_SOURCE | O22: =IFERROR(INDEX(tQueue[RecommendedAction],MATCH(13,Calc!$C$52:$C$236,0)),"") -> Sole source with real money at stake and a reachable requalification. Qualify a second supplier, then reopen the price.
A23: =IF(14>MIN(QueueRowsShown,$H$4),"",14) -> 14 | B23: =IFERROR(INDEX(tQueue[PartNumber],MATCH(14,Calc!$C$52:$C$236,0)),"") -> LOM-0098 | C23: =IFERROR(INDEX(tQueue[Category],MATCH(14,Calc!$C$52:$C$236,0)),"") -> Optical Fibre | D23: =IFERROR(INDEX(tQueue[VendorID],MATCH(14,Calc!$C$52:$C$236,0)),"") -> VEN-028 | E23: =IFERROR(INDEX(tQueue[BuyerName],MATCH(14,Calc!$C$52:$C$236,0)),"") -> Mei-Ling Chow | F23: =IFERROR(INDEX(tQueue[QualifiedSupplierCount],MATCH(14,Calc!$C$52:$C$236,0)),"") -> 3 | G23: =IFERROR(INDEX(tQueue[BenchmarkErosionPct],MATCH(14,Calc!$C$52:$C$236,0)),"") -> 4 | H23: =IFERROR(INDEX(tQueue[ActualErosionPct],MATCH(14,Calc!$C$52:$C$236,0)),"") -> 0.466 | I23: =IFERROR(INDEX(tQueue[ErosionCapturePct],MATCH(14,Calc!$C$52:$C$236,0)),"") -> 11.65 | J23: =IFERROR(INDEX(tQueue[ErosionGapPerUnit],MATCH(14,Calc!$C$52:$C$236,0)),"") -> 3.7052 | K23: =IFERROR(INDEX(tQueue[TTMSpend],MATCH(14,Calc!$C$52:$C$236,0)),"") -> 739415.54 | L23: =IFERROR(INDEX(tQueue[AnnualOpportunity],MATCH(14,Calc!$C$52:$C$236,0)),"") -> 66048.73 | M23: =IFERROR(INDEX(tQueue[LeverageScore],MATCH(14,Calc!$C$52:$C$236,0)),"") -> 90 | N23: =IFERROR(INDEX(tQueue[ActionCode],MATCH(14,Calc!$C$52:$C$236,0)),"") -> PUT_ON_CONTRACT | O23: =IFERROR(INDEX(tQueue[RecommendedAction],MATCH(14,Calc!$C$52:$C$236,0)),"") -> Most of this spend has no agreement in force. Put it under contract before attempting to negotiate a price against nothing.
A24: =IF(15>MIN(QueueRowsShown,$H$4),"",15) -> 15 | B24: =IFERROR(INDEX(tQueue[PartNumber],MATCH(15,Calc!$C$52:$C$236,0)),"") -> LOM-0074 | C24: =IFERROR(INDEX(tQueue[Category],MATCH(15,Calc!$C$52:$C$236,0)),"") -> Optical Fibre | D24: =IFERROR(INDEX(tQueue[VendorID],MATCH(15,Calc!$C$52:$C$236,0)),"") -> VEN-027 | E24: =IFERROR(INDEX(tQueue[BuyerName],MATCH(15,Calc!$C$52:$C$236,0)),"") -> Johan Lindberg | F24: =IFERROR(INDEX(tQueue[QualifiedSupplierCount],MATCH(15,Calc!$C$52:$C$236,0)),"") -> 1 | G24: =IFERROR(INDEX(tQueue[BenchmarkErosionPct],MATCH(15,Calc!$C$52:$C$236,0)),"") -> 4 | H24: =IFERROR(INDEX(tQueue[ActualErosionPct],MATCH(15,Calc!$C$52:$C$236,0)),"") -> 0.166 | I24: =IFERROR(INDEX(tQueue[ErosionCapturePct],MATCH(15,Calc!$C$52:$C$236,0)),"") -> 4.15 | J24: =IFERROR(INDEX(tQueue[ErosionGapPerUnit],MATCH(15,Calc!$C$52:$C$236,0)),"") -> 3.2367 | K24: =IFERROR(INDEX(tQueue[TTMSpend],MATCH(15,Calc!$C$52:$C$236,0)),"") -> 667640.96 | L24: =IFERROR(INDEX(tQueue[AnnualOpportunity],MATCH(15,Calc!$C$52:$C$236,0)),"") -> 64044.58 | M24: =IFERROR(INDEX(tQueue[LeverageScore],MATCH(15,Calc!$C$52:$C$236,0)),"") -> 36 | N24: =IFERROR(INDEX(tQueue[ActionCode],MATCH(15,Calc!$C$52:$C$236,0)),"") -> DUAL_SOURCE | O24: =IFERROR(INDEX(tQueue[RecommendedAction],MATCH(15,Calc!$C$52:$C$236,0)),"") -> Sole source with real money at stake and a reachable requalification. Qualify a second supplier, then reopen the price.
A25: =IF(16>MIN(QueueRowsShown,$H$4),"",16) -> 16 | B25: =IFERROR(INDEX(tQueue[PartNumber],MATCH(16,Calc!$C$52:$C$236,0)),"") -> LOM-0016 | C25: =IFERROR(INDEX(tQueue[Category],MATCH(16,Calc!$C$52:$C$236,0)),"") -> Laser Diode | D25: =IFERROR(INDEX(tQueue[VendorID],MATCH(16,Calc!$C$52:$C$236,0)),"") -> VEN-017 | E25: =IFERROR(INDEX(tQueue[BuyerName],MATCH(16,Calc!$C$52:$C$236,0)),"") -> Adaeze Okonkwo | F25: =IFERROR(INDEX(tQueue[QualifiedSupplierCount],MATCH(16,Calc!$C$52:$C$236,0)),"") -> 1 | G25: =IFERROR(INDEX(tQueue[BenchmarkErosionPct],MATCH(16,Calc!$C$52:$C$236,0)),"") -> 8 | H25: =IFERROR(INDEX(tQueue[ActualErosionPct],MATCH(16,Calc!$C$52:$C$236,0)),"") -> 0.142 | I25: =IFERROR(INDEX(tQueue[ErosionCapturePct],MATCH(16,Calc!$C$52:$C$236,0)),"") -> 1.78 | J25: =IFERROR(INDEX(tQueue[ErosionGapPerUnit],MATCH(16,Calc!$C$52:$C$236,0)),"") -> 51.8803 | K25: =IFERROR(INDEX(tQueue[TTMSpend],MATCH(16,Calc!$C$52:$C$236,0)),"") -> 341330.3 | L25: =IFERROR(INDEX(tQueue[AnnualOpportunity],MATCH(16,Calc!$C$52:$C$236,0)),"") -> 63760.89 | M25: =IFERROR(INDEX(tQueue[LeverageScore],MATCH(16,Calc!$C$52:$C$236,0)),"") -> 36 | N25: =IFERROR(INDEX(tQueue[ActionCode],MATCH(16,Calc!$C$52:$C$236,0)),"") -> DUAL_SOURCE | O25: =IFERROR(INDEX(tQueue[RecommendedAction],MATCH(16,Calc!$C$52:$C$236,0)),"") -> Sole source with real money at stake and a reachable requalification. Qualify a second supplier, then reopen the price.
A26: =IF(17>MIN(QueueRowsShown,$H$4),"",17) -> 17 | B26: =IFERROR(INDEX(tQueue[PartNumber],MATCH(17,Calc!$C$52:$C$236,0)),"") -> LOM-0097 | C26: =IFERROR(INDEX(tQueue[Category],MATCH(17,Calc!$C$52:$C$236,0)),"") -> Photodetector | D26: =IFERROR(INDEX(tQueue[VendorID],MATCH(17,Calc!$C$52:$C$236,0)),"") -> VEN-014 | E26: =IFERROR(INDEX(tQueue[BuyerName],MATCH(17,Calc!$C$52:$C$236,0)),"") -> Adaeze Okonkwo | F26: =IFERROR(INDEX(tQueue[QualifiedSupplierCount],MATCH(17,Calc!$C$52:$C$236,0)),"") -> 3 | G26: =IFERROR(INDEX(tQueue[BenchmarkErosionPct],MATCH(17,Calc!$C$52:$C$236,0)),"") -> 6.5 | H26: =IFERROR(INDEX(tQueue[ActualErosionPct],MATCH(17,Calc!$C$52:$C$236,0)),"") -> 2.137 | I26: =IFERROR(INDEX(tQueue[ErosionCapturePct],MATCH(17,Calc!$C$52:$C$236,0)),"") -> 32.88 | J26: =IFERROR(INDEX(tQueue[ErosionGapPerUnit],MATCH(17,Calc!$C$52:$C$236,0)),"") -> 52.6555 | K26: =IFERROR(INDEX(tQueue[TTMSpend],MATCH(17,Calc!$C$52:$C$236,0)),"") -> 548805.62 | L26: =IFERROR(INDEX(tQueue[AnnualOpportunity],MATCH(17,Calc!$C$52:$C$236,0)),"") -> 61764.9 | M26: =IFERROR(INDEX(tQueue[LeverageScore],MATCH(17,Calc!$C$52:$C$236,0)),"") -> 70 | N26: =IFERROR(INDEX(tQueue[ActionCode],MATCH(17,Calc!$C$52:$C$236,0)),"") -> RENEGOTIATE | O26: =IFERROR(INDEX(tQueue[RecommendedAction],MATCH(17,Calc!$C$52:$C$236,0)),"") -> Renegotiate. A qualified alternative exists, though Lumen is under 8% of this supplier's revenue. Open with the category erosion benchmark.
A27: =IF(18>MIN(QueueRowsShown,$H$4),"",18) -> 18 | B27: =IFERROR(INDEX(tQueue[PartNumber],MATCH(18,Calc!$C$52:$C$236,0)),"") -> LOM-0043 | C27: =IFERROR(INDEX(tQueue[Category],MATCH(18,Calc!$C$52:$C$236,0)),"") -> Lens Assembly | D27: =IFERROR(INDEX(tQueue[VendorID],MATCH(18,Calc!$C$52:$C$236,0)),"") -> VEN-029 | E27: =IFERROR(INDEX(tQueue[BuyerName],MATCH(18,Calc!$C$52:$C$236,0)),"") -> Johan Lindberg | F27: =IFERROR(INDEX(tQueue[QualifiedSupplierCount],MATCH(18,Calc!$C$52:$C$236,0)),"") -> 1 | G27: =IFERROR(INDEX(tQueue[BenchmarkErosionPct],MATCH(18,Calc!$C$52:$C$236,0)),"") -> 3 | H27: =IFERROR(INDEX(tQueue[ActualErosionPct],MATCH(18,Calc!$C$52:$C$236,0)),"") -> -3.536 | I27: =IFERROR(INDEX(tQueue[ErosionCapturePct],MATCH(18,Calc!$C$52:$C$236,0)),"") -> -117.87 | J27: =IFERROR(INDEX(tQueue[ErosionGapPerUnit],MATCH(18,Calc!$C$52:$C$236,0)),"") -> 51.3169 | K27: =IFERROR(INDEX(tQueue[TTMSpend],MATCH(18,Calc!$C$52:$C$236,0)),"") -> 378324.53 | L27: =IFERROR(INDEX(tQueue[AnnualOpportunity],MATCH(18,Calc!$C$52:$C$236,0)),"") -> 61734.18 | M27: =IFERROR(INDEX(tQueue[LeverageScore],MATCH(18,Calc!$C$52:$C$236,0)),"") -> 64 | N27: =IFERROR(INDEX(tQueue[ActionCode],MATCH(18,Calc!$C$52:$C$236,0)),"") -> PUT_ON_CONTRACT | O27: =IFERROR(INDEX(tQueue[RecommendedAction],MATCH(18,Calc!$C$52:$C$236,0)),"") -> Most of this spend has no agreement in force. Put it under contract before attempting to negotiate a price against nothing.
A28: =IF(19>MIN(QueueRowsShown,$H$4),"",19) -> 19 | B28: =IFERROR(INDEX(tQueue[PartNumber],MATCH(19,Calc!$C$52:$C$236,0)),"") -> LOM-0001 | C28: =IFERROR(INDEX(tQueue[Category],MATCH(19,Calc!$C$52:$C$236,0)),"") -> Photodetector | D28: =IFERROR(INDEX(tQueue[VendorID],MATCH(19,Calc!$C$52:$C$236,0)),"") -> VEN-015 | E28: =IFERROR(INDEX(tQueue[BuyerName],MATCH(19,Calc!$C$52:$C$236,0)),"") -> Rafael Duarte | F28: =IFERROR(INDEX(tQueue[QualifiedSupplierCount],MATCH(19,Calc!$C$52:$C$236,0)),"") -> 1 | G28: =IFERROR(INDEX(tQueue[BenchmarkErosionPct],MATCH(19,Calc!$C$52:$C$236,0)),"") -> 6.5 | H28: =IFERROR(INDEX(tQueue[ActualErosionPct],MATCH(19,Calc!$C$52:$C$236,0)),"") -> 0.538 | I28: =IFERROR(INDEX(tQueue[ErosionCapturePct],MATCH(19,Calc!$C$52:$C$236,0)),"") -> 8.28 | J28: =IFERROR(INDEX(tQueue[ErosionGapPerUnit],MATCH(19,Calc!$C$52:$C$236,0)),"") -> 54.52 | K28: =IFERROR(INDEX(tQueue[TTMSpend],MATCH(19,Calc!$C$52:$C$236,0)),"") -> 403455.27 | L28: =IFERROR(INDEX(tQueue[AnnualOpportunity],MATCH(19,Calc!$C$52:$C$236,0)),"") -> 60462.65 | M28: =IFERROR(INDEX(tQueue[LeverageScore],MATCH(19,Calc!$C$52:$C$236,0)),"") -> 23 | N28: =IFERROR(INDEX(tQueue[ActionCode],MATCH(19,Calc!$C$52:$C$236,0)),"") -> PUT_ON_CONTRACT | O28: =IFERROR(INDEX(tQueue[RecommendedAction],MATCH(19,Calc!$C$52:$C$236,0)),"") -> Most of this spend has no agreement in force. Put it under contract before attempting to negotiate a price against nothing.
A29: =IF(20>MIN(QueueRowsShown,$H$4),"",20) -> 20 | B29: =IFERROR(INDEX(tQueue[PartNumber],MATCH(20,Calc!$C$52:$C$236,0)),"") -> LOM-0034 | C29: =IFERROR(INDEX(tQueue[Category],MATCH(20,Calc!$C$52:$C$236,0)),"") -> Optical Fibre | D29: =IFERROR(INDEX(tQueue[VendorID],MATCH(20,Calc!$C$52:$C$236,0)),"") -> VEN-016 | E29: =IFERROR(INDEX(tQueue[BuyerName],MATCH(20,Calc!$C$52:$C$236,0)),"") -> Mei-Ling Chow | F29: =IFERROR(INDEX(tQueue[QualifiedSupplierCount],MATCH(20,Calc!$C$52:$C$236,0)),"") -> 2 | G29: =IFERROR(INDEX(tQueue[BenchmarkErosionPct],MATCH(20,Calc!$C$52:$C$236,0)),"") -> 4 | H29: =IFERROR(INDEX(tQueue[ActualErosionPct],MATCH(20,Calc!$C$52:$C$236,0)),"") -> 1.024 | I29: =IFERROR(INDEX(tQueue[ErosionCapturePct],MATCH(20,Calc!$C$52:$C$236,0)),"") -> 25.6 | J29: =IFERROR(INDEX(tQueue[ErosionGapPerUnit],MATCH(20,Calc!$C$52:$C$236,0)),"") -> 3.5834 | K29: =IFERROR(INDEX(tQueue[TTMSpend],MATCH(20,Calc!$C$52:$C$236,0)),"") -> 742352.47 | L29: =IFERROR(INDEX(tQueue[AnnualOpportunity],MATCH(20,Calc!$C$52:$C$236,0)),"") -> 54657.48 | M29: =IFERROR(INDEX(tQueue[LeverageScore],MATCH(20,Calc!$C$52:$C$236,0)),"") -> 47 | N29: =IFERROR(INDEX(tQueue[ActionCode],MATCH(20,Calc!$C$52:$C$236,0)),"") -> PUT_ON_CONTRACT | O29: =IFERROR(INDEX(tQueue[RecommendedAction],MATCH(20,Calc!$C$52:$C$236,0)),"") -> Most of this spend has no agreement in force. Put it under contract before attempting to negotiate a price against nothing.
A30: =IF(21>MIN(QueueRowsShown,$H$4),"",21) -> 21 | B30: =IFERROR(INDEX(tQueue[PartNumber],MATCH(21,Calc!$C$52:$C$236,0)),"") -> LOM-0048 | C30: =IFERROR(INDEX(tQueue[Category],MATCH(21,Calc!$C$52:$C$236,0)),"") -> Laser Diode | D30: =IFERROR(INDEX(tQueue[VendorID],MATCH(21,Calc!$C$52:$C$236,0)),"") -> VEN-014 | E30: =IFERROR(INDEX(tQueue[BuyerName],MATCH(21,Calc!$C$52:$C$236,0)),"") -> Rafael Duarte | F30: =IFERROR(INDEX(tQueue[QualifiedSupplierCount],MATCH(21,Calc!$C$52:$C$236,0)),"") -> 3 | G30: =IFERROR(INDEX(tQueue[BenchmarkErosionPct],MATCH(21,Calc!$C$52:$C$236,0)),"") -> 8 | H30: =IFERROR(INDEX(tQueue[ActualErosionPct],MATCH(21,Calc!$C$52:$C$236,0)),"") -> -0.085 | I30: =IFERROR(INDEX(tQueue[ErosionCapturePct],MATCH(21,Calc!$C$52:$C$236,0)),"") -> -1.06 | J30: =IFERROR(INDEX(tQueue[ErosionGapPerUnit],MATCH(21,Calc!$C$52:$C$236,0)),"") -> 160.3057 | K30: =IFERROR(INDEX(tQueue[TTMSpend],MATCH(21,Calc!$C$52:$C$236,0)),"") -> 241053.34 | L30: =IFERROR(INDEX(tQueue[AnnualOpportunity],MATCH(21,Calc!$C$52:$C$236,0)),"") -> 49855.09 | M30: =IFERROR(INDEX(tQueue[LeverageScore],MATCH(21,Calc!$C$52:$C$236,0)),"") -> 74 | N30: =IFERROR(INDEX(tQueue[ActionCode],MATCH(21,Calc!$C$52:$C$236,0)),"") -> PUT_ON_CONTRACT | O30: =IFERROR(INDEX(tQueue[RecommendedAction],MATCH(21,Calc!$C$52:$C$236,0)),"") -> Most of this spend has no agreement in force. Put it under contract before attempting to negotiate a price against nothing.
A31: =IF(22>MIN(QueueRowsShown,$H$4),"",22) -> 22 | B31: =IFERROR(INDEX(tQueue[PartNumber],MATCH(22,Calc!$C$52:$C$236,0)),"") -> LOM-0125 | C31: =IFERROR(INDEX(tQueue[Category],MATCH(22,Calc!$C$52:$C$236,0)),"") -> Precision Mount | D31: =IFERROR(INDEX(tQueue[VendorID],MATCH(22,Calc!$C$52:$C$236,0)),"") -> VEN-009 | E31: =IFERROR(INDEX(tQueue[BuyerName],MATCH(22,Calc!$C$52:$C$236,0)),"") -> Priya Raghunathan | F31: =IFERROR(INDEX(tQueue[QualifiedSupplierCount],MATCH(22,Calc!$C$52:$C$236,0)),"") -> 2 | G31: =IFERROR(INDEX(tQueue[BenchmarkErosionPct],MATCH(22,Calc!$C$52:$C$236,0)),"") -> 2 | H31: =IFERROR(INDEX(tQueue[ActualErosionPct],MATCH(22,Calc!$C$52:$C$236,0)),"") -> -6.799 | I31: =IFERROR(INDEX(tQueue[ErosionCapturePct],MATCH(22,Calc!$C$52:$C$236,0)),"") -> -339.95 | J31: =IFERROR(INDEX(tQueue[ErosionGapPerUnit],MATCH(22,Calc!$C$52:$C$236,0)),"") -> 46.8777 | K31: =IFERROR(INDEX(tQueue[TTMSpend],MATCH(22,Calc!$C$52:$C$236,0)),"") -> 235463.37 | L31: =IFERROR(INDEX(tQueue[AnnualOpportunity],MATCH(22,Calc!$C$52:$C$236,0)),"") -> 48846.59 | M31: =IFERROR(INDEX(tQueue[LeverageScore],MATCH(22,Calc!$C$52:$C$236,0)),"") -> 76 | N31: =IFERROR(INDEX(tQueue[ActionCode],MATCH(22,Calc!$C$52:$C$236,0)),"") -> PUT_ON_CONTRACT | O31: =IFERROR(INDEX(tQueue[RecommendedAction],MATCH(22,Calc!$C$52:$C$236,0)),"") -> Most of this spend has no agreement in force. Put it under contract before attempting to negotiate a price against nothing.
A32: =IF(23>MIN(QueueRowsShown,$H$4),"",23) -> 23 | B32: =IFERROR(INDEX(tQueue[PartNumber],MATCH(23,Calc!$C$52:$C$236,0)),"") -> LOM-0083 | C32: =IFERROR(INDEX(tQueue[Category],MATCH(23,Calc!$C$52:$C$236,0)),"") -> Lens Assembly | D32: =IFERROR(INDEX(tQueue[VendorID],MATCH(23,Calc!$C$52:$C$236,0)),"") -> VEN-003 | E32: =IFERROR(INDEX(tQueue[BuyerName],MATCH(23,Calc!$C$52:$C$236,0)),"") -> Johan Lindberg | F32: =IFERROR(INDEX(tQueue[QualifiedSupplierCount],MATCH(23,Calc!$C$52:$C$236,0)),"") -> 1 | G32: =IFERROR(INDEX(tQueue[BenchmarkErosionPct],MATCH(23,Calc!$C$52:$C$236,0)),"") -> 3 | H32: =IFERROR(INDEX(tQueue[ActualErosionPct],MATCH(23,Calc!$C$52:$C$236,0)),"") -> -0.147 | I32: =IFERROR(INDEX(tQueue[ErosionCapturePct],MATCH(23,Calc!$C$52:$C$236,0)),"") -> -4.9 | J32: =IFERROR(INDEX(tQueue[ErosionGapPerUnit],MATCH(23,Calc!$C$52:$C$236,0)),"") -> 28.7023 | K32: =IFERROR(INDEX(tQueue[TTMSpend],MATCH(23,Calc!$C$52:$C$236,0)),"") -> 550211.7 | L32: =IFERROR(INDEX(tQueue[AnnualOpportunity],MATCH(23,Calc!$C$52:$C$236,0)),"") -> 43570.09 | M32: =IFERROR(INDEX(tQueue[LeverageScore],MATCH(23,Calc!$C$52:$C$236,0)),"") -> 19 | N32: =IFERROR(INDEX(tQueue[ActionCode],MATCH(23,Calc!$C$52:$C$236,0)),"") -> DUAL_SOURCE | O32: =IFERROR(INDEX(tQueue[RecommendedAction],MATCH(23,Calc!$C$52:$C$236,0)),"") -> Sole source with real money at stake and a reachable requalification. Qualify a second supplier, then reopen the price.
A33: =IF(24>MIN(QueueRowsShown,$H$4),"",24) -> 24 | B33: =IFERROR(INDEX(tQueue[PartNumber],MATCH(24,Calc!$C$52:$C$236,0)),"") -> LOM-0042 | C33: =IFERROR(INDEX(tQueue[Category],MATCH(24,Calc!$C$52:$C$236,0)),"") -> Optical Fibre | D33: =IFERROR(INDEX(tQueue[VendorID],MATCH(24,Calc!$C$52:$C$236,0)),"") -> VEN-032 | E33: =IFERROR(INDEX(tQueue[BuyerName],MATCH(24,Calc!$C$52:$C$236,0)),"") -> Mei-Ling Chow | F33: =IFERROR(INDEX(tQueue[QualifiedSupplierCount],MATCH(24,Calc!$C$52:$C$236,0)),"") -> 1 | G33: =IFERROR(INDEX(tQueue[BenchmarkErosionPct],MATCH(24,Calc!$C$52:$C$236,0)),"") -> 4 | H33: =IFERROR(INDEX(tQueue[ActualErosionPct],MATCH(24,Calc!$C$52:$C$236,0)),"") -> 1.633 | I33: =IFERROR(INDEX(tQueue[ErosionCapturePct],MATCH(24,Calc!$C$52:$C$236,0)),"") -> 40.83 | J33: =IFERROR(INDEX(tQueue[ErosionGapPerUnit],MATCH(24,Calc!$C$52:$C$236,0)),"") -> 3.6684 | K33: =IFERROR(INDEX(tQueue[TTMSpend],MATCH(24,Calc!$C$52:$C$236,0)),"") -> 660641.39 | L33: =IFERROR(INDEX(tQueue[AnnualOpportunity],MATCH(24,Calc!$C$52:$C$236,0)),"") -> 42377.36 | M33: =IFERROR(INDEX(tQueue[LeverageScore],MATCH(24,Calc!$C$52:$C$236,0)),"") -> 46 | N33: =IFERROR(INDEX(tQueue[ActionCode],MATCH(24,Calc!$C$52:$C$236,0)),"") -> DUAL_SOURCE | O33: =IFERROR(INDEX(tQueue[RecommendedAction],MATCH(24,Calc!$C$52:$C$236,0)),"") -> Sole source with real money at stake and a reachable requalification. Qualify a second supplier, then reopen the price.
A34: =IF(25>MIN(QueueRowsShown,$H$4),"",25) -> 25 | B34: =IFERROR(INDEX(tQueue[PartNumber],MATCH(25,Calc!$C$52:$C$236,0)),"") -> LOM-0086 | C34: =IFERROR(INDEX(tQueue[Category],MATCH(25,Calc!$C$52:$C$236,0)),"") -> Fibre Connector | D34: =IFERROR(INDEX(tQueue[VendorID],MATCH(25,Calc!$C$52:$C$236,0)),"") -> VEN-004 | E34: =IFERROR(INDEX(tQueue[BuyerName],MATCH(25,Calc!$C$52:$C$236,0)),"") -> Mei-Ling Chow | F34: =IFERROR(INDEX(tQueue[QualifiedSupplierCount],MATCH(25,Calc!$C$52:$C$236,0)),"") -> 1 | G34: =IFERROR(INDEX(tQueue[BenchmarkErosionPct],MATCH(25,Calc!$C$52:$C$236,0)),"") -> 7 | H34: =IFERROR(INDEX(tQueue[ActualErosionPct],MATCH(25,Calc!$C$52:$C$236,0)),"") -> 0.603 | I34: =IFERROR(INDEX(tQueue[ErosionCapturePct],MATCH(25,Calc!$C$52:$C$236,0)),"") -> 8.61 | J34: =IFERROR(INDEX(tQueue[ErosionGapPerUnit],MATCH(25,Calc!$C$52:$C$236,0)),"") -> 4.9134 | K34: =IFERROR(INDEX(tQueue[TTMSpend],MATCH(25,Calc!$C$52:$C$236,0)),"") -> 264990.97 | L34: =IFERROR(INDEX(tQueue[AnnualOpportunity],MATCH(25,Calc!$C$52:$C$236,0)),"") -> 41537.77 | M34: =IFERROR(INDEX(tQueue[LeverageScore],MATCH(25,Calc!$C$52:$C$236,0)),"") -> 19 | N34: =IFERROR(INDEX(tQueue[ActionCode],MATCH(25,Calc!$C$52:$C$236,0)),"") -> DUAL_SOURCE | O34: =IFERROR(INDEX(tQueue[RecommendedAction],MATCH(25,Calc!$C$52:$C$236,0)),"") -> Sole source with real money at stake and a reachable requalification. Qualify a second supplier, then reopen the price.

Sheet Vendor Scorecard
A1: VENDOR SCORECARD
A2: Cost index compares each vendor with the cheapest cost per ACCEPTED unit on the same parts, so 100 is the best available and 108 is eight per cent dearer per usable part. Unit price alone cannot show this.
A4: Vendor | B4: Name | C4: Tier | D4: Spend (12m) | E4: Our share of their revenue % | F4: On contract % | G4: Acceptance % | H4: Rejected value | I4: On-time % | J4: Cost index vs best | K4: Shared parts | L4: Read
A5: =IFERROR(INDEX(tVendor[VendorID],1),"") -> VEN-008 | B5: =IFERROR(INDEX(tVendor[VendorName],1),"") -> Meridian Photonics GmbH | C5: =IFERROR(INDEX(tVendor[VendorTier],1),"") -> Preferred | D5: =IFERROR(INDEX(tVendor[TotalSpend],1),"") -> 8518594 | E5: =IFERROR(INDEX(tVendor[LumenRevenueSharePct],1),"") -> 5.01 | F5: =IFERROR(INDEX(tVendor[OnContractPct],1),"") -> 87.9 | G5: =IFERROR(INDEX(tVendor[AcceptanceRatePct],1),"") -> 99.13 | H5: =IFERROR(INDEX(tVendor[RejectedValue],1),"") -> 81655.48 | I5: =IFERROR(INDEX(tVendor[OnTimePct],1),"") -> 81.11 | J5: =IFERROR(INDEX(tVendor[CostIndexVsBest],1),"") -> 104.42 | K5: =IFERROR(INDEX(tVendor[SharedParts],1),"") -> 14 | L5: =IF(J5="","",IF(J5>105,"Dearer per usable part than the best alternative",IF(G5<97,"Quality is the problem, not price","Competitive"))) -> Competitive
A6: =IFERROR(INDEX(tVendor[VendorID],2),"") -> VEN-010 | B6: =IFERROR(INDEX(tVendor[VendorName],2),"") -> Vectra GmbH | C6: =IFERROR(INDEX(tVendor[VendorTier],2),"") -> Preferred | D6: =IFERROR(INDEX(tVendor[TotalSpend],2),"") -> 8098186.8 | E6: =IFERROR(INDEX(tVendor[LumenRevenueSharePct],2),"") -> 5.43 | F6: =IFERROR(INDEX(tVendor[OnContractPct],2),"") -> 89.75 | G6: =IFERROR(INDEX(tVendor[AcceptanceRatePct],2),"") -> 99.2 | H6: =IFERROR(INDEX(tVendor[RejectedValue],2),"") -> 62897.76 | I6: =IFERROR(INDEX(tVendor[OnTimePct],2),"") -> 81.84 | J6: =IFERROR(INDEX(tVendor[CostIndexVsBest],2),"") -> 101.77 | K6: =IFERROR(INDEX(tVendor[SharedParts],2),"") -> 10 | L6: =IF(J6="","",IF(J6>105,"Dearer per usable part than the best alternative",IF(G6<97,"Quality is the problem, not price","Competitive"))) -> Competitive
A7: =IFERROR(INDEX(tVendor[VendorID],3),"") -> VEN-016 | B7: =IFERROR(INDEX(tVendor[VendorName],3),"") -> Spectra Industries | C7: =IFERROR(INDEX(tVendor[VendorTier],3),"") -> Preferred | D7: =IFERROR(INDEX(tVendor[TotalSpend],3),"") -> 7562968.4 | E7: =IFERROR(INDEX(tVendor[LumenRevenueSharePct],3),"") -> 7.82 | F7: =IFERROR(INDEX(tVendor[OnContractPct],3),"") -> 79.49 | G7: =IFERROR(INDEX(tVendor[AcceptanceRatePct],3),"") -> 99.13 | H7: =IFERROR(INDEX(tVendor[RejectedValue],3),"") -> 77381.04 | I7: =IFERROR(INDEX(tVendor[OnTimePct],3),"") -> 77.95 | J7: =IFERROR(INDEX(tVendor[CostIndexVsBest],3),"") -> 100.8 | K7: =IFERROR(INDEX(tVendor[SharedParts],3),"") -> 11 | L7: =IF(J7="","",IF(J7>105,"Dearer per usable part than the best alternative",IF(G7<97,"Quality is the problem, not price","Competitive"))) -> Competitive
A8: =IFERROR(INDEX(tVendor[VendorID],4),"") -> VEN-032 | B8: =IFERROR(INDEX(tVendor[VendorName],4),"") -> Meridian Photonics Technologies | C8: =IFERROR(INDEX(tVendor[VendorTier],4),"") -> Transactional | D8: =IFERROR(INDEX(tVendor[TotalSpend],4),"") -> 7188922.6 | E8: =IFERROR(INDEX(tVendor[LumenRevenueSharePct],4),"") -> 28.3 | F8: =IFERROR(INDEX(tVendor[OnContractPct],4),"") -> 93.87 | G8: =IFERROR(INDEX(tVendor[AcceptanceRatePct],4),"") -> 99.28 | H8: =IFERROR(INDEX(tVendor[RejectedValue],4),"") -> 56967.13 | I8: =IFERROR(INDEX(tVendor[OnTimePct],4),"") -> 86.19 | J8: =IFERROR(INDEX(tVendor[CostIndexVsBest],4),"") -> 101.04 | K8: =IFERROR(INDEX(tVendor[SharedParts],4),"") -> 6 | L8: =IF(J8="","",IF(J8>105,"Dearer per usable part than the best alternative",IF(G8<97,"Quality is the problem, not price","Competitive"))) -> Competitive
A9: =IFERROR(INDEX(tVendor[VendorID],5),"") -> VEN-014 | B9: =IFERROR(INDEX(tVendor[VendorName],5),"") -> Photonica Industries | C9: =IFERROR(INDEX(tVendor[VendorTier],5),"") -> Preferred | D9: =IFERROR(INDEX(tVendor[TotalSpend],5),"") -> 6776342.2 | E9: =IFERROR(INDEX(tVendor[LumenRevenueSharePct],5),"") -> 4.81 | F9: =IFERROR(INDEX(tVendor[OnContractPct],5),"") -> 83.68 | G9: =IFERROR(INDEX(tVendor[AcceptanceRatePct],5),"") -> 99.15 | H9: =IFERROR(INDEX(tVendor[RejectedValue],5),"") -> 54049.22 | I9: =IFERROR(INDEX(tVendor[OnTimePct],5),"") -> 84.48 | J9: =IFERROR(INDEX(tVendor[CostIndexVsBest],5),"") -> 104.15 | K9: =IFERROR(INDEX(tVendor[SharedParts],5),"") -> 13 | L9: =IF(J9="","",IF(J9>105,"Dearer per usable part than the best alternative",IF(G9<97,"Quality is the problem, not price","Competitive"))) -> Competitive
A10: =IFERROR(INDEX(tVendor[VendorID],6),"") -> VEN-005 | B10: =IFERROR(INDEX(tVendor[VendorName],6),"") -> Helix Optics GmbH | C10: =IFERROR(INDEX(tVendor[VendorTier],6),"") -> Strategic | D10: =IFERROR(INDEX(tVendor[TotalSpend],6),"") -> 6535276.6 | E10: =IFERROR(INDEX(tVendor[LumenRevenueSharePct],6),"") -> 1.75 | F10: =IFERROR(INDEX(tVendor[OnContractPct],6),"") -> 80.07 | G10: =IFERROR(INDEX(tVendor[AcceptanceRatePct],6),"") -> 99.15 | H10: =IFERROR(INDEX(tVendor[RejectedValue],6),"") -> 60207.61 | I10: =IFERROR(INDEX(tVendor[OnTimePct],6),"") -> 84.25 | J10: =IFERROR(INDEX(tVendor[CostIndexVsBest],6),"") -> 101.57 | K10: =IFERROR(INDEX(tVendor[SharedParts],6),"") -> 11 | L10: =IF(J10="","",IF(J10>105,"Dearer per usable part than the best alternative",IF(G10<97,"Quality is the problem, not price","Competitive"))) -> Competitive
A11: =IFERROR(INDEX(tVendor[VendorID],7),"") -> VEN-003 | B11: =IFERROR(INDEX(tVendor[VendorName],7),"") -> Crystalline GmbH | C11: =IFERROR(INDEX(tVendor[VendorTier],7),"") -> Strategic | D11: =IFERROR(INDEX(tVendor[TotalSpend],7),"") -> 5774441.6 | E11: =IFERROR(INDEX(tVendor[LumenRevenueSharePct],7),"") -> 3.69 | F11: =IFERROR(INDEX(tVendor[OnContractPct],7),"") -> 74.79 | G11: =IFERROR(INDEX(tVendor[AcceptanceRatePct],7),"") -> 99.03 | H11: =IFERROR(INDEX(tVendor[RejectedValue],7),"") -> 60006.31 | I11: =IFERROR(INDEX(tVendor[OnTimePct],7),"") -> 82.17 | J11: =IFERROR(INDEX(tVendor[CostIndexVsBest],7),"") -> 102.13 | K11: =IFERROR(INDEX(tVendor[SharedParts],7),"") -> 6 | L11: =IF(J11="","",IF(J11>105,"Dearer per usable part than the best alternative",IF(G11<97,"Quality is the problem, not price","Competitive"))) -> Competitive
A12: =IFERROR(INDEX(tVendor[VendorID],8),"") -> VEN-031 | B12: =IFERROR(INDEX(tVendor[VendorName],8),"") -> Quantex Technologies | C12: =IFERROR(INDEX(tVendor[VendorTier],8),"") -> Transactional | D12: =IFERROR(INDEX(tVendor[TotalSpend],8),"") -> 5598522.4 | E12: =IFERROR(INDEX(tVendor[LumenRevenueSharePct],8),"") -> 14.93 | F12: =IFERROR(INDEX(tVendor[OnContractPct],8),"") -> 88.76 | G12: =IFERROR(INDEX(tVendor[AcceptanceRatePct],8),"") -> 99.18 | H12: =IFERROR(INDEX(tVendor[RejectedValue],8),"") -> 52890.82 | I12: =IFERROR(INDEX(tVendor[OnTimePct],8),"") -> 84.27 | J12: =IFERROR(INDEX(tVendor[CostIndexVsBest],8),"") -> 105.59 | K12: =IFERROR(INDEX(tVendor[SharedParts],8),"") -> 14 | L12: =IF(J12="","",IF(J12>105,"Dearer per usable part than the best alternative",IF(G12<97,"Quality is the problem, not price","Competitive"))) -> Dearer per usable part than the best alternative
A13: =IFERROR(INDEX(tVendor[VendorID],9),"") -> VEN-023 | B13: =IFERROR(INDEX(tVendor[VendorName],9),"") -> Kestrel Optical Industries | C13: =IFERROR(INDEX(tVendor[VendorTier],9),"") -> Approved | D13: =IFERROR(INDEX(tVendor[TotalSpend],9),"") -> 5429746.9 | E13: =IFERROR(INDEX(tVendor[LumenRevenueSharePct],9),"") -> 6.75 | F13: =IFERROR(INDEX(tVendor[OnContractPct],9),"") -> 85.53 | G13: =IFERROR(INDEX(tVendor[AcceptanceRatePct],9),"") -> 99.23 | H13: =IFERROR(INDEX(tVendor[RejectedValue],9),"") -> 47208.63 | I13: =IFERROR(INDEX(tVendor[OnTimePct],9),"") -> 76.43 | J13: =IFERROR(INDEX(tVendor[CostIndexVsBest],9),"") -> 108.5 | K13: =IFERROR(INDEX(tVendor[SharedParts],9),"") -> 10 | L13: =IF(J13="","",IF(J13>105,"Dearer per usable part than the best alternative",IF(G13<97,"Quality is the problem, not price","Competitive"))) -> Dearer per usable part than the best alternative
A14: =IFERROR(INDEX(tVendor[VendorID],10),"") -> VEN-020 | B14: =IFERROR(INDEX(tVendor[VendorName],10),"") -> Meridian Photonics Industries | C14: =IFERROR(INDEX(tVendor[VendorTier],10),"") -> Approved | D14: =IFERROR(INDEX(tVendor[TotalSpend],10),"") -> 5336318.3 | E14: =IFERROR(INDEX(tVendor[LumenRevenueSharePct],10),"") -> 12.07 | F14: =IFERROR(INDEX(tVendor[OnContractPct],10),"") -> 98.44 | G14: =IFERROR(INDEX(tVendor[AcceptanceRatePct],10),"") -> 99.2 | H14: =IFERROR(INDEX(tVendor[RejectedValue],10),"") -> 41513.03 | I14: =IFERROR(INDEX(tVendor[OnTimePct],10),"") -> 80.32 | J14: =IFERROR(INDEX(tVendor[CostIndexVsBest],10),"") -> 104.12 | K14: =IFERROR(INDEX(tVendor[SharedParts],10),"") -> 11 | L14: =IF(J14="","",IF(J14>105,"Dearer per usable part than the best alternative",IF(G14<97,"Quality is the problem, not price","Competitive"))) -> Competitive
A15: =IFERROR(INDEX(tVendor[VendorID],11),"") -> VEN-028 | B15: =IFERROR(INDEX(tVendor[VendorName],11),"") -> Spectra Technologies | C15: =IFERROR(INDEX(tVendor[VendorTier],11),"") -> Approved | D15: =IFERROR(INDEX(tVendor[TotalSpend],11),"") -> 5082227.7 | E15: =IFERROR(INDEX(tVendor[LumenRevenueSharePct],11),"") -> 8.62 | F15: =IFERROR(INDEX(tVendor[OnContractPct],11),"") -> 85.71 | G15: =IFERROR(INDEX(tVendor[AcceptanceRatePct],11),"") -> 99.18 | H15: =IFERROR(INDEX(tVendor[RejectedValue],11),"") -> 38312.96 | I15: =IFERROR(INDEX(tVendor[OnTimePct],11),"") -> 79.8 | J15: =IFERROR(INDEX(tVendor[CostIndexVsBest],11),"") -> 105.42 | K15: =IFERROR(INDEX(tVendor[SharedParts],11),"") -> 10 | L15: =IF(J15="","",IF(J15>105,"Dearer per usable part than the best alternative",IF(G15<97,"Quality is the problem, not price","Competitive"))) -> Dearer per usable part than the best alternative
A16: =IFERROR(INDEX(tVendor[VendorID],12),"") -> VEN-004 | B16: =IFERROR(INDEX(tVendor[VendorName],12),"") -> Spectra GmbH | C16: =IFERROR(INDEX(tVendor[VendorTier],12),"") -> Strategic | D16: =IFERROR(INDEX(tVendor[TotalSpend],12),"") -> 4712776.1 | E16: =IFERROR(INDEX(tVendor[LumenRevenueSharePct],12),"") -> 1.51 | F16: =IFERROR(INDEX(tVendor[OnContractPct],12),"") -> 81.43 | G16: =IFERROR(INDEX(tVendor[AcceptanceRatePct],12),"") -> 98.33 | H16: =IFERROR(INDEX(tVendor[RejectedValue],12),"") -> 289024.27 | I16: =IFERROR(INDEX(tVendor[OnTimePct],12),"") -> 83.94 | J16: =IFERROR(INDEX(tVendor[CostIndexVsBest],12),"") -> 100.23 | K16: =IFERROR(INDEX(tVendor[SharedParts],12),"") -> 5 | L16: =IF(J16="","",IF(J16>105,"Dearer per usable part than the best alternative",IF(G16<97,"Quality is the problem, not price","Competitive"))) -> Competitive
A17: =IFERROR(INDEX(tVendor[VendorID],13),"") -> VEN-007 | B17: =IFERROR(INDEX(tVendor[VendorName],13),"") -> Quantex GmbH | C17: =IFERROR(INDEX(tVendor[VendorTier],13),"") -> Preferred | D17: =IFERROR(INDEX(tVendor[TotalSpend],13),"") -> 4232747.9 | E17: =IFERROR(INDEX(tVendor[LumenRevenueSharePct],13),"") -> 10.21 | F17: =IFERROR(INDEX(tVendor[OnContractPct],13),"") -> 93.24 | G17: =IFERROR(INDEX(tVendor[AcceptanceRatePct],13),"") -> 99.09 | H17: =IFERROR(INDEX(tVendor[RejectedValue],13),"") -> 37788.82 | I17: =IFERROR(INDEX(tVendor[OnTimePct],13),"") -> 84.8 | J17: =IFERROR(INDEX(tVendor[CostIndexVsBest],13),"") -> 103.4 | K17: =IFERROR(INDEX(tVendor[SharedParts],13),"") -> 9 | L17: =IF(J17="","",IF(J17>105,"Dearer per usable part than the best alternative",IF(G17<97,"Quality is the problem, not price","Competitive"))) -> Competitive
A18: =IFERROR(INDEX(tVendor[VendorID],14),"") -> VEN-017 | B18: =IFERROR(INDEX(tVendor[VendorName],14),"") -> Helix Optics Industries | C18: =IFERROR(INDEX(tVendor[VendorTier],14),"") -> Approved | D18: =IFERROR(INDEX(tVendor[TotalSpend],14),"") -> 4074084.9 | E18: =IFERROR(INDEX(tVendor[LumenRevenueSharePct],14),"") -> 10.21 | F18: =IFERROR(INDEX(tVendor[OnContractPct],14),"") -> 93.52 | G18: =IFERROR(INDEX(tVendor[AcceptanceRatePct],14),"") -> 99.13 | H18: =IFERROR(INDEX(tVendor[RejectedValue],14),"") -> 39904.83 | I18: =IFERROR(INDEX(tVendor[OnTimePct],14),"") -> 78.95 | J18: =IFERROR(INDEX(tVendor[CostIndexVsBest],14),"") -> 101.58 | K18: =IFERROR(INDEX(tVendor[SharedParts],14),"") -> 4 | L18: =IF(J18="","",IF(J18>105,"Dearer per usable part than the best alternative",IF(G18<97,"Quality is the problem, not price","Competitive"))) -> Competitive
A19: =IFERROR(INDEX(tVendor[VendorID],15),"") -> VEN-009 | B19: =IFERROR(INDEX(tVendor[VendorName],15),"") -> Oribel GmbH | C19: =IFERROR(INDEX(tVendor[VendorTier],15),"") -> Preferred | D19: =IFERROR(INDEX(tVendor[TotalSpend],15),"") -> 4072508.9 | E19: =IFERROR(INDEX(tVendor[LumenRevenueSharePct],15),"") -> 9.47 | F19: =IFERROR(INDEX(tVendor[OnContractPct],15),"") -> 71.3 | G19: =IFERROR(INDEX(tVendor[AcceptanceRatePct],15),"") -> 98.88 | H19: =IFERROR(INDEX(tVendor[RejectedValue],15),"") -> 46617.13 | I19: =IFERROR(INDEX(tVendor[OnTimePct],15),"") -> 59.64 | J19: =IFERROR(INDEX(tVendor[CostIndexVsBest],15),"") -> 103.99 | K19: =IFERROR(INDEX(tVendor[SharedParts],15),"") -> 10 | L19: =IF(J19="","",IF(J19>105,"Dearer per usable part than the best alternative",IF(G19<97,"Quality is the problem, not price","Competitive"))) -> Competitive
A20: =IFERROR(INDEX(tVendor[VendorID],16),"") -> VEN-011 | B20: =IFERROR(INDEX(tVendor[VendorName],16),"") -> Kestrel Optical GmbH | C20: =IFERROR(INDEX(tVendor[VendorTier],16),"") -> Preferred | D20: =IFERROR(INDEX(tVendor[TotalSpend],16),"") -> 3942976 | E20: =IFERROR(INDEX(tVendor[LumenRevenueSharePct],16),"") -> 3.73 | F20: =IFERROR(INDEX(tVendor[OnContractPct],16),"") -> 66.67 | G20: =IFERROR(INDEX(tVendor[AcceptanceRatePct],16),"") -> 99.17 | H20: =IFERROR(INDEX(tVendor[RejectedValue],16),"") -> 37088.25 | I20: =IFERROR(INDEX(tVendor[OnTimePct],16),"") -> 82.35 | J20: =IFERROR(INDEX(tVendor[CostIndexVsBest],16),"") -> 101.98 | K20: =IFERROR(INDEX(tVendor[SharedParts],16),"") -> 5 | L20: =IF(J20="","",IF(J20>105,"Dearer per usable part than the best alternative",IF(G20<97,"Quality is the problem, not price","Competitive"))) -> Competitive
A21: =IFERROR(INDEX(tVendor[VendorID],17),"") -> VEN-029 | B21: =IFERROR(INDEX(tVendor[VendorName],17),"") -> Helix Optics Technologies | C21: =IFERROR(INDEX(tVendor[VendorTier],17),"") -> Transactional | D21: =IFERROR(INDEX(tVendor[TotalSpend],17),"") -> 3860779 | E21: =IFERROR(INDEX(tVendor[LumenRevenueSharePct],17),"") -> 36.48 | F21: =IFERROR(INDEX(tVendor[OnContractPct],17),"") -> 88.07 | G21: =IFERROR(INDEX(tVendor[AcceptanceRatePct],17),"") -> 98.76 | H21: =IFERROR(INDEX(tVendor[RejectedValue],17),"") -> 47507.28 | I21: =IFERROR(INDEX(tVendor[OnTimePct],17),"") -> 81.5 | J21: =IFERROR(INDEX(tVendor[CostIndexVsBest],17),"") -> 100.94 | K21: =IFERROR(INDEX(tVendor[SharedParts],17),"") -> 7 | L21: =IF(J21="","",IF(J21>105,"Dearer per usable part than the best alternative",IF(G21<97,"Quality is the problem, not price","Competitive"))) -> Competitive
A22: =IFERROR(INDEX(tVendor[VendorID],18),"") -> VEN-015 | B22: =IFERROR(INDEX(tVendor[VendorName],18),"") -> Crystalline Industries | C22: =IFERROR(INDEX(tVendor[VendorTier],18),"") -> Preferred | D22: =IFERROR(INDEX(tVendor[TotalSpend],18),"") -> 3849672.2 | E22: =IFERROR(INDEX(tVendor[LumenRevenueSharePct],18),"") -> 3.57 | F22: =IFERROR(INDEX(tVendor[OnContractPct],18),"") -> 66.67 | G22: =IFERROR(INDEX(tVendor[AcceptanceRatePct],18),"") -> 99.17 | H22: =IFERROR(INDEX(tVendor[RejectedValue],18),"") -> 31122.44 | I22: =IFERROR(INDEX(tVendor[OnTimePct],18),"") -> 81.08 | J22: =IFERROR(INDEX(tVendor[CostIndexVsBest],18),"") -> 108.71 | K22: =IFERROR(INDEX(tVendor[SharedParts],18),"") -> 6 | L22: =IF(J22="","",IF(J22>105,"Dearer per usable part than the best alternative",IF(G22<97,"Quality is the problem, not price","Competitive"))) -> Dearer per usable part than the best alternative
A23: =IFERROR(INDEX(tVendor[VendorID],19),"") -> VEN-006 | B23: =IFERROR(INDEX(tVendor[VendorName],19),"") -> Northlight GmbH | C23: =IFERROR(INDEX(tVendor[VendorTier],19),"") -> Strategic | D23: =IFERROR(INDEX(tVendor[TotalSpend],19),"") -> 3718821.1 | E23: =IFERROR(INDEX(tVendor[LumenRevenueSharePct],19),"") -> 4.77 | F23: =IFERROR(INDEX(tVendor[OnContractPct],19),"") -> 93.65 | G23: =IFERROR(INDEX(tVendor[AcceptanceRatePct],19),"") -> 99.06 | H23: =IFERROR(INDEX(tVendor[RejectedValue],19),"") -> 44321.59 | I23: =IFERROR(INDEX(tVendor[OnTimePct],19),"") -> 83.51 | J23: =IFERROR(INDEX(tVendor[CostIndexVsBest],19),"") -> 101.43 | K23: =IFERROR(INDEX(tVendor[SharedParts],19),"") -> 8 | L23: =IF(J23="","",IF(J23>105,"Dearer per usable part than the best alternative",IF(G23<97,"Quality is the problem, not price","Competitive"))) -> Competitive
A24: =IFERROR(INDEX(tVendor[VendorID],20),"") -> VEN-019 | B24: =IFERROR(INDEX(tVendor[VendorName],20),"") -> Quantex Industries | C24: =IFERROR(INDEX(tVendor[VendorTier],20),"") -> Approved | D24: =IFERROR(INDEX(tVendor[TotalSpend],20),"") -> 3376415 | E24: =IFERROR(INDEX(tVendor[LumenRevenueSharePct],20),"") -> 16 | F24: =IFERROR(INDEX(tVendor[OnContractPct],20),"") -> 78.62 | G24: =IFERROR(INDEX(tVendor[AcceptanceRatePct],20),"") -> 98.86 | H24: =IFERROR(INDEX(tVendor[RejectedValue],20),"") -> 34364.03 | I24: =IFERROR(INDEX(tVendor[OnTimePct],20),"") -> 76.92 | J24: =IFERROR(INDEX(tVendor[CostIndexVsBest],20),"") -> 101.9 | K24: =IFERROR(INDEX(tVendor[SharedParts],20),"") -> 6 | L24: =IF(J24="","",IF(J24>105,"Dearer per usable part than the best alternative",IF(G24<97,"Quality is the problem, not price","Competitive"))) -> Competitive
A25: =IFERROR(INDEX(tVendor[VendorID],21),"") -> VEN-002 | B25: =IFERROR(INDEX(tVendor[VendorName],21),"") -> Photonica GmbH | C25: =IFERROR(INDEX(tVendor[VendorTier],21),"") -> Strategic | D25: =IFERROR(INDEX(tVendor[TotalSpend],21),"") -> 3168434 | E25: =IFERROR(INDEX(tVendor[LumenRevenueSharePct],21),"") -> 2.49 | F25: =IFERROR(INDEX(tVendor[OnContractPct],21),"") -> 49.06 | G25: =IFERROR(INDEX(tVendor[AcceptanceRatePct],21),"") -> 98.96 | H25: =IFERROR(INDEX(tVendor[RejectedValue],21),"") -> 27294.97 | I25: =IFERROR(INDEX(tVendor[OnTimePct],21),"") -> 85.29 | J25: =IFERROR(INDEX(tVendor[CostIndexVsBest],21),"") -> 103.08 | K25: =IFERROR(INDEX(tVendor[SharedParts],21),"") -> 4 | L25: =IF(J25="","",IF(J25>105,"Dearer per usable part than the best alternative",IF(G25<97,"Quality is the problem, not price","Competitive"))) -> Competitive
A26: =IFERROR(INDEX(tVendor[VendorID],22),"") -> VEN-034 | B26: =IFERROR(INDEX(tVendor[VendorName],22),"") -> Vectra Technologies | C26: =IFERROR(INDEX(tVendor[VendorTier],22),"") -> Transactional | D26: =IFERROR(INDEX(tVendor[TotalSpend],22),"") -> 3147306.5 | E26: =IFERROR(INDEX(tVendor[LumenRevenueSharePct],22),"") -> 34.49 | F26: =IFERROR(INDEX(tVendor[OnContractPct],22),"") -> 97.62 | G26: =IFERROR(INDEX(tVendor[AcceptanceRatePct],22),"") -> 99.04 | H26: =IFERROR(INDEX(tVendor[RejectedValue],22),"") -> 33523.61 | I26: =IFERROR(INDEX(tVendor[OnTimePct],22),"") -> 82.13 | J26: =IFERROR(INDEX(tVendor[CostIndexVsBest],22),"") -> 102.94 | K26: =IFERROR(INDEX(tVendor[SharedParts],22),"") -> 9 | L26: =IF(J26="","",IF(J26>105,"Dearer per usable part than the best alternative",IF(G26<97,"Quality is the problem, not price","Competitive"))) -> Competitive
A27: =IFERROR(INDEX(tVendor[VendorID],23),"") -> VEN-026 | B27: =IFERROR(INDEX(tVendor[VendorName],23),"") -> Photonica Technologies | C27: =IFERROR(INDEX(tVendor[VendorTier],23),"") -> Approved | D27: =IFERROR(INDEX(tVendor[TotalSpend],23),"") -> 3122969 | E27: =IFERROR(INDEX(tVendor[LumenRevenueSharePct],23),"") -> 9.22 | F27: =IFERROR(INDEX(tVendor[OnContractPct],23),"") -> 58.55 | G27: =IFERROR(INDEX(tVendor[AcceptanceRatePct],23),"") -> 99.16 | H27: =IFERROR(INDEX(tVendor[RejectedValue],23),"") -> 28359.02 | I27: =IFERROR(INDEX(tVendor[OnTimePct],23),"") -> 86.67 | J27: =IFERROR(INDEX(tVendor[CostIndexVsBest],23),"") -> 104.32 | K27: =IFERROR(INDEX(tVendor[SharedParts],23),"") -> 12 | L27: =IF(J27="","",IF(J27>105,"Dearer per usable part than the best alternative",IF(G27<97,"Quality is the problem, not price","Competitive"))) -> Competitive
A28: =IFERROR(INDEX(tVendor[VendorID],24),"") -> VEN-022 | B28: =IFERROR(INDEX(tVendor[VendorName],24),"") -> Vectra Industries | C28: =IFERROR(INDEX(tVendor[VendorTier],24),"") -> Approved | D28: =IFERROR(INDEX(tVendor[TotalSpend],24),"") -> 2991524.2 | E28: =IFERROR(INDEX(tVendor[LumenRevenueSharePct],24),"") -> 12.65 | F28: =IFERROR(INDEX(tVendor[OnContractPct],24),"") -> 92.98 | G28: =IFERROR(INDEX(tVendor[AcceptanceRatePct],24),"") -> 98.84 | H28: =IFERROR(INDEX(tVendor[RejectedValue],24),"") -> 28958.92 | I28: =IFERROR(INDEX(tVendor[OnTimePct],24),"") -> 86.75 | J28: =IFERROR(INDEX(tVendor[CostIndexVsBest],24),"") -> 102.72 | K28: =IFERROR(INDEX(tVendor[SharedParts],24),"") -> 11 | L28: =IF(J28="","",IF(J28>105,"Dearer per usable part than the best alternative",IF(G28<97,"Quality is the problem, not price","Competitive"))) -> Competitive
A29: =IFERROR(INDEX(tVendor[VendorID],25),"") -> VEN-033 | B29: =IFERROR(INDEX(tVendor[VendorName],25),"") -> Oribel Technologies | C29: =IFERROR(INDEX(tVendor[VendorTier],25),"") -> Transactional | D29: =IFERROR(INDEX(tVendor[TotalSpend],25),"") -> 2972739.4 | E29: =IFERROR(INDEX(tVendor[LumenRevenueSharePct],25),"") -> 17.66 | F29: =IFERROR(INDEX(tVendor[OnContractPct],25),"") -> 53.85 | G29: =IFERROR(INDEX(tVendor[AcceptanceRatePct],25),"") -> 99.05 | H29: =IFERROR(INDEX(tVendor[RejectedValue],25),"") -> 26321.09 | I29: =IFERROR(INDEX(tVendor[OnTimePct],25),"") -> 80.26 | J29: =IFERROR(INDEX(tVendor[CostIndexVsBest],25),"") -> 101.68 | K29: =IFERROR(INDEX(tVendor[SharedParts],25),"") -> 8 | L29: =IF(J29="","",IF(J29>105,"Dearer per usable part than the best alternative",IF(G29<97,"Quality is the problem, not price","Competitive"))) -> Competitive
A30: =IFERROR(INDEX(tVendor[VendorID],26),"") -> VEN-013 | B30: =IFERROR(INDEX(tVendor[VendorName],26),"") -> Lumitek Industries | C30: =IFERROR(INDEX(tVendor[VendorTier],26),"") -> Preferred | D30: =IFERROR(INDEX(tVendor[TotalSpend],26),"") -> 2846030.6 | E30: =IFERROR(INDEX(tVendor[LumenRevenueSharePct],26),"") -> 9.15 | F30: =IFERROR(INDEX(tVendor[OnContractPct],26),"") -> 79.27 | G30: =IFERROR(INDEX(tVendor[AcceptanceRatePct],26),"") -> 99.17 | H30: =IFERROR(INDEX(tVendor[RejectedValue],26),"") -> 26707.16 | I30: =IFERROR(INDEX(tVendor[OnTimePct],26),"") -> 88.61 | J30: =IFERROR(INDEX(tVendor[CostIndexVsBest],26),"") -> 104.41 | K30: =IFERROR(INDEX(tVendor[SharedParts],26),"") -> 6 | L30: =IF(J30="","",IF(J30>105,"Dearer per usable part than the best alternative",IF(G30<97,"Quality is the problem, not price","Competitive"))) -> Competitive
A31: =IFERROR(INDEX(tVendor[VendorID],27),"") -> VEN-018 | B31: =IFERROR(INDEX(tVendor[VendorName],27),"") -> Northlight Industries | C31: =IFERROR(INDEX(tVendor[VendorTier],27),"") -> Approved | D31: =IFERROR(INDEX(tVendor[TotalSpend],27),"") -> 2708008.8 | E31: =IFERROR(INDEX(tVendor[LumenRevenueSharePct],27),"") -> 17.17 | F31: =IFERROR(INDEX(tVendor[OnContractPct],27),"") -> 98.31 | G31: =IFERROR(INDEX(tVendor[AcceptanceRatePct],27),"") -> 99 | H31: =IFERROR(INDEX(tVendor[RejectedValue],27),"") -> 25979.26 | I31: =IFERROR(INDEX(tVendor[OnTimePct],27),"") -> 85.09 | J31: =IFERROR(INDEX(tVendor[CostIndexVsBest],27),"") -> 104.45 | K31: =IFERROR(INDEX(tVendor[SharedParts],27),"") -> 8 | L31: =IF(J31="","",IF(J31>105,"Dearer per usable part than the best alternative",IF(G31<97,"Quality is the problem, not price","Competitive"))) -> Competitive
A32: =IFERROR(INDEX(tVendor[VendorID],28),"") -> VEN-001 | B32: =IFERROR(INDEX(tVendor[VendorName],28),"") -> Lumitek GmbH | C32: =IFERROR(INDEX(tVendor[VendorTier],28),"") -> Strategic | D32: =IFERROR(INDEX(tVendor[TotalSpend],28),"") -> 2610446.9 | E32: =IFERROR(INDEX(tVendor[LumenRevenueSharePct],28),"") -> 1.37 | F32: =IFERROR(INDEX(tVendor[OnContractPct],28),"") -> 94.34 | G32: =IFERROR(INDEX(tVendor[AcceptanceRatePct],28),"") -> 99.04 | H32: =IFERROR(INDEX(tVendor[RejectedValue],28),"") -> 26356.41 | I32: =IFERROR(INDEX(tVendor[OnTimePct],28),"") -> 81.94 | J32: =IFERROR(INDEX(tVendor[CostIndexVsBest],28),"") -> 101.86 | K32: =IFERROR(INDEX(tVendor[SharedParts],28),"") -> 8 | L32: =IF(J32="","",IF(J32>105,"Dearer per usable part than the best alternative",IF(G32<97,"Quality is the problem, not price","Competitive"))) -> Competitive
A33: =IFERROR(INDEX(tVendor[VendorID],29),"") -> VEN-027 | B33: =IFERROR(INDEX(tVendor[VendorName],29),"") -> Crystalline Technologies | C33: =IFERROR(INDEX(tVendor[VendorTier],29),"") -> Approved | D33: =IFERROR(INDEX(tVendor[TotalSpend],29),"") -> 2420353 | E33: =IFERROR(INDEX(tVendor[LumenRevenueSharePct],29),"") -> 14.24 | F33: =IFERROR(INDEX(tVendor[OnContractPct],29),"") -> 100 | G33: =IFERROR(INDEX(tVendor[AcceptanceRatePct],29),"") -> 99.33 | H33: =IFERROR(INDEX(tVendor[RejectedValue],29),"") -> 16227.01 | I33: =IFERROR(INDEX(tVendor[OnTimePct],29),"") -> 86.08 | J33: =IFERROR(INDEX(tVendor[CostIndexVsBest],29),"") -> 100.03 | K33: =IFERROR(INDEX(tVendor[SharedParts],29),"") -> 2 | L33: =IF(J33="","",IF(J33>105,"Dearer per usable part than the best alternative",IF(G33<97,"Quality is the problem, not price","Competitive"))) -> Competitive
A34: =IFERROR(INDEX(tVendor[VendorID],30),"") -> VEN-012 | B34: =IFERROR(INDEX(tVendor[VendorName],30),"") -> Aperture Industries | C34: =IFERROR(INDEX(tVendor[VendorTier],30),"") -> Preferred | D34: =IFERROR(INDEX(tVendor[TotalSpend],30),"") -> 1932201.8 | E34: =IFERROR(INDEX(tVendor[LumenRevenueSharePct],30),"") -> 4.72 | F34: =IFERROR(INDEX(tVendor[OnContractPct],30),"") -> 72.63 | G34: =IFERROR(INDEX(tVendor[AcceptanceRatePct],30),"") -> 99.03 | H34: =IFERROR(INDEX(tVendor[RejectedValue],30),"") -> 19397.22 | I34: =IFERROR(INDEX(tVendor[OnTimePct],30),"") -> 84.75 | J34: =IFERROR(INDEX(tVendor[CostIndexVsBest],30),"") -> 101.71 | K34: =IFERROR(INDEX(tVendor[SharedParts],30),"") -> 7 | L34: =IF(J34="","",IF(J34>105,"Dearer per usable part than the best alternative",IF(G34<97,"Quality is the problem, not price","Competitive"))) -> Competitive
A35: =IFERROR(INDEX(tVendor[VendorID],31),"") -> VEN-036 | B35: =IFERROR(INDEX(tVendor[VendorName],31),"") -> Aperture Technologies | C35: =IFERROR(INDEX(tVendor[VendorTier],31),"") -> Transactional | D35: =IFERROR(INDEX(tVendor[TotalSpend],31),"") -> 1503596.7 | E35: =IFERROR(INDEX(tVendor[LumenRevenueSharePct],31),"") -> 30.07 | F35: =IFERROR(INDEX(tVendor[OnContractPct],31),"") -> 76.19 | G35: =IFERROR(INDEX(tVendor[AcceptanceRatePct],31),"") -> 98.51 | H35: =IFERROR(INDEX(tVendor[RejectedValue],31),"") -> 21548.24 | I35: =IFERROR(INDEX(tVendor[OnTimePct],31),"") -> 85 | J35: =IFERROR(INDEX(tVendor[CostIndexVsBest],31),"") -> 109.71 | K35: =IFERROR(INDEX(tVendor[SharedParts],31),"") -> 3 | L35: =IF(J35="","",IF(J35>105,"Dearer per usable part than the best alternative",IF(G35<97,"Quality is the problem, not price","Competitive"))) -> Dearer per usable part than the best alternative
A36: =IFERROR(INDEX(tVendor[VendorID],32),"") -> VEN-024 | B36: =IFERROR(INDEX(tVendor[VendorName],32),"") -> Aperture Technologies | C36: =IFERROR(INDEX(tVendor[VendorTier],32),"") -> Approved | D36: =IFERROR(INDEX(tVendor[TotalSpend],32),"") -> 1469457 | E36: =IFERROR(INDEX(tVendor[LumenRevenueSharePct],32),"") -> 18.36 | F36: =IFERROR(INDEX(tVendor[OnContractPct],32),"") -> 100 | G36: =IFERROR(INDEX(tVendor[AcceptanceRatePct],32),"") -> 98.8 | H36: =IFERROR(INDEX(tVendor[RejectedValue],32),"") -> 16471.86 | I36: =IFERROR(INDEX(tVendor[OnTimePct],32),"") -> 78.65 | J36: =IFERROR(INDEX(tVendor[CostIndexVsBest],32),"") -> 100.07 | K36: =IFERROR(INDEX(tVendor[SharedParts],32),"") -> 5 | L36: =IF(J36="","",IF(J36>105,"Dearer per usable part than the best alternative",IF(G36<97,"Quality is the problem, not price","Competitive"))) -> Competitive
A37: =IFERROR(INDEX(tVendor[VendorID],33),"") -> VEN-035 | B37: =IFERROR(INDEX(tVendor[VendorName],33),"") -> Kestrel Optical Technologies | C37: =IFERROR(INDEX(tVendor[VendorTier],33),"") -> Transactional | D37: =IFERROR(INDEX(tVendor[TotalSpend],33),"") -> 1445470.4 | E37: =IFERROR(INDEX(tVendor[LumenRevenueSharePct],33),"") -> 36.86 | F37: =IFERROR(INDEX(tVendor[OnContractPct],33),"") -> 90.18 | G37: =IFERROR(INDEX(tVendor[AcceptanceRatePct],33),"") -> 99.24 | H37: =IFERROR(INDEX(tVendor[RejectedValue],33),"") -> 10359.57 | I37: =IFERROR(INDEX(tVendor[OnTimePct],33),"") -> 86.11 | J37: =IFERROR(INDEX(tVendor[CostIndexVsBest],33),"") -> 101.74 | K37: =IFERROR(INDEX(tVendor[SharedParts],33),"") -> 3 | L37: =IF(J37="","",IF(J37>105,"Dearer per usable part than the best alternative",IF(G37<97,"Quality is the problem, not price","Competitive"))) -> Competitive
A38: =IFERROR(INDEX(tVendor[VendorID],34),"") -> VEN-025 | B38: =IFERROR(INDEX(tVendor[VendorName],34),"") -> Lumitek Technologies | C38: =IFERROR(INDEX(tVendor[VendorTier],34),"") -> Approved | D38: =IFERROR(INDEX(tVendor[TotalSpend],34),"") -> 971234.04 | E38: =IFERROR(INDEX(tVendor[LumenRevenueSharePct],34),"") -> 14.26 | F38: =IFERROR(INDEX(tVendor[OnContractPct],34),"") -> 83.05 | G38: =IFERROR(INDEX(tVendor[AcceptanceRatePct],34),"") -> 99.1 | H38: =IFERROR(INDEX(tVendor[RejectedValue],34),"") -> 8851.33 | I38: =IFERROR(INDEX(tVendor[OnTimePct],34),"") -> 84.48 | J38: =IFERROR(INDEX(tVendor[CostIndexVsBest],34),"") -> 102.99 | K38: =IFERROR(INDEX(tVendor[SharedParts],34),"") -> 5 | L38: =IF(J38="","",IF(J38>105,"Dearer per usable part than the best alternative",IF(G38<97,"Quality is the problem, not price","Competitive"))) -> Competitive
A39: =IFERROR(INDEX(tVendor[VendorID],35),"") -> VEN-030 | B39: =IFERROR(INDEX(tVendor[VendorName],35),"") -> Northlight Technologies | C39: =IFERROR(INDEX(tVendor[VendorTier],35),"") -> Transactional | D39: =IFERROR(INDEX(tVendor[TotalSpend],35),"") -> 670517.98 | E39: =IFERROR(INDEX(tVendor[LumenRevenueSharePct],35),"") -> 26.4 | F39: =IFERROR(INDEX(tVendor[OnContractPct],35),"") -> 90.48 | G39: =IFERROR(INDEX(tVendor[AcceptanceRatePct],35),"") -> 98.53 | H39: =IFERROR(INDEX(tVendor[RejectedValue],35),"") -> 9800.57 | I39: =IFERROR(INDEX(tVendor[OnTimePct],35),"") -> 80.95 | J39: =IFERROR(INDEX(tVendor[CostIndexVsBest],35),"") -> 102.51 | K39: =IFERROR(INDEX(tVendor[SharedParts],35),"") -> 3 | L39: =IF(J39="","",IF(J39>105,"Dearer per usable part than the best alternative",IF(G39<97,"Quality is the problem, not price","Competitive"))) -> Competitive
A40: =IFERROR(INDEX(tVendor[VendorID],36),"") -> VEN-021 | B40: =IFERROR(INDEX(tVendor[VendorName],36),"") -> Oribel Industries | C40: =IFERROR(INDEX(tVendor[VendorTier],36),"") -> Approved | D40: =IFERROR(INDEX(tVendor[TotalSpend],36),"") -> 591810.45 | E40: =IFERROR(INDEX(tVendor[LumenRevenueSharePct],36),"") -> 7.24 | F40: =IFERROR(INDEX(tVendor[OnContractPct],36),"") -> 100 | G40: =IFERROR(INDEX(tVendor[AcceptanceRatePct],36),"") -> 99.28 | H40: =IFERROR(INDEX(tVendor[RejectedValue],36),"") -> 4183.17 | I40: =IFERROR(INDEX(tVendor[OnTimePct],36),"") -> 100 | J40: =IFERROR(INDEX(tVendor[CostIndexVsBest],36),"") -> 104.39 | K40: =IFERROR(INDEX(tVendor[SharedParts],36),"") -> 2 | L40: =IF(J40="","",IF(J40>105,"Dearer per usable part than the best alternative",IF(G40<97,"Quality is the problem, not price","Competitive"))) -> Competitive

Sheet Validation
A1: CROSS-IMPLEMENTATION VALIDATION
A2: Each figure below was computed twice: once in T-SQL against the database, once in Excel formulas against the extract. A dashboard that only displays what the database told it cannot detect that the database was wrong.
A4: # | B4: Figure | C4: SQL | D4: Excel | E4: Difference | F4: Result
A5: 1 | B5: Extended price (12 months) | C5: =INDEX(tKPI[TotalSpend],MATCH(MAX(tKPI[AsOfDate]),tKPI[AsOfDate],0)) -> 48586387 | D5: =Dashboard!$C$8 -> 48586387 | E5: =C5-D5 -> 0 | F5: =IF(ABS(E5)<=0.05,"MATCH","DIFFERS") -> MATCH
A6: 2 | B6: Landed cost (12 months) | C6: =INDEX(tKPI[LandedSpend],MATCH(MAX(tKPI[AsOfDate]),tKPI[AsOfDate],0)) -> 49474786 | D6: =Dashboard!$C$9 -> 49474786 | E6: =C6-D6 -> -6.7055225e-08 | F6: =IF(ABS(E6)<=0.05,"MATCH","DIFFERS") -> MATCH
A7: 3 | B7: Erosion capture % | C7: =INDEX(tKPI[ErosionCapturePct],MATCH(MAX(tKPI[AsOfDate]),tKPI[AsOfDate],0)) -> 29.5 | D7: =Dashboard!$B$20 -> 29.499101 | E7: =C7-D7 -> 0.00089901247 | F7: =IF(ABS(E7)<=0.01,"MATCH","DIFFERS") -> MATCH
A8: 4 | B8: Annual erosion opportunity | C8: =INDEX(tKPI[ErosionOpportunity],MATCH(MAX(tKPI[AsOfDate]),tKPI[AsOfDate],0)) -> 4047608.7 | D8: =Dashboard!$G$10 -> 4047608.7 | E8: =C8-D8 -> 0 | F8: =IF(ABS(E8)<=0.05,"MATCH","DIFFERS") -> MATCH
A9: 5 | B9: Maverick spend % | C9: =INDEX(tKPI[MaverickSpendPct],MATCH(MAX(tKPI[AsOfDate]),tKPI[AsOfDate],0)) -> 27.09 | D9: =Dashboard!$B$21 -> 27.08911 | E9: =C9-D9 -> 0.00088955035 | F9: =IF(ABS(E9)<=0.01,"MATCH","DIFFERS") -> MATCH
A10: 6 | B10: Purchase price variance % | C10: =INDEX(tKPI[PPVPct],MATCH(MAX(tKPI[AsOfDate]),tKPI[AsOfDate],0)) -> -0.189 | D10: =Dashboard!$B$22 -> -0.18902298 | E10: =C10-D10 -> 2.297661e-05 | F10: =IF(ABS(E10)<=0.01,"MATCH","DIFFERS") -> MATCH
A11: 7 | B11: Acceptance rate % | C11: =INDEX(tKPI[AcceptanceRatePct],MATCH(MAX(tKPI[AsOfDate]),tKPI[AsOfDate],0)) -> 99.11 | D11: =Dashboard!$B$23 -> 99.113823 | E11: =C11-D11 -> -0.0038227931 | F11: =IF(ABS(E11)<=0.01,"MATCH","DIFFERS") -> MATCH
A12: 8 | B12: On-time delivery % | C12: =INDEX(tKPI[OnTimeDeliveryPct],MATCH(MAX(tKPI[AsOfDate]),tKPI[AsOfDate],0)) -> 80.62 | D12: =Dashboard!$B$24 -> 80.622837 | E12: =C12-D12 -> -0.0028373702 | F12: =IF(ABS(E12)<=0.01,"MATCH","DIFFERS") -> MATCH
A13: 9 | B13: Expedite spend % | C13: =INDEX(tKPI[ExpediteSpendPct],MATCH(MAX(tKPI[AsOfDate]),tKPI[AsOfDate],0)) -> 0.23 | D13: =Dashboard!$B$25 -> 0.22504707 | E13: =C13-D13 -> 0.0049529301 | F13: =IF(ABS(E13)<=0.01,"MATCH","DIFFERS") -> MATCH
A14: 10 | B14: Single-source spend % | C14: =INDEX(tKPI[SingleSourceSpendPct],MATCH(MAX(tKPI[AsOfDate]),tKPI[AsOfDate],0)) -> 27.17 | D14: =Dashboard!$B$26 -> 27.170244 | E14: =C14-D14 -> -0.0002436282 | F14: =IF(ABS(E14)<=0.01,"MATCH","DIFFERS") -> MATCH
A15: 11 | B15: Top-5 vendor share % | C15: =INDEX(tKPI[Top5VendorSharePct],MATCH(MAX(tKPI[AsOfDate]),tKPI[AsOfDate],0)) -> 27.2 | D15: =Dashboard!$B$27 -> 27.198155 | E15: =C15-D15 -> 0.0018449734 | F15: =IF(ABS(E15)<=0.01,"MATCH","DIFFERS") -> MATCH
A16: 12 | B16: Value of rejected material | C16: =INDEX(tKPI[RejectedValue],MATCH(MAX(tKPI[AsOfDate]),tKPI[AsOfDate],0)) -> 498840.71 | D16: =Dashboard!$C$16 -> 498840.71 | E16: =C16-D16 -> 7.5669959e-10 | F16: =IF(ABS(E16)<=0.05,"MATCH","DIFFERS") -> MATCH
A17: 13 | B17: Queue: pairs assessed | C17: =COUNTA(tQueue[PartNumber]) -> 185 | D17: =COUNTA(tErosion[PartNumber]) -> 185 | E17: =C17-D17 -> 0 | F17: =IF(ABS(E17)<=0.5,"MATCH","DIFFERS") -> MATCH
A18: 14 | B18: Queue: total opportunity | C18: =SUM(tQueue[AnnualOpportunity]) -> 4047608.7 | D18: =SUMIF(tErosion[AnnualOpportunity],">0") -> 4047608.7 | E18: =C18-D18 -> 0 | F18: =IF(ABS(E18)<=0.05,"MATCH","DIFFERS") -> MATCH
B20: Checks reconciling | C20: =COUNTIF($F$5:$F$18,"MATCH")&" of "&COUNTA($F$5:$F$18) -> 14 of 14
B21: =IF(COUNTIF($F$5:$F$18,"DIFFERS")=0,"All figures reconcile between the two independent implementations.","RECONCILIATION FAILED -- do not publish these figures.") -> All figures reconcile between the two independent implementations.

Sheet Calc
A1: WORKING -- the twelve-month window, the top-five concentration and the queue ranking
A2: Nothing here is decorative. The Dashboard and the Queue read these cells.
A4: Window opens after | C4: =EOMONTH(AsOfDate,-12) -> 45657
A5: Window closes | C5: =AsOfDate -> 46022
A7: VENDOR SPEND IN THE TWELVE-MONTH WINDOW (the top-five concentration, computed not read)
A8: Vendor | C8: Spend in window
A9: =IFERROR(INDEX(tVendor[VendorID],1),"") -> VEN-008 | C9: =IF($A9="","",SUMIFS(tPO[ExtendedPrice],tPO[VendorID],$A9,tPO[OrderDate],">"&WinFrom,tPO[OrderDate],"<="&WinTo)) -> 3406341.3
A10: =IFERROR(INDEX(tVendor[VendorID],2),"") -> VEN-010 | C10: =IF($A10="","",SUMIFS(tPO[ExtendedPrice],tPO[VendorID],$A10,tPO[OrderDate],">"&WinFrom,tPO[OrderDate],"<="&WinTo)) -> 3004333.2
A11: =IFERROR(INDEX(tVendor[VendorID],3),"") -> VEN-016 | C11: =IF($A11="","",SUMIFS(tPO[ExtendedPrice],tPO[VendorID],$A11,tPO[OrderDate],">"&WinFrom,tPO[OrderDate],"<="&WinTo)) -> 2068684.2
A12: =IFERROR(INDEX(tVendor[VendorID],4),"") -> VEN-032 | C12: =IF($A12="","",SUMIFS(tPO[ExtendedPrice],tPO[VendorID],$A12,tPO[OrderDate],">"&WinFrom,tPO[OrderDate],"<="&WinTo)) -> 2428046.1
A13: =IFERROR(INDEX(tVendor[VendorID],5),"") -> VEN-014 | C13: =IF($A13="","",SUMIFS(tPO[ExtendedPrice],tPO[VendorID],$A13,tPO[OrderDate],">"&WinFrom,tPO[OrderDate],"<="&WinTo)) -> 2247898
A14: =IFERROR(INDEX(tVendor[VendorID],6),"") -> VEN-005 | C14: =IF($A14="","",SUMIFS(tPO[ExtendedPrice],tPO[VendorID],$A14,tPO[OrderDate],">"&WinFrom,tPO[OrderDate],"<="&WinTo)) -> 2124976.6
A15: =IFERROR(INDEX(tVendor[VendorID],7),"") -> VEN-003 | C15: =IF($A15="","",SUMIFS(tPO[ExtendedPrice],tPO[VendorID],$A15,tPO[OrderDate],">"&WinFrom,tPO[OrderDate],"<="&WinTo)) -> 2127982.2
A16: =IFERROR(INDEX(tVendor[VendorID],8),"") -> VEN-031 | C16: =IF($A16="","",SUMIFS(tPO[ExtendedPrice],tPO[VendorID],$A16,tPO[OrderDate],">"&WinFrom,tPO[OrderDate],"<="&WinTo)) -> 2025356.8
A17: =IFERROR(INDEX(tVendor[VendorID],9),"") -> VEN-023 | C17: =IF($A17="","",SUMIFS(tPO[ExtendedPrice],tPO[VendorID],$A17,tPO[OrderDate],">"&WinFrom,tPO[OrderDate],"<="&WinTo)) -> 1861975.4
A18: =IFERROR(INDEX(tVendor[VendorID],10),"") -> VEN-020 | C18: =IF($A18="","",SUMIFS(tPO[ExtendedPrice],tPO[VendorID],$A18,tPO[OrderDate],">"&WinFrom,tPO[OrderDate],"<="&WinTo)) -> 1920190.4
A19: =IFERROR(INDEX(tVendor[VendorID],11),"") -> VEN-028 | C19: =IF($A19="","",SUMIFS(tPO[ExtendedPrice],tPO[VendorID],$A19,tPO[OrderDate],">"&WinFrom,tPO[OrderDate],"<="&WinTo)) -> 1965909.9
A20: =IFERROR(INDEX(tVendor[VendorID],12),"") -> VEN-004 | C20: =IF($A20="","",SUMIFS(tPO[ExtendedPrice],tPO[VendorID],$A20,tPO[OrderDate],">"&WinFrom,tPO[OrderDate],"<="&WinTo)) -> 1632035.6
A21: =IFERROR(INDEX(tVendor[VendorID],13),"") -> VEN-007 | C21: =IF($A21="","",SUMIFS(tPO[ExtendedPrice],tPO[VendorID],$A21,tPO[OrderDate],">"&WinFrom,tPO[OrderDate],"<="&WinTo)) -> 1501484.3
A22: =IFERROR(INDEX(tVendor[VendorID],14),"") -> VEN-017 | C22: =IF($A22="","",SUMIFS(tPO[ExtendedPrice],tPO[VendorID],$A22,tPO[OrderDate],">"&WinFrom,tPO[OrderDate],"<="&WinTo)) -> 1476499.2
A23: =IFERROR(INDEX(tVendor[VendorID],15),"") -> VEN-009 | C23: =IF($A23="","",SUMIFS(tPO[ExtendedPrice],tPO[VendorID],$A23,tPO[OrderDate],">"&WinFrom,tPO[OrderDate],"<="&WinTo)) -> 1255888.7
A24: =IFERROR(INDEX(tVendor[VendorID],16),"") -> VEN-011 | C24: =IF($A24="","",SUMIFS(tPO[ExtendedPrice],tPO[VendorID],$A24,tPO[OrderDate],">"&WinFrom,tPO[OrderDate],"<="&WinTo)) -> 1294496.4
A25: =IFERROR(INDEX(tVendor[VendorID],17),"") -> VEN-029 | C25: =IF($A25="","",SUMIFS(tPO[ExtendedPrice],tPO[VendorID],$A25,tPO[OrderDate],">"&WinFrom,tPO[OrderDate],"<="&WinTo)) -> 1144931.8
A26: =IFERROR(INDEX(tVendor[VendorID],18),"") -> VEN-015 | C26: =IF($A26="","",SUMIFS(tPO[ExtendedPrice],tPO[VendorID],$A26,tPO[OrderDate],">"&WinFrom,tPO[OrderDate],"<="&WinTo)) -> 1554548.1
A27: =IFERROR(INDEX(tVendor[VendorID],19),"") -> VEN-006 | C27: =IF($A27="","",SUMIFS(tPO[ExtendedPrice],tPO[VendorID],$A27,tPO[OrderDate],">"&WinFrom,tPO[OrderDate],"<="&WinTo)) -> 1164628.8
A28: =IFERROR(INDEX(tVendor[VendorID],20),"") -> VEN-019 | C28: =IF($A28="","",SUMIFS(tPO[ExtendedPrice],tPO[VendorID],$A28,tPO[OrderDate],">"&WinFrom,tPO[OrderDate],"<="&WinTo)) -> 882986.48
A29: =IFERROR(INDEX(tVendor[VendorID],21),"") -> VEN-002 | C29: =IF($A29="","",SUMIFS(tPO[ExtendedPrice],tPO[VendorID],$A29,tPO[OrderDate],">"&WinFrom,tPO[OrderDate],"<="&WinTo)) -> 937751.65
A30: =IFERROR(INDEX(tVendor[VendorID],22),"") -> VEN-034 | C30: =IF($A30="","",SUMIFS(tPO[ExtendedPrice],tPO[VendorID],$A30,tPO[OrderDate],">"&WinFrom,tPO[OrderDate],"<="&WinTo)) -> 882151.12
A31: =IFERROR(INDEX(tVendor[VendorID],23),"") -> VEN-026 | C31: =IF($A31="","",SUMIFS(tPO[ExtendedPrice],tPO[VendorID],$A31,tPO[OrderDate],">"&WinFrom,tPO[OrderDate],"<="&WinTo)) -> 1084136.4
A32: =IFERROR(INDEX(tVendor[VendorID],24),"") -> VEN-022 | C32: =IF($A32="","",SUMIFS(tPO[ExtendedPrice],tPO[VendorID],$A32,tPO[OrderDate],">"&WinFrom,tPO[OrderDate],"<="&WinTo)) -> 1158064
A33: =IFERROR(INDEX(tVendor[VendorID],25),"") -> VEN-033 | C33: =IF($A33="","",SUMIFS(tPO[ExtendedPrice],tPO[VendorID],$A33,tPO[OrderDate],">"&WinFrom,tPO[OrderDate],"<="&WinTo)) -> 1083274.8
A34: =IFERROR(INDEX(tVendor[VendorID],26),"") -> VEN-013 | C34: =IF($A34="","",SUMIFS(tPO[ExtendedPrice],tPO[VendorID],$A34,tPO[OrderDate],">"&WinFrom,tPO[OrderDate],"<="&WinTo)) -> 803560.53
A35: =IFERROR(INDEX(tVendor[VendorID],27),"") -> VEN-018 | C35: =IF($A35="","",SUMIFS(tPO[ExtendedPrice],tPO[VendorID],$A35,tPO[OrderDate],">"&WinFrom,tPO[OrderDate],"<="&WinTo)) -> 1131076.6
A36: =IFERROR(INDEX(tVendor[VendorID],28),"") -> VEN-001 | C36: =IF($A36="","",SUMIFS(tPO[ExtendedPrice],tPO[VendorID],$A36,tPO[OrderDate],">"&WinFrom,tPO[OrderDate],"<="&WinTo)) -> 996803.69
A37: =IFERROR(INDEX(tVendor[VendorID],29),"") -> VEN-027 | C37: =IF($A37="","",SUMIFS(tPO[ExtendedPrice],tPO[VendorID],$A37,tPO[OrderDate],">"&WinFrom,tPO[OrderDate],"<="&WinTo)) -> 753254.8
A38: =IFERROR(INDEX(tVendor[VendorID],30),"") -> VEN-012 | C38: =IF($A38="","",SUMIFS(tPO[ExtendedPrice],tPO[VendorID],$A38,tPO[OrderDate],">"&WinFrom,tPO[OrderDate],"<="&WinTo)) -> 533827.7
A39: =IFERROR(INDEX(tVendor[VendorID],31),"") -> VEN-036 | C39: =IF($A39="","",SUMIFS(tPO[ExtendedPrice],tPO[VendorID],$A39,tPO[OrderDate],">"&WinFrom,tPO[OrderDate],"<="&WinTo)) -> 491992.36
A40: =IFERROR(INDEX(tVendor[VendorID],32),"") -> VEN-024 | C40: =IF($A40="","",SUMIFS(tPO[ExtendedPrice],tPO[VendorID],$A40,tPO[OrderDate],">"&WinFrom,tPO[OrderDate],"<="&WinTo)) -> 430217.7
A41: =IFERROR(INDEX(tVendor[VendorID],33),"") -> VEN-035 | C41: =IF($A41="","",SUMIFS(tPO[ExtendedPrice],tPO[VendorID],$A41,tPO[OrderDate],">"&WinFrom,tPO[OrderDate],"<="&WinTo)) -> 474909.06
A42: =IFERROR(INDEX(tVendor[VendorID],34),"") -> VEN-025 | C42: =IF($A42="","",SUMIFS(tPO[ExtendedPrice],tPO[VendorID],$A42,tPO[OrderDate],">"&WinFrom,tPO[OrderDate],"<="&WinTo)) -> 283802.05
A43: =IFERROR(INDEX(tVendor[VendorID],35),"") -> VEN-030 | C43: =IF($A43="","",SUMIFS(tPO[ExtendedPrice],tPO[VendorID],$A43,tPO[OrderDate],">"&WinFrom,tPO[OrderDate],"<="&WinTo)) -> 185329.95
A44: =IFERROR(INDEX(tVendor[VendorID],36),"") -> VEN-021 | C44: =IF($A44="","",SUMIFS(tPO[ExtendedPrice],tPO[VendorID],$A44,tPO[OrderDate],">"&WinFrom,tPO[OrderDate],"<="&WinTo)) -> 267040.7
A46: Top five total | C46: =LARGE($C$9:$C$44,1)+LARGE($C$9:$C$44,2)+LARGE($C$9:$C$44,3)+LARGE($C$9:$C$44,4)+LARGE($C$9:$C$44,5) -> 13214601
A47: All vendors in window | C47: =SUM($C$9:$C$44) -> 48586387
A50: QUEUE RANKING -- re-ranks the SQL queue under the filters set on the Renegotiation Queue sheet
A51: Row | B51: Matches filters | C51: Rank within filter
A52: 1 | B52: =IF(AND(OR('Renegotiation Queue'!$C$4="(All)",INDEX(tQueue[BuyerName],1)='Renegotiation Queue'!$C$4),OR('Renegotiation Queue'!$C$5="(All)",INDEX(tQueue[ActionCode],1)='Renegotiation Queue'!$C$5),OR('Renegotiation Queue'!$C$6="(All)",INDEX(tQueue[Category],1)='Renegotiation Queue'!$C$6),OR('Renegotiation Queue'!$C$7="No",INDEX(tQueue[IsThisQuarter],1)=1)),1,0) -> 1 | C52: =IF($B52=0,"",SUMPRODUCT(($B$52:$B$236=1)*(tQueue[PriorityRank]<INDEX(tQueue[PriorityRank],1)))+1) -> 1
A53: 2 | B53: =IF(AND(OR('Renegotiation Queue'!$C$4="(All)",INDEX(tQueue[BuyerName],2)='Renegotiation Queue'!$C$4),OR('Renegotiation Queue'!$C$5="(All)",INDEX(tQueue[ActionCode],2)='Renegotiation Queue'!$C$5),OR('Renegotiation Queue'!$C$6="(All)",INDEX(tQueue[Category],2)='Renegotiation Queue'!$C$6),OR('Renegotiation Queue'!$C$7="No",INDEX(tQueue[IsThisQuarter],2)=1)),1,0) -> 1 | C53: =IF($B53=0,"",SUMPRODUCT(($B$52:$B$236=1)*(tQueue[PriorityRank]<INDEX(tQueue[PriorityRank],2)))+1) -> 2
A54: 3 | B54: =IF(AND(OR('Renegotiation Queue'!$C$4="(All)",INDEX(tQueue[BuyerName],3)='Renegotiation Queue'!$C$4),OR('Renegotiation Queue'!$C$5="(All)",INDEX(tQueue[ActionCode],3)='Renegotiation Queue'!$C$5),OR('Renegotiation Queue'!$C$6="(All)",INDEX(tQueue[Category],3)='Renegotiation Queue'!$C$6),OR('Renegotiation Queue'!$C$7="No",INDEX(tQueue[IsThisQuarter],3)=1)),1,0) -> 1 | C54: =IF($B54=0,"",SUMPRODUCT(($B$52:$B$236=1)*(tQueue[PriorityRank]<INDEX(tQueue[PriorityRank],3)))+1) -> 3
A55: 4 | B55: =IF(AND(OR('Renegotiation Queue'!$C$4="(All)",INDEX(tQueue[BuyerName],4)='Renegotiation Queue'!$C$4),OR('Renegotiation Queue'!$C$5="(All)",INDEX(tQueue[ActionCode],4)='Renegotiation Queue'!$C$5),OR('Renegotiation Queue'!$C$6="(All)",INDEX(tQueue[Category],4)='Renegotiation Queue'!$C$6),OR('Renegotiation Queue'!$C$7="No",INDEX(tQueue[IsThisQuarter],4)=1)),1,0) -> 1 | C55: =IF($B55=0,"",SUMPRODUCT(($B$52:$B$236=1)*(tQueue[PriorityRank]<INDEX(tQueue[PriorityRank],4)))+1) -> 4
A56: 5 | B56: =IF(AND(OR('Renegotiation Queue'!$C$4="(All)",INDEX(tQueue[BuyerName],5)='Renegotiation Queue'!$C$4),OR('Renegotiation Queue'!$C$5="(All)",INDEX(tQueue[ActionCode],5)='Renegotiation Queue'!$C$5),OR('Renegotiation Queue'!$C$6="(All)",INDEX(tQueue[Category],5)='Renegotiation Queue'!$C$6),OR('Renegotiation Queue'!$C$7="No",INDEX(tQueue[IsThisQuarter],5)=1)),1,0) -> 1 | C56: =IF($B56=0,"",SUMPRODUCT(($B$52:$B$236=1)*(tQueue[PriorityRank]<INDEX(tQueue[PriorityRank],5)))+1) -> 5
A57: 6 | B57: =IF(AND(OR('Renegotiation Queue'!$C$4="(All)",INDEX(tQueue[BuyerName],6)='Renegotiation Queue'!$C$4),OR('Renegotiation Queue'!$C$5="(All)",INDEX(tQueue[ActionCode],6)='Renegotiation Queue'!$C$5),OR('Renegotiation Queue'!$C$6="(All)",INDEX(tQueue[Category],6)='Renegotiation Queue'!$C$6),OR('Renegotiation Queue'!$C$7="No",INDEX(tQueue[IsThisQuarter],6)=1)),1,0) -> 1 | C57: =IF($B57=0,"",SUMPRODUCT(($B$52:$B$236=1)*(tQueue[PriorityRank]<INDEX(tQueue[PriorityRank],6)))+1) -> 6
A58: 7 | B58: =IF(AND(OR('Renegotiation Queue'!$C$4="(All)",INDEX(tQueue[BuyerName],7)='Renegotiation Queue'!$C$4),OR('Renegotiation Queue'!$C$5="(All)",INDEX(tQueue[ActionCode],7)='Renegotiation Queue'!$C$5),OR('Renegotiation Queue'!$C$6="(All)",INDEX(tQueue[Category],7)='Renegotiation Queue'!$C$6),OR('Renegotiation Queue'!$C$7="No",INDEX(tQueue[IsThisQuarter],7)=1)),1,0) -> 1 | C58: =IF($B58=0,"",SUMPRODUCT(($B$52:$B$236=1)*(tQueue[PriorityRank]<INDEX(tQueue[PriorityRank],7)))+1) -> 7
A59: 8 | B59: =IF(AND(OR('Renegotiation Queue'!$C$4="(All)",INDEX(tQueue[BuyerName],8)='Renegotiation Queue'!$C$4),OR('Renegotiation Queue'!$C$5="(All)",INDEX(tQueue[ActionCode],8)='Renegotiation Queue'!$C$5),OR('Renegotiation Queue'!$C$6="(All)",INDEX(tQueue[Category],8)='Renegotiation Queue'!$C$6),OR('Renegotiation Queue'!$C$7="No",INDEX(tQueue[IsThisQuarter],8)=1)),1,0) -> 1 | C59: =IF($B59=0,"",SUMPRODUCT(($B$52:$B$236=1)*(tQueue[PriorityRank]<INDEX(tQueue[PriorityRank],8)))+1) -> 8
A60: 9 | B60: =IF(AND(OR('Renegotiation Queue'!$C$4="(All)",INDEX(tQueue[BuyerName],9)='Renegotiation Queue'!$C$4),OR('Renegotiation Queue'!$C$5="(All)",INDEX(tQueue[ActionCode],9)='Renegotiation Queue'!$C$5),OR('Renegotiation Queue'!$C$6="(All)",INDEX(tQueue[Category],9)='Renegotiation Queue'!$C$6),OR('Renegotiation Queue'!$C$7="No",INDEX(tQueue[IsThisQuarter],9)=1)),1,0) -> 1 | C60: =IF($B60=0,"",SUMPRODUCT(($B$52:$B$236=1)*(tQueue[PriorityRank]<INDEX(tQueue[PriorityRank],9)))+1) -> 9
A61: 10 | B61: =IF(AND(OR('Renegotiation Queue'!$C$4="(All)",INDEX(tQueue[BuyerName],10)='Renegotiation Queue'!$C$4),OR('Renegotiation Queue'!$C$5="(All)",INDEX(tQueue[ActionCode],10)='Renegotiation Queue'!$C$5),OR('Renegotiation Queue'!$C$6="(All)",INDEX(tQueue[Category],10)='Renegotiation Queue'!$C$6),OR('Renegotiation Queue'!$C$7="No",INDEX(tQueue[IsThisQuarter],10)=1)),1,0) -> 1 | C61: =IF($B61=0,"",SUMPRODUCT(($B$52:$B$236=1)*(tQueue[PriorityRank]<INDEX(tQueue[PriorityRank],10)))+1) -> 10
A62: 11 | B62: =IF(AND(OR('Renegotiation Queue'!$C$4="(All)",INDEX(tQueue[BuyerName],11)='Renegotiation Queue'!$C$4),OR('Renegotiation Queue'!$C$5="(All)",INDEX(tQueue[ActionCode],11)='Renegotiation Queue'!$C$5),OR('Renegotiation Queue'!$C$6="(All)",INDEX(tQueue[Category],11)='Renegotiation Queue'!$C$6),OR('Renegotiation Queue'!$C$7="No",INDEX(tQueue[IsThisQuarter],11)=1)),1,0) -> 1 | C62: =IF($B62=0,"",SUMPRODUCT(($B$52:$B$236=1)*(tQueue[PriorityRank]<INDEX(tQueue[PriorityRank],11)))+1) -> 11
A63: 12 | B63: =IF(AND(OR('Renegotiation Queue'!$C$4="(All)",INDEX(tQueue[BuyerName],12)='Renegotiation Queue'!$C$4),OR('Renegotiation Queue'!$C$5="(All)",INDEX(tQueue[ActionCode],12)='Renegotiation Queue'!$C$5),OR('Renegotiation Queue'!$C$6="(All)",INDEX(tQueue[Category],12)='Renegotiation Queue'!$C$6),OR('Renegotiation Queue'!$C$7="No",INDEX(tQueue[IsThisQuarter],12)=1)),1,0) -> 1 | C63: =IF($B63=0,"",SUMPRODUCT(($B$52:$B$236=1)*(tQueue[PriorityRank]<INDEX(tQueue[PriorityRank],12)))+1) -> 12
A64: 13 | B64: =IF(AND(OR('Renegotiation Queue'!$C$4="(All)",INDEX(tQueue[BuyerName],13)='Renegotiation Queue'!$C$4),OR('Renegotiation Queue'!$C$5="(All)",INDEX(tQueue[ActionCode],13)='Renegotiation Queue'!$C$5),OR('Renegotiation Queue'!$C$6="(All)",INDEX(tQueue[Category],13)='Renegotiation Queue'!$C$6),OR('Renegotiation Queue'!$C$7="No",INDEX(tQueue[IsThisQuarter],13)=1)),1,0) -> 1 | C64: =IF($B64=0,"",SUMPRODUCT(($B$52:$B$236=1)*(tQueue[PriorityRank]<INDEX(tQueue[PriorityRank],13)))+1) -> 13
A65: 14 | B65: =IF(AND(OR('Renegotiation Queue'!$C$4="(All)",INDEX(tQueue[BuyerName],14)='Renegotiation Queue'!$C$4),OR('Renegotiation Queue'!$C$5="(All)",INDEX(tQueue[ActionCode],14)='Renegotiation Queue'!$C$5),OR('Renegotiation Queue'!$C$6="(All)",INDEX(tQueue[Category],14)='Renegotiation Queue'!$C$6),OR('Renegotiation Queue'!$C$7="No",INDEX(tQueue[IsThisQuarter],14)=1)),1,0) -> 1 | C65: =IF($B65=0,"",SUMPRODUCT(($B$52:$B$236=1)*(tQueue[PriorityRank]<INDEX(tQueue[PriorityRank],14)))+1) -> 14
A66: 15 | B66: =IF(AND(OR('Renegotiation Queue'!$C$4="(All)",INDEX(tQueue[BuyerName],15)='Renegotiation Queue'!$C$4),OR('Renegotiation Queue'!$C$5="(All)",INDEX(tQueue[ActionCode],15)='Renegotiation Queue'!$C$5),OR('Renegotiation Queue'!$C$6="(All)",INDEX(tQueue[Category],15)='Renegotiation Queue'!$C$6),OR('Renegotiation Queue'!$C$7="No",INDEX(tQueue[IsThisQuarter],15)=1)),1,0) -> 1 | C66: =IF($B66=0,"",SUMPRODUCT(($B$52:$B$236=1)*(tQueue[PriorityRank]<INDEX(tQueue[PriorityRank],15)))+1) -> 15
A67: 16 | B67: =IF(AND(OR('Renegotiation Queue'!$C$4="(All)",INDEX(tQueue[BuyerName],16)='Renegotiation Queue'!$C$4),OR('Renegotiation Queue'!$C$5="(All)",INDEX(tQueue[ActionCode],16)='Renegotiation Queue'!$C$5),OR('Renegotiation Queue'!$C$6="(All)",INDEX(tQueue[Category],16)='Renegotiation Queue'!$C$6),OR('Renegotiation Queue'!$C$7="No",INDEX(tQueue[IsThisQuarter],16)=1)),1,0) -> 1 | C67: =IF($B67=0,"",SUMPRODUCT(($B$52:$B$236=1)*(tQueue[PriorityRank]<INDEX(tQueue[PriorityRank],16)))+1) -> 16
A68: 17 | B68: =IF(AND(OR('Renegotiation Queue'!$C$4="(All)",INDEX(tQueue[BuyerName],17)='Renegotiation Queue'!$C$4),OR('Renegotiation Queue'!$C$5="(All)",INDEX(tQueue[ActionCode],17)='Renegotiation Queue'!$C$5),OR('Renegotiation Queue'!$C$6="(All)",INDEX(tQueue[Category],17)='Renegotiation Queue'!$C$6),OR('Renegotiation Queue'!$C$7="No",INDEX(tQueue[IsThisQuarter],17)=1)),1,0) -> 1 | C68: =IF($B68=0,"",SUMPRODUCT(($B$52:$B$236=1)*(tQueue[PriorityRank]<INDEX(tQueue[PriorityRank],17)))+1) -> 17
A69: 18 | B69: =IF(AND(OR('Renegotiation Queue'!$C$4="(All)",INDEX(tQueue[BuyerName],18)='Renegotiation Queue'!$C$4),OR('Renegotiation Queue'!$C$5="(All)",INDEX(tQueue[ActionCode],18)='Renegotiation Queue'!$C$5),OR('Renegotiation Queue'!$C$6="(All)",INDEX(tQueue[Category],18)='Renegotiation Queue'!$C$6),OR('Renegotiation Queue'!$C$7="No",INDEX(tQueue[IsThisQuarter],18)=1)),1,0) -> 1 | C69: =IF($B69=0,"",SUMPRODUCT(($B$52:$B$236=1)*(tQueue[PriorityRank]<INDEX(tQueue[PriorityRank],18)))+1) -> 18
A70: 19 | B70: =IF(AND(OR('Renegotiation Queue'!$C$4="(All)",INDEX(tQueue[BuyerName],19)='Renegotiation Queue'!$C$4),OR('Renegotiation Queue'!$C$5="(All)",INDEX(tQueue[ActionCode],19)='Renegotiation Queue'!$C$5),OR('Renegotiation Queue'!$C$6="(All)",INDEX(tQueue[Category],19)='Renegotiation Queue'!$C$6),OR('Renegotiation Queue'!$C$7="No",INDEX(tQueue[IsThisQuarter],19)=1)),1,0) -> 1 | C70: =IF($B70=0,"",SUMPRODUCT(($B$52:$B$236=1)*(tQueue[PriorityRank]<INDEX(tQueue[PriorityRank],19)))+1) -> 19
A71: 20 | B71: =IF(AND(OR('Renegotiation Queue'!$C$4="(All)",INDEX(tQueue[BuyerName],20)='Renegotiation Queue'!$C$4),OR('Renegotiation Queue'!$C$5="(All)",INDEX(tQueue[ActionCode],20)='Renegotiation Queue'!$C$5),OR('Renegotiation Queue'!$C$6="(All)",INDEX(tQueue[Category],20)='Renegotiation Queue'!$C$6),OR('Renegotiation Queue'!$C$7="No",INDEX(tQueue[IsThisQuarter],20)=1)),1,0) -> 1 | C71: =IF($B71=0,"",SUMPRODUCT(($B$52:$B$236=1)*(tQueue[PriorityRank]<INDEX(tQueue[PriorityRank],20)))+1) -> 20
A72: 21 | B72: =IF(AND(OR('Renegotiation Queue'!$C$4="(All)",INDEX(tQueue[BuyerName],21)='Renegotiation Queue'!$C$4),OR('Renegotiation Queue'!$C$5="(All)",INDEX(tQueue[ActionCode],21)='Renegotiation Queue'!$C$5),OR('Renegotiation Queue'!$C$6="(All)",INDEX(tQueue[Category],21)='Renegotiation Queue'!$C$6),OR('Renegotiation Queue'!$C$7="No",INDEX(tQueue[IsThisQuarter],21)=1)),1,0) -> 1 | C72: =IF($B72=0,"",SUMPRODUCT(($B$52:$B$236=1)*(tQueue[PriorityRank]<INDEX(tQueue[PriorityRank],21)))+1) -> 21
A73: 22 | B73: =IF(AND(OR('Renegotiation Queue'!$C$4="(All)",INDEX(tQueue[BuyerName],22)='Renegotiation Queue'!$C$4),OR('Renegotiation Queue'!$C$5="(All)",INDEX(tQueue[ActionCode],22)='Renegotiation Queue'!$C$5),OR('Renegotiation Queue'!$C$6="(All)",INDEX(tQueue[Category],22)='Renegotiation Queue'!$C$6),OR('Renegotiation Queue'!$C$7="No",INDEX(tQueue[IsThisQuarter],22)=1)),1,0) -> 1 | C73: =IF($B73=0,"",SUMPRODUCT(($B$52:$B$236=1)*(tQueue[PriorityRank]<INDEX(tQueue[PriorityRank],22)))+1) -> 22
A74: 23 | B74: =IF(AND(OR('Renegotiation Queue'!$C$4="(All)",INDEX(tQueue[BuyerName],23)='Renegotiation Queue'!$C$4),OR('Renegotiation Queue'!$C$5="(All)",INDEX(tQueue[ActionCode],23)='Renegotiation Queue'!$C$5),OR('Renegotiation Queue'!$C$6="(All)",INDEX(tQueue[Category],23)='Renegotiation Queue'!$C$6),OR('Renegotiation Queue'!$C$7="No",INDEX(tQueue[IsThisQuarter],23)=1)),1,0) -> 0 | C74: =IF($B74=0,"",SUMPRODUCT(($B$52:$B$236=1)*(tQueue[PriorityRank]<INDEX(tQueue[PriorityRank],23)))+1)
A75: 24 | B75: =IF(AND(OR('Renegotiation Queue'!$C$4="(All)",INDEX(tQueue[BuyerName],24)='Renegotiation Queue'!$C$4),OR('Renegotiation Queue'!$C$5="(All)",INDEX(tQueue[ActionCode],24)='Renegotiation Queue'!$C$5),OR('Renegotiation Queue'!$C$6="(All)",INDEX(tQueue[Category],24)='Renegotiation Queue'!$C$6),OR('Renegotiation Queue'!$C$7="No",INDEX(tQueue[IsThisQuarter],24)=1)),1,0) -> 1 | C75: =IF($B75=0,"",SUMPRODUCT(($B$52:$B$236=1)*(tQueue[PriorityRank]<INDEX(tQueue[PriorityRank],24)))+1) -> 23
A76: 25 | B76: =IF(AND(OR('Renegotiation Queue'!$C$4="(All)",INDEX(tQueue[BuyerName],25)='Renegotiation Queue'!$C$4),OR('Renegotiation Queue'!$C$5="(All)",INDEX(tQueue[ActionCode],25)='Renegotiation Queue'!$C$5),OR('Renegotiation Queue'!$C$6="(All)",INDEX(tQueue[Category],25)='Renegotiation Queue'!$C$6),OR('Renegotiation Queue'!$C$7="No",INDEX(tQueue[IsThisQuarter],25)=1)),1,0) -> 1 | C76: =IF($B76=0,"",SUMPRODUCT(($B$52:$B$236=1)*(tQueue[PriorityRank]<INDEX(tQueue[PriorityRank],25)))+1) -> 24
A77: 26 | B77: =IF(AND(OR('Renegotiation Queue'!$C$4="(All)",INDEX(tQueue[BuyerName],26)='Renegotiation Queue'!$C$4),OR('Renegotiation Queue'!$C$5="(All)",INDEX(tQueue[ActionCode],26)='Renegotiation Queue'!$C$5),OR('Renegotiation Queue'!$C$6="(All)",INDEX(tQueue[Category],26)='Renegotiation Queue'!$C$6),OR('Renegotiation Queue'!$C$7="No",INDEX(tQueue[IsThisQuarter],26)=1)),1,0) -> 1 | C77: =IF($B77=0,"",SUMPRODUCT(($B$52:$B$236=1)*(tQueue[PriorityRank]<INDEX(tQueue[PriorityRank],26)))+1) -> 25
A78: 27 | B78: =IF(AND(OR('Renegotiation Queue'!$C$4="(All)",INDEX(tQueue[BuyerName],27)='Renegotiation Queue'!$C$4),OR('Renegotiation Queue'!$C$5="(All)",INDEX(tQueue[ActionCode],27)='Renegotiation Queue'!$C$5),OR('Renegotiation Queue'!$C$6="(All)",INDEX(tQueue[Category],27)='Renegotiation Queue'!$C$6),OR('Renegotiation Queue'!$C$7="No",INDEX(tQueue[IsThisQuarter],27)=1)),1,0) -> 1 | C78: =IF($B78=0,"",SUMPRODUCT(($B$52:$B$236=1)*(tQueue[PriorityRank]<INDEX(tQueue[PriorityRank],27)))+1) -> 26
A79: 28 | B79: =IF(AND(OR('Renegotiation Queue'!$C$4="(All)",INDEX(tQueue[BuyerName],28)='Renegotiation Queue'!$C$4),OR('Renegotiation Queue'!$C$5="(All)",INDEX(tQueue[ActionCode],28)='Renegotiation Queue'!$C$5),OR('Renegotiation Queue'!$C$6="(All)",INDEX(tQueue[Category],28)='Renegotiation Queue'!$C$6),OR('Renegotiation Queue'!$C$7="No",INDEX(tQueue[IsThisQuarter],28)=1)),1,0) -> 0 | C79: =IF($B79=0,"",SUMPRODUCT(($B$52:$B$236=1)*(tQueue[PriorityRank]<INDEX(tQueue[PriorityRank],28)))+1)
A80: 29 | B80: =IF(AND(OR('Renegotiation Queue'!$C$4="(All)",INDEX(tQueue[BuyerName],29)='Renegotiation Queue'!$C$4),OR('Renegotiation Queue'!$C$5="(All)",INDEX(tQueue[ActionCode],29)='Renegotiation Queue'!$C$5),OR('Renegotiation Queue'!$C$6="(All)",INDEX(tQueue[Category],29)='Renegotiation Queue'!$C$6),OR('Renegotiation Queue'!$C$7="No",INDEX(tQueue[IsThisQuarter],29)=1)),1,0) -> 0 | C80: =IF($B80=0,"",SUMPRODUCT(($B$52:$B$236=1)*(tQueue[PriorityRank]<INDEX(tQueue[PriorityRank],29)))+1)
A81: 30 | B81: =IF(AND(OR('Renegotiation Queue'!$C$4="(All)",INDEX(tQueue[BuyerName],30)='Renegotiation Queue'!$C$4),OR('Renegotiation Queue'!$C$5="(All)",INDEX(tQueue[ActionCode],30)='Renegotiation Queue'!$C$5),OR('Renegotiation Queue'!$C$6="(All)",INDEX(tQueue[Category],30)='Renegotiation Queue'!$C$6),OR('Renegotiation Queue'!$C$7="No",INDEX(tQueue[IsThisQuarter],30)=1)),1,0) -> 1 | C81: =IF($B81=0,"",SUMPRODUCT(($B$52:$B$236=1)*(tQueue[PriorityRank]<INDEX(tQueue[PriorityRank],30)))+1) -> 27
A82: 31 | B82: =IF(AND(OR('Renegotiation Queue'!$C$4="(All)",INDEX(tQueue[BuyerName],31)='Renegotiation Queue'!$C$4),OR('Renegotiation Queue'!$C$5="(All)",INDEX(tQueue[ActionCode],31)='Renegotiation Queue'!$C$5),OR('Renegotiation Queue'!$C$6="(All)",INDEX(tQueue[Category],31)='Renegotiation Queue'!$C$6),OR('Renegotiation Queue'!$C$7="No",INDEX(tQueue[IsThisQuarter],31)=1)),1,0) -> 0 | C82: =IF($B82=0,"",SUMPRODUCT(($B$52:$B$236=1)*(tQueue[PriorityRank]<INDEX(tQueue[PriorityRank],31)))+1)
A83: 32 | B83: =IF(AND(OR('Renegotiation Queue'!$C$4="(All)",INDEX(tQueue[BuyerName],32)='Renegotiation Queue'!$C$4),OR('Renegotiation Queue'!$C$5="(All)",INDEX(tQueue[ActionCode],32)='Renegotiation Queue'!$C$5),OR('Renegotiation Queue'!$C$6="(All)",INDEX(tQueue[Category],32)='Renegotiation Queue'!$C$6),OR('Renegotiation Queue'!$C$7="No",INDEX(tQueue[IsThisQuarter],32)=1)),1,0) -> 0 | C83: =IF($B83=0,"",SUMPRODUCT(($B$52:$B$236=1)*(tQueue[PriorityRank]<INDEX(tQueue[PriorityRank],32)))+1)
A84: 33 | B84: =IF(AND(OR('Renegotiation Queue'!$C$4="(All)",INDEX(tQueue[BuyerName],33)='Renegotiation Queue'!$C$4),OR('Renegotiation Queue'!$C$5="(All)",INDEX(tQueue[ActionCode],33)='Renegotiation Queue'!$C$5),OR('Renegotiation Queue'!$C$6="(All)",INDEX(tQueue[Category],33)='Renegotiation Queue'!$C$6),OR('Renegotiation Queue'!$C$7="No",INDEX(tQueue[IsThisQuarter],33)=1)),1,0) -> 0 | C84: =IF($B84=0,"",SUMPRODUCT(($B$52:$B$236=1)*(tQueue[PriorityRank]<INDEX(tQueue[PriorityRank],33)))+1)
A85: 34 | B85: =IF(AND(OR('Renegotiation Queue'!$C$4="(All)",INDEX(tQueue[BuyerName],34)='Renegotiation Queue'!$C$4),OR('Renegotiation Queue'!$C$5="(All)",INDEX(tQueue[ActionCode],34)='Renegotiation Queue'!$C$5),OR('Renegotiation Queue'!$C$6="(All)",INDEX(tQueue[Category],34)='Renegotiation Queue'!$C$6),OR('Renegotiation Queue'!$C$7="No",INDEX(tQueue[IsThisQuarter],34)=1)),1,0) -> 1 | C85: =IF($B85=0,"",SUMPRODUCT(($B$52:$B$236=1)*(tQueue[PriorityRank]<INDEX(tQueue[PriorityRank],34)))+1) -> 28
A86: 35 | B86: =IF(AND(OR('Renegotiation Queue'!$C$4="(All)",INDEX(tQueue[BuyerName],35)='Renegotiation Queue'!$C$4),OR('Renegotiation Queue'!$C$5="(All)",INDEX(tQueue[ActionCode],35)='Renegotiation Queue'!$C$5),OR('Renegotiation Queue'!$C$6="(All)",INDEX(tQueue[Category],35)='Renegotiation Queue'!$C$6),OR('Renegotiation Queue'!$C$7="No",INDEX(tQueue[IsThisQuarter],35)=1)),1,0) -> 1 | C86: =IF($B86=0,"",SUMPRODUCT(($B$52:$B$236=1)*(tQueue[PriorityRank]<INDEX(tQueue[PriorityRank],35)))+1) -> 29
A87: 36 | B87: =IF(AND(OR('Renegotiation Queue'!$C$4="(All)",INDEX(tQueue[BuyerName],36)='Renegotiation Queue'!$C$4),OR('Renegotiation Queue'!$C$5="(All)",INDEX(tQueue[ActionCode],36)='Renegotiation Queue'!$C$5),OR('Renegotiation Queue'!$C$6="(All)",INDEX(tQueue[Category],36)='Renegotiation Queue'!$C$6),OR('Renegotiation Queue'!$C$7="No",INDEX(tQueue[IsThisQuarter],36)=1)),1,0) -> 0 | C87: =IF($B87=0,"",SUMPRODUCT(($B$52:$B$236=1)*(tQueue[PriorityRank]<INDEX(tQueue[PriorityRank],36)))+1)
A88: 37 | B88: =IF(AND(OR('Renegotiation Queue'!$C$4="(All)",INDEX(tQueue[BuyerName],37)='Renegotiation Queue'!$C$4),OR('Renegotiation Queue'!$C$5="(All)",INDEX(tQueue[ActionCode],37)='Renegotiation Queue'!$C$5),OR('Renegotiation Queue'!$C$6="(All)",INDEX(tQueue[Category],37)='Renegotiation Queue'!$C$6),OR('Renegotiation Queue'!$C$7="No",INDEX(tQueue[IsThisQuarter],37)=1)),1,0) -> 1 | C88: =IF($B88=0,"",SUMPRODUCT(($B$52:$B$236=1)*(tQueue[PriorityRank]<INDEX(tQueue[PriorityRank],37)))+1) -> 30
A89: 38 | B89: =IF(AND(OR('Renegotiation Queue'!$C$4="(All)",INDEX(tQueue[BuyerName],38)='Renegotiation Queue'!$C$4),OR('Renegotiation Queue'!$C$5="(All)",INDEX(tQueue[ActionCode],38)='Renegotiation Queue'!$C$5),OR('Renegotiation Queue'!$C$6="(All)",INDEX(tQueue[Category],38)='Renegotiation Queue'!$C$6),OR('Renegotiation Queue'!$C$7="No",INDEX(tQueue[IsThisQuarter],38)=1)),1,0) -> 1 | C89: =IF($B89=0,"",SUMPRODUCT(($B$52:$B$236=1)*(tQueue[PriorityRank]<INDEX(tQueue[PriorityRank],38)))+1) -> 31
A90: 39 | B90: =IF(AND(OR('Renegotiation Queue'!$C$4="(All)",INDEX(tQueue[BuyerName],39)='Renegotiation Queue'!$C$4),OR('Renegotiation Queue'!$C$5="(All)",INDEX(tQueue[ActionCode],39)='Renegotiation Queue'!$C$5),OR('Renegotiation Queue'!$C$6="(All)",INDEX(tQueue[Category],39)='Renegotiation Queue'!$C$6),OR('Renegotiation Queue'!$C$7="No",INDEX(tQueue[IsThisQuarter],39)=1)),1,0) -> 1 | C90: =IF($B90=0,"",SUMPRODUCT(($B$52:$B$236=1)*(tQueue[PriorityRank]<INDEX(tQueue[PriorityRank],39)))+1) -> 32
A91: 40 | B91: =IF(AND(OR('Renegotiation Queue'!$C$4="(All)",INDEX(tQueue[BuyerName],40)='Renegotiation Queue'!$C$4),OR('Renegotiation Queue'!$C$5="(All)",INDEX(tQueue[ActionCode],40)='Renegotiation Queue'!$C$5),OR('Renegotiation Queue'!$C$6="(All)",INDEX(tQueue[Category],40)='Renegotiation Queue'!$C$6),OR('Renegotiation Queue'!$C$7="No",INDEX(tQueue[IsThisQuarter],40)=1)),1,0) -> 0 | C91: =IF($B91=0,"",SUMPRODUCT(($B$52:$B$236=1)*(tQueue[PriorityRank]<INDEX(tQueue[PriorityRank],40)))+1)
A92: 41 | B92: =IF(AND(OR('Renegotiation Queue'!$C$4="(All)",INDEX(tQueue[BuyerName],41)='Renegotiation Queue'!$C$4),OR('Renegotiation Queue'!$C$5="(All)",INDEX(tQueue[ActionCode],41)='Renegotiation Queue'!$C$5),OR('Renegotiation Queue'!$C$6="(All)",INDEX(tQueue[Category],41)='Renegotiation Queue'!$C$6),OR('Renegotiation Queue'!$C$7="No",INDEX(tQueue[IsThisQuarter],41)=1)),1,0) -> 1 | C92: =IF($B92=0,"",SUMPRODUCT(($B$52:$B$236=1)*(tQueue[PriorityRank]<INDEX(tQueue[PriorityRank],41)))+1) -> 33
A93: 42 | B93: =IF(AND(OR('Renegotiation Queue'!$C$4="(All)",INDEX(tQueue[BuyerName],42)='Renegotiation Queue'!$C$4),OR('Renegotiation Queue'!$C$5="(All)",INDEX(tQueue[ActionCode],42)='Renegotiation Queue'!$C$5),OR('Renegotiation Queue'!$C$6="(All)",INDEX(tQueue[Category],42)='Renegotiation Queue'!$C$6),OR('Renegotiation Queue'!$C$7="No",INDEX(tQueue[IsThisQuarter],42)=1)),1,0) -> 0 | C93: =IF($B93=0,"",SUMPRODUCT(($B$52:$B$236=1)*(tQueue[PriorityRank]<INDEX(tQueue[PriorityRank],42)))+1)
A94: 43 | B94: =IF(AND(OR('Renegotiation Queue'!$C$4="(All)",INDEX(tQueue[BuyerName],43)='Renegotiation Queue'!$C$4),OR('Renegotiation Queue'!$C$5="(All)",INDEX(tQueue[ActionCode],43)='Renegotiation Queue'!$C$5),OR('Renegotiation Queue'!$C$6="(All)",INDEX(tQueue[Category],43)='Renegotiation Queue'!$C$6),OR('Renegotiation Queue'!$C$7="No",INDEX(tQueue[IsThisQuarter],43)=1)),1,0) -> 1 | C94: =IF($B94=0,"",SUMPRODUCT(($B$52:$B$236=1)*(tQueue[PriorityRank]<INDEX(tQueue[PriorityRank],43)))+1) -> 34
A95: 44 | B95: =IF(AND(OR('Renegotiation Queue'!$C$4="(All)",INDEX(tQueue[BuyerName],44)='Renegotiation Queue'!$C$4),OR('Renegotiation Queue'!$C$5="(All)",INDEX(tQueue[ActionCode],44)='Renegotiation Queue'!$C$5),OR('Renegotiation Queue'!$C$6="(All)",INDEX(tQueue[Category],44)='Renegotiation Queue'!$C$6),OR('Renegotiation Queue'!$C$7="No",INDEX(tQueue[IsThisQuarter],44)=1)),1,0) -> 1 | C95: =IF($B95=0,"",SUMPRODUCT(($B$52:$B$236=1)*(tQueue[PriorityRank]<INDEX(tQueue[PriorityRank],44)))+1) -> 35
A96: 45 | B96: =IF(AND(OR('Renegotiation Queue'!$C$4="(All)",INDEX(tQueue[BuyerName],45)='Renegotiation Queue'!$C$4),OR('Renegotiation Queue'!$C$5="(All)",INDEX(tQueue[ActionCode],45)='Renegotiation Queue'!$C$5),OR('Renegotiation Queue'!$C$6="(All)",INDEX(tQueue[Category],45)='Renegotiation Queue'!$C$6),OR('Renegotiation Queue'!$C$7="No",INDEX(tQueue[IsThisQuarter],45)=1)),1,0) -> 0 | C96: =IF($B96=0,"",SUMPRODUCT(($B$52:$B$236=1)*(tQueue[PriorityRank]<INDEX(tQueue[PriorityRank],45)))+1)
A97: 46 | B97: =IF(AND(OR('Renegotiation Queue'!$C$4="(All)",INDEX(tQueue[BuyerName],46)='Renegotiation Queue'!$C$4),OR('Renegotiation Queue'!$C$5="(All)",INDEX(tQueue[ActionCode],46)='Renegotiation Queue'!$C$5),OR('Renegotiation Queue'!$C$6="(All)",INDEX(tQueue[Category],46)='Renegotiation Queue'!$C$6),OR('Renegotiation Queue'!$C$7="No",INDEX(tQueue[IsThisQuarter],46)=1)),1,0) -> 0 | C97: =IF($B97=0,"",SUMPRODUCT(($B$52:$B$236=1)*(tQueue[PriorityRank]<INDEX(tQueue[PriorityRank],46)))+1)
A98: 47 | B98: =IF(AND(OR('Renegotiation Queue'!$C$4="(All)",INDEX(tQueue[BuyerName],47)='Renegotiation Queue'!$C$4),OR('Renegotiation Queue'!$C$5="(All)",INDEX(tQueue[ActionCode],47)='Renegotiation Queue'!$C$5),OR('Renegotiation Queue'!$C$6="(All)",INDEX(tQueue[Category],47)='Renegotiation Queue'!$C$6),OR('Renegotiation Queue'!$C$7="No",INDEX(tQueue[IsThisQuarter],47)=1)),1,0) -> 1 | C98: =IF($B98=0,"",SUMPRODUCT(($B$52:$B$236=1)*(tQueue[PriorityRank]<INDEX(tQueue[PriorityRank],47)))+1) -> 36
A99: 48 | B99: =IF(AND(OR('Renegotiation Queue'!$C$4="(All)",INDEX(tQueue[BuyerName],48)='Renegotiation Queue'!$C$4),OR('Renegotiation Queue'!$C$5="(All)",INDEX(tQueue[ActionCode],48)='Renegotiation Queue'!$C$5),OR('Renegotiation Queue'!$C$6="(All)",INDEX(tQueue[Category],48)='Renegotiation Queue'!$C$6),OR('Renegotiation Queue'!$C$7="No",INDEX(tQueue[IsThisQuarter],48)=1)),1,0) -> 0 | C99: =IF($B99=0,"",SUMPRODUCT(($B$52:$B$236=1)*(tQueue[PriorityRank]<INDEX(tQueue[PriorityRank],48)))+1)
A100: 49 | B100: =IF(AND(OR('Renegotiation Queue'!$C$4="(All)",INDEX(tQueue[BuyerName],49)='Renegotiation Queue'!$C$4),OR('Renegotiation Queue'!$C$5="(All)",INDEX(tQueue[ActionCode],49)='Renegotiation Queue'!$C$5),OR('Renegotiation Queue'!$C$6="(All)",INDEX(tQueue[Category],49)='Renegotiation Queue'!$C$6),OR('Renegotiation Queue'!$C$7="No",INDEX(tQueue[IsThisQuarter],49)=1)),1,0) -> 0 | C100: =IF($B100=0,"",SUMPRODUCT(($B$52:$B$236=1)*(tQueue[PriorityRank]<INDEX(tQueue[PriorityRank],49)))+1)
A101: 50 | B101: =IF(AND(OR('Renegotiation Queue'!$C$4="(All)",INDEX(tQueue[BuyerName],50)='Renegotiation Queue'!$C$4),OR('Renegotiation Queue'!$C$5="(All)",INDEX(tQueue[ActionCode],50)='Renegotiation Queue'!$C$5),OR('Renegotiation Queue'!$C$6="(All)",INDEX(tQueue[Category],50)='Renegotiation Queue'!$C$6),OR('Renegotiation Queue'!$C$7="No",INDEX(tQueue[IsThisQuarter],50)=1)),1,0) -> 0 | C101: =IF($B101=0,"",SUMPRODUCT(($B$52:$B$236=1)*(tQueue[PriorityRank]<INDEX(tQueue[PriorityRank],50)))+1)
A102: 51 | B102: =IF(AND(OR('Renegotiation Queue'!$C$4="(All)",INDEX(tQueue[BuyerName],51)='Renegotiation Queue'!$C$4),OR('Renegotiation Queue'!$C$5="(All)",INDEX(tQueue[ActionCode],51)='Renegotiation Queue'!$C$5),OR('Renegotiation Queue'!$C$6="(All)",INDEX(tQueue[Category],51)='Renegotiation Queue'!$C$6),OR('Renegotiation Queue'!$C$7="No",INDEX(tQueue[IsThisQuarter],51)=1)),1,0) -> 0 | C102: =IF($B102=0,"",SUMPRODUCT(($B$52:$B$236=1)*(tQueue[PriorityRank]<INDEX(tQueue[PriorityRank],51)))+1)
A103: 52 | B103: =IF(AND(OR('Renegotiation Queue'!$C$4="(All)",INDEX(tQueue[BuyerName],52)='Renegotiation Queue'!$C$4),OR('Renegotiation Queue'!$C$5="(All)",INDEX(tQueue[ActionCode],52)='Renegotiation Queue'!$C$5),OR('Renegotiation Queue'!$C$6="(All)",INDEX(tQueue[Category],52)='Renegotiation Queue'!$C$6),OR('Renegotiation Queue'!$C$7="No",INDEX(tQueue[IsThisQuarter],52)=1)),1,0) -> 1 | C103: =IF($B103=0,"",SUMPRODUCT(($B$52:$B$236=1)*(tQueue[PriorityRank]<INDEX(tQueue[PriorityRank],52)))+1) -> 37
A104: 53 | B104: =IF(AND(OR('Renegotiation Queue'!$C$4="(All)",INDEX(tQueue[BuyerName],53)='Renegotiation Queue'!$C$4),OR('Renegotiation Queue'!$C$5="(All)",INDEX(tQueue[ActionCode],53)='Renegotiation Queue'!$C$5),OR('Renegotiation Queue'!$C$6="(All)",INDEX(tQueue[Category],53)='Renegotiation Queue'!$C$6),OR('Renegotiation Queue'!$C$7="No",INDEX(tQueue[IsThisQuarter],53)=1)),1,0) -> 0 | C104: =IF($B104=0,"",SUMPRODUCT(($B$52:$B$236=1)*(tQueue[PriorityRank]<INDEX(tQueue[PriorityRank],53)))+1)
A105: 54 | B105: =IF(AND(OR('Renegotiation Queue'!$C$4="(All)",INDEX(tQueue[BuyerName],54)='Renegotiation Queue'!$C$4),OR('Renegotiation Queue'!$C$5="(All)",INDEX(tQueue[ActionCode],54)='Renegotiation Queue'!$C$5),OR('Renegotiation Queue'!$C$6="(All)",INDEX(tQueue[Category],54)='Renegotiation Queue'!$C$6),OR('Renegotiation Queue'!$C$7="No",INDEX(tQueue[IsThisQuarter],54)=1)),1,0) -> 0 | C105: =IF($B105=0,"",SUMPRODUCT(($B$52:$B$236=1)*(tQueue[PriorityRank]<INDEX(tQueue[PriorityRank],54)))+1)
...

Sheet Control
A1: LUMEN OPTICS MANUFACTURING -- SPEND SCORECARD
A2: Control panel. Every sheet reads its parameters from the cells below.
A4: PARAMETER | B4: VALUE | C4: WHAT IT CONTROLS
A5: Reporting date | B5: =DATE(2025,12,31) -> 46022 | C5: The as-of date for every figure. Spend metrics use the twelve months ending here.
A6: Extract folder | B6: =IF(OR(CELL("filename")="",LEFT(CELL("filename"),4)="http"),"Set this cell to the full path of the erp_extracts folder, then Data > Refresh All",LEFT(CELL("filename"),FIND("[",CELL("filename"))-1)&"..\erp_extracts") -> Set this cell to the full path of the erp_extracts folder, then Data > Refresh All | C6: Where Power Query looks for the CSV extracts. Edit if you move the repo, then Data > Refresh All.
A7: Negotiations / buyer | B7: 8 | C7: Capacity assumption behind the quarter's worklist. Raising it lengthens every category manager's list.
A8: Queue rows shown | B8: 25 | C8: How many ranked pairs the Renegotiation Queue sheet displays.
A9: Baseline lag (days) | B9: 100000 | C9: Opportunity above which a negotiation is worth opening regardless of leverage.
A12: DATA DISCLOSURE
A13: Lumen Optics Manufacturing is a fictional company. All data in this workbook is synthetic and generated by the scripts in the sql\ folder. No confidential data is used and no claim is made about any production system.

Sheet Data_PO
A1: PONumber | B1: PartNumber | C1: PartName | D1: Category | E1: Criticality | F1: QualifiedSupplierCount | G1: QualificationMonths | H1: IsSingleSource | I1: VendorID | J1: VendorName | K1: Country | L1: VendorTier | M1: LumenRevenueSharePct | N1: BuyerID | O1: BuyerName | P1: Team | Q1: OrderDate | R1: PromisedDate | S1: OrderYear | T1: OrderYearMonth | U1: OrderQty | V1: UnitPrice | W1: FreightAmount | X1: ExpediteFee | Y1: IsExpedited | Z1: ExtendedPrice | AA1: LandedCost | AB1: AgreementNo | AC1: ContractedUnitPrice | AD1: AgreementsInForce | AE1: IsOnContract | AF1: PPVAmount | AG1: ContractedExtended | AH1: QtyReceived | AI1: QtyAccepted | AJ1: QtyRejected | AK1: Receipts | AL1: IsReceived | AM1: AcceptanceRatePct | AN1: CostPerAcceptedUnit | AO1: RejectedValue | AP1: LastReceiptDate | AQ1: DaysLate | AR1: IsOnTime
A2: PO-000001 | B2: LOM-0046 | C2: Fibre Connector Module 0046 | D2: Fibre Connector | E2: Standard | F2: 1 | G2: 2 | H2: 1 | I2: VEN-033 | J2: Oribel Technologies | K2: Taiwan | L2: Transactional | M2: 17.66 | N2: BUY-03 | O2: Mei-Ling Chow | P2: Optics & Coatings | Q2: 44935 | R2: 44961 | S2: 2023 | T2: 2023-01 | U2: 396 | V2: 24.687 | W2: 135.81 | X2: 0 | Y2: 0 | Z2: 9776.05 | AA2: 9911.86 | AB2: PA-0000205 | AC2: 24.687 | AD2: 1 | AE2: 1 | AF2: 0 | AG2: 9776.05 | AH2: 396 | AI2: 394 | AJ2: 2 | AK2: 1 | AL2: 1 | AM2: 99.49 | AN2: 25.157 | AO2: 49.37 | AP2: 44967 | AQ2: 6 | AR2: 0
A3: PO-000002 | B3: LOM-0036 | C3: Optical Coating Module 0036 | D3: Optical Coating | E3: Standard | F3: 2 | G3: 4 | H3: 0 | I3: VEN-020 | J3: Meridian Photonics Industries | K3: Japan | L3: Approved | M3: 12.07 | N3: BUY-03 | O3: Mei-Ling Chow | P3: Optics & Coatings | Q3: 44937 | R3: 44964 | S3: 2023 | T3: 2023-01 | U3: 138 | V3: 45.991 | W3: 115.1 | X3: 0 | Y3: 0 | Z3: 6346.76 | AA3: 6461.86 | AB3: PA-0000157 | AC3: 45.991 | AD3: 1 | AE3: 1 | AF3: 0 | AG3: 6346.76 | AH3: 138 | AI3: 136 | AJ3: 2 | AK3: 1 | AL3: 1 | AM3: 98.55 | AN3: 47.5137 | AO3: 91.98 | AP3: 44971 | AQ3: 7 | AR3: 0
A4: PO-000003 | B4: LOM-0124 | C4: Optical Coating Module 0124 | D4: Optical Coating | E4: Standard | F4: 3 | G4: 5 | H4: 0 | I4: VEN-031 | J4: Quantex Technologies | K4: United States | L4: Transactional | M4: 14.93 | N4: BUY-03 | O4: Mei-Ling Chow | P4: Optics & Coatings | Q4: 44937 | R4: 44963 | S4: 2023 | T4: 2023-01 | U4: 122 | V4: 147.55 | W4: 228.24 | X4: 0 | Y4: 0 | Z4: 18001.1 | AA4: 18229.34 | AB4: PA-0000572 | AC4: 147.55 | AD4: 1 | AE4: 1 | AF4: 0 | AG4: 18001.1 | AH4: 122 | AI4: 121 | AJ4: 1 | AK4: 1 | AL4: 1 | AM4: 99.18 | AN4: 150.6557 | AO4: 147.55 | AP4: 44961 | AQ4: -2 | AR4: 1
A5: PO-000004 | B5: LOM-0094 | C5: Fibre Connector Module 0094 | D5: Fibre Connector | E5: Standard | F5: 3 | G5: 5 | H5: 0 | I5: VEN-014 | J5: Photonica Industries | K5: Japan | L5: Preferred | M5: 4.81 | N5: BUY-04 | O5: Johan Lindberg | P5: Optics & Coatings | Q5: 44938 | R5: 44964 | S5: 2023 | T5: 2023-01 | U5: 380 | V5: 24.6179 | W5: 121.33 | X5: 0 | Y5: 0 | Z5: 9354.8 | AA5: 9476.13 | AB5: PA-0000428 | AC5: 24.6179 | AD5: 1 | AE5: 1 | AF5: 0 | AG5: 9354.8 | AH5: 380 | AI5: 375 | AJ5: 5 | AK5: 1 | AL5: 1 | AM5: 98.68 | AN5: 25.2697 | AO5: 123.09 | AP5: 44969 | AQ5: 5 | AR5: 0
A6: PO-000005 | B6: LOM-0013 | C6: Precision Mount Component 0013 | D6: Precision Mount | E6: Commodity | F6: 1 | G6: 0 | H6: 1 | I6: VEN-008 | J6: Meridian Photonics GmbH | K6: Japan | L6: Preferred | M6: 5.01 | N6: BUY-05 | O6: Priya Raghunathan | P6: Mechanical & Thermal | Q6: 44942 | R6: 44954 | S6: 2023 | T6: 2023-01 | U6: 14 | V6: 207.4813 | W6: 42.4 | X6: 93.94 | Y6: 1 | Z6: 2904.74 | AA6: 3041.08 | AB6: PA-0000057 | AC6: 207.4813 | AD6: 1 | AE6: 1 | AF6: 0 | AG6: 2904.74 | AH6: 14 | AI6: 14 | AJ6: 0 | AK6: 1 | AL6: 1 | AM6: 100 | AN6: 217.2199 | AO6: 0 | AP6: 44956 | AQ6: 2 | AR6: 0
A7: PO-000006 | B7: LOM-0027 | C7: Lens Assembly Component 0027 | D7: Lens Assembly | E7: Commodity | F7: 3 | G7: 1 | H7: 0 | I7: VEN-018 | J7: Northlight Industries | K7: Germany | L7: Approved | M7: 17.17 | N7: BUY-04 | O7: Johan Lindberg | P7: Optics & Coatings | Q7: 44942 | R7: 44958 | S7: 2023 | T7: 2023-01 | U7: 47 | V7: 264.1759 | W7: 287.11 | X7: 0 | Y7: 0 | Z7: 12416.27 | AA7: 12703.38 | AB7: PA-0000122 | AC7: 264.1759 | AD7: 1 | AE7: 1 | AF7: 0 | AG7: 12416.27 | AH7: 47 | AI7: 46 | AJ7: 1 | AK7: 1 | AL7: 1 | AM7: 97.87 | AN7: 276.1604 | AO7: 264.18 | AP7: 44955 | AQ7: -3 | AR7: 1
A8: PO-000007 | B8: LOM-0058 | C8: Optical Fibre Module 0058 | D8: Optical Fibre | E8: Standard | F8: 3 | G8: 4 | H8: 0 | I8: VEN-023 | J8: Kestrel Optical Industries | K8: Switzerland | L8: Approved | M8: 6.75 | N8: BUY-03 | O8: Mei-Ling Chow | P8: Optics & Coatings | Q8: 44942 | R8: 44964 | S8: 2023 | T8: 2023-01 | U8: 360 | V8: 55.5447 | W8: 189.52 | X8: 0 | Y8: 0 | Z8: 19996.09 | AA8: 20185.61 | AB8: PA-0000259 | AC8: 55.5447 | AD8: 1 | AE8: 1 | AF8: 0 | AG8: 19996.09 | AH8: 360 | AI8: 358 | AJ8: 2 | AK8: 1 | AL8: 1 | AM8: 99.44 | AN8: 56.3844 | AO8: 111.09 | AP8: 44972 | AQ8: 8 | AR8: 0
A9: PO-000008 | B9: LOM-0080 | C9: Laser Diode Module 0080 | D9: Laser Diode | E9: Standard | F9: 3 | G9: 5 | H9: 0 | I9: VEN-004 | J9: Spectra GmbH | K9: United Kingdom | L9: Strategic | M9: 1.51 | N9: BUY-01 | O9: Adaeze Okonkwo | P9: Optoelectronics | Q9: 44942 | R9: 44978 | S9: 2023 | T9: 2023-01 | U9: 130 | V9: 501.9232 | W9: 525.43 | X9: 0 | Y9: 0 | Z9: 65250.02 | AA9: 65775.45 | AB9: PA-0000361 | AC9: 501.9232 | AD9: 1 | AE9: 1 | AF9: 0 | AG9: 65250.02 | AH9: 130 | AI9: 117 | AJ9: 13 | AK9: 1 | AL9: 1 | AM9: 90 | AN9: 562.1833 | AO9: 6525 | AP9: 44978 | AQ9: 0 | AR9: 1
A10: PO-000009 | B10: LOM-0109 | C10: Precision Mount Assy 0109 | D10: Precision Mount | E10: Critical | F10: 1 | G10: 7 | H10: 1 | I10: VEN-010 | J10: Vectra GmbH | K10: United Kingdom | L10: Preferred | M10: 5.43 | N10: BUY-06 | O10: Tomas Varga | P10: Mechanical & Thermal | Q10: 44942 | R10: 44984 | S10: 2023 | T10: 2023-01 | U10: 71 | V10: 211.7856 | W10: 103.99 | X10: 0 | Y10: 0 | Z10: 15036.78 | AA10: 15140.77 | AB10: PA-0000497 | AC10: 211.7856 | AD10: 1 | AE10: 1 | AF10: 0 | AG10: 15036.78 | AH10: 71 | AI10: 70 | AJ10: 1 | AK10: 1 | AL10: 1 | AM10: 98.59 | AN10: 216.2967 | AO10: 211.79 | AP10: 44985 | AQ10: 1 | AR10: 0
A11: PO-000010 | B11: LOM-0004 | C11: Optical Coating Module 0004 | D11: Optical Coating | E11: Standard | F11: 2 | G11: 2 | H11: 0 | I11: VEN-029 | J11: Helix Optics Technologies | K11: Switzerland | L11: Transactional | M11: 36.48 | N11: BUY-03 | O11: Mei-Ling Chow | P11: Optics & Coatings | Q11: 44946 | R11: 44968 | S11: 2023 | T11: 2023-01 | U11: 61 | V11: 76.0924 | W11: 57.39 | X11: 0 | Y11: 0 | Z11: 4641.64 | AA11: 4699.03 | AB11: PA-0000013 | AC11: 76.0924 | AD11: 1 | AE11: 1 | AF11: 0 | AG11: 4641.64 | AH11: 61 | AI11: 60 | AJ11: 1 | AK11: 1 | AL11: 1 | AM11: 98.36 | AN11: 78.3171 | AO11: 76.09 | AP11: 44965 | AQ11: -3 | AR11: 1
A12: PO-000011 | B12: LOM-0072 | C12: Laser Diode Component 0072 | D12: Laser Diode | E12: Commodity | F12: 3 | G12: 1 | H12: 0 | I12: VEN-012 | J12: Aperture Industries | K12: Germany | L12: Preferred | M12: 4.72 | N12: BUY-02 | O12: Rafael Duarte | P12: Optoelectronics | Q12: 44946 | R12: 44974 | S12: 2023 | T12: 2023-01 | U12: 137 | V12: 206.2888 | W12: 658.96 | X12: 0 | Y12: 0 | Z12: 28261.57 | AA12: 28920.53 | AB12: PA-0000328 | AC12: 206.2888 | AD12: 1 | AE12: 1 | AF12: 0 | AG12: 28261.57 | AH12: 137 | AI12: 135 | AJ12: 2 | AK12: 1 | AL12: 1 | AM12: 98.54 | AN12: 214.2261 | AO12: 412.58 | AP12: 44974 | AQ12: 0 | AR12: 1
A13: PO-000012 | B13: LOM-0014 | C13: Fibre Connector Component 0014 | D13: Fibre Connector | E13: Commodity | F13: 2 | G13: 0 | H13: 0 | I13: VEN-020 | J13: Meridian Photonics Industries | K13: Japan | L13: Approved | M13: 12.07 | N13: BUY-03 | O13: Mei-Ling Chow | P13: Optics & Coatings | Q13: 44949 | R13: 44969 | S13: 2023 | T13: 2023-01 | U13: 544 | V13: 12.8643 | W13: 60.85 | X13: 0 | Y13: 0 | Z13: 6998.18 | AA13: 7059.03 | AB13: PA-0000060 | AC13: 12.8643 | AD13: 1 | AE13: 1 | AF13: 0 | AG13: 6998.18 | AH13: 544 | AI13: 542 | AJ13: 2 | AK13: 1 | AL13: 1 | AM13: 99.63 | AN13: 13.024 | AO13: 25.73 | AP13: 44968 | AQ13: -1 | AR13: 1
... A25: PO-000024 | B25: LOM-0099 | C25: Lens Assembly Module 0099 | D25: Lens Assembly | E25: Standard | F25: 3 | G25: 4 | H25: 0 | I25: VEN-006 | J25: Northlight GmbH | K25: Germany | L25: Strategic | M25: 4.77 | N25: BUY-04 | O25: Johan Lindberg | P25: Optics & Coatings | Q25: 44956 | R25: 44993 | S25: 2023 | T25: 2023-01 | U25: 136 | V25: 107.2827 | W25: 256.07 | X25: 458.05 | Y25: 1 | Z25: 14590.45 | AA25: 15304.57 | AB25: PA-0000446 | AC25: 107.2827 | AD25: 1 | AE25: 1 | AF25: 0 | AG25: 14590.45 | AH25: 136 | AI25: 135 | AJ25: 1 | AK25: 1 | AL25: 1 | AM25: 99.26 | AN25: 113.3672 | AO25: 107.28 | AP25: 44993 | AQ25: 0 | AR25: 1
A26: PO-000025 | B26: LOM-0072 | C26: Laser Diode Component 0072 | D26: Laser Diode | E26: Commodity | F26: 3 | G26: 1 | H26: 0 | I26: VEN-009 | J26: Oribel GmbH | K26: Taiwan | L26: Preferred | M26: 9.47 | N26: BUY-02 | O26: Rafael Duarte | P26: Optoelectronics | Q26: 44957 | R26: 44979 | S26: 2023 | T26: 2023-01 | U26: 91 | V26: 214.7429 | W26: 125.99 | X26: 0 | Y26: 0 | Z26: 19541.6 | AA26: 19667.59 | AD26: 0 | AE26: 0 | AH26: 91 | AI26: 90 | AJ26: 1 | AK26: 1 | AL26: 1 | AM26: 98.9 | AN26: 218.5288 | AO26: 214.74 | AP26: 44979 | AQ26: 0 | AR26: 1
A27: PO-000026 | B27: LOM-0046 | C27: Fibre Connector Module 0046 | D27: Fibre Connector | E27: Standard | F27: 1 | G27: 2 | H27: 1 | I27: VEN-033 | J27: Oribel Technologies | K27: Taiwan | L27: Transactional | M27: 17.66 | N27: BUY-04 | O27: Johan Lindberg | P27: Optics & Coatings | Q27: 44959 | R27: 44994 | S27: 2023 | T27: 2023-02 | U27: 844 | V27: 24.687 | W27: 208.81 | X27: 0 | Y27: 0 | Z27: 20835.83 | AA27: 21044.64 | AB27: PA-0000205 | AC27: 24.687 | AD27: 1 | AE27: 1 | AF27: 0 | AG27: 20835.83 | AH27: 844 | AI27: 832 | AJ27: 12 | AK27: 1 | AL27: 1 | AM27: 98.58 | AN27: 25.294 | AO27: 296.24 | AP27: 44994 | AQ27: 0 | AR27: 1
A28: PO-000027 | B28: LOM-0072 | C28: Laser Diode Component 0072 | D28: Laser Diode | E28: Commodity | F28: 3 | G28: 1 | H28: 0 | I28: VEN-004 | J28: Spectra GmbH | K28: United Kingdom | L28: Strategic | M28: 1.51 | N28: BUY-02 | O28: Rafael Duarte | P28: Optoelectronics | Q28: 44959 | R28: 44988 | S28: 2023 | T28: 2023-02 | U28: 146 | V28: 206.2888 | W28: 395.36 | X28: 0 | Y28: 0 | Z28: 30118.16 | AA28: 30513.52 | AB28: PA-0000325 | AC28: 206.2888 | AD28: 1 | AE28: 1 | AF28: 0 | AG28: 30118.16 | AH28: 146 | AI28: 133 | AJ28: 13 | AK28: 1 | AL28: 1 | AM28: 91.1 | AN28: 229.425 | AO28: 2681.75 | AP28: 44994 | AQ28: 6 | AR28: 0
A29: PO-000028 | B29: LOM-0084 | C29: Optical Coating Module 0084 | D29: Optical Coating | E29: Standard | F29: 2 | G29: 3 | H29: 0 | I29: VEN-016 | J29: Spectra Industries | K29: United Kingdom | L29: Preferred | M29: 7.82 | N29: BUY-03 | O29: Mei-Ling Chow | P29: Optics & Coatings | Q29: 44959 | R29: 44997 | S29: 2023 | T29: 2023-02 | U29: 286 | V29: 152.1308 | W29: 278.33 | X29: 0 | Y29: 0 | Z29: 43509.41 | AA29: 43787.74 | AB29: PA-0000377 | AC29: 152.1308 | AD29: 1 | AE29: 1 | AF29: 0 | AG29: 43509.41 | AH29: 286 | AI29: 285 | AJ29: 1 | AK29: 1 | AL29: 1 | AM29: 99.65 | AN29: 153.6412 | AO29: 152.13 | AP29: 45004 | AQ29: 7 | AR29: 0
A30: PO-000029 | B30: LOM-0099 | C30: Lens Assembly Module 0099 | D30: Lens Assembly | E30: Standard | F30: 3 | G30: 4 | H30: 0 | I30: VEN-010 | J30: Vectra GmbH | K30: United Kingdom | L30: Preferred | M30: 5.43 | N30: BUY-04 | O30: Johan Lindberg | P30: Optics & Coatings | Q30: 44959 | R30: 44995 | S30: 2023 | T30: 2023-02 | U30: 129 | V30: 107.2827 | W30: 247.86 | X30: 0 | Y30: 0 | Z30: 13839.47 | AA30: 14087.33 | AB30: PA-0000449 | AC30: 107.2827 | AD30: 1 | AE30: 1 | AF30: 0 | AG30: 13839.47 | AH30: 129 | AI30: 128 | AJ30: 1 | AK30: 1 | AL30: 1 | AM30: 99.22 | AN30: 110.0573 | AO30: 107.28 | AP30: 44995 | AQ30: 0 | AR30: 1
A31: PO-000030 | B31: LOM-0114 | C31: Optical Fibre Assy 0114 | D31: Optical Fibre | E31: Critical | F31: 3 | G31: 11 | H31: 0 | I31: VEN-027 | J31: Crystalline Technologies | K31: Taiwan | L31: Approved | M31: 14.24 | N31: BUY-03 | O31: Mei-Ling Chow | P31: Optics & Coatings | Q31: 44959 | R31: 45002 | S31: 2023 | T31: 2023-02 | U31: 1082 | V31: 15.4622 | W31: 188.33 | X31: 0 | Y31: 0 | Z31: 16730.1 | AA31: 16918.43 | AB31: PA-0000525 | AC31: 15.4622 | AD31: 1 | AE31: 1 | AF31: 0 | AG31: 16730.1 | AH31: 1082 | AI31: 1076 | AJ31: 6 | AK31: 1 | AL31: 1 | AM31: 99.45 | AN31: 15.7234 | AO31: 92.77 | AP31: 44999 | AQ31: -3 | AR31: 1
A32: PO-000031 | B32: LOM-0123 | C32: Lens Assembly Assy 0123 | D32: Lens Assembly | E32: Critical | F32: 3 | G32: 11 | H32: 0 | I32: VEN-002 | J32: Photonica GmbH | K32: Japan | L32: Strategic | M32: 2.49 | N32: BUY-04 | O32: Johan Lindberg | P32: Optics & Coatings | Q32: 44959 | R32: 45009 | S32: 2023 | T32: 2023-02 | U32: 126 | V32: 239.1274 | W32: 597.51 | X32: 972.12 | Y32: 1 | Z32: 30130.05 | AA32: 31699.68 | AB32: PA-0000565 | AC32: 239.1274 | AD32: 1 | AE32: 1 | AF32: 0 | AG32: 30130.05 | AH32: 126 | AI32: 123 | AJ32: 3 | AK32: 1 | AL32: 1 | AM32: 97.62 | AN32: 257.721 | AO32: 717.38 | AP32: 45006 | AQ32: -3 | AR32: 1
A33: PO-000032 | B33: LOM-0071 | C33: Thermal Control Component 0071 | D33: Thermal Control | E33: Commodity | F33: 3 | G33: 1 | H33: 0 | I33: VEN-013 | J33: Lumitek Industries | K33: United States | L33: Preferred | M33: 9.15 | N33: BUY-06 | O33: Tomas Varga | P33: Mechanical & Thermal | Q33: 44960 | R33: 44974 | S33: 2023 | T33: 2023-02 | U33: 30 | V33: 79.9559 | W33: 60.46 | X33: 0 | Y33: 0 | Z33: 2398.68 | AA33: 2459.14 | AB33: PA-0000322 | AC33: 79.9559 | AD33: 1 | AE33: 1 | AF33: 0 | AG33: 2398.68 | AH33: 30 | AI33: 30 | AJ33: 0 | AK33: 1 | AL33: 1 | AM33: 100 | AN33: 81.9712 | AO33: 0 | AP33: 44974 | AQ33: 0 | AR33: 1
A34: PO-000033 | B34: LOM-0096 | C34: Laser Diode Module 0096 | D34: Laser Diode | E34: Standard | F34: 1 | G34: 2 | H34: 1 | I34: VEN-011 | J34: Kestrel Optical GmbH | K34: Switzerland | L34: Preferred | M34: 3.73 | N34: BUY-01 | O34: Adaeze Okonkwo | P34: Optoelectronics | Q34: 44960 | R34: 44993 | S34: 2023 | T34: 2023-02 | U34: 105 | V34: 416.4004 | W34: 652.65 | X34: 0 | Y34: 0 | Z34: 43722.04 | AA34: 44374.69 | AB34: PA-0000434 | AC34: 416.4004 | AD34: 1 | AE34: 1 | AF34: 0 | AG34: 43722.04 | AH34: 105 | AI34: 104 | AJ34: 1 | AK34: 1 | AL34: 1 | AM34: 99.05 | AN34: 426.6797 | AO34: 416.4 | AP34: 44991 | AQ34: -2 | AR34: 1
A35: PO-000034 | B35: LOM-0124 | C35: Optical Coating Module 0124 | D35: Optical Coating | E35: Standard | F35: 3 | G35: 5 | H35: 0 | I35: VEN-031 | J35: Quantex Technologies | K35: United States | L35: Transactional | M35: 14.93 | N35: BUY-03 | O35: Mei-Ling Chow | P35: Optics & Coatings | Q35: 44960 | R35: 44998 | S35: 2023 | T35: 2023-02 | U35: 294 | V35: 147.55 | W35: 588.22 | X35: 0 | Y35: 0 | Z35: 43379.7 | AA35: 43967.92 | AB35: PA-0000572 | AC35: 147.55 | AD35: 1 | AE35: 1 | AF35: 0 | AG35: 43379.7 | AH35: 294 | AI35: 292 | AJ35: 2 | AK35: 1 | AL35: 1 | AM35: 99.32 | AN35: 150.5751 | AO35: 295.1 | AP35: 44995 | AQ35: -3 | AR35: 1
A36: PO-000035 | B36: LOM-0138 | C36: Optical Fibre Module 0138 | D36: Optical Fibre | E36: Standard | F36: 3 | G36: 4 | H36: 0 | I36: VEN-010 | J36: Vectra GmbH | K36: United Kingdom | L36: Preferred | M36: 5.43 | N36: BUY-04 | O36: Johan Lindberg | P36: Optics & Coatings | Q36: 44960 | R36: 44983 | S36: 2023 | T36: 2023-02 | U36: 432 | V36: 39.8613 | W36: 369.88 | X36: 0 | Y36: 0 | Z36: 17220.08 | AA36: 17589.96 | AD36: 0 | AE36: 0 | AH36: 432 | AI36: 427 | AJ36: 5 | AK36: 1 | AL36: 1 | AM36: 98.84 | AN36: 41.1943 | AO36: 199.31 | AP36: 44982 | AQ36: -1 | AR36: 1
A37: PO-000036 | B37: LOM-0053 | C37: Precision Mount Assy 0053 | D37: Precision Mount | E37: Critical | F37: 3 | G37: 11 | H37: 0 | I37: VEN-026 | J37: Photonica Technologies | K37: Japan | L37: Approved | M37: 9.22 | N37: BUY-06 | O37: Tomas Varga | P37: Mechanical & Thermal | Q37: 44963 | R37: 45004 | S37: 2023 | T37: 2023-02 | U37: 58 | V37: 164.8845 | W37: 111.48 | X37: 0 | Y37: 0 | Z37: 9563.3 | AA37: 9674.78 | AB37: PA-0000237 | AC37: 164.8845 | AD37: 1 | AE37: 1 | AF37: 0 | AG37: 9563.3 | AH37: 58 | AI37: 57 | AJ37: 1 | AK37: 1 | AL37: 1 | AM37: 98.28 | AN37: 169.733 | AO37: 164.88 | AP37: 45004 | AQ37: 0 | AR37: 1
A38: PO-000037 | B38: LOM-0080 | C38: Laser Diode Module 0080 | D38: Laser Diode | E38: Standard | F38: 3 | G38: 5 | H38: 0 | I38: VEN-004 | J38: Spectra GmbH | K38: United Kingdom | L38: Strategic | M38: 1.51 | N38: BUY-01 | O38: Adaeze Okonkwo | P38: Optoelectronics | Q38: 44963 | R38: 44987 | S38: 2023 | T38: 2023-02 | U38: 35 | V38: 501.9232 | W38: 285.32 | X38: 0 | Y38: 0 | Z38: 17567.31 | AA38: 17852.63 | AB38: PA-0000361 | AC38: 501.9232 | AD38: 1 | AE38: 1 | AF38: 0 | AG38: 17567.31 | AH38: 35 | AI38: 32 | AJ38: 3 | AK38: 1 | AL38: 1 | AM38: 91.43 | AN38: 557.8948 | AO38: 1505.77 | AP38: 44983 | AQ38: -4 | AR38: 1
A39: PO-000038 | B39: LOM-0027 | C39: Lens Assembly Component 0027 | D39: Lens Assembly | E39: Commodity | F39: 3 | G39: 1 | H39: 0 | I39: VEN-011 | J39: Kestrel Optical GmbH | K39: Switzerland | L39: Preferred | M39: 3.73 | N39: BUY-04 | O39: Johan Lindberg | P39: Optics & Coatings | Q39: 44964 | R39: 44986 | S39: 2023 | T39: 2023-02 | U39: 88 | V39: 303.3489 | W39: 558.13 | X39: 814.89 | Y39: 1 | Z39: 26694.7 | AA39: 28067.72 | AD39: 0 | AE39: 0 | AH39: 88 | AI39: 87 | AJ39: 1 | AK39: 1 | AL39: 1 | AM39: 98.86 | AN39: 322.6175 | AO39: 303.35 | AP39: 44991 | AQ39: 5 | AR39: 0
A40: PO-000039 | B40: LOM-0062 | C40: Fibre Connector Module 0062 | D40: Fibre Connector | E40: Standard | F40: 2 | G40: 3 | H40: 0 | I40: VEN-034 | J40: Vectra Technologies | K40: United Kingdom | L40: Transactional | M40: 34.49 | N40: BUY-03 | O40: Mei-Ling Chow | P40: Optics & Coatings | Q40: 44964 | R40: 44995 | S40: 2023 | T40: 2023-02 | U40: 605 | V40: 10.6486 | W40: 130.98 | X40: 0 | Y40: 0 | Z40: 6442.4 | AA40: 6573.38 | AB40: PA-0000277 | AC40: 10.6486 | AD40: 1 | AE40: 1 | AF40: 0 | AG40: 6442.4 | AH40: 605 | AI40: 601 | AJ40: 4 | AK40: 1 | AL40: 1 | AM40: 99.34 | AN40: 10.9374 | AO40: 42.59 | AP40: 44996 | AQ40: 1 | AR40: 0
A41: PO-000040 | B41: LOM-0093 | C41: Precision Mount Module 0093 | D41: Precision Mount | E41: Standard | F41: 2 | G41: 4 | H41: 0 | I41: VEN-034 | J41: Vectra Technologies | K41: United Kingdom | L41: Transactional | M41: 34.49 | N41: BUY-06 | O41: Tomas Varga | P41: Mechanical & Thermal | Q41: 44965 | R41: 44986 | S41: 2023 | T41: 2023-02 | U41: 12 | V41: 89.5497 | W41: 17.64 | X41: 0 | Y41: 0 | Z41: 1074.6 | AA41: 1092.24 | AB41: PA-0000424 | AC41: 95.0857 | AD41: 1 | AE41: 1 | AF41: -66.43 | AG41: 1141.03 | AH41: 12 | AI41: 12 | AJ41: 0 | AK41: 1 | AL41: 1 | AM41: 100 | AN41: 91.0197 | AO41: 0 | AP41: 44985 | AQ41: -1 | AR41: 1
A42: PO-000041 | B42: LOM-0114 | C42: Optical Fibre Assy 0114 | D42: Optical Fibre | E42: Critical | F42: 3 | G42: 11 | H42: 0 | I42: VEN-027 | J42: Crystalline Technologies | K42: Taiwan | L42: Approved | M42: 14.24 | N42: BUY-03 | O42: Mei-Ling Chow | P42: Optics & Coatings | Q42: 44965 | R42: 45001 | S42: 2023 | T42: 2023-02 | U42: 392 | V42: 15.4622 | W42: 135.14 | X42: 0 | Y42: 0 | Z42: 6061.18 | AA42: 6196.32 | AB42: PA-0000525 | AC42: 15.4622 | AD42: 1 | AE42: 1 | AF42: 0 | AG42: 6061.18 | AH42: 392 | AI42: 388 | AJ42: 4 | AK42: 1 | AL42: 1 | AM42: 98.98 | AN42: 15.9699 | AO42: 61.85 | AP42: 45001 | AQ42: 0 | AR42: 1
A43: PO-000042 | B43: LOM-0114 | C43: Optical Fibre Assy 0114 | D43: Optical Fibre | E43: Critical | F43: 3 | G43: 11 | H43: 0 | I43: VEN-027 | J43: Crystalline Technologies | K43: Taiwan | L43: Approved | M43: 14.24 | N43: BUY-04 | O43: Johan Lindberg | P43: Optics & Coatings | Q43: 44965 | R43: 45006 | S43: 2023 | T43: 2023-02 | U43: 815 | V43: 15.4622 | W43: 196.86 | X43: 0 | Y43: 0 | Z43: 12601.69 | AA43: 12798.55 | AB43: PA-0000525 | AC43: 15.4622 | AD43: 1 | AE43: 1 | AF43: 0 | AG43: 12601.69 | AH43: 815 | AI43: 812 | AJ43: 3 | AK43: 1 | AL43: 1 | AM43: 99.63 | AN43: 15.7618 | AO43: 46.39 | AP43: 45004 | AQ43: -2 | AR43: 1
A44: PO-000043 | B44: LOM-0035 | C44: Lens Assembly Assy 0035 | D44: Lens Assembly | E44: Critical | F44: 1 | G44: 8 | H44: 1 | I44: VEN-017 | J44: Helix Optics Industries | K44: Switzerland | L44: Approved | M44: 10.21 | N44: BUY-03 | O44: Mei-Ling Chow | P44: Optics & Coatings | Q44: 44967 | R44: 45004 | S44: 2023 | T44: 2023-02 | U44: 28 | V44: 138.256 | W44: 62.24 | X44: 0 | Y44: 0 | Z44: 3871.17 | AA44: 3933.41 | AB44: PA-0000155 | AC44: 138.256 | AD44: 1 | AE44: 1 | AF44: 0 | AG44: 3871.17 | AH44: 28 | AI44: 28 | AJ44: 0 | AK44: 1 | AL44: 1 | AM44: 100 | AN44: 140.4789 | AO44: 0 | AP44: 45004 | AQ44: 0 | AR44: 1
A45: PO-000044 | B45: LOM-0089 | C45: Photodetector Assy 0089 | D45: Photodetector | E45: Critical | F45: 1 | G45: 8 | H45: 1 | I45: VEN-014 | J45: Photonica Industries | K45: Japan | L45: Preferred | M45: 4.81 | N45: BUY-02 | O45: Rafael Duarte | P45: Optoelectronics | Q45: 44967 | R45: 45003 | S45: 2023 | T45: 2023-02 | U45: 22 | V45: 247.3183 | W45: 53.57 | X45: 0 | Y45: 0 | Z45: 5441 | AA45: 5494.57 | AB45: PA-0000403 | AC45: 247.3183 | AD45: 1 | AE45: 1 | AF45: 0 | AG45: 5441 | AH45: 22 | AI45: 22 | AJ45: 0 | AK45: 1 | AL45: 1 | AM45: 100 | AN45: 249.7533 | AO45: 0 | AP45: 45003 | AQ45: 0 | AR45: 1
A46: PO-000045 | B46: LOM-0035 | C46: Lens Assembly Assy 0035 | D46: Lens Assembly | E46: Critical | F46: 1 | G46: 8 | H46: 1 | I46: VEN-017 | J46: Helix Optics Industries | K46: Switzerland | L46: Approved | M46: 10.21 | N46: BUY-04 | O46: Johan Lindberg | P46: Optics & Coatings | Q46: 44970 | R46: 45010 | S46: 2023 | T46: 2023-02 | U46: 50 | V46: 138.256 | W46: 152.97 | X46: 0 | Y46: 0 | Z46: 6912.8 | AA46: 7065.77 | AB46: PA-0000155 | AC46: 138.256 | AD46: 1 | AE46: 1 | AF46: 0 | AG46: 6912.8 | AH46: 50 | AI46: 49 | AJ46: 1 | AK46: 1 | AL46: 1 | AM46: 98 | AN46: 144.1994 | AO46: 138.26 | AP46: 45010 | AQ46: 0 | AR46: 1
A47: PO-000046 | B47: LOM-0055 | C47: Thermal Control Component 0055 | D47: Thermal Control | E47: Commodity | F47: 3 | G47: 1 | H47: 0 | I47: VEN-025 | J47: Lumitek Technologies | K47: United States | L47: Approved | M47: 14.26 | N47: BUY-05 | O47: Priya Raghunathan | P47: Mechanical & Thermal | Q47: 44970 | R47: 44998 | S47: 2023 | T47: 2023-02 | U47: 138 | V47: 113.5119 | W47: 395.35 | X47: 0 | Y47: 0 | Z47: 15664.64 | AA47: 16059.99 | AB47: PA-X000002 | AC47: 117.4848 | AD47: 2 | AE47: 1 | AF47: -548.26 | AG47: 16212.9 | AH47: 138 | AI47: 136 | AJ47: 2 | AK47: 1 | AL47: 1 | AM47: 98.55 | AN47: 118.0882 | AO47: 227.02 | AP47: 44998 | AQ47: 0 | AR47: 1
A48: PO-000047 | B48: LOM-0084 | C48: Optical Coating Module 0084 | D48: Optical Coating | E48: Standard | F48: 2 | G48: 3 | H48: 0 | I48: VEN-016 | J48: Spectra Industries | K48: United Kingdom | L48: Preferred | M48: 7.82 | N48: BUY-03 | O48: Mei-Ling Chow | P48: Optics & Coatings | Q48: 44970 | R48: 44997 | S48: 2023 | T48: 2023-02 | U48: 127 | V48: 152.1308 | W48: 373.86 | X48: 0 | Y48: 0 | Z48: 19320.61 | AA48: 19694.47 | AB48: PA-0000377 | AC48: 152.1308 | AD48: 1 | AE48: 1 | AF48: 0 | AG48: 19320.61 | AH48: 127 | AI48: 126 | AJ48: 1 | AK48: 1 | AL48: 1 | AM48: 99.21 | AN48: 156.3053 | AO48: 152.13 | AP48: 44996 | AQ48: -1 | AR48: 1
A49: PO-000048 | B49: LOM-0093 | C49: Precision Mount Module 0093 | D49: Precision Mount | E49: Standard | F49: 2 | G49: 4 | H49: 0 | I49: VEN-034 | J49: Vectra Technologies | K49: United Kingdom | L49: Transactional | M49: 34.49 | N49: BUY-06 | O49: Tomas Varga | P49: Mechanical & Thermal | Q49: 44970 | R49: 45007 | S49: 2023 | T49: 2023-02 | U49: 140 | V49: 99.6119 | W49: 324.85 | X49: 0 | Y49: 0 | Z49: 13945.67 | AA49: 14270.52 | AB49: PA-0000424 | AC49: 95.0857 | AD49: 1 | AE49: 1 | AF49: 633.67 | AG49: 13312 | AH49: 140 | AI49: 139 | AJ49: 1 | AK49: 1 | AL49: 1 | AM49: 99.29 | AN49: 102.6656 | AO49: 99.61 | AP49: 45005 | AQ49: -2 | AR49: 1
A50: PO-000049 | B50: LOM-0013 | C50: Precision Mount Component 0013 | D50: Precision Mount | E50: Commodity | F50: 1 | G50: 0 | H50: 1 | I50: VEN-008 | J50: Meridian Photonics GmbH | K50: Japan | L50: Preferred | M50: 5.01 | N50: BUY-05 | O50: Priya Raghunathan | P50: Mechanical & Thermal | Q50: 44971 | R50: 44994 | S50: 2023 | T50: 2023-02 | U50: 103 | V50: 207.4813 | W50: 476.48 | X50: 0 | Y50: 0 | Z50: 21370.57 | AA50: 21847.05 | AB50: PA-0000057 | AC50: 207.4813 | AD50: 1 | AE50: 1 | AF50: 0 | AG50: 21370.57 | AH50: 103 | AI50: 103 | AJ50: 0 | AK50: 1 | AL50: 1 | AM50: 100 | AN50: 212.1073 | AO50: 0 | AP50: 44993 | AQ50: -1 | AR50: 1
A51: PO-000050 | B51: LOM-0027 | C51: Lens Assembly Component 0027 | D51: Lens Assembly | E51: Commodity | F51: 3 | G51: 1 | H51: 0 | I51: VEN-013 | J51: Lumitek Industries | K51: United States | L51: Preferred | M51: 9.15 | N51: BUY-03 | O51: Mei-Ling Chow | P51: Optics & Coatings | Q51: 44971 | R51: 44995 | S51: 2023 | T51: 2023-02 | U51: 107 | V51: 264.1759 | W51: 521.08 | X51: 886.53 | Y51: 1 | Z51: 28266.82 | AA51: 29674.43 | AB51: PA-0000120 | AC51: 264.1759 | AD51: 1 | AE51: 1 | AF51: 0 | AG51: 28266.82 | AH51: 107 | AI51: 106 | AJ51: 1 | AK51: 1 | AL51: 1 | AM51: 99.07 | AN51: 279.9475 | AO51: 264.18 | AP51: 45005 | AQ51: 10 | AR51: 0
... A74: PO-000073 | B74: LOM-0077 | C74: Precision Mount Assy 0077 | D74: Precision Mount | E74: Critical | F74: 2 | G74: 9 | H74: 0 | I74: VEN-001 | J74: Lumitek GmbH | K74: United States | L74: Strategic | M74: 1.37 | N74: BUY-05 | O74: Priya Raghunathan | P74: Mechanical & Thermal | Q74: 44979 | R74: 45023 | S74: 2023 | T74: 2023-02 | U74: 84 | V74: 249.9879 | W74: 280.03 | X74: 0 | Y74: 0 | Z74: 20998.98 | AA74: 21279.01 | AB74: PA-0000349 | AC74: 249.9879 | AD74: 1 | AE74: 1 | AF74: 0 | AG74: 20998.98 | AH74: 84 | AI74: 83 | AJ74: 1 | AK74: 1 | AL74: 1 | AM74: 98.81 | AN74: 256.3737 | AO74: 249.99 | AP74: 45022 | AQ74: -1 | AR74: 1
A75: PO-000074 | B75: LOM-0012 | C75: Optical Coating Component 0012 | D75: Optical Coating | E75: Commodity | F75: 3 | G75: 1 | H75: 0 | I75: VEN-031 | J75: Quantex Technologies | K75: United States | L75: Transactional | M75: 14.93 | N75: BUY-04 | O75: Johan Lindberg | P75: Optics & Coatings | Q75: 44980 | R75: 44994 | S75: 2023 | T75: 2023-02 | U75: 73 | V75: 109.1384 | W75: 152.28 | X75: 0 | Y75: 0 | Z75: 7967.1 | AA75: 8119.38 | AD75: 0 | AE75: 0 | AH75: 73 | AI75: 72 | AJ75: 1 | AK75: 1 | AL75: 1 | AM75: 98.63 | AN75: 112.7692 | AO75: 109.14 | AP75: 44991 | AQ75: -3 | AR75: 1
A76: PO-000075 | B76: LOM-0038 | C76: Fibre Connector Component 0038 | D76: Fibre Connector | E76: Commodity | F76: 3 | G76: 1 | H76: 0 | I76: VEN-013 | J76: Lumitek Industries | K76: United States | L76: Preferred | M76: 9.15 | N76: BUY-04 | O76: Johan Lindberg | P76: Optics & Coatings | Q76: 44980 | R76: 45006 | S76: 2023 | T76: 2023-02 | U76: 823 | V76: 8.7274 | W76: 169.58 | X76: 0 | Y76: 0 | Z76: 7182.65 | AA76: 7352.23 | AB76: PA-0000169 | AC76: 8.7274 | AD76: 1 | AE76: 1 | AF76: 0 | AG76: 7182.65 | AH76: 823 | AI76: 820 | AJ76: 3 | AK76: 1 | AL76: 1 | AM76: 99.64 | AN76: 8.9661 | AO76: 26.18 | AP76: 45003 | AQ76: -3 | AR76: 1
A77: PO-000076 | B77: LOM-0053 | C77: Precision Mount Assy 0053 | D77: Precision Mount | E77: Critical | F77: 3 | G77: 11 | H77: 0 | I77: VEN-026 | J77: Photonica Technologies | K77: Japan | L77: Approved | M77: 9.22 | N77: BUY-05 | O77: Priya Raghunathan | P77: Mechanical & Thermal | Q77: 44980 | R77: 45016 | S77: 2023 | T77: 2023-02 | U77: 22 | V77: 164.8845 | W77: 54.55 | X77: 0 | Y77: 0 | Z77: 3627.46 | AA77: 3682.01 | AB77: PA-0000237 | AC77: 164.8845 | AD77: 1 | AE77: 1 | AF77: 0 | AG77: 3627.46 | AH77: 22 | AI77: 22 | AJ77: 0 | AK77: 1 | AL77: 1 | AM77: 100 | AN77: 167.364 | AO77: 0 | AP77: 45025 | AQ77: 9 | AR77: 0
A78: PO-000077 | B78: LOM-0072 | C78: Laser Diode Component 0072 | D78: Laser Diode | E78: Commodity | F78: 3 | G78: 1 | H78: 0 | I78: VEN-012 | J78: Aperture Industries | K78: Germany | L78: Preferred | M78: 4.72 | N78: BUY-01 | O78: Adaeze Okonkwo | P78: Optoelectronics | Q78: 44980 | R78: 44997 | S78: 2023 | T78: 2023-02 | U78: 54 | V78: 206.2888 | W78: 205.43 | X78: 0 | Y78: 0 | Z78: 11139.6 | AA78: 11345.03 | AB78: PA-0000328 | AC78: 206.2888 | AD78: 1 | AE78: 1 | AF78: 0 | AG78: 11139.6 | AH78: 54 | AI78: 54 | AJ78: 0 | AK78: 1 | AL78: 1 | AM78: 100 | AN78: 210.0931 | AO78: 0 | AP78: 44994 | AQ78: -3 | AR78: 1
A79: PO-000078 | B79: LOM-0084 | C79: Optical Coating Module 0084 | D79: Optical Coating | E79: Standard | F79: 2 | G79: 3 | H79: 0 | I79: VEN-016 | J79: Spectra Industries | K79: United Kingdom | L79: Preferred | M79: 7.82 | N79: BUY-03 | O79: Mei-Ling Chow | P79: Optics & Coatings | Q79: 44980 | R79: 45002 | S79: 2023 | T79: 2023-02 | U79: 59 | V79: 152.1308 | W79: 94.97 | X79: 0 | Y79: 0 | Z79: 8975.72 | AA79: 9070.69 | AB79: PA-0000377 | AC79: 152.1308 | AD79: 1 | AE79: 1 | AF79: 0 | AG79: 8975.72 | AH79: 59 | AI79: 58 | AJ79: 1 | AK79: 1 | AL79: 1 | AM79: 98.31 | AN79: 156.3912 | AO79: 152.13 | AP79: 44999 | AQ79: -3 | AR79: 1
A80: PO-000079 | B80: LOM-0085 | C80: Precision Mount Component 0085 | D80: Precision Mount | E80: Commodity | F80: 3 | G80: 1 | H80: 0 | I80: VEN-022 | J80: Vectra Industries | K80: United Kingdom | L80: Approved | M80: 12.65 | N80: BUY-06 | O80: Tomas Varga | P80: Mechanical & Thermal | Q80: 44980 | R80: 44999 | S80: 2023 | T80: 2023-02 | U80: 65 | V80: 116.7718 | W80: 175.84 | X80: 0 | Y80: 0 | Z80: 7590.17 | AA80: 7766.01 | AD80: 0 | AE80: 0 | AH80: 65 | AI80: 64 | AJ80: 1 | AK80: 1 | AL80: 1 | AM80: 98.46 | AN80: 121.3439 | AO80: 116.77 | AP80: 44998 | AQ80: -1 | AR80: 1
A81: PO-000080 | B81: LOM-0092 | C81: Optical Coating Component 0092 | D81: Optical Coating | E81: Commodity | F81: 3 | G81: 0 | H81: 0 | I81: VEN-012 | J81: Aperture Industries | K81: Germany | L81: Preferred | M81: 4.72 | N81: BUY-03 | O81: Mei-Ling Chow | P81: Optics & Coatings | Q81: 44981 | R81: 44993 | S81: 2023 | T81: 2023-02 | U81: 52 | V81: 63.1406 | W81: 48.89 | X81: 0 | Y81: 0 | Z81: 3283.31 | AA81: 3332.2 | AB81: PA-0000419 | AC81: 63.1406 | AD81: 1 | AE81: 1 | AF81: 0 | AG81: 3283.31 | AH81: 52 | AI81: 51 | AJ81: 1 | AK81: 1 | AL81: 1 | AM81: 98.08 | AN81: 65.3373 | AO81: 63.14 | AP81: 44992 | AQ81: -1 | AR81: 1
A82: PO-000081 | B82: LOM-0093 | C82: Precision Mount Module 0093 | D82: Precision Mount | E82: Standard | F82: 2 | G82: 4 | H82: 0 | I82: VEN-010 | J82: Vectra GmbH | K82: United Kingdom | L82: Preferred | M82: 5.43 | N82: BUY-05 | O82: Priya Raghunathan | P82: Mechanical & Thermal | Q82: 44981 | R82: 45003 | S82: 2023 | T82: 2023-02 | U82: 18 | V82: 89.4811 | W82: 25.75 | X82: 0 | Y82: 0 | Z82: 1610.66 | AA82: 1636.41 | AB82: PA-0000421 | AC82: 95.0857 | AD82: 1 | AE82: 1 | AF82: -100.88 | AG82: 1711.54 | AH82: 18 | AI82: 18 | AJ82: 0 | AK82: 1 | AL82: 1 | AM82: 100 | AN82: 90.9117 | AO82: 0 | AP82: 45002 | AQ82: -1 | AR82: 1
A83: PO-000082 | B83: LOM-0096 | C83: Laser Diode Module 0096 | D83: Laser Diode | E83: Standard | F83: 1 | G83: 2 | H83: 1 | I83: VEN-011 | J83: Kestrel Optical GmbH | K83: Switzerland | L83: Preferred | M83: 3.73 | N83: BUY-01 | O83: Adaeze Okonkwo | P83: Optoelectronics | Q83: 44981 | R83: 45012 | S83: 2023 | T83: 2023-02 | U83: 88 | V83: 416.4004 | W83: 739.74 | X83: 0 | Y83: 0 | Z83: 36643.24 | AA83: 37382.98 | AB83: PA-0000434 | AC83: 416.4004 | AD83: 1 | AE83: 1 | AF83: 0 | AG83: 36643.24 | AH83: 88 | AI83: 87 | AJ83: 1 | AK83: 1 | AL83: 1 | AM83: 98.86 | AN83: 429.6894 | AO83: 416.4 | AP83: 45012 | AQ83: 0 | AR83: 1
A84: PO-000083 | B84: LOM-0103 | C84: Thermal Control Component 0103 | D84: Thermal Control | E84: Commodity | F84: 3 | G84: 1 | H84: 0 | I84: VEN-022 | J84: Vectra Industries | K84: United Kingdom | L84: Approved | M84: 12.65 | N84: BUY-06 | O84: Tomas Varga | P84: Mechanical & Thermal | Q84: 44981 | R84: 45010 | S84: 2023 | T84: 2023-02 | U84: 144 | V84: 183.362 | W84: 257.52 | X84: 0 | Y84: 0 | Z84: 26404.13 | AA84: 26661.65 | AB84: PA-0000469 | AC84: 194.9136 | AD84: 1 | AE84: 1 | AF84: -1663.43 | AG84: 28067.56 | AH84: 144 | AI84: 143 | AJ84: 1 | AK84: 1 | AL84: 1 | AM84: 99.31 | AN84: 186.4451 | AO84: 183.36 | AP84: 45008 | AQ84: -2 | AR84: 1
A85: PO-000084 | B85: LOM-0006 | C85: Fibre Connector Component 0006 | D85: Fibre Connector | E85: Commodity | F85: 2 | G85: 0 | H85: 0 | I85: VEN-001 | J85: Lumitek GmbH | K85: United States | L85: Strategic | M85: 1.37 | N85: BUY-03 | O85: Mei-Ling Chow | P85: Optics & Coatings | Q85: 44984 | R85: 44996 | S85: 2023 | T85: 2023-02 | U85: 106 | V85: 15.8481 | W85: 33.07 | X85: 0 | Y85: 0 | Z85: 1679.9 | AA85: 1712.97 | AB85: PA-0000022 | AC85: 15.8481 | AD85: 1 | AE85: 1 | AF85: 0 | AG85: 1679.9 | AH85: 106 | AI85: 105 | AJ85: 1 | AK85: 1 | AL85: 1 | AM85: 99.06 | AN85: 16.314 | AO85: 15.85 | AP85: 44996 | AQ85: 0 | AR85: 1
A86: PO-000085 | B86: LOM-0013 | C86: Precision Mount Component 0013 | D86: Precision Mount | E86: Commodity | F86: 1 | G86: 0 | H86: 1 | I86: VEN-008 | J86: Meridian Photonics GmbH | K86: Japan | L86: Preferred | M86: 5.01 | N86: BUY-06 | O86: Tomas Varga | P86: Mechanical & Thermal | Q86: 44984 | R86: 45005 | S86: 2023 | T86: 2023-02 | U86: 84 | V86: 195.117 | W86: 398.92 | X86: 0 | Y86: 0 | Z86: 16389.83 | AA86: 16788.75 | AB86: PA-0000057 | AC86: 207.4813 | AD86: 1 | AE86: 1 | AF86: -1038.6 | AG86: 17428.43 | AH86: 84 | AI86: 83 | AJ86: 1 | AK86: 1 | AL86: 1 | AM86: 98.81 | AN86: 202.2741 | AO86: 195.12 | AP86: 45004 | AQ86: -1 | AR86: 1
A87: PO-000086 | B87: LOM-0036 | C87: Optical Coating Module 0036 | D87: Optical Coating | E87: Standard | F87: 2 | G87: 4 | H87: 0 | I87: VEN-020 | J87: Meridian Photonics Industries | K87: Japan | L87: Approved | M87: 12.07 | N87: BUY-03 | O87: Mei-Ling Chow | P87: Optics & Coatings | Q87: 44984 | R87: 45017 | S87: 2023 | T87: 2023-02 | U87: 218 | V87: 45.991 | W87: 122.84 | X87: 308.61 | Y87: 1 | Z87: 10026.04 | AA87: 10457.49 | AB87: PA-0000157 | AC87: 45.991 | AD87: 1 | AE87: 1 | AF87: 0 | AG87: 10026.04 | AH87: 218 | AI87: 214 | AJ87: 4 | AK87: 1 | AL87: 1 | AM87: 98.17 | AN87: 48.8668 | AO87: 183.96 | AP87: 45017 | AQ87: 0 | AR87: 1
A88: PO-000087 | B88: LOM-0046 | C88: Fibre Connector Module 0046 | D88: Fibre Connector | E88: Standard | F88: 1 | G88: 2 | H88: 1 | I88: VEN-033 | J88: Oribel Technologies | K88: Taiwan | L88: Transactional | M88: 17.66 | N88: BUY-03 | O88: Mei-Ling Chow | P88: Optics & Coatings | Q88: 44984 | R88: 45010 | S88: 2023 | T88: 2023-02 | U88: 363 | V88: 24.687 | W88: 156.23 | X88: 0 | Y88: 0 | Z88: 8961.38 | AA88: 9117.61 | AB88: PA-0000205 | AC88: 24.687 | AD88: 1 | AE88: 1 | AF88: 0 | AG88: 8961.38 | AH88: 363 | AI88: 362 | AJ88: 1 | AK88: 1 | AL88: 1 | AM88: 99.72 | AN88: 25.1868 | AO88: 24.69 | AP88: 45019 | AQ88: 9 | AR88: 0
A89: PO-000088 | B89: LOM-0092 | C89: Optical Coating Component 0092 | D89: Optical Coating | E89: Commodity | F89: 3 | G89: 0 | H89: 0 | I89: VEN-012 | J89: Aperture Industries | K89: Germany | L89: Preferred | M89: 4.72 | N89: BUY-03 | O89: Mei-Ling Chow | P89: Optics & Coatings | Q89: 44985 | R89: 45005 | S89: 2023 | T89: 2023-02 | U89: 164 | V89: 63.1406 | W89: 249.16 | X89: 0 | Y89: 0 | Z89: 10355.06 | AA89: 10604.22 | AB89: PA-0000419 | AC89: 63.1406 | AD89: 1 | AE89: 1 | AF89: 0 | AG89: 10355.06 | AH89: 164 | AI89: 163 | AJ89: 1 | AK89: 1 | AL89: 1 | AM89: 99.39 | AN89: 65.0566 | AO89: 63.14 | AP89: 45004 | AQ89: -1 | AR89: 1
A90: PO-000089 | B90: LOM-0058 | C90: Optical Fibre Module 0058 | D90: Optical Fibre | E90: Standard | F90: 3 | G90: 4 | H90: 0 | I90: VEN-023 | J90: Kestrel Optical Industries | K90: Switzerland | L90: Approved | M90: 6.75 | N90: BUY-03 | O90: Mei-Ling Chow | P90: Optics & Coatings | Q90: 44986 | R90: 45012 | S90: 2023 | T90: 2023-03 | U90: 702 | V90: 55.5447 | W90: 709.91 | X90: 0 | Y90: 0 | Z90: 38992.38 | AA90: 39702.29 | AB90: PA-0000259 | AC90: 55.5447 | AD90: 1 | AE90: 1 | AF90: 0 | AG90: 38992.38 | AH90: 702 | AI90: 700 | AJ90: 2 | AK90: 1 | AL90: 1 | AM90: 99.72 | AN90: 56.7176 | AO90: 111.09 | AP90: 45009 | AQ90: -3 | AR90: 1
A91: PO-000090 | B91: LOM-0070 | C91: Fibre Connector Component 0070 | D91: Fibre Connector | E91: Commodity | F91: 3 | G91: 1 | H91: 0 | I91: VEN-007 | J91: Quantex GmbH | K91: United States | L91: Preferred | M91: 10.21 | N91: BUY-03 | O91: Mei-Ling Chow | P91: Optics & Coatings | Q91: 44986 | R91: 45011 | S91: 2023 | T91: 2023-03 | U91: 791 | V91: 16.8649 | W91: 178.88 | X91: 0 | Y91: 0 | Z91: 13340.14 | AA91: 13519.02 | AB91: PA-0000316 | AC91: 16.1609 | AD91: 1 | AE91: 1 | AF91: 556.86 | AG91: 12783.27 | AH91: 791 | AI91: 781 | AJ91: 10 | AK91: 1 | AL91: 1 | AM91: 98.74 | AN91: 17.3099 | AO91: 168.65 | AP91: 45009 | AQ91: -2 | AR91: 1
A92: PO-000091 | B92: LOM-0114 | C92: Optical Fibre Assy 0114 | D92: Optical Fibre | E92: Critical | F92: 3 | G92: 11 | H92: 0 | I92: VEN-027 | J92: Crystalline Technologies | K92: Taiwan | L92: Approved | M92: 14.24 | N92: BUY-04 | O92: Johan Lindberg | P92: Optics & Coatings | Q92: 44986 | R92: 45036 | S92: 2023 | T92: 2023-03 | U92: 1790 | V92: 15.4622 | W92: 478.91 | X92: 0 | Y92: 0 | Z92: 27677.34 | AA92: 28156.25 | AB92: PA-0000525 | AC92: 15.4622 | AD92: 1 | AE92: 1 | AF92: 0 | AG92: 27677.34 | AH92: 1790 | AI92: 1778 | AJ92: 12 | AK92: 1 | AL92: 1 | AM92: 99.33 | AN92: 15.8359 | AO92: 185.55 | AP92: 45033 | AQ92: -3 | AR92: 1
... A118: PO-000117 | B118: LOM-0129 | C118: Photodetector Module 0129 | D118: Photodetector | E118: Standard | F118: 2 | G118: 2 | H118: 0 | I118: VEN-014 | J118: Photonica Industries | K118: Japan | L118: Preferred | M118: 4.81 | N118: BUY-01 | O118: Adaeze Okonkwo | P118: Optoelectronics | Q118: 44994 | R118: 45031 | S118: 2023 | T118: 2023-03 | U118: 138 | V118: 388.5493 | W118: 925.39 | X118: 0 | Y118: 0 | Z118: 53619.8 | AA118: 54545.19 | AB118: PA-0000599 | AC118: 388.5493 | AD118: 1 | AE118: 1 | AF118: 0 | AG118: 53619.8 | AH118: 138 | AI118: 136 | AJ118: 2 | AK118: 1 | AL118: 1 | AM118: 98.55 | AN118: 401.0676 | AO118: 777.1 | AP118: 45041 | AQ118: 10 | AR118: 0
A119: PO-000118 | B119: LOM-0063 | C119: Thermal Control Component 0063 | D119: Thermal Control | E119: Commodity | F119: 3 | G119: 1 | H119: 0 | I119: VEN-012 | J119: Aperture Industries | K119: Germany | L119: Preferred | M119: 4.72 | N119: BUY-06 | O119: Tomas Varga | P119: Mechanical & Thermal | Q119: 44995 | R119: 45007 | S119: 2023 | T119: 2023-03 | U119: 14 | V119: 283.6766 | W119: 50.01 | X119: 0 | Y119: 0 | Z119: 3971.47 | AA119: 4021.48 | AD119: 0 | AE119: 0 | AH119: 14 | AI119: 14 | AJ119: 0 | AK119: 1 | AL119: 1 | AM119: 100 | AN119: 287.2487 | AO119: 0 | AP119: 45005 | AQ119: -2 | AR119: 1
A120: PO-000119 | B120: LOM-0090 | C120: Optical Fibre Component 0090 | D120: Optical Fibre | E120: Commodity | F120: 3 | G120: 1 | H120: 0 | I120: VEN-031 | J120: Quantex Technologies | K120: United States | L120: Transactional | M120: 14.93 | N120: BUY-04 | O120: Johan Lindberg | P120: Optics & Coatings | Q120: 44995 | R120: 45013 | S120: 2023 | T120: 2023-03 | U120: 813 | V120: 21.7962 | W120: 430.16 | X120: 0 | Y120: 0 | Z120: 17720.31 | AA120: 18150.47 | AB120: PA-0000407 | AC120: 21.7962 | AD120: 1 | AE120: 1 | AF120: 0 | AG120: 17720.31 | AH120: 813 | AI120: 803 | AJ120: 10 | AK120: 1 | AL120: 1 | AM120: 98.77 | AN120: 22.6033 | AO120: 217.96 | AP120: 45012 | AQ120: -1 | AR120: 1
A121: PO-000120 | B121: LOM-0102 | C121: Fibre Connector Component 0102 | D121: Fibre Connector | E121: Commodity | F121: 2 | G121: 0 | H121: 0 | I121: VEN-009 | J121: Oribel GmbH | K121: Taiwan | L121: Preferred | M121: 9.47 | N121: BUY-04 | O121: Johan Lindberg | P121: Optics & Coatings | Q121: 44995 | R121: 45023 | S121: 2023 | T121: 2023-03 | U121: 942 | V121: 24.7823 | W121: 383.68 | X121: 0 | Y121: 0 | Z121: 23344.93 | AA121: 23728.61 | AB121: PA-0000461 | AC121: 24.7823 | AD121: 1 | AE121: 1 | AF121: 0 | AG121: 23344.93 | AH121: 942 | AI121: 936 | AJ121: 6 | AK121: 1 | AL121: 1 | AM121: 99.36 | AN121: 25.3511 | AO121: 148.69 | AP121: 45029 | AQ121: 6 | AR121: 0
A122: PO-000121 | B122: LOM-0102 | C122: Fibre Connector Component 0102 | D122: Fibre Connector | E122: Commodity | F122: 2 | G122: 0 | H122: 0 | I122: VEN-009 | J122: Oribel GmbH | K122: Taiwan | L122: Preferred | M122: 9.47 | N122: BUY-03 | O122: Mei-Ling Chow | P122: Optics & Coatings | Q122: 44995 | R122: 45023 | S122: 2023 | T122: 2023-03 | U122: 920 | V122: 24.7823 | W122: 190.9 | X122: 0 | Y122: 0 | Z122: 22799.72 | AA122: 22990.62 | AB122: PA-0000461 | AC122: 24.7823 | AD122: 1 | AE122: 1 | AF122: 0 | AG122: 22799.72 | AH122: 920 | AI122: 914 | AJ122: 6 | AK122: 1 | AL122: 1 | AM122: 99.35 | AN122: 25.1538 | AO122: 148.69 | AP122: 45022 | AQ122: -1 | AR122: 1
A123: PO-000122 | B123: LOM-0140 | C123: Optical Coating Module 0140 | D123: Optical Coating | E123: Standard | F123: 2 | G123: 4 | H123: 0 | I123: VEN-008 | J123: Meridian Photonics GmbH | K123: Japan | L123: Preferred | M123: 5.01 | N123: BUY-04 | O123: Johan Lindberg | P123: Optics & Coatings | Q123: 44995 | R123: 45019 | S123: 2023 | T123: 2023-03 | U123: 87 | V123: 76.3311 | W123: 161.78 | X123: 0 | Y123: 0 | Z123: 6640.81 | AA123: 6802.59 | AB123: PA-0000644 | AC123: 76.3311 | AD123: 1 | AE123: 1 | AF123: 0 | AG123: 6640.81 | AH123: 87 | AI123: 86 | AJ123: 1 | AK123: 1 | AL123: 1 | AM123: 98.85 | AN123: 79.0998 | AO123: 76.33 | AP123: 45016 | AQ123: -3 | AR123: 1
A124: PO-000123 | B124: LOM-0044 | C124: Optical Coating Assy 0044 | D124: Optical Coating | E124: Critical | F124: 3 | G124: 11 | H124: 0 | I124: VEN-006 | J124: Northlight GmbH | K124: Germany | L124: Strategic | M124: 4.77 | N124: BUY-03 | O124: Mei-Ling Chow | P124: Optics & Coatings | Q124: 44998 | R124: 45050 | S124: 2023 | T124: 2023-03 | U124: 287 | V124: 103.5621 | W124: 647.58 | X124: 0 | Y124: 0 | Z124: 29722.32 | AA124: 30369.9 | AB124: PA-0000194 | AC124: 110.1158 | AD124: 1 | AE124: 1 | AF124: -1880.91 | AG124: 31603.23 | AH124: 287 | AI124: 280 | AJ124: 7 | AK124: 1 | AL124: 1 | AM124: 97.56 | AN124: 108.4639 | AO124: 724.93 | AP124: 45057 | AQ124: 7 | AR124: 0
A125: PO-000124 | B125: LOM-0072 | C125: Laser Diode Component 0072 | D125: Laser Diode | E125: Commodity | F125: 3 | G125: 1 | H125: 0 | I125: VEN-012 | J125: Aperture Industries | K125: Germany | L125: Preferred | M125: 4.72 | N125: BUY-02 | O125: Rafael Duarte | P125: Optoelectronics | Q125: 44998 | R125: 45015 | S125: 2023 | T125: 2023-03 | U125: 51 | V125: 206.2888 | W125: 96.15 | X125: 0 | Y125: 0 | Z125: 10520.73 | AA125: 10616.88 | AB125: PA-0000328 | AC125: 206.2888 | AD125: 1 | AE125: 1 | AF125: 0 | AG125: 10520.73 | AH125: 51 | AI125: 50 | AJ125: 1 | AK125: 1 | AL125: 1 | AM125: 98.04 | AN125: 212.3376 | AO125: 206.29 | AP125: 45020 | AQ125: 5 | AR125: 0
A126: PO-000125 | B126: LOM-0080 | C126: Laser Diode Module 0080 | D126: Laser Diode | E126: Standard | F126: 3 | G126: 5 | H126: 0 | I126: VEN-004 | J126: Spectra GmbH | K126: United Kingdom | L126: Strategic | M126: 1.51 | N126: BUY-01 | O126: Adaeze Okonkwo | P126: Optoelectronics | Q126: 44998 | R126: 45030 | S126: 2023 | T126: 2023-03 | U126: 103 | V126: 501.9232 | W126: 1296.79 | X126: 0 | Y126: 0 | Z126: 51698.09 | AA126: 52994.88 | AB126: PA-0000361 | AC126: 501.9232 | AD126: 1 | AE126: 1 | AF126: 0 | AG126: 51698.09 | AH126: 103 | AI126: 92 | AJ126: 11 | AK126: 1 | AL126: 1 | AM126: 89.32 | AN126: 576.0313 | AO126: 5521.16 | AP126: 45030 | AQ126: 0 | AR126: 1
A127: PO-000126 | B127: LOM-0094 | C127: Fibre Connector Module 0094 | D127: Fibre Connector | E127: Standard | F127: 3 | G127: 5 | H127: 0 | I127: VEN-014 | J127: Photonica Industries | K127: Japan | L127: Preferred | M127: 4.81 | N127: BUY-03 | O127: Mei-Ling Chow | P127: Optics & Coatings | Q127: 44998 | R127: 45028 | S127: 2023 | T127: 2023-03 | U127: 577 | V127: 24.6179 | W127: 239.76 | X127: 0 | Y127: 0 | Z127: 14204.53 | AA127: 14444.29 | AB127: PA-0000428 | AC127: 24.6179 | AD127: 1 | AE127: 1 | AF127: 0 | AG127: 14204.53 | AH127: 577 | AI127: 570 | AJ127: 7 | AK127: 1 | AL127: 1 | AM127: 98.79 | AN127: 25.3409 | AO127: 172.33 | AP127: 45028 | AQ127: 0 | AR127: 1
A128: PO-000127 | B128: LOM-0034 | C128: Optical Fibre Assy 0034 | D128: Optical Fibre | E128: Critical | F128: 2 | G128: 9 | H128: 0 | I128: VEN-016 | J128: Spectra Industries | K128: United Kingdom | L128: Preferred | M128: 7.82 | N128: BUY-03 | O128: Mei-Ling Chow | P128: Optics & Coatings | Q128: 44999 | R128: 45038 | S128: 2023 | T128: 2023-03 | U128: 658 | V128: 48.7896 | W128: 325.63 | X128: 0 | Y128: 0 | Z128: 32103.56 | AA128: 32429.19 | AB128: PA-0000150 | AC128: 48.7896 | AD128: 1 | AE128: 1 | AF128: 0 | AG128: 32103.56 | AH128: 658 | AI128: 655 | AJ128: 3 | AK128: 1 | AL128: 1 | AM128: 99.54 | AN128: 49.5102 | AO128: 146.37 | AP128: 45035 | AQ128: -3 | AR128: 1
A129: PO-000128 | B129: LOM-0058 | C129: Optical Fibre Module 0058 | D129: Optical Fibre | E129: Standard | F129: 3 | G129: 4 | H129: 0 | I129: VEN-023 | J129: Kestrel Optical Industries | K129: Switzerland | L129: Approved | M129: 6.75 | N129: BUY-03 | O129: Mei-Ling Chow | P129: Optics & Coatings | Q129: 44999 | R129: 45037 | S129: 2023 | T129: 2023-03 | U129: 1913 | V129: 55.5447 | W129: 991.35 | X129: 0 | Y129: 0 | Z129: 106257.01 | AA129: 107248.36 | AB129: PA-0000259 | AC129: 55.5447 | AD129: 1 | AE129: 1 | AF129: 0 | AG129: 106257.01 | AH129: 1913 | AI129: 1896 | AJ129: 17 | AK129: 1 | AL129: 1 | AM129: 99.11 | AN129: 56.5656 | AO129: 944.26 | AP129: 45044 | AQ129: 7 | AR129: 0
A130: PO-000129 | B130: LOM-0064 | C130: Laser Diode Component 0064 | D130: Laser Diode | E130: Commodity | F130: 3 | G130: 1 | H130: 0 | I130: VEN-031 | J130: Quantex Technologies | K130: United States | L130: Transactional | M130: 14.93 | N130: BUY-02 | O130: Rafael Duarte | P130: Optoelectronics | Q130: 44999 | R130: 45024 | S130: 2023 | T130: 2023-03 | U130: 116 | V130: 810.5773 | W130: 981.89 | X130: 0 | Y130: 0 | Z130: 94026.97 | AA130: 95008.86 | AD130: 0 | AE130: 0 | AH130: 116 | AI130: 116 | AJ130: 0 | AK130: 1 | AL130: 1 | AM130: 100 | AN130: 819.0419 | AO130: 0 | AP130: 45022 | AQ130: -2 | AR130: 1
A131: PO-000130 | B131: LOM-0102 | C131: Fibre Connector Component 0102 | D131: Fibre Connector | E131: Commodity | F131: 2 | G131: 0 | H131: 0 | I131: VEN-010 | J131: Vectra GmbH | K131: United Kingdom | L131: Preferred | M131: 5.43 | N131: BUY-04 | O131: Johan Lindberg | P131: Optics & Coatings | Q131: 44999 | R131: 45017 | S131: 2023 | T131: 2023-03 | U131: 425 | V131: 24.7823 | W131: 240.26 | X131: 0 | Y131: 0 | Z131: 10532.48 | AA131: 10772.74 | AB131: PA-0000464 | AC131: 24.7823 | AD131: 1 | AE131: 1 | AF131: 0 | AG131: 10532.48 | AH131: 425 | AI131: 419 | AJ131: 6 | AK131: 1 | AL131: 1 | AM131: 98.59 | AN131: 25.7106 | AO131: 148.69 | AP131: 45021 | AQ131: 4 | AR131: 0
A132: PO-000131 | B132: LOM-0116 | C132: Optical Coating Assy 0116 | D132: Optical Coating | E132: Critical | F132: 2 | G132: 9 | H132: 0 | I132: VEN-031 | J132: Quantex Technologies | K132: United States | L132: Transactional | M132: 14.93 | N132: BUY-04 | O132: Johan Lindberg | P132: Optics & Coatings | Q132: 44999 | R132: 45049 | S132: 2023 | T132: 2023-03 | U132: 259 | V132: 49.6859 | W132: 155.72 | X132: 0 | Y132: 0 | Z132: 12868.65 | AA132: 13024.37 | AB132: PA-0000533 | AC132: 49.6859 | AD132: 1 | AE132: 1 | AF132: 0 | AG132: 12868.65 | AH132: 259 | AI132: 255 | AJ132: 4 | AK132: 1 | AL132: 1 | AM132: 98.46 | AN132: 51.076 | AO132: 198.74 | AP132: 45057 | AQ132: 8 | AR132: 0
A133: PO-000132 | B133: LOM-0038 | C133: Fibre Connector Component 0038 | D133: Fibre Connector | E133: Commodity | F133: 3 | G133: 1 | H133: 0 | I133: VEN-035 | J133: Kestrel Optical Technologies | K133: Switzerland | L133: Transactional | M133: 36.86 | N133: BUY-03 | O133: Mei-Ling Chow | P133: Optics & Coatings | Q133: 45000 | R133: 45020 | S133: 2023 | T133: 2023-03 | U133: 526 | V133: 8.7274 | W133: 108.42 | X133: 0 | Y133: 0 | Z133: 4590.61 | AA133: 4699.03 | AB133: PA-0000172 | AC133: 8.7274 | AD133: 1 | AE133: 1 | AF133: 0 | AG133: 4590.61 | AH133: 526 | AI133: 520 | AJ133: 6 | AK133: 1 | AL133: 1 | AM133: 98.86 | AN133: 9.0366 | AO133: 52.36 | AP133: 45020 | AQ133: 0 | AR133: 1
A134: PO-000133 | B134: LOM-0088 | C134: Laser Diode Component 0088 | D134: Laser Diode | E134: Commodity | F134: 3 | G134: 1 | H134: 0 | I134: VEN-005 | J134: Helix Optics GmbH | K134: Switzerland | L134: Strategic | M134: 1.75 | N134: BUY-01 | O134: Adaeze Okonkwo | P134: Optoelectronics | Q134: 45000 | R134: 45022 | S134: 2023 | T134: 2023-03 | U134: 88 | V134: 297.199 | W134: 247.41 | X134: 0 | Y134: 0 | Z134: 26153.51 | AA134: 26400.92 | AB134: PA-0000397 | AC134: 297.199 | AD134: 1 | AE134: 1 | AF134: 0 | AG134: 26153.51 | AH134: 88 | AI134: 88 | AJ134: 0 | AK134: 1 | AL134: 1 | AM134: 100 | AN134: 300.0105 | AO134: 0 | AP134: 45022 | AQ134: 0 | AR134: 1
A135: PO-000134 | B135: LOM-0119 | C135: Thermal Control Module 0119 | D135: Thermal Control | E135: Standard | F135: 2 | G135: 3 | H135: 0 | I135: VEN-025 | J135: Lumitek Technologies | K135: United States | L135: Approved | M135: 14.26 | N135: BUY-06 | O135: Tomas Varga | P135: Mechanical & Thermal | Q135: 45000 | R135: 45031 | S135: 2023 | T135: 2023-03 | U135: 93 | V135: 161.942 | W135: 279.05 | X135: 0 | Y135: 0 | Z135: 15060.61 | AA135: 15339.66 | AB135: PA-0000549 | AC135: 161.942 | AD135: 1 | AE135: 1 | AF135: 0 | AG135: 15060.61 | AH135: 93 | AI135: 93 | AJ135: 0 | AK135: 1 | AL135: 1 | AM135: 100 | AN135: 164.9425 | AO135: 0 | AP135: 45028 | AQ135: -3 | AR135: 1
A136: PO-000135 | B136: LOM-0135 | C136: Thermal Control Component 0135 | D136: Thermal Control | E136: Commodity | F136: 3 | G136: 1 | H136: 0 | I136: VEN-011 | J136: Kestrel Optical GmbH | K136: Switzerland | L136: Preferred | M136: 3.73 | N136: BUY-05 | O136: Priya Raghunathan | P136: Mechanical & Thermal | Q136: 45000 | R136: 45026 | S136: 2023 | T136: 2023-03 | U136: 119 | V136: 275.127 | W136: 358.46 | X136: 0 | Y136: 0 | Z136: 32740.11 | AA136: 33098.57 | AB136: PA-X000006 | AC136: 284.7564 | AD136: 2 | AE136: 1 | AF136: -1145.9 | AG136: 33886.01 | AH136: 119 | AI136: 118 | AJ136: 1 | AK136: 1 | AL136: 1 | AM136: 99.16 | AN136: 280.4964 | AO136: 275.13 | AP136: 45032 | AQ136: 6 | AR136: 0
A137: PO-000136 | B137: LOM-0009 | C137: Photodetector Module 0009 | D137: Photodetector | E137: Standard | F137: 3 | G137: 5 | H137: 0 | I137: VEN-014 | J137: Photonica Industries | K137: Japan | L137: Preferred | M137: 4.81 | N137: BUY-02 | O137: Rafael Duarte | P137: Optoelectronics | Q137: 45001 | R137: 45022 | S137: 2023 | T137: 2023-03 | U137: 14 | V137: 481.4753 | W137: 98.49 | X137: 0 | Y137: 0 | Z137: 6740.65 | AA137: 6839.14 | AD137: 0 | AE137: 0 | AH137: 14 | AI137: 14 | AJ137: 0 | AK137: 1 | AL137: 1 | AM137: 100 | AN137: 488.5103 | AO137: 0 | AP137: 45020 | AQ137: -2 | AR137: 1
A138: PO-000137 | B138: LOM-0029 | C138: Precision Mount Component 0029 | D138: Precision Mount | E138: Commodity | F138: 3 | G138: 1 | H138: 0 | I138: VEN-016 | J138: Spectra Industries | K138: United Kingdom | L138: Preferred | M138: 7.82 | N138: BUY-05 | O138: Priya Raghunathan | P138: Mechanical & Thermal | Q138: 45001 | R138: 45029 | S138: 2023 | T138: 2023-03 | U138: 137 | V138: 158.0091 | W138: 429.13 | X138: 0 | Y138: 0 | Z138: 21647.25 | AA138: 22076.38 | AB138: PA-0000129 | AC138: 158.0091 | AD138: 1 | AE138: 1 | AF138: 0 | AG138: 21647.25 | AH138: 137 | AI138: 135 | AJ138: 2 | AK138: 1 | AL138: 1 | AM138: 98.54 | AN138: 163.5287 | AO138: 316.02 | AP138: 45027 | AQ138: -2 | AR138: 1
A139: PO-000138 | B139: LOM-0056 | C139: Laser Diode Module 0056 | D139: Laser Diode | E139: Standard | F139: 3 | G139: 4 | H139: 0 | I139: VEN-034 | J139: Vectra Technologies | K139: United Kingdom | L139: Transactional | M139: 34.49 | N139: BUY-01 | O139: Adaeze Okonkwo | P139: Optoelectronics | Q139: 45001 | R139: 45034 | S139: 2023 | T139: 2023-03 | U139: 110 | V139: 632.3692 | W139: 1784.17 | X139: 0 | Y139: 0 | Z139: 69560.61 | AA139: 71344.78 | AB139: PA-0000251 | AC139: 610.7279 | AD139: 1 | AE139: 1 | AF139: 2380.54 | AG139: 67180.07 | AH139: 110 | AI139: 108 | AJ139: 2 | AK139: 1 | AL139: 1 | AM139: 98.18 | AN139: 660.5998 | AO139: 1264.74 | AP139: 45031 | AQ139: -3 | AR139: 1
A140: PO-000139 | B140: LOM-0070 | C140: Fibre Connector Component 0070 | D140: Fibre Connector | E140: Commodity | F140: 3 | G140: 1 | H140: 0 | I140: VEN-007 | J140: Quantex GmbH | K140: United States | L140: Preferred | M140: 10.21 | N140: BUY-03 | O140: Mei-Ling Chow | P140: Optics & Coatings | Q140: 45001 | R140: 45023 | S140: 2023 | T140: 2023-03 | U140: 602 | V140: 17.0285 | W140: 243.31 | X140: 0 | Y140: 0 | Z140: 10251.16 | AA140: 10494.47 | AB140: PA-0000316 | AC140: 16.1609 | AD140: 1 | AE140: 1 | AF140: 522.3 | AG140: 9728.86 | AH140: 602 | AI140: 594 | AJ140: 8 | AK140: 1 | AL140: 1 | AM140: 98.67 | AN140: 17.6675 | AO140: 136.23 | AP140: 45023 | AQ140: 0 | AR140: 1
A141: PO-000140 | B141: LOM-0132 | C141: Optical Coating Assy 0132 | D141: Optical Coating | E141: Critical | F141: 3 | G141: 11 | H141: 0 | I141: VEN-005 | J141: Helix Optics GmbH | K141: Switzerland | L141: Strategic | M141: 1.75 | N141: BUY-03 | O141: Mei-Ling Chow | P141: Optics & Coatings | Q141: 45001 | R141: 45042 | S141: 2023 | T141: 2023-03 | U141: 130 | V141: 148.1114 | W141: 411.19 | X141: 0 | Y141: 0 | Z141: 19254.48 | AA141: 19665.67 | AB141: PA-0000608 | AC141: 144.5126 | AD141: 1 | AE141: 1 | AF141: 467.84 | AG141: 18786.64 | AH141: 130 | AI141: 129 | AJ141: 1 | AK141: 1 | AL141: 1 | AM141: 99.23 | AN141: 152.4471 | AO141: 148.11 | AP141: 45039 | AQ141: -3 | AR141: 1
A142: PO-000141 | B142: LOM-0033 | C142: Photodetector Module 0033 | D142: Photodetector | E142: Standard | F142: 1 | G142: 2 | H142: 1 | I142: VEN-003 | J142: Crystalline GmbH | K142: Taiwan | L142: Strategic | M142: 3.69 | N142: BUY-01 | O142: Adaeze Okonkwo | P142: Optoelectronics | Q142: 45002 | R142: 45035 | S142: 2023 | T142: 2023-03 | U142: 110 | V142: 229.3486 | W142: 242.16 | X142: 0 | Y142: 0 | Z142: 25228.35 | AA142: 25470.51 | AB142: PA-0000149 | AC142: 229.3486 | AD142: 1 | AE142: 1 | AF142: 0 | AG142: 25228.35 | AH142: 110 | AI142: 109 | AJ142: 1 | AK142: 1 | AL142: 1 | AM142: 99.09 | AN142: 233.6744 | AO142: 229.35 | AP142: 45033 | AQ142: -2 | AR142: 1
A143: PO-000142 | B143: LOM-0060 | C143: Optical Coating Module 0060 | D143: Optical Coating | E143: Standard | F143: 2 | G143: 3 | H143: 0 | I143: VEN-033 | J143: Oribel Technologies | K143: Taiwan | L143: Transactional | M143: 17.66 | N143: BUY-04 | O143: Johan Lindberg | P143: Optics & Coatings | Q143: 45002 | R143: 45025 | S143: 2023 | T143: 2023-03 | U143: 79 | V143: 31.7883 | W143: 46.36 | X143: 0 | Y143: 0 | Z143: 2511.28 | AA143: 2557.64 | AB143: PA-0000270 | AC143: 31.7883 | AD143: 1 | AE143: 1 | AF143: 0 | AG143: 2511.28 | AH143: 79 | AI143: 78 | AJ143: 1 | AK143: 1 | AL143: 1 | AM143: 98.73 | AN143: 32.7902 | AO143: 31.79 | AP143: 45022 | AQ143: -3 | AR143: 1
A144: PO-000143 | B144: LOM-0080 | C144: Laser Diode Module 0080 | D144: Laser Diode | E144: Standard | F144: 3 | G144: 5 | H144: 0 | I144: VEN-033 | J144: Oribel Technologies | K144: Taiwan | L144: Transactional | M144: 17.66 | N144: BUY-02 | O144: Rafael Duarte | P144: Optoelectronics | Q144: 45002 | R144: 45024 | S144: 2023 | T144: 2023-03 | U144: 19 | V144: 529.5158 | W144: 215.68 | X144: 0 | Y144: 0 | Z144: 10060.8 | AA144: 10276.48 | AD144: 0 | AE144: 0 | AH144: 19 | AI144: 19 | AJ144: 0 | AK144: 1 | AL144: 1 | AM144: 100 | AN144: 540.8674 | AO144: 0 | AP144: 45024 | AQ144: 0 | AR144: 1
A145: PO-000144 | B145: LOM-0092 | C145: Optical Coating Component 0092 | D145: Optical Coating | E145: Commodity | F145: 3 | G145: 0 | H145: 0 | I145: VEN-012 | J145: Aperture Industries | K145: Germany | L145: Preferred | M145: 4.72 | N145: BUY-04 | O145: Johan Lindberg | P145: Optics & Coatings | Q145: 45002 | R145: 45029 | S145: 2023 | T145: 2023-03 | U145: 266 | V145: 59.3798 | W145: 370.01 | X145: 0 | Y145: 0 | Z145: 15795.03 | AA145: 16165.04 | AB145: PA-0000419 | AC145: 63.1406 | AD145: 1 | AE145: 1 | AF145: -1000.37 | AG145: 16795.4 | AH145: 266 | AI145: 262 | AJ145: 4 | AK145: 1 | AL145: 1 | AM145: 98.5 | AN145: 61.6986 | AO145: 237.52 | AP145: 45028 | AQ145: -1 | AR145: 1
A146: PO-000145 | B146: LOM-0102 | C146: Fibre Connector Component 0102 | D146: Fibre Connector | E146: Commodity | F146: 2 | G146: 0 | H146: 0 | I146: VEN-010 | J146: Vectra GmbH | K146: United Kingdom | L146: Preferred | M146: 5.43 | N146: BUY-04 | O146: Johan Lindberg | P146: Optics & Coatings | Q146: 45002 | R146: 45026 | S146: 2023 | T146: 2023-03 | U146: 727 | V146: 24.7823 | W146: 424.67 | X146: 0 | Y146: 0 | Z146: 18016.73 | AA146: 18441.4 | AB146: PA-0000464 | AC146: 24.7823 | AD146: 1 | AE146: 1 | AF146: 0 | AG146: 18016.73 | AH146: 727 | AI146: 717 | AJ146: 10 | AK146: 1 | AL146: 1 | AM146: 98.62 | AN146: 25.7202 | AO146: 247.82 | AP146: 45028 | AQ146: 2 | AR146: 0
A147: PO-000146 | B147: LOM-0129 | C147: Photodetector Module 0129 | D147: Photodetector | E147: Standard | F147: 2 | G147: 2 | H147: 0 | I147: VEN-014 | J147: Photonica Industries | K147: Japan | L147: Preferred | M147: 4.81 | N147: BUY-01 | O147: Adaeze Okonkwo | P147: Optoelectronics | Q147: 45002 | R147: 45035 | S147: 2023 | T147: 2023-03 | U147: 105 | V147: 388.5493 | W147: 670.42 | X147: 0 | Y147: 0 | Z147: 40797.68 | AA147: 41468.1 | AB147: PA-0000599 | AC147: 388.5493 | AD147: 1 | AE147: 1 | AF147: 0 | AG147: 40797.68 | AH147: 105 | AI147: 104 | AJ147: 1 | AK147: 1 | AL147: 1 | AM147: 99.05 | AN147: 398.7317 | AO147: 388.55 | AP147: 45033 | AQ147: -2 | AR147: 1
A148: PO-000147 | B148: LOM-0132 | C148: Optical Coating Assy 0132 | D148: Optical Coating | E148: Critical | F148: 3 | G148: 11 | H148: 0 | I148: VEN-034 | J148: Vectra Technologies | K148: United Kingdom | L148: Transactional | M148: 34.49 | N148: BUY-04 | O148: Johan Lindberg | P148: Optics & Coatings | Q148: 45002 | R148: 45040 | S148: 2023 | T148: 2023-03 | U148: 94 | V148: 165.7534 | W148: 199.46 | X148: 0 | Y148: 0 | Z148: 15580.82 | AA148: 15780.28 | AD148: 0 | AE148: 0 | AH148: 94 | AI148: 92 | AJ148: 2 | AK148: 1 | AL148: 1 | AM148: 97.87 | AN148: 171.5248 | AO148: 331.51 | AP148: 45042 | AQ148: 2 | AR148: 0
A149: PO-000148 | B149: LOM-0038 | C149: Fibre Connector Component 0038 | D149: Fibre Connector | E149: Commodity | F149: 3 | G149: 1 | H149: 0 | I149: VEN-002 | J149: Photonica GmbH | K149: Japan | L149: Strategic | M149: 2.49 | N149: BUY-04 | O149: Johan Lindberg | P149: Optics & Coatings | Q149: 45006 | R149: 45025 | S149: 2023 | T149: 2023-03 | U149: 493 | V149: 9.592 | W149: 41.45 | X149: 0 | Y149: 0 | Z149: 4728.86 | AA149: 4770.31 | AD149: 0 | AE149: 0 | AH149: 493 | AI149: 485 | AJ149: 8 | AK149: 1 | AL149: 1 | AM149: 98.38 | AN149: 9.8357 | AO149: 76.74 | AP149: 45027 | AQ149: 2 | AR149: 0
A150: PO-000149 | B150: LOM-0046 | C150: Fibre Connector Module 0046 | D150: Fibre Connector | E150: Standard | F150: 1 | G150: 2 | H150: 1 | I150: VEN-033 | J150: Oribel Technologies | K150: Taiwan | L150: Transactional | M150: 17.66 | N150: BUY-04 | O150: Johan Lindberg | P150: Optics & Coatings | Q150: 45006 | R150: 45030 | S150: 2023 | T150: 2023-03 | U150: 252 | V150: 24.687 | W150: 61.26 | X150: 0 | Y150: 0 | Z150: 6221.12 | AA150: 6282.38 | AB150: PA-0000205 | AC150: 24.687 | AD150: 1 | AE150: 1 | AF150: 0 | AG150: 6221.12 | AH150: 252 | AI150: 250 | AJ150: 2 | AK150: 1 | AL150: 1 | AM150: 99.21 | AN150: 25.1295 | AO150: 49.37 | AP150: 45027 | AQ150: -3 | AR150: 1
A151: PO-000150 | B151: LOM-0054 | C151: Fibre Connector Component 0054 | D151: Fibre Connector | E151: Commodity | F151: 3 | G151: 1 | H151: 0 | I151: VEN-026 | J151: Photonica Technologies | K151: Japan | L151: Approved | M151: 9.22 | N151: BUY-04 | O151: Johan Lindberg | P151: Optics & Coatings | Q151: 45006 | R151: 45030 | S151: 2023 | T151: 2023-03 | U151: 733 | V151: 28.7181 | W151: 370.41 | X151: 0 | Y151: 0 | Z151: 21050.37 | AA151: 21420.78 | AB151: PA-0000241 | AC151: 28.7181 | AD151: 1 | AE151: 1 | AF151: 0 | AG151: 21050.37 | AH151: 733 | AI151: 726 | AJ151: 7 | AK151: 1 | AL151: 1 | AM151: 99.05 | AN151: 29.5052 | AO151: 201.03 | AP151: 45039 | AQ151: 9 | AR151: 0
A152: PO-000151 | B152: LOM-0107 | C152: Lens Assembly Module 0107 | D152: Lens Assembly | E152: Standard | F152: 2 | G152: 3 | H152: 0 | I152: VEN-008 | J152: Meridian Photonics GmbH | K152: Japan | L152: Preferred | M152: 5.01 | N152: BUY-04 | O152: Johan Lindberg | P152: Optics & Coatings | Q152: 45006 | R152: 45034 | S152: 2023 | T152: 2023-03 | U152: 65 | V152: 250.0097 | W152: 163.39 | X152: 525.47 | Y152: 1 | Z152: 16250.63 | AA152: 16939.49 | AB152: PA-0000485 | AC152: 250.0097 | AD152: 1 | AE152: 1 | AF152: 0 | AG152: 16250.63 | AH152: 65 | AI152: 64 | AJ152: 1 | AK152: 1 | AL152: 1 | AM152: 98.46 | AN152: 264.6795 | AO152: 250.01 | AP152: 45034 | AQ152: 0 | AR152: 1
A153: PO-000152 | B153: LOM-0132 | C153: Optical Coating Assy 0132 | D153: Optical Coating | E153: Critical | F153: 3 | G153: 11 | H153: 0 | I153: VEN-005 | J153: Helix Optics GmbH | K153: Switzerland | L153: Strategic | M153: 1.75 | N153: BUY-04 | O153: Johan Lindberg | P153: Optics & Coatings | Q153: 45006 | R153: 45055 | S153: 2023 | T153: 2023-03 | U153: 251 | V153: 144.5126 | W153: 511.8 | X153: 0 | Y153: 0 | Z153: 36272.66 | AA153: 36784.46 | AB153: PA-0000608 | AC153: 144.5126 | AD153: 1 | AE153: 1 | AF153: 0 | AG153: 36272.66 | AH153: 251 | AI153: 245 | AJ153: 6 | AK153: 1 | AL153: 1 | AM153: 97.61 | AN153: 150.1407 | AO153: 867.08 | AP153: 45052 | AQ153: -3 | AR153: 1
A154: PO-000153 | B154: LOM-0005 | C154: Precision Mount Component 0005 | D154: Precision Mount | E154: Commodity | F154: 3 | G154: 0 | H154: 0 | I154: VEN-007 | J154: Quantex GmbH | K154: United States | L154: Preferred | M154: 10.21 | N154: BUY-05 | O154: Priya Raghunathan | P154: Mechanical & Thermal | Q154: 45007 | R154: 45021 | S154: 2023 | T154: 2023-03 | U154: 32 | V154: 228.6361 | W154: 147.57 | X154: 0 | Y154: 0 | Z154: 7316.36 | AA154: 7463.93 | AB154: PA-0000016 | AC154: 242.5684 | AD154: 1 | AE154: 1 | AF154: -445.83 | AG154: 7762.19 | AH154: 32 | AI154: 32 | AJ154: 0 | AK154: 1 | AL154: 1 | AM154: 100 | AN154: 233.2477 | AO154: 0 | AP154: 45020 | AQ154: -1 | AR154: 1
A155: PO-000154 | B155: LOM-0028 | C155: Optical Coating Module 0028 | D155: Optical Coating | E155: Standard | F155: 3 | G155: 5 | H155: 0 | I155: VEN-001 | J155: Lumitek GmbH | K155: United States | L155: Strategic | M155: 1.37 | N155: BUY-04 | O155: Johan Lindberg | P155: Optics & Coatings | Q155: 45007 | R155: 45034 | S155: 2023 | T155: 2023-03 | U155: 127 | V155: 144.1571 | W155: 151.64 | X155: 0 | Y155: 0 | Z155: 18307.95 | AA155: 18459.59 | AB155: PA-0000125 | AC155: 144.1571 | AD155: 1 | AE155: 1 | AF155: 0 | AG155: 18307.95 | AH155: 127 | AI155: 124 | AJ155: 3 | AK155: 1 | AL155: 1 | AM155: 97.64 | AN155: 148.8677 | AO155: 432.47 | AP155: 45030 | AQ155: -4 | AR155: 1
A156: PO-000155 | B156: LOM-0041 | C156: Photodetector Component 0041 | D156: Photodetector | E156: Commodity | F156: 3 | G156: 1 | H156: 0 | I156: VEN-009 | J156: Oribel GmbH | K156: Taiwan | L156: Preferred | M156: 9.47 | N156: BUY-01 | O156: Adaeze Okonkwo | P156: Optoelectronics | Q156: 45007 | R156: 45035 | S156: 2023 | T156: 2023-03 | U156: 138 | V156: 397.87 | W156: 561.04 | X156: 0 | Y156: 0 | Z156: 54906.06 | AA156: 55467.1 | AB156: PA-0000185 | AC156: 397.87 | AD156: 1 | AE156: 1 | AF156: 0 | AG156: 54906.06 | AH156: 138 | AI156: 137 | AJ156: 1 | AK156: 1 | AL156: 1 | AM156: 99.28 | AN156: 404.8693 | AO156: 397.87 | AP156: 45035 | AQ156: 0 | AR156: 1
A157: PO-000156 | B157: LOM-0138 | C157: Optical Fibre Module 0138 | D157: Optical Fibre | E157: Standard | F157: 3 | G157: 4 | H157: 0 | I157: VEN-020 | J157: Meridian Photonics Industries | K157: Japan | L157: Approved | M157: 12.07 | N157: BUY-03 | O157: Mei-Ling Chow | P157: Optics & Coatings | Q157: 45007 | R157: 45034 | S157: 2023 | T157: 2023-03 | U157: 823 | V157: 37.1436 | W157: 749.21 | X157: 0 | Y157: 0 | Z157: 30569.18 | AA157: 31318.39 | AB157: PA-0000632 | AC157: 37.1436 | AD157: 1 | AE157: 1 | AF157: 0 | AG157: 30569.18 | AH157: 823 | AI157: 815 | AJ157: 8 | AK157: 1 | AL157: 1 | AM157: 99.03 | AN157: 38.4275 | AO157: 297.15 | AP157: 45033 | AQ157: -1 | AR157: 1
A158: PO-000157 | B158: LOM-0007 | C158: Thermal Control Module 0007 | D158: Thermal Control | E158: Standard | F158: 3 | G158: 5 | H158: 0 | I158: VEN-033 | J158: Oribel Technologies | K158: Taiwan | L158: Transactional | M158: 17.66 | N158: BUY-05 | O158: Priya Raghunathan | P158: Mechanical & Thermal | Q158: 45008 | R158: 45037 | S158: 2023 | T158: 2023-03 | U158: 76 | V158: 155.3694 | W158: 228.99 | X158: 0 | Y158: 0 | Z158: 11808.07 | AA158: 12037.06 | AB158: PA-0000031 | AC158: 155.3694 | AD158: 1 | AE158: 1 | AF158: 0 | AG158: 11808.07 | AH158: 76 | AI158: 76 | AJ158: 0 | AK158: 1 | AL158: 1 | AM158: 100 | AN158: 158.3824 | AO158: 0 | AP158: 45037 | AQ158: 0 | AR158: 1
...

Sheet Data_Erosion
A1: PartNumber | B1: PartName | C1: Category | D1: Criticality | E1: QualifiedSupplierCount | F1: QualificationMonths | G1: VendorID | H1: VendorName | I1: VendorTier | J1: LumenRevenueSharePct | K1: FirstDate | L1: LastDate | M1: YearsElapsed | N1: Lines | O1: TotalQty | P1: TotalSpend | Q1: TTMQty | R1: TTMSpend | S1: FirstPrice | T1: LastPrice | U1: ExpectedPrice | V1: BenchmarkErosionPct | W1: ToleranceBandPct | X1: ActualErosionPct | Y1: ErosionCapturePct | Z1: ErosionGapPerUnit | AA1: AnnualOpportunity
A2: LOM-0104 | B2: Laser Diode Component 0104 | C2: Laser Diode | D2: Commodity | E2: 2 | F2: 0 | G2: VEN-003 | H2: Crystalline GmbH | I2: Strategic | J2: 3.69 | K2: 45043 | L2: 45973 | M2: 2.546 | N2: 34 | O2: 2688 | P2: 1686697.1 | Q2: 1108 | R2: 714564.24 | S2: 583.3423 | T2: 652.1172 | U2: 471.7667 | V2: 8 | W2: 2 | X2: -4.474 | Y2: -55.93 | Z2: 180.3505 | AA2: 199828.4
A3: LOM-0128 | B3: Laser Diode Assy 0128 | C3: Laser Diode | D3: Critical | E3: 2 | F3: 9 | G3: VEN-015 | H3: Crystalline Industries | I3: Preferred | J3: 3.57 | K3: 45054 | L3: 46013 | M3: 2.626 | N3: 32 | O3: 2380 | P3: 2003959.4 | Q3: 1189 | R3: 997643.82 | S3: 849.1721 | T3: 832.8071 | U3: 682.1857 | V3: 8 | W3: 2 | X3: 0.738 | Y3: 9.23 | Z3: 150.6214 | AA3: 179088.8
A4: LOM-0096 | B4: Laser Diode Module 0096 | C4: Laser Diode | D4: Standard | E4: 1 | F4: 2 | G4: VEN-011 | H4: Kestrel Optical GmbH | I4: Preferred | J4: 3.73 | K4: 44960 | L4: 46007 | M4: 2.867 | N4: 48 | O4: 4301 | P4: 2459614.6 | Q4: 1521 | R4: 686912.99 | S4: 416.4004 | T4: 443.9747 | U4: 327.8618 | V4: 8 | W4: 2 | X4: -2.262 | Y4: -28.28 | Z4: 116.1129 | AA4: 176607.69
A5: LOM-0048 | B5: Laser Diode Module 0048 | C5: Laser Diode | D5: Standard | E5: 3 | F5: 5 | G5: VEN-008 | H5: Meridian Photonics GmbH | I5: Preferred | J5: 5.01 | K5: 44991 | L5: 46010 | M5: 2.79 | N5: 33 | O5: 2680 | P5: 1994642.9 | Q5: 1357 | R5: 988567.39 | S5: 770.4723 | T5: 724.0698 | U5: 610.5554 | V5: 8 | W5: 2 | X5: 2.202 | Y5: 27.53 | Z5: 113.5144 | AA5: 154039.04
A6: LOM-0057 | B6: Photodetector Module 0057 | C6: Photodetector | D6: Standard | E6: 1 | F6: 2 | G6: VEN-005 | H6: Helix Optics GmbH | I6: Strategic | J6: 1.75 | K6: 45015 | L6: 46007 | M6: 2.716 | N6: 33 | O6: 2500 | P6: 1176025.1 | Q6: 875 | R6: 436614.97 | S6: 454.9047 | T6: 499.5045 | U6: 379.0049 | V6: 6.5 | W6: 2 | X6: -3.504 | Y6: -53.91 | Z6: 120.4996 | AA6: 105437.11
A7: LOM-0082 | B7: Optical Fibre Module 0082 | C7: Optical Fibre | D7: Standard | E7: 1 | F7: 2 | G7: VEN-032 | H7: Meridian Photonics Technologies | I7: Transactional | J7: 28.3 | K7: 45055 | L7: 46015 | M7: 2.628 | N7: 43 | O7: 50236 | P7: 2184683.9 | Q7: 23567 | R7: 1026650.2 | S7: 43.7097 | T7: 43.6912 | U7: 39.2633 | V7: 4 | W7: 1.5 | X7: 0.016 | Y7: 0.4 | Z7: 4.4279 | AA7: 104353.4
A8: LOM-0024 | B8: Laser Diode Module 0024 | C8: Laser Diode | D8: Standard | E8: 1 | F8: 2 | G8: VEN-019 | H8: Quantex Industries | I8: Approved | J8: 16 | K8: 45020 | L8: 46008 | M8: 2.705 | N8: 51 | O8: 3886 | P8: 1721836.9 | Q8: 1026 | R8: 454797.44 | S8: 432.7746 | T8: 444.2963 | U8: 345.3884 | V8: 8 | W8: 2 | X8: -0.976 | Y8: -12.2 | Z8: 98.9079 | AA8: 101479.51
A9: LOM-0130 | B9: Optical Fibre Assy 0130 | C9: Optical Fibre | D9: Critical | E9: 1 | F9: 6 | G9: VEN-008 | H9: Meridian Photonics GmbH | I9: Preferred | J9: 5.01 | K9: 45047 | L9: 46010 | M9: 2.637 | N9: 48 | O9: 54417 | P9: 2260442.2 | Q9: 16744 | R9: 694927.1 | S9: 40.079 | T9: 41.7484 | U9: 35.9887 | V9: 4 | W9: 1.5 | X9: -1.56 | Y9: -39 | Z9: 5.7597 | AA9: 96439.91
A10: LOM-0009 | B10: Photodetector Module 0009 | C10: Photodetector | D10: Standard | E10: 3 | F10: 5 | G10: VEN-020 | H10: Meridian Photonics Industries | I10: Approved | J10: 12.07 | K10: 44991 | L10: 46001 | M10: 2.765 | N10: 35 | O10: 2857 | P10: 1231784.6 | Q10: 1293 | R10: 557683.88 | S10: 430.4107 | T10: 430.1006 | U10: 357.4186 | V10: 6.5 | W10: 2 | X10: 0.026 | Y10: 0.4 | Z10: 72.682 | AA10: 93977.83
A11: LOM-0106 | B11: Optical Fibre Assy 0106 | C11: Optical Fibre | D11: Critical | E11: 1 | F11: 8 | G11: VEN-010 | H11: Vectra GmbH | I11: Preferred | J11: 5.43 | K11: 45082 | L11: 46020 | M11: 2.568 | N11: 42 | O11: 48448 | P11: 2532755.2 | Q11: 21131 | R11: 1096526.6 | S11: 53.2035 | T11: 52.2099 | U11: 47.9085 | V11: 4 | W11: 1.5 | X11: 0.732 | Y11: 18.3 | Z11: 4.3014 | AA11: 90892.88
A12: LOM-0120 | B12: Laser Diode Component 0120 | C12: Laser Diode | D12: Commodity | E12: 3 | F12: 0 | G12: VEN-016 | H12: Spectra Industries | I12: Preferred | J12: 7.82 | K12: 45020 | L12: 45924 | M12: 2.475 | N12: 33 | O12: 2685 | P12: 2650923 | Q12: 675 | R12: 646871.89 | S12: 1008.4116 | T12: 947.0531 | U12: 820.3755 | V12: 8 | W12: 2 | X12: 2.505 | Y12: 31.31 | Z12: 126.6776 | AA12: 85507.38
A13: LOM-0123 | B13: Lens Assembly Assy 0123 | C13: Lens Assembly | D13: Critical | E13: 3 | F13: 11 | G13: VEN-008 | H13: Meridian Photonics GmbH | I13: Preferred | J13: 5.01 | K13: 45089 | L13: 46020 | M13: 2.549 | N13: 38 | O13: 2765 | P13: 703073.96 | Q13: 1548 | R13: 410583.38 | S13: 231.463 | T13: 264.5891 | U13: 214.1721 | V13: 3 | W13: 1.5 | X13: -5.388 | Y13: -179.6 | Z13: 50.417 | AA13: 78045.54
... A186: LOM-0050 | B186: Optical Fibre Module 0050 | C186: Optical Fibre | D186: Standard | E186: 2 | F186: 2 | G186: VEN-020 | H186: Meridian Photonics Industries | I186: Approved | J186: 12.07 | K186: 45069 | L186: 45999 | M186: 2.546 | N186: 46 | O186: 52764 | P186: 1198647.6 | Q186: 16885 | R186: 350455.91 | S186: 28.9311 | T186: 20.5132 | U186: 26.0752 | V186: 4 | W186: 1.5 | X186: 12.632 | Y186: 315.8 | Z186: -5.562 | AA186: -93913.66

Sheet Data_Queue
A1: PriorityRank | B1: BuyerRank | C1: PartNumber | D1: PartName | E1: Category | F1: Criticality | G1: QualifiedSupplierCount | H1: QualificationMonths | I1: IsSingleSource | J1: VendorID | K1: VendorName | L1: VendorTier | M1: LumenRevenueSharePct | N1: BuyerID | O1: BuyerName | P1: Team | Q1: FirstPrice | R1: LastPrice | S1: ExpectedPrice | T1: BenchmarkErosionPct | U1: ActualErosionPct | V1: ErosionCapturePct | W1: ErosionGapPerUnit | X1: TTMQty | Y1: TTMSpend | Z1: AnnualOpportunity | AA1: RejectedValue | AB1: PPV | AC1: OffContractSpend | AD1: AcceptanceRatePct | AE1: LeverageScore | AF1: ActionCode | AG1: IsThisQuarter | AH1: RecommendedAction
A2: 1 | B2: 1 | C2: LOM-0104 | D2: Laser Diode Component 0104 | E2: Laser Diode | F2: Commodity | G2: 2 | H2: 0 | I2: 0 | J2: VEN-003 | K2: Crystalline GmbH | L2: Strategic | M2: 3.69 | N2: BUY-01 | O2: Adaeze Okonkwo | P2: Optoelectronics | Q2: 583.3423 | R2: 652.1172 | S2: 471.7667 | T2: 8 | U2: -4.474 | V2: -55.93 | W2: 180.3505 | X2: 1108 | Y2: 714564.24 | Z2: 199828.4 | AA2: 6453.74 | AC2: 714564.24 | AD2: 99.1 | AE2: 59 | AF2: PUT_ON_CONTRACT | AG2: 1 | AH2: Most of this spend has no agreement in force. Put it under contract before attempting to negotiate a price against nothing.
A3: 2 | B3: 2 | C3: LOM-0128 | D3: Laser Diode Assy 0128 | E3: Laser Diode | F3: Critical | G3: 2 | H3: 9 | I3: 0 | J3: VEN-015 | K3: Crystalline Industries | L3: Preferred | M3: 3.57 | N3: BUY-01 | O3: Adaeze Okonkwo | P3: Optoelectronics | Q3: 849.1721 | R3: 832.8071 | S3: 682.1857 | T3: 8 | U3: 0.738 | V3: 9.23 | W3: 150.6214 | X3: 1189 | Y3: 997643.82 | Z3: 179088.8 | AA3: 6721.47 | AB3: -1116.53 | AC3: 0 | AD3: 99.15 | AE3: 35 | AF3: RENEGOTIATE | AG3: 1 | AH3: Renegotiate. A qualified alternative exists, though Lumen is under 8% of this supplier's revenue: leverage is weak, but the gap is large enough to justify the meeting. Open with the category erosion benchmark.
A4: 3 | B4: 3 | C4: LOM-0096 | D4: Laser Diode Module 0096 | E4: Laser Diode | F4: Standard | G4: 1 | H4: 2 | I4: 1 | J4: VEN-011 | K4: Kestrel Optical GmbH | L4: Preferred | M4: 3.73 | N4: BUY-01 | O4: Adaeze Okonkwo | P4: Optoelectronics | Q4: 416.4004 | R4: 443.9747 | S4: 327.8618 | T4: 8 | U4: -2.262 | V4: -28.28 | W4: 116.1129 | X4: 1521 | Y4: 686912.99 | Z4: 176607.69 | AA4: 5872.56 | AC4: 686912.99 | AD4: 99.09 | AE4: 37 | AF4: PUT_ON_CONTRACT | AG4: 1 | AH4: Most of this spend has no agreement in force. Put it under contract before attempting to negotiate a price against nothing.
A5: 4 | B5: 4 | C5: LOM-0048 | D5: Laser Diode Module 0048 | E5: Laser Diode | F5: Standard | G5: 3 | H5: 5 | I5: 0 | J5: VEN-008 | K5: Meridian Photonics GmbH | L5: Preferred | M5: 5.01 | N5: BUY-01 | O5: Adaeze Okonkwo | P5: Optoelectronics | Q5: 770.4723 | R5: 724.0698 | S5: 610.5554 | T5: 8 | U5: 2.202 | V5: 27.53 | W5: 113.5144 | X5: 1357 | Y5: 988567.39 | Z5: 154039.04 | AA5: 5129.45 | AB5: 2149.92 | AC5: 0 | AD5: 99.26 | AE5: 70 | AF5: RENEGOTIATE | AG5: 1 | AH5: Renegotiate. A qualified alternative exists, though Lumen is under 8% of this supplier's revenue. Open with the category erosion benchmark.
A6: 5 | B6: 1 | C6: LOM-0057 | D6: Photodetector Module 0057 | E6: Photodetector | F6: Standard | G6: 1 | H6: 2 | I6: 1 | J6: VEN-005 | K6: Helix Optics GmbH | L6: Strategic | M6: 1.75 | N6: BUY-02 | O6: Rafael Duarte | P6: Optoelectronics | Q6: 454.9047 | R6: 499.5045 | S6: 379.0049 | T6: 6.5 | U6: -3.504 | V6: -53.91 | W6: 120.4996 | X6: 875 | Y6: 436614.97 | Z6: 105437.11 | AA6: 3030.77 | AB6: 0 | AC6: 378435.02 | AD6: 98.95 | AE6: 37 | AF6: PUT_ON_CONTRACT | AG6: 1 | AH6: Most of this spend has no agreement in force. Put it under contract before attempting to negotiate a price against nothing.
A7: 6 | B7: 1 | C7: LOM-0082 | D7: Optical Fibre Module 0082 | E7: Optical Fibre | F7: Standard | G7: 1 | H7: 2 | I7: 1 | J7: VEN-032 | K7: Meridian Photonics Technologies | L7: Transactional | M7: 28.3 | N7: BUY-03 | O7: Mei-Ling Chow | P7: Optics & Coatings | Q7: 43.7097 | R7: 43.6912 | S7: 39.2633 | T7: 4 | U7: 0.016 | V7: 0.4 | W7: 4.4279 | X7: 23567 | Y7: 1026650.2 | Z7: 104353.4 | AA7: 7411.81 | AB7: 1892.88 | AC7: 0 | AD7: 99.23 | AE7: 60 | AF7: RENEGOTIATE | AG7: 1 | AH7: Renegotiate. No second supplier is qualified, but Lumen is at least 8% of this supplier's revenue. Open with the category erosion benchmark.
A8: 7 | B8: 2 | C8: LOM-0024 | D8: Laser Diode Module 0024 | E8: Laser Diode | F8: Standard | G8: 1 | H8: 2 | I8: 1 | J8: VEN-019 | K8: Quantex Industries | L8: Approved | M8: 16 | N8: BUY-02 | O8: Rafael Duarte | P8: Optoelectronics | Q8: 432.7746 | R8: 444.2963 | S8: 345.3884 | T8: 8 | U8: -0.976 | V8: -12.2 | W8: 98.9079 | X8: 1026 | Y8: 454797.44 | Z8: 101479.51 | AA8: 3530.55 | AB8: -1270.08 | AC8: 0 | AD8: 99.2 | AE8: 60 | AF8: RENEGOTIATE | AG8: 1 | AH8: Renegotiate. No second supplier is qualified, but Lumen is at least 8% of this supplier's revenue. Open with the category erosion benchmark.
