Workbook
Name AsOfDate: Control!$B$5
Name Bucket90Threshold: Control!$B$9
Name CallsPerCollectorPerDay: Control!$B$7
Name DisputeDiscount: Control!$B$8
Name QueueRowsShown: Control!$B$10
Name SourceFolder: Control!$B$6
Name xlADD: Calc!$C$23
Name xlBPDSO: Calc!$C$22
Name xlDSOCountback: Calc!$C$20

Sheet README
A1: VANTAGE WHOLESALE SUPPLY -- RECEIVABLES CONTROL
A3: Vantage Wholesale Supply is a fictional industrial parts distributor. Every figure in this workbook is synthetic, generated by the SQL scripts in the sql\ folder of this project. No confidential data is used and no claim is made about any production system.
A5: THE QUESTION THIS ANSWERS
A6: DSO has risen. How many of those days did Vantage grant itself through the terms it sold, how many are customers taking beyond those terms, and who should collections call first?
A8: SHEETS
A9: Dashboard The scorecard, the DSO bridge and the ageing profile. Every number is a formula over the extract.
A10: Priority Queue The operational control: who to call, in what order, with the instruction and the dollar ask.
A11: Cash Application The OTHER worklist: money already banked that nobody matched. Where it covers at least half the past-due balance (APPLY_CASH) the account must not be called; elsewhere, quote the balance net of it.
A12: Ageing Matrix Open AR by bucket, cut by any dimension you pick.
A13: Validation Each headline figure computed twice -- once in SQL, once in Excel -- and reconciled.
A14: Control Every parameter the workbook obeys.
A15: Calc The working behind countback DSO and the queue ranking. Visible on purpose.
... A35: Nothing on the Dashboard is a pasted value. The balances come from SUMIFS over the open-item extract, the countback DSO from a real month-by-month loop on the Calc sheet, and the red/amber/green status from INDEX/MATCH against the target table -- so changing a target changes the status, and changing the data changes the numbers. The Validation sheet then checks the Excel implementation against the SQL one and says on its own face if they ever disagree.

Sheet Dashboard
A1: VANTAGE WHOLESALE SUPPLY -- RECEIVABLES PERFORMANCE
A2: ="Reporting date: "&TEXT(AsOfDate,"d mmmm yyyy")&" | Fictional company, synthetic data, no production system." -> Reporting date: 31 December 2025 | Fictional company, synthetic data, no production system.
A4: THE QUESTION
A5: DSO has risen. How many of those days did Vantage GRANT itself through the terms it sold, how many are customers TAKING beyond those terms -- and who should collections call first?
A7: BALANCES -- recomputed in Excel from the open-item extract | E7: DSO BRIDGE -- granted versus taken (these three add to classic DSO exactly)
A8: Total open AR | C8: =SUM(tOpenItems[OpenBalance]) -> 10847081 | E8: Component | F8: Days | G8: Cash | H8: Who owns it
A9: Not yet due (granted) | C9: =SUMIFS(tOpenItems[OpenBalance],tOpenItems[DaysPastDue],"<=0") -> 8095793.8 | E9: Granted -- not yet due | F9: =C9*$C$15/$C$14 -> 45.967923 | G9: =C9 -> 8095793.8 | H9: Sales / terms policy
A10: Past due, disputed | C10: =SUMIFS(tOpenItems[OpenBalance],tOpenItems[DaysPastDue],">0",tOpenItems[IsDisputedOpen],1) -> 154864.71 | E10: Taken -- disputed | F10: =C10*$C$15/$C$14 -> 0.87932194 | G10: =C10 -> 154864.71 | H10: Billing / sales
A11: Past due, undisputed | C11: =SUMIFS(tOpenItems[OpenBalance],tOpenItems[DaysPastDue],">0",tOpenItems[IsDisputedOpen],0) -> 2596423 | E11: Taken -- undisputed | F11: =C11*$C$15/$C$14 -> 14.742492 | G11: =C11 -> 2596423 | H11: Collections
A12: Of which 90+ days | C12: =SUMIFS(tOpenItems[OpenBalance],tOpenItems[DaysPastDue],">"&Bucket90Threshold) -> 362863.78 | E12: TOTAL -- classic DSO | F12: =C8*$C$15/$C$14 -> 61.589737 | G12: =C8 -> 10847081
A13: Open invoices | C13: =COUNTA(tOpenItems[InvoiceNo]) -> 2346 | E13: Check: parts less total | F13: =ROUND(F9+F10+F11-F12,10) -> 0 | H13: =IF(ABS(F13)<0.0000001,"Identity holds","BRIDGE DOES NOT CLOSE") -> Identity holds
A14: Credit sales, last 12 mths | C14: =SUMIFS(tSales[CreditSales],tSales[MonthEndDate],">"&EOMONTH(AsOfDate,-12),tSales[MonthEndDate],"<="&AsOfDate) -> 64283189 | E14: Weighted average terms sold | F14: =SUMPRODUCT((tSales[MonthEndDate]>EOMONTH(AsOfDate,-12))*(tSales[MonthEndDate]<=AsOfDate)*tSales[CreditSales]*tSales[WeightedAvgTermsDays])/$C$14 -> 46.675073 | H14: The floor: DSO if every customer paid exactly on the due date
A15: Days in that window | C15: =SUMIFS(tSales[DaysInMonth],tSales[MonthEndDate],">"&EOMONTH(AsOfDate,-12),tSales[MonthEndDate],"<="&AsOfDate) -> 365 | E15: DSO target | F15: =INDEX(tTargets[TargetValue],MATCH("DSO",tTargets[MetricName],0)) -> 45
A16: Credit sales per day | C16: =C14/C15 -> 176118.33 | E16: Allowance the target leaves over terms | F16: =F15-F14 -> -1.6750732 | H16: =IF(F16<0,"TARGET IS BELOW THE TERMS FLOOR -- unachievable","Achievable: "&TEXT(F16,"0.0")&" days of collection allowance") -> TARGET IS BELOW THE TERMS FLOOR -- unachievable
E17: Billing lag (despatch to invoice) | F17: =SUMPRODUCT((tLag[MonthEndDate]>EOMONTH(AsOfDate,-12))*(tLag[MonthEndDate]<=AsOfDate)*tLag[CreditSales]*tLag[BillingLagDays])/SUMPRODUCT((tLag[MonthEndDate]>EOMONTH(AsOfDate,-12))*(tLag[MonthEndDate]<=AsOfDate)*tLag[CreditSales]) -> 1.7841244 | H17: Before the DSO clock starts, so additive -- and the only days fixable without a customer conversation
E18: TRUE CASH CYCLE (despatch to cash) | F18: =F17+F12 -> 63.373862 | H18: ="Larger than the DSO anyone is reporting, by "&TEXT(F17,"0.00")&" days" -> Larger than the DSO anyone is reporting, by 1.78 days
A20: SCORECARD -- status is computed against the target table, not typed in
A21: Metric | B21: Value | C21: Target | D21: Warning | E21: Status | F21: Variance to target | G21: What it means
A22: DSO (countback) | B22: =xlDSOCountback -> 63.071066 | C22: =INDEX(tTargets[TargetValue],MATCH("DSO",tTargets[MetricName],0)) -> 45 | D22: =INDEX(tTargets[WarningValue],MATCH("DSO",tTargets[MetricName],0)) -> 55 | E22: =IF(INDEX(tTargets[Direction],MATCH("DSO",tTargets[MetricName],0))="LowerBetter",IF(B22<=C22,"Green",IF(B22<=D22,"Amber","Red")),IF(B22>=C22,"Green",IF(B22>=D22,"Amber","Red"))) -> Red | F22: =IF(INDEX(tTargets[Direction],MATCH("DSO",tTargets[MetricName],0))="LowerBetter",B22-C22,C22-B22) -> 18.071066 | G22: Days of recent sales sitting in receivables.
A23: Average days delinquent | B23: =xlADD -> 16.8 | C23: =INDEX(tTargets[TargetValue],MATCH("AvgDaysDelinquent",tTargets[MetricName],0)) -> 8 | D23: =INDEX(tTargets[WarningValue],MATCH("AvgDaysDelinquent",tTargets[MetricName],0)) -> 15 | E23: =IF(INDEX(tTargets[Direction],MATCH("AvgDaysDelinquent",tTargets[MetricName],0))="LowerBetter",IF(B23<=C23,"Green",IF(B23<=D23,"Amber","Red")),IF(B23>=C23,"Green",IF(B23>=D23,"Amber","Red"))) -> Red | F23: =IF(INDEX(tTargets[Direction],MATCH("AvgDaysDelinquent",tTargets[MetricName],0))="LowerBetter",B23-C23,C23-B23) -> 8.8 | G23: Days lost purely to late payment, terms stripped out.
A24: Past due share of AR | B24: =100*($C$10+$C$11)/$C$8 -> 25.364313 | C24: =INDEX(tTargets[TargetValue],MATCH("PctPastDue",tTargets[MetricName],0)) -> 15 | D24: =INDEX(tTargets[WarningValue],MATCH("PctPastDue",tTargets[MetricName],0)) -> 25 | E24: =IF(INDEX(tTargets[Direction],MATCH("PctPastDue",tTargets[MetricName],0))="LowerBetter",IF(B24<=C24,"Green",IF(B24<=D24,"Amber","Red")),IF(B24>=C24,"Green",IF(B24>=D24,"Amber","Red"))) -> Red | F24: =IF(INDEX(tTargets[Direction],MATCH("PctPastDue",tTargets[MetricName],0))="LowerBetter",B24-C24,C24-B24) -> 10.364313 | G24: By value. Compare with the count version before concluding anything.
A25: 90+ share of AR | B25: =100*$C$12/$C$8 -> 3.3452665 | C25: =INDEX(tTargets[TargetValue],MATCH("Pct90Plus",tTargets[MetricName],0)) -> 3 | D25: =INDEX(tTargets[WarningValue],MATCH("Pct90Plus",tTargets[MetricName],0)) -> 6 | E25: =IF(INDEX(tTargets[Direction],MATCH("Pct90Plus",tTargets[MetricName],0))="LowerBetter",IF(B25<=C25,"Green",IF(B25<=D25,"Amber","Red")),IF(B25>=C25,"Green",IF(B25>=D25,"Amber","Red"))) -> Amber | F25: =IF(INDEX(tTargets[Direction],MATCH("Pct90Plus",tTargets[MetricName],0))="LowerBetter",B25-C25,C25-B25) -> 0.34526647 | G25: Seriously delinquent balance as a share of the book.
A26: Collection effectiveness (book) | B26: =INDEX(tKPI[CEI_Book],MATCH(MAX(tKPI[AsOfDate]),tKPI[AsOfDate],0)) -> 66.91 | C26: =INDEX(tTargets[TargetValue],MATCH("CEI",tTargets[MetricName],0)) -> 85 | D26: =INDEX(tTargets[WarningValue],MATCH("CEI",tTargets[MetricName],0)) -> 75 | E26: =IF(B26>=C26,"Green",IF(B26>=D26,"Amber","Red")) -> Red | F26: =C26-B26 -> 18.09 | G26: ="Cash variant reads "&TEXT(INDEX(tKPI[CEI_Cash],MATCH(MAX(tKPI[AsOfDate]),tKPI[AsOfDate],0)),"0.00")&"%. The gap is write-offs counted as collections."&" (from SQL: needs a prior-month balance the open-item file does not carry.)" -> Cash variant reads 65.26%. The gap is write-offs counted as collections. (from SQL: needs a prior-month balance the open-item file does not carry.)
A27: Unapplied cash % of AR | B27: =100*SUM(tCashApp[UnappliedCash])/$C$8 -> 3.8664053 | C27: =INDEX(tTargets[TargetValue],MATCH("UnappliedCashPct",tTargets[MetricName],0)) -> 0.5 | D27: =INDEX(tTargets[WarningValue],MATCH("UnappliedCashPct",tTargets[MetricName],0)) -> 1.5 | E27: =IF(B27<=C27,"Green",IF(B27<=D27,"Amber","Red")) -> Red | F27: =B27-C27 -> 3.3664053 | G27: ="Cash banked against "&COUNTA(tCashApp[CustomerID])&" accounts that nobody has matched. Every dollar of it makes an invoice look unpaid when it is not." -> Cash banked against 97 accounts that nobody has matched. Every dollar of it makes an invoice look unpaid when it is not.
A28: Billing lag (days) | B28: =SUMPRODUCT((tLag[MonthEndDate]>EOMONTH(AsOfDate,-12))*(tLag[MonthEndDate]<=AsOfDate)*tLag[CreditSales]*tLag[BillingLagDays])/SUMPRODUCT((tLag[MonthEndDate]>EOMONTH(AsOfDate,-12))*(tLag[MonthEndDate]<=AsOfDate)*tLag[CreditSales]) -> 1.7841244 | C28: =INDEX(tTargets[TargetValue],MATCH("BillingLagDays",tTargets[MetricName],0)) -> 2 | D28: =INDEX(tTargets[WarningValue],MATCH("BillingLagDays",tTargets[MetricName],0)) -> 4 | E28: =IF(B28<=C28,"Green",IF(B28<=D28,"Amber","Red")) -> Green | F28: =B28-C28 -> -0.21587556 | G28: Despatch to invoice, dollar-weighted. Sits BEFORE the DSO clock starts, so it adds to the cycle rather than being part of DSO.
A29: Promise kept rate % | B29: =100*SUMIFS(tPromise[PromisedAmount],tPromise[PromiseStatus],"Kept",tPromise[PromisedPayDate],">"&EOMONTH(AsOfDate,-12))/SUMIFS(tPromise[PromisedAmount],tPromise[PromiseStatus],"<>Outstanding",tPromise[PromisedPayDate],">"&EOMONTH(AsOfDate,-12)) -> 86.599287 | C29: =INDEX(tTargets[TargetValue],MATCH("PromiseKeptRate",tTargets[MetricName],0)) -> 80 | D29: =INDEX(tTargets[WarningValue],MATCH("PromiseKeptRate",tTargets[MetricName],0)) -> 65 | E29: =IF(B29>=C29,"Green",IF(B29>=D29,"Amber","Red")) -> Green | F29: =C29-B29 -> -6.5992866 | G29: ="Portfolio figure. The High-risk tier reads "&TEXT(100*SUMIFS(tPromise[PromisedAmount],tPromise[PromiseStatus],"Kept",tPromise[RiskTier],"High")/SUMIFS(tPromise[PromisedAmount],tPromise[PromiseStatus],"<>Outstanding",tPromise[RiskTier],"High"),"0.0")&"% -- read the cohort, never the headline." -> Portfolio figure. The High-risk tier reads 54.6% -- read the cohort, never the headline.
A31: AGEING -- buckets re-derived in Excel from days past due, not taken from the extract
A32: Bucket | B32: Invoices | C32: Balance | D32: Share of AR | E32: Risk-weighted exposure
A33: =INDEX(tBuckets[BucketName],1) -> Current | B33: =COUNTIFS(tOpenItems[DaysPastDue],">="&INDEX(tBuckets[MinDaysPastDue],1),tOpenItems[DaysPastDue],"<="&INDEX(tBuckets[MaxDaysPastDue],1)) -> 1672 | C33: =SUMIFS(tOpenItems[OpenBalance],tOpenItems[DaysPastDue],">="&INDEX(tBuckets[MinDaysPastDue],1),tOpenItems[DaysPastDue],"<="&INDEX(tBuckets[MaxDaysPastDue],1)) -> 8095793.8 | D33: =C33/$C$8 -> 0.74635687 | E33: =C33*INDEX(tBuckets[RiskWeight],1) -> 0
A34: =INDEX(tBuckets[BucketName],2) -> 1-30 | B34: =COUNTIFS(tOpenItems[DaysPastDue],">="&INDEX(tBuckets[MinDaysPastDue],2),tOpenItems[DaysPastDue],"<="&INDEX(tBuckets[MaxDaysPastDue],2)) -> 414 | C34: =SUMIFS(tOpenItems[OpenBalance],tOpenItems[DaysPastDue],">="&INDEX(tBuckets[MinDaysPastDue],2),tOpenItems[DaysPastDue],"<="&INDEX(tBuckets[MaxDaysPastDue],2)) -> 1839519.4 | D34: =C34/$C$8 -> 0.16958658 | E34: =C34*INDEX(tBuckets[RiskWeight],2) -> 459879.85
A35: =INDEX(tBuckets[BucketName],3) -> 31-60 | B35: =COUNTIFS(tOpenItems[DaysPastDue],">="&INDEX(tBuckets[MinDaysPastDue],3),tOpenItems[DaysPastDue],"<="&INDEX(tBuckets[MaxDaysPastDue],3)) -> 101 | C35: =SUMIFS(tOpenItems[OpenBalance],tOpenItems[DaysPastDue],">="&INDEX(tBuckets[MinDaysPastDue],3),tOpenItems[DaysPastDue],"<="&INDEX(tBuckets[MaxDaysPastDue],3)) -> 405938.13 | D35: =C35/$C$8 -> 0.037423719 | E35: =C35*INDEX(tBuckets[RiskWeight],3) -> 202969.06
A36: =INDEX(tBuckets[BucketName],4) -> 61-90 | B36: =COUNTIFS(tOpenItems[DaysPastDue],">="&INDEX(tBuckets[MinDaysPastDue],4),tOpenItems[DaysPastDue],"<="&INDEX(tBuckets[MaxDaysPastDue],4)) -> 34 | C36: =SUMIFS(tOpenItems[OpenBalance],tOpenItems[DaysPastDue],">="&INDEX(tBuckets[MinDaysPastDue],4),tOpenItems[DaysPastDue],"<="&INDEX(tBuckets[MaxDaysPastDue],4)) -> 142966.39 | D36: =C36/$C$8 -> 0.013180171 | E36: =C36*INDEX(tBuckets[RiskWeight],4) -> 107224.79
A37: =INDEX(tBuckets[BucketName],5) -> 90+ | B37: =COUNTIFS(tOpenItems[DaysPastDue],">="&INDEX(tBuckets[MinDaysPastDue],5),tOpenItems[DaysPastDue],"<="&INDEX(tBuckets[MaxDaysPastDue],5)) -> 125 | C37: =SUMIFS(tOpenItems[OpenBalance],tOpenItems[DaysPastDue],">="&INDEX(tBuckets[MinDaysPastDue],5),tOpenItems[DaysPastDue],"<="&INDEX(tBuckets[MaxDaysPastDue],5)) -> 362863.78 | D37: =C37/$C$8 -> 0.033452665 | E37: =C37*INDEX(tBuckets[RiskWeight],5) -> 362863.78
A38: TOTAL | B38: =SUM(B33:B37) -> 2346 | C38: =SUM(C33:C37) -> 10847081 | D38: =SUM(D33:D37) -> 1 | E38: =SUM(E33:E37) -> 1132937.5

Sheet Priority Queue
A1: PRIORITY ACTION QUEUE
A2: Who collections should call first, ranked by risk-weighted money a call can actually move. Change the filters; the list re-ranks itself.
B4: Collector | C4: (All) | E4: Accounts matching | F4: =SUM(Calc!$B$28:$B$299) -> 65
B5: Action | C5: (All) | E5: Past due in scope | F5: =SUMPRODUCT(Calc!$B$28:$B$299,tQueue[PastDueBalance]) -> 1685560
B6: Today's worklist only | C6: Yes | E6: Collectable exposure in scope | F6: =SUMPRODUCT(Calc!$B$28:$B$299,tQueue[CollectableExposure]) -> 640540.01
B7: Minimum past due ($) | C7: 0 | E7: ="Showing top "&MIN(QueueRowsShown,F4)&" of "&F4 -> Showing top 25 of 65
A9: # | B9: Customer | C9: Segment | D9: Risk | E9: Collector | F9: Terms | G9: Open balance | H9: Past due | I9: 90+ | J9: Disputed | K9: Collectable exposure | L9: Oldest days | M9: Credit use % | N9: Hold | O9: Action | P9: What to do
A10: =IF(1>MIN(QueueRowsShown,$F$4),"",1) -> 1 | B10: =IFERROR(INDEX(tQueue[CustomerName],MATCH(1,Calc!$C$28:$C$299,0)),"") -> Ironbridge Components | C10: =IFERROR(INDEX(tQueue[Segment],MATCH(1,Calc!$C$28:$C$299,0)),"") -> OEM Manufacturer | D10: =IFERROR(INDEX(tQueue[RiskTier],MATCH(1,Calc!$C$28:$C$299,0)),"") -> High | E10: =IFERROR(INDEX(tQueue[CollectorName],MATCH(1,Calc!$C$28:$C$299,0)),"") -> Priya Natarajan | F10: =IFERROR(INDEX(tQueue[TermsCode],MATCH(1,Calc!$C$28:$C$299,0)),"") -> NET45 | G10: =IFERROR(INDEX(tQueue[OpenBalance],MATCH(1,Calc!$C$28:$C$299,0)),"") -> 171140.07 | H10: =IFERROR(INDEX(tQueue[PastDueBalance],MATCH(1,Calc!$C$28:$C$299,0)),"") -> 132293.14 | I10: =IFERROR(INDEX(tQueue[Balance90Plus],MATCH(1,Calc!$C$28:$C$299,0)),"") -> 0 | J10: =IFERROR(INDEX(tQueue[DisputedBalance],MATCH(1,Calc!$C$28:$C$299,0)),"") -> 15640.04 | K10: =IFERROR(INDEX(tQueue[CollectableExposure],MATCH(1,Calc!$C$28:$C$299,0)),"") -> 57024.44 | L10: =IFERROR(INDEX(tQueue[OldestDaysPastDue],MATCH(1,Calc!$C$28:$C$299,0)),"") -> 90 | M10: =IFERROR(INDEX(tQueue[CreditUtilizationPct],MATCH(1,Calc!$C$28:$C$299,0)),"") -> 38.03 | N10: =IFERROR(INDEX(tQueue[CreditHoldFlag],MATCH(1,Calc!$C$28:$C$299,0)),"") -> 0 | O10: =IFERROR(INDEX(tQueue[ActionCode],MATCH(1,Calc!$C$28:$C$299,0)),"") -> ESCALATE | P10: =IFERROR(INDEX(tQueue[RecommendedAction],MATCH(1,Calc!$C$28:$C$299,0)),"") -> Escalate: high-risk account carrying a 90+ balance. Hold further shipments and agree a payment plan or refer for recovery.
A11: =IF(2>MIN(QueueRowsShown,$F$4),"",2) -> 2 | B11: =IFERROR(INDEX(tQueue[CustomerName],MATCH(2,Calc!$C$28:$C$299,0)),"") -> Westbrook Industries - West | C11: =IFERROR(INDEX(tQueue[Segment],MATCH(2,Calc!$C$28:$C$299,0)),"") -> OEM Manufacturer | D11: =IFERROR(INDEX(tQueue[RiskTier],MATCH(2,Calc!$C$28:$C$299,0)),"") -> Medium | E11: =IFERROR(INDEX(tQueue[CollectorName],MATCH(2,Calc!$C$28:$C$299,0)),"") -> Marcus Bell | F11: =IFERROR(INDEX(tQueue[TermsCode],MATCH(2,Calc!$C$28:$C$299,0)),"") -> NET60 | G11: =IFERROR(INDEX(tQueue[OpenBalance],MATCH(2,Calc!$C$28:$C$299,0)),"") -> 122327.81 | H11: =IFERROR(INDEX(tQueue[PastDueBalance],MATCH(2,Calc!$C$28:$C$299,0)),"") -> 82857.53 | I11: =IFERROR(INDEX(tQueue[Balance90Plus],MATCH(2,Calc!$C$28:$C$299,0)),"") -> 0 | J11: =IFERROR(INDEX(tQueue[DisputedBalance],MATCH(2,Calc!$C$28:$C$299,0)),"") -> 0 | K11: =IFERROR(INDEX(tQueue[CollectableExposure],MATCH(2,Calc!$C$28:$C$299,0)),"") -> 37750.08 | L11: =IFERROR(INDEX(tQueue[OldestDaysPastDue],MATCH(2,Calc!$C$28:$C$299,0)),"") -> 68 | M11: =IFERROR(INDEX(tQueue[CreditUtilizationPct],MATCH(2,Calc!$C$28:$C$299,0)),"") -> 38.23 | N11: =IFERROR(INDEX(tQueue[CreditHoldFlag],MATCH(2,Calc!$C$28:$C$299,0)),"") -> 0 | O11: =IFERROR(INDEX(tQueue[ActionCode],MATCH(2,Calc!$C$28:$C$299,0)),"") -> COLLECTION_CALL | P11: =IFERROR(INDEX(tQueue[RecommendedAction],MATCH(2,Calc!$C$28:$C$299,0)),"") -> Collection call: oldest item is more than 30 days past due.
A12: =IF(3>MIN(QueueRowsShown,$F$4),"",3) -> 3 | B12: =IFERROR(INDEX(tQueue[CustomerName],MATCH(3,Calc!$C$28:$C$299,0)),"") -> Crestview Contracting - Northeast 3 | C12: =IFERROR(INDEX(tQueue[Segment],MATCH(3,Calc!$C$28:$C$299,0)),"") -> Contractor | D12: =IFERROR(INDEX(tQueue[RiskTier],MATCH(3,Calc!$C$28:$C$299,0)),"") -> High | E12: =IFERROR(INDEX(tQueue[CollectorName],MATCH(3,Calc!$C$28:$C$299,0)),"") -> Tomas Okafor | F12: =IFERROR(INDEX(tQueue[TermsCode],MATCH(3,Calc!$C$28:$C$299,0)),"") -> 2/10NET30 | G12: =IFERROR(INDEX(tQueue[OpenBalance],MATCH(3,Calc!$C$28:$C$299,0)),"") -> 60651.51 | H12: =IFERROR(INDEX(tQueue[PastDueBalance],MATCH(3,Calc!$C$28:$C$299,0)),"") -> 52023.36 | I12: =IFERROR(INDEX(tQueue[Balance90Plus],MATCH(3,Calc!$C$28:$C$299,0)),"") -> 19027.82 | J12: =IFERROR(INDEX(tQueue[DisputedBalance],MATCH(3,Calc!$C$28:$C$299,0)),"") -> 0 | K12: =IFERROR(INDEX(tQueue[CollectableExposure],MATCH(3,Calc!$C$28:$C$299,0)),"") -> 37672.1 | L12: =IFERROR(INDEX(tQueue[OldestDaysPastDue],MATCH(3,Calc!$C$28:$C$299,0)),"") -> 139 | M12: =IFERROR(INDEX(tQueue[CreditUtilizationPct],MATCH(3,Calc!$C$28:$C$299,0)),"") -> 48.52 | N12: =IFERROR(INDEX(tQueue[CreditHoldFlag],MATCH(3,Calc!$C$28:$C$299,0)),"") -> 0 | O12: =IFERROR(INDEX(tQueue[ActionCode],MATCH(3,Calc!$C$28:$C$299,0)),"") -> ESCALATE | P12: =IFERROR(INDEX(tQueue[RecommendedAction],MATCH(3,Calc!$C$28:$C$299,0)),"") -> Escalate: high-risk account carrying a 90+ balance. Hold further shipments and agree a payment plan or refer for recovery.
A13: =IF(4>MIN(QueueRowsShown,$F$4),"",4) -> 4 | B13: =IFERROR(INDEX(tQueue[CustomerName],MATCH(4,Calc!$C$28:$C$299,0)),"") -> Titan Builders - Southwest | C13: =IFERROR(INDEX(tQueue[Segment],MATCH(4,Calc!$C$28:$C$299,0)),"") -> Contractor | D13: =IFERROR(INDEX(tQueue[RiskTier],MATCH(4,Calc!$C$28:$C$299,0)),"") -> High | E13: =IFERROR(INDEX(tQueue[CollectorName],MATCH(4,Calc!$C$28:$C$299,0)),"") -> Tomas Okafor | F13: =IFERROR(INDEX(tQueue[TermsCode],MATCH(4,Calc!$C$28:$C$299,0)),"") -> 2/10NET30 | G13: =IFERROR(INDEX(tQueue[OpenBalance],MATCH(4,Calc!$C$28:$C$299,0)),"") -> 60280.9 | H13: =IFERROR(INDEX(tQueue[PastDueBalance],MATCH(4,Calc!$C$28:$C$299,0)),"") -> 48278 | I13: =IFERROR(INDEX(tQueue[Balance90Plus],MATCH(4,Calc!$C$28:$C$299,0)),"") -> 24426.9 | J13: =IFERROR(INDEX(tQueue[DisputedBalance],MATCH(4,Calc!$C$28:$C$299,0)),"") -> 0 | K13: =IFERROR(INDEX(tQueue[CollectableExposure],MATCH(4,Calc!$C$28:$C$299,0)),"") -> 35663.13 | L13: =IFERROR(INDEX(tQueue[OldestDaysPastDue],MATCH(4,Calc!$C$28:$C$299,0)),"") -> 147 | M13: =IFERROR(INDEX(tQueue[CreditUtilizationPct],MATCH(4,Calc!$C$28:$C$299,0)),"") -> 57.41 | N13: =IFERROR(INDEX(tQueue[CreditHoldFlag],MATCH(4,Calc!$C$28:$C$299,0)),"") -> 0 | O13: =IFERROR(INDEX(tQueue[ActionCode],MATCH(4,Calc!$C$28:$C$299,0)),"") -> ESCALATE | P13: =IFERROR(INDEX(tQueue[RecommendedAction],MATCH(4,Calc!$C$28:$C$299,0)),"") -> Escalate: high-risk account carrying a 90+ balance. Hold further shipments and agree a payment plan or refer for recovery.
A14: =IF(5>MIN(QueueRowsShown,$F$4),"",5) -> 5 | B14: =IFERROR(INDEX(tQueue[CustomerName],MATCH(5,Calc!$C$28:$C$299,0)),"") -> Bluewater Electric | C14: =IFERROR(INDEX(tQueue[Segment],MATCH(5,Calc!$C$28:$C$299,0)),"") -> Contractor | D14: =IFERROR(INDEX(tQueue[RiskTier],MATCH(5,Calc!$C$28:$C$299,0)),"") -> High | E14: =IFERROR(INDEX(tQueue[CollectorName],MATCH(5,Calc!$C$28:$C$299,0)),"") -> Elena Ruiz | F14: =IFERROR(INDEX(tQueue[TermsCode],MATCH(5,Calc!$C$28:$C$299,0)),"") -> NET60 | G14: =IFERROR(INDEX(tQueue[OpenBalance],MATCH(5,Calc!$C$28:$C$299,0)),"") -> 76941.41 | H14: =IFERROR(INDEX(tQueue[PastDueBalance],MATCH(5,Calc!$C$28:$C$299,0)),"") -> 46413.57 | I14: =IFERROR(INDEX(tQueue[Balance90Plus],MATCH(5,Calc!$C$28:$C$299,0)),"") -> 10287.08 | J14: =IFERROR(INDEX(tQueue[DisputedBalance],MATCH(5,Calc!$C$28:$C$299,0)),"") -> 0 | K14: =IFERROR(INDEX(tQueue[CollectableExposure],MATCH(5,Calc!$C$28:$C$299,0)),"") -> 32793.73 | L14: =IFERROR(INDEX(tQueue[OldestDaysPastDue],MATCH(5,Calc!$C$28:$C$299,0)),"") -> 120 | M14: =IFERROR(INDEX(tQueue[CreditUtilizationPct],MATCH(5,Calc!$C$28:$C$299,0)),"") -> 76.94 | N14: =IFERROR(INDEX(tQueue[CreditHoldFlag],MATCH(5,Calc!$C$28:$C$299,0)),"") -> 0 | O14: =IFERROR(INDEX(tQueue[ActionCode],MATCH(5,Calc!$C$28:$C$299,0)),"") -> ESCALATE | P14: =IFERROR(INDEX(tQueue[RecommendedAction],MATCH(5,Calc!$C$28:$C$299,0)),"") -> Escalate: high-risk account carrying a 90+ balance. Hold further shipments and agree a payment plan or refer for recovery.
A15: =IF(6>MIN(QueueRowsShown,$F$4),"",6) -> 6 | B15: =IFERROR(INDEX(tQueue[CustomerName],MATCH(6,Calc!$C$28:$C$299,0)),"") -> Pioneer Construction | C15: =IFERROR(INDEX(tQueue[Segment],MATCH(6,Calc!$C$28:$C$299,0)),"") -> Contractor | D15: =IFERROR(INDEX(tQueue[RiskTier],MATCH(6,Calc!$C$28:$C$299,0)),"") -> High | E15: =IFERROR(INDEX(tQueue[CollectorName],MATCH(6,Calc!$C$28:$C$299,0)),"") -> Elena Ruiz | F15: =IFERROR(INDEX(tQueue[TermsCode],MATCH(6,Calc!$C$28:$C$299,0)),"") -> 2/10NET30 | G15: =IFERROR(INDEX(tQueue[OpenBalance],MATCH(6,Calc!$C$28:$C$299,0)),"") -> 65460.37 | H15: =IFERROR(INDEX(tQueue[PastDueBalance],MATCH(6,Calc!$C$28:$C$299,0)),"") -> 51420.43 | I15: =IFERROR(INDEX(tQueue[Balance90Plus],MATCH(6,Calc!$C$28:$C$299,0)),"") -> 18333.73 | J15: =IFERROR(INDEX(tQueue[DisputedBalance],MATCH(6,Calc!$C$28:$C$299,0)),"") -> 7692.27 | K15: =IFERROR(INDEX(tQueue[CollectableExposure],MATCH(6,Calc!$C$28:$C$299,0)),"") -> 32505.02 | L15: =IFERROR(INDEX(tQueue[OldestDaysPastDue],MATCH(6,Calc!$C$28:$C$299,0)),"") -> 140 | M15: =IFERROR(INDEX(tQueue[CreditUtilizationPct],MATCH(6,Calc!$C$28:$C$299,0)),"") -> 45.15 | N15: =IFERROR(INDEX(tQueue[CreditHoldFlag],MATCH(6,Calc!$C$28:$C$299,0)),"") -> 0 | O15: =IFERROR(INDEX(tQueue[ActionCode],MATCH(6,Calc!$C$28:$C$299,0)),"") -> ESCALATE | P15: =IFERROR(INDEX(tQueue[RecommendedAction],MATCH(6,Calc!$C$28:$C$299,0)),"") -> Escalate: high-risk account carrying a 90+ balance. Hold further shipments and agree a payment plan or refer for recovery.
A16: =IF(7>MIN(QueueRowsShown,$F$4),"",7) -> 7 | B16: =IFERROR(INDEX(tQueue[CustomerName],MATCH(7,Calc!$C$28:$C$299,0)),"") -> Apex Mechanical | C16: =IFERROR(INDEX(tQueue[Segment],MATCH(7,Calc!$C$28:$C$299,0)),"") -> Contractor | D16: =IFERROR(INDEX(tQueue[RiskTier],MATCH(7,Calc!$C$28:$C$299,0)),"") -> High | E16: =IFERROR(INDEX(tQueue[CollectorName],MATCH(7,Calc!$C$28:$C$299,0)),"") -> Marcus Bell | F16: =IFERROR(INDEX(tQueue[TermsCode],MATCH(7,Calc!$C$28:$C$299,0)),"") -> NET30 | G16: =IFERROR(INDEX(tQueue[OpenBalance],MATCH(7,Calc!$C$28:$C$299,0)),"") -> 53593.68 | H16: =IFERROR(INDEX(tQueue[PastDueBalance],MATCH(7,Calc!$C$28:$C$299,0)),"") -> 45881.37 | I16: =IFERROR(INDEX(tQueue[Balance90Plus],MATCH(7,Calc!$C$28:$C$299,0)),"") -> 16968.16 | J16: =IFERROR(INDEX(tQueue[DisputedBalance],MATCH(7,Calc!$C$28:$C$299,0)),"") -> 0 | K16: =IFERROR(INDEX(tQueue[CollectableExposure],MATCH(7,Calc!$C$28:$C$299,0)),"") -> 31940.25 | L16: =IFERROR(INDEX(tQueue[OldestDaysPastDue],MATCH(7,Calc!$C$28:$C$299,0)),"") -> 143 | M16: =IFERROR(INDEX(tQueue[CreditUtilizationPct],MATCH(7,Calc!$C$28:$C$299,0)),"") -> 35.73 | N16: =IFERROR(INDEX(tQueue[CreditHoldFlag],MATCH(7,Calc!$C$28:$C$299,0)),"") -> 0 | O16: =IFERROR(INDEX(tQueue[ActionCode],MATCH(7,Calc!$C$28:$C$299,0)),"") -> ESCALATE | P16: =IFERROR(INDEX(tQueue[RecommendedAction],MATCH(7,Calc!$C$28:$C$299,0)),"") -> Escalate: high-risk account carrying a 90+ balance. Hold further shipments and agree a payment plan or refer for recovery.
A17: =IF(8>MIN(QueueRowsShown,$F$4),"",8) -> 8 | B17: =IFERROR(INDEX(tQueue[CustomerName],MATCH(8,Calc!$C$28:$C$299,0)),"") -> Stonegate Machine Works | C17: =IFERROR(INDEX(tQueue[Segment],MATCH(8,Calc!$C$28:$C$299,0)),"") -> OEM Manufacturer | D17: =IFERROR(INDEX(tQueue[RiskTier],MATCH(8,Calc!$C$28:$C$299,0)),"") -> Low | E17: =IFERROR(INDEX(tQueue[CollectorName],MATCH(8,Calc!$C$28:$C$299,0)),"") -> Marcus Bell | F17: =IFERROR(INDEX(tQueue[TermsCode],MATCH(8,Calc!$C$28:$C$299,0)),"") -> NET60 | G17: =IFERROR(INDEX(tQueue[OpenBalance],MATCH(8,Calc!$C$28:$C$299,0)),"") -> 150926.78 | H17: =IFERROR(INDEX(tQueue[PastDueBalance],MATCH(8,Calc!$C$28:$C$299,0)),"") -> 85720.95 | I17: =IFERROR(INDEX(tQueue[Balance90Plus],MATCH(8,Calc!$C$28:$C$299,0)),"") -> 1675.15 | J17: =IFERROR(INDEX(tQueue[DisputedBalance],MATCH(8,Calc!$C$28:$C$299,0)),"") -> 0 | K17: =IFERROR(INDEX(tQueue[CollectableExposure],MATCH(8,Calc!$C$28:$C$299,0)),"") -> 31517.91 | L17: =IFERROR(INDEX(tQueue[OldestDaysPastDue],MATCH(8,Calc!$C$28:$C$299,0)),"") -> 274 | M17: =IFERROR(INDEX(tQueue[CreditUtilizationPct],MATCH(8,Calc!$C$28:$C$299,0)),"") -> 29.31 | N17: =IFERROR(INDEX(tQueue[CreditHoldFlag],MATCH(8,Calc!$C$28:$C$299,0)),"") -> 0 | O17: =IFERROR(INDEX(tQueue[ActionCode],MATCH(8,Calc!$C$28:$C$299,0)),"") -> FINAL_NOTICE | P17: =IFERROR(INDEX(tQueue[RecommendedAction],MATCH(8,Calc!$C$28:$C$299,0)),"") -> Issue a final notice on the 90+ balance and confirm a payment date in writing.
A18: =IF(9>MIN(QueueRowsShown,$F$4),"",9) -> 9 | B18: =IFERROR(INDEX(tQueue[CustomerName],MATCH(9,Calc!$C$28:$C$299,0)),"") -> Riverbend Electric - Midwest 3 | C18: =IFERROR(INDEX(tQueue[Segment],MATCH(9,Calc!$C$28:$C$299,0)),"") -> Contractor | D18: =IFERROR(INDEX(tQueue[RiskTier],MATCH(9,Calc!$C$28:$C$299,0)),"") -> High | E18: =IFERROR(INDEX(tQueue[CollectorName],MATCH(9,Calc!$C$28:$C$299,0)),"") -> Elena Ruiz | F18: =IFERROR(INDEX(tQueue[TermsCode],MATCH(9,Calc!$C$28:$C$299,0)),"") -> 2/10NET30 | G18: =IFERROR(INDEX(tQueue[OpenBalance],MATCH(9,Calc!$C$28:$C$299,0)),"") -> 59342.1 | H18: =IFERROR(INDEX(tQueue[PastDueBalance],MATCH(9,Calc!$C$28:$C$299,0)),"") -> 46818.72 | I18: =IFERROR(INDEX(tQueue[Balance90Plus],MATCH(9,Calc!$C$28:$C$299,0)),"") -> 14609.63 | J18: =IFERROR(INDEX(tQueue[DisputedBalance],MATCH(9,Calc!$C$28:$C$299,0)),"") -> 0 | K18: =IFERROR(INDEX(tQueue[CollectableExposure],MATCH(9,Calc!$C$28:$C$299,0)),"") -> 27084.27 | L18: =IFERROR(INDEX(tQueue[OldestDaysPastDue],MATCH(9,Calc!$C$28:$C$299,0)),"") -> 140 | M18: =IFERROR(INDEX(tQueue[CreditUtilizationPct],MATCH(9,Calc!$C$28:$C$299,0)),"") -> 42.39 | N18: =IFERROR(INDEX(tQueue[CreditHoldFlag],MATCH(9,Calc!$C$28:$C$299,0)),"") -> 0 | O18: =IFERROR(INDEX(tQueue[ActionCode],MATCH(9,Calc!$C$28:$C$299,0)),"") -> ESCALATE | P18: =IFERROR(INDEX(tQueue[RecommendedAction],MATCH(9,Calc!$C$28:$C$299,0)),"") -> Escalate: high-risk account carrying a 90+ balance. Hold further shipments and agree a payment plan or refer for recovery.
A19: =IF(10>MIN(QueueRowsShown,$F$4),"",10) -> 10 | B19: =IFERROR(INDEX(tQueue[CustomerName],MATCH(10,Calc!$C$28:$C$299,0)),"") -> Apex Mechanical - Southeast 3 | C19: =IFERROR(INDEX(tQueue[Segment],MATCH(10,Calc!$C$28:$C$299,0)),"") -> Contractor | D19: =IFERROR(INDEX(tQueue[RiskTier],MATCH(10,Calc!$C$28:$C$299,0)),"") -> High | E19: =IFERROR(INDEX(tQueue[CollectorName],MATCH(10,Calc!$C$28:$C$299,0)),"") -> Tomas Okafor | F19: =IFERROR(INDEX(tQueue[TermsCode],MATCH(10,Calc!$C$28:$C$299,0)),"") -> NET30 | G19: =IFERROR(INDEX(tQueue[OpenBalance],MATCH(10,Calc!$C$28:$C$299,0)),"") -> 31830.69 | H19: =IFERROR(INDEX(tQueue[PastDueBalance],MATCH(10,Calc!$C$28:$C$299,0)),"") -> 28601.28 | I19: =IFERROR(INDEX(tQueue[Balance90Plus],MATCH(10,Calc!$C$28:$C$299,0)),"") -> 26001.78 | J19: =IFERROR(INDEX(tQueue[DisputedBalance],MATCH(10,Calc!$C$28:$C$299,0)),"") -> 0 | K19: =IFERROR(INDEX(tQueue[CollectableExposure],MATCH(10,Calc!$C$28:$C$299,0)),"") -> 27073.54 | L19: =IFERROR(INDEX(tQueue[OldestDaysPastDue],MATCH(10,Calc!$C$28:$C$299,0)),"") -> 138 | M19: =IFERROR(INDEX(tQueue[CreditUtilizationPct],MATCH(10,Calc!$C$28:$C$299,0)),"") -> 106.1 | N19: =IFERROR(INDEX(tQueue[CreditHoldFlag],MATCH(10,Calc!$C$28:$C$299,0)),"") -> 1 | O19: =IFERROR(INDEX(tQueue[ActionCode],MATCH(10,Calc!$C$28:$C$299,0)),"") -> ESCALATE | P19: =IFERROR(INDEX(tQueue[RecommendedAction],MATCH(10,Calc!$C$28:$C$299,0)),"") -> Escalate: high-risk account carrying a 90+ balance. Hold further shipments and agree a payment plan or refer for recovery. Also place a credit hold: the account is at or over its credit limit.
A20: =IF(11>MIN(QueueRowsShown,$F$4),"",11) -> 11 | B20: =IFERROR(INDEX(tQueue[CustomerName],MATCH(11,Calc!$C$28:$C$299,0)),"") -> Keystone Contracting | C20: =IFERROR(INDEX(tQueue[Segment],MATCH(11,Calc!$C$28:$C$299,0)),"") -> Contractor | D20: =IFERROR(INDEX(tQueue[RiskTier],MATCH(11,Calc!$C$28:$C$299,0)),"") -> High | E20: =IFERROR(INDEX(tQueue[CollectorName],MATCH(11,Calc!$C$28:$C$299,0)),"") -> Tomas Okafor | F20: =IFERROR(INDEX(tQueue[TermsCode],MATCH(11,Calc!$C$28:$C$299,0)),"") -> NET60 | G20: =IFERROR(INDEX(tQueue[OpenBalance],MATCH(11,Calc!$C$28:$C$299,0)),"") -> 84970.22 | H20: =IFERROR(INDEX(tQueue[PastDueBalance],MATCH(11,Calc!$C$28:$C$299,0)),"") -> 41199.26 | I20: =IFERROR(INDEX(tQueue[Balance90Plus],MATCH(11,Calc!$C$28:$C$299,0)),"") -> 9337.53 | J20: =IFERROR(INDEX(tQueue[DisputedBalance],MATCH(11,Calc!$C$28:$C$299,0)),"") -> 0 | K20: =IFERROR(INDEX(tQueue[CollectableExposure],MATCH(11,Calc!$C$28:$C$299,0)),"") -> 25099.35 | L20: =IFERROR(INDEX(tQueue[OldestDaysPastDue],MATCH(11,Calc!$C$28:$C$299,0)),"") -> 122 | M20: =IFERROR(INDEX(tQueue[CreditUtilizationPct],MATCH(11,Calc!$C$28:$C$299,0)),"") -> 80.92 | N20: =IFERROR(INDEX(tQueue[CreditHoldFlag],MATCH(11,Calc!$C$28:$C$299,0)),"") -> 0 | O20: =IFERROR(INDEX(tQueue[ActionCode],MATCH(11,Calc!$C$28:$C$299,0)),"") -> ESCALATE | P20: =IFERROR(INDEX(tQueue[RecommendedAction],MATCH(11,Calc!$C$28:$C$299,0)),"") -> Escalate: high-risk account carrying a 90+ balance. Hold further shipments and agree a payment plan or refer for recovery.
A21: =IF(12>MIN(QueueRowsShown,$F$4),"",12) -> 12 | B21: =IFERROR(INDEX(tQueue[CustomerName],MATCH(12,Calc!$C$28:$C$299,0)),"") -> Bluewater Industries - Southeast | C21: =IFERROR(INDEX(tQueue[Segment],MATCH(12,Calc!$C$28:$C$299,0)),"") -> OEM Manufacturer | D21: =IFERROR(INDEX(tQueue[RiskTier],MATCH(12,Calc!$C$28:$C$299,0)),"") -> Low | E21: =IFERROR(INDEX(tQueue[CollectorName],MATCH(12,Calc!$C$28:$C$299,0)),"") -> Marcus Bell | F21: =IFERROR(INDEX(tQueue[TermsCode],MATCH(12,Calc!$C$28:$C$299,0)),"") -> NET45 | G21: =IFERROR(INDEX(tQueue[OpenBalance],MATCH(12,Calc!$C$28:$C$299,0)),"") -> 125485.34 | H21: =IFERROR(INDEX(tQueue[PastDueBalance],MATCH(12,Calc!$C$28:$C$299,0)),"") -> 87648.64 | I21: =IFERROR(INDEX(tQueue[Balance90Plus],MATCH(12,Calc!$C$28:$C$299,0)),"") -> 0 | J21: =IFERROR(INDEX(tQueue[DisputedBalance],MATCH(12,Calc!$C$28:$C$299,0)),"") -> 17811.56 | K21: =IFERROR(INDEX(tQueue[CollectableExposure],MATCH(12,Calc!$C$28:$C$299,0)),"") -> 24700.44 | L21: =IFERROR(INDEX(tQueue[OldestDaysPastDue],MATCH(12,Calc!$C$28:$C$299,0)),"") -> 69 | M21: =IFERROR(INDEX(tQueue[CreditUtilizationPct],MATCH(12,Calc!$C$28:$C$299,0)),"") -> 23.46 | N21: =IFERROR(INDEX(tQueue[CreditHoldFlag],MATCH(12,Calc!$C$28:$C$299,0)),"") -> 0 | O21: =IFERROR(INDEX(tQueue[ActionCode],MATCH(12,Calc!$C$28:$C$299,0)),"") -> COLLECTION_CALL | P21: =IFERROR(INDEX(tQueue[RecommendedAction],MATCH(12,Calc!$C$28:$C$299,0)),"") -> Collection call: oldest item is more than 30 days past due.
A22: =IF(13>MIN(QueueRowsShown,$F$4),"",13) -> 13 | B22: =IFERROR(INDEX(tQueue[CustomerName],MATCH(13,Calc!$C$28:$C$299,0)),"") -> Redline Industries - Northeast | C22: =IFERROR(INDEX(tQueue[Segment],MATCH(13,Calc!$C$28:$C$299,0)),"") -> OEM Manufacturer | D22: =IFERROR(INDEX(tQueue[RiskTier],MATCH(13,Calc!$C$28:$C$299,0)),"") -> Low | E22: =IFERROR(INDEX(tQueue[CollectorName],MATCH(13,Calc!$C$28:$C$299,0)),"") -> Marcus Bell | F22: =IFERROR(INDEX(tQueue[TermsCode],MATCH(13,Calc!$C$28:$C$299,0)),"") -> NET45 | G22: =IFERROR(INDEX(tQueue[OpenBalance],MATCH(13,Calc!$C$28:$C$299,0)),"") -> 152726.53 | H22: =IFERROR(INDEX(tQueue[PastDueBalance],MATCH(13,Calc!$C$28:$C$299,0)),"") -> 58576.86 | I22: =IFERROR(INDEX(tQueue[Balance90Plus],MATCH(13,Calc!$C$28:$C$299,0)),"") -> 0 | J22: =IFERROR(INDEX(tQueue[DisputedBalance],MATCH(13,Calc!$C$28:$C$299,0)),"") -> 0 | K22: =IFERROR(INDEX(tQueue[CollectableExposure],MATCH(13,Calc!$C$28:$C$299,0)),"") -> 21504.84 | L22: =IFERROR(INDEX(tQueue[OldestDaysPastDue],MATCH(13,Calc!$C$28:$C$299,0)),"") -> 44 | M22: =IFERROR(INDEX(tQueue[CreditUtilizationPct],MATCH(13,Calc!$C$28:$C$299,0)),"") -> 45.59 | N22: =IFERROR(INDEX(tQueue[CreditHoldFlag],MATCH(13,Calc!$C$28:$C$299,0)),"") -> 0 | O22: =IFERROR(INDEX(tQueue[ActionCode],MATCH(13,Calc!$C$28:$C$299,0)),"") -> COLLECTION_CALL | P22: =IFERROR(INDEX(tQueue[RecommendedAction],MATCH(13,Calc!$C$28:$C$299,0)),"") -> Collection call: oldest item is more than 30 days past due.
A23: =IF(14>MIN(QueueRowsShown,$F$4),"",14) -> 14 | B23: =IFERROR(INDEX(tQueue[CustomerName],MATCH(14,Calc!$C$28:$C$299,0)),"") -> Lakeshore Fabrication | C23: =IFERROR(INDEX(tQueue[Segment],MATCH(14,Calc!$C$28:$C$299,0)),"") -> OEM Manufacturer | D23: =IFERROR(INDEX(tQueue[RiskTier],MATCH(14,Calc!$C$28:$C$299,0)),"") -> Medium | E23: =IFERROR(INDEX(tQueue[CollectorName],MATCH(14,Calc!$C$28:$C$299,0)),"") -> Priya Natarajan | F23: =IFERROR(INDEX(tQueue[TermsCode],MATCH(14,Calc!$C$28:$C$299,0)),"") -> NET45 | G23: =IFERROR(INDEX(tQueue[OpenBalance],MATCH(14,Calc!$C$28:$C$299,0)),"") -> 127031.86 | H23: =IFERROR(INDEX(tQueue[PastDueBalance],MATCH(14,Calc!$C$28:$C$299,0)),"") -> 51164.87 | I23: =IFERROR(INDEX(tQueue[Balance90Plus],MATCH(14,Calc!$C$28:$C$299,0)),"") -> 0 | J23: =IFERROR(INDEX(tQueue[DisputedBalance],MATCH(14,Calc!$C$28:$C$299,0)),"") -> 15908.3 | K23: =IFERROR(INDEX(tQueue[CollectableExposure],MATCH(14,Calc!$C$28:$C$299,0)),"") -> 20707.5 | L23: =IFERROR(INDEX(tQueue[OldestDaysPastDue],MATCH(14,Calc!$C$28:$C$299,0)),"") -> 47 | M23: =IFERROR(INDEX(tQueue[CreditUtilizationPct],MATCH(14,Calc!$C$28:$C$299,0)),"") -> 52.93 | N23: =IFERROR(INDEX(tQueue[CreditHoldFlag],MATCH(14,Calc!$C$28:$C$299,0)),"") -> 0 | O23: =IFERROR(INDEX(tQueue[ActionCode],MATCH(14,Calc!$C$28:$C$299,0)),"") -> COLLECTION_CALL | P23: =IFERROR(INDEX(tQueue[RecommendedAction],MATCH(14,Calc!$C$28:$C$299,0)),"") -> Collection call: oldest item is more than 30 days past due.
A24: =IF(15>MIN(QueueRowsShown,$F$4),"",15) -> 15 | B24: =IFERROR(INDEX(tQueue[CustomerName],MATCH(15,Calc!$C$28:$C$299,0)),"") -> Riverbend Fabrication | C24: =IFERROR(INDEX(tQueue[Segment],MATCH(15,Calc!$C$28:$C$299,0)),"") -> OEM Manufacturer | D24: =IFERROR(INDEX(tQueue[RiskTier],MATCH(15,Calc!$C$28:$C$299,0)),"") -> Low | E24: =IFERROR(INDEX(tQueue[CollectorName],MATCH(15,Calc!$C$28:$C$299,0)),"") -> Marcus Bell | F24: =IFERROR(INDEX(tQueue[TermsCode],MATCH(15,Calc!$C$28:$C$299,0)),"") -> NET60 | G24: =IFERROR(INDEX(tQueue[OpenBalance],MATCH(15,Calc!$C$28:$C$299,0)),"") -> 90154.01 | H24: =IFERROR(INDEX(tQueue[PastDueBalance],MATCH(15,Calc!$C$28:$C$299,0)),"") -> 52664.06 | I24: =IFERROR(INDEX(tQueue[Balance90Plus],MATCH(15,Calc!$C$28:$C$299,0)),"") -> 0 | J24: =IFERROR(INDEX(tQueue[DisputedBalance],MATCH(15,Calc!$C$28:$C$299,0)),"") -> 9987.4 | K24: =IFERROR(INDEX(tQueue[CollectableExposure],MATCH(15,Calc!$C$28:$C$299,0)),"") -> 13961.98 | L24: =IFERROR(INDEX(tQueue[OldestDaysPastDue],MATCH(15,Calc!$C$28:$C$299,0)),"") -> 47 | M24: =IFERROR(INDEX(tQueue[CreditUtilizationPct],MATCH(15,Calc!$C$28:$C$299,0)),"") -> 36.8 | N24: =IFERROR(INDEX(tQueue[CreditHoldFlag],MATCH(15,Calc!$C$28:$C$299,0)),"") -> 0 | O24: =IFERROR(INDEX(tQueue[ActionCode],MATCH(15,Calc!$C$28:$C$299,0)),"") -> COLLECTION_CALL | P24: =IFERROR(INDEX(tQueue[RecommendedAction],MATCH(15,Calc!$C$28:$C$299,0)),"") -> Collection call: oldest item is more than 30 days past due.
A25: =IF(16>MIN(QueueRowsShown,$F$4),"",16) -> 16 | B25: =IFERROR(INDEX(tQueue[CustomerName],MATCH(16,Calc!$C$28:$C$299,0)),"") -> Cedar Ridge Machine Works - Southwest | C25: =IFERROR(INDEX(tQueue[Segment],MATCH(16,Calc!$C$28:$C$299,0)),"") -> OEM Manufacturer | D25: =IFERROR(INDEX(tQueue[RiskTier],MATCH(16,Calc!$C$28:$C$299,0)),"") -> High | E25: =IFERROR(INDEX(tQueue[CollectorName],MATCH(16,Calc!$C$28:$C$299,0)),"") -> Priya Natarajan | F25: =IFERROR(INDEX(tQueue[TermsCode],MATCH(16,Calc!$C$28:$C$299,0)),"") -> NET60 | G25: =IFERROR(INDEX(tQueue[OpenBalance],MATCH(16,Calc!$C$28:$C$299,0)),"") -> 159690.8 | H25: =IFERROR(INDEX(tQueue[PastDueBalance],MATCH(16,Calc!$C$28:$C$299,0)),"") -> 50936.25 | I25: =IFERROR(INDEX(tQueue[Balance90Plus],MATCH(16,Calc!$C$28:$C$299,0)),"") -> 0 | J25: =IFERROR(INDEX(tQueue[DisputedBalance],MATCH(16,Calc!$C$28:$C$299,0)),"") -> 0 | K25: =IFERROR(INDEX(tQueue[CollectableExposure],MATCH(16,Calc!$C$28:$C$299,0)),"") -> 12734.06 | L25: =IFERROR(INDEX(tQueue[OldestDaysPastDue],MATCH(16,Calc!$C$28:$C$299,0)),"") -> 18 | M25: =IFERROR(INDEX(tQueue[CreditUtilizationPct],MATCH(16,Calc!$C$28:$C$299,0)),"") -> 29.85 | N25: =IFERROR(INDEX(tQueue[CreditHoldFlag],MATCH(16,Calc!$C$28:$C$299,0)),"") -> 0 | O25: =IFERROR(INDEX(tQueue[ActionCode],MATCH(16,Calc!$C$28:$C$299,0)),"") -> STANDARD_DUNNING | P25: =IFERROR(INDEX(tQueue[RecommendedAction],MATCH(16,Calc!$C$28:$C$299,0)),"") -> Standard dunning letter and follow-up call.
A26: =IF(17>MIN(QueueRowsShown,$F$4),"",17) -> 17 | B26: =IFERROR(INDEX(tQueue[CustomerName],MATCH(17,Calc!$C$28:$C$299,0)),"") -> Lakeshore Construction - West | C26: =IFERROR(INDEX(tQueue[Segment],MATCH(17,Calc!$C$28:$C$299,0)),"") -> Contractor | D26: =IFERROR(INDEX(tQueue[RiskTier],MATCH(17,Calc!$C$28:$C$299,0)),"") -> High | E26: =IFERROR(INDEX(tQueue[CollectorName],MATCH(17,Calc!$C$28:$C$299,0)),"") -> Tomas Okafor | F26: =IFERROR(INDEX(tQueue[TermsCode],MATCH(17,Calc!$C$28:$C$299,0)),"") -> 2/10NET30 | G26: =IFERROR(INDEX(tQueue[OpenBalance],MATCH(17,Calc!$C$28:$C$299,0)),"") -> 24570.62 | H26: =IFERROR(INDEX(tQueue[PastDueBalance],MATCH(17,Calc!$C$28:$C$299,0)),"") -> 16849.82 | I26: =IFERROR(INDEX(tQueue[Balance90Plus],MATCH(17,Calc!$C$28:$C$299,0)),"") -> 8126.02 | J26: =IFERROR(INDEX(tQueue[DisputedBalance],MATCH(17,Calc!$C$28:$C$299,0)),"") -> 0 | K26: =IFERROR(INDEX(tQueue[CollectableExposure],MATCH(17,Calc!$C$28:$C$299,0)),"") -> 12487.92 | L26: =IFERROR(INDEX(tQueue[OldestDaysPastDue],MATCH(17,Calc!$C$28:$C$299,0)),"") -> 111 | M26: =IFERROR(INDEX(tQueue[CreditUtilizationPct],MATCH(17,Calc!$C$28:$C$299,0)),"") -> 98.28 | N26: =IFERROR(INDEX(tQueue[CreditHoldFlag],MATCH(17,Calc!$C$28:$C$299,0)),"") -> 0 | O26: =IFERROR(INDEX(tQueue[ActionCode],MATCH(17,Calc!$C$28:$C$299,0)),"") -> ESCALATE | P26: =IFERROR(INDEX(tQueue[RecommendedAction],MATCH(17,Calc!$C$28:$C$299,0)),"") -> Escalate: high-risk account carrying a 90+ balance. Hold further shipments and agree a payment plan or refer for recovery.
A27: =IF(18>MIN(QueueRowsShown,$F$4),"",18) -> 18 | B27: =IFERROR(INDEX(tQueue[CustomerName],MATCH(18,Calc!$C$28:$C$299,0)),"") -> Bluewater Industries | C27: =IFERROR(INDEX(tQueue[Segment],MATCH(18,Calc!$C$28:$C$299,0)),"") -> OEM Manufacturer | D27: =IFERROR(INDEX(tQueue[RiskTier],MATCH(18,Calc!$C$28:$C$299,0)),"") -> High | E27: =IFERROR(INDEX(tQueue[CollectorName],MATCH(18,Calc!$C$28:$C$299,0)),"") -> Priya Natarajan | F27: =IFERROR(INDEX(tQueue[TermsCode],MATCH(18,Calc!$C$28:$C$299,0)),"") -> NET60 | G27: =IFERROR(INDEX(tQueue[OpenBalance],MATCH(18,Calc!$C$28:$C$299,0)),"") -> 93887.29 | H27: =IFERROR(INDEX(tQueue[PastDueBalance],MATCH(18,Calc!$C$28:$C$299,0)),"") -> 53541.39 | I27: =IFERROR(INDEX(tQueue[Balance90Plus],MATCH(18,Calc!$C$28:$C$299,0)),"") -> 3658.04 | J27: =IFERROR(INDEX(tQueue[DisputedBalance],MATCH(18,Calc!$C$28:$C$299,0)),"") -> 0 | K27: =IFERROR(INDEX(tQueue[CollectableExposure],MATCH(18,Calc!$C$28:$C$299,0)),"") -> 12470.84 | L27: =IFERROR(INDEX(tQueue[OldestDaysPastDue],MATCH(18,Calc!$C$28:$C$299,0)),"") -> 502 | M27: =IFERROR(INDEX(tQueue[CreditUtilizationPct],MATCH(18,Calc!$C$28:$C$299,0)),"") -> 26.45 | N27: =IFERROR(INDEX(tQueue[CreditHoldFlag],MATCH(18,Calc!$C$28:$C$299,0)),"") -> 0 | O27: =IFERROR(INDEX(tQueue[ActionCode],MATCH(18,Calc!$C$28:$C$299,0)),"") -> ESCALATE | P27: =IFERROR(INDEX(tQueue[RecommendedAction],MATCH(18,Calc!$C$28:$C$299,0)),"") -> Escalate: high-risk account carrying a 90+ balance. Hold further shipments and agree a payment plan or refer for recovery.
A28: =IF(19>MIN(QueueRowsShown,$F$4),"",19) -> 19 | B28: =IFERROR(INDEX(tQueue[CustomerName],MATCH(19,Calc!$C$28:$C$299,0)),"") -> Frontier Fabrication | C28: =IFERROR(INDEX(tQueue[Segment],MATCH(19,Calc!$C$28:$C$299,0)),"") -> OEM Manufacturer | D28: =IFERROR(INDEX(tQueue[RiskTier],MATCH(19,Calc!$C$28:$C$299,0)),"") -> Medium | E28: =IFERROR(INDEX(tQueue[CollectorName],MATCH(19,Calc!$C$28:$C$299,0)),"") -> Priya Natarajan | F28: =IFERROR(INDEX(tQueue[TermsCode],MATCH(19,Calc!$C$28:$C$299,0)),"") -> NET45 | G28: =IFERROR(INDEX(tQueue[OpenBalance],MATCH(19,Calc!$C$28:$C$299,0)),"") -> 116620.23 | H28: =IFERROR(INDEX(tQueue[PastDueBalance],MATCH(19,Calc!$C$28:$C$299,0)),"") -> 44023.4 | I28: =IFERROR(INDEX(tQueue[Balance90Plus],MATCH(19,Calc!$C$28:$C$299,0)),"") -> 0 | J28: =IFERROR(INDEX(tQueue[DisputedBalance],MATCH(19,Calc!$C$28:$C$299,0)),"") -> 11224.6 | K28: =IFERROR(INDEX(tQueue[CollectableExposure],MATCH(19,Calc!$C$28:$C$299,0)),"") -> 11005.85 | L28: =IFERROR(INDEX(tQueue[OldestDaysPastDue],MATCH(19,Calc!$C$28:$C$299,0)),"") -> 4 | M28: =IFERROR(INDEX(tQueue[CreditUtilizationPct],MATCH(19,Calc!$C$28:$C$299,0)),"") -> 19.44 | N28: =IFERROR(INDEX(tQueue[CreditHoldFlag],MATCH(19,Calc!$C$28:$C$299,0)),"") -> 0 | O28: =IFERROR(INDEX(tQueue[ActionCode],MATCH(19,Calc!$C$28:$C$299,0)),"") -> STANDARD_DUNNING | P28: =IFERROR(INDEX(tQueue[RecommendedAction],MATCH(19,Calc!$C$28:$C$299,0)),"") -> Standard dunning letter and follow-up call.
A29: =IF(20>MIN(QueueRowsShown,$F$4),"",20) -> 20 | B29: =IFERROR(INDEX(tQueue[CustomerName],MATCH(20,Calc!$C$28:$C$299,0)),"") -> Stonegate Fabrication - West | C29: =IFERROR(INDEX(tQueue[Segment],MATCH(20,Calc!$C$28:$C$299,0)),"") -> OEM Manufacturer | D29: =IFERROR(INDEX(tQueue[RiskTier],MATCH(20,Calc!$C$28:$C$299,0)),"") -> High | E29: =IFERROR(INDEX(tQueue[CollectorName],MATCH(20,Calc!$C$28:$C$299,0)),"") -> Marcus Bell | F29: =IFERROR(INDEX(tQueue[TermsCode],MATCH(20,Calc!$C$28:$C$299,0)),"") -> NET60 | G29: =IFERROR(INDEX(tQueue[OpenBalance],MATCH(20,Calc!$C$28:$C$299,0)),"") -> 75601.21 | H29: =IFERROR(INDEX(tQueue[PastDueBalance],MATCH(20,Calc!$C$28:$C$299,0)),"") -> 47161.13 | I29: =IFERROR(INDEX(tQueue[Balance90Plus],MATCH(20,Calc!$C$28:$C$299,0)),"") -> 3522.98 | J29: =IFERROR(INDEX(tQueue[DisputedBalance],MATCH(20,Calc!$C$28:$C$299,0)),"") -> 0 | K29: =IFERROR(INDEX(tQueue[CollectableExposure],MATCH(20,Calc!$C$28:$C$299,0)),"") -> 10909.54 | L29: =IFERROR(INDEX(tQueue[OldestDaysPastDue],MATCH(20,Calc!$C$28:$C$299,0)),"") -> 277 | M29: =IFERROR(INDEX(tQueue[CreditUtilizationPct],MATCH(20,Calc!$C$28:$C$299,0)),"") -> 19.9 | N29: =IFERROR(INDEX(tQueue[CreditHoldFlag],MATCH(20,Calc!$C$28:$C$299,0)),"") -> 0 | O29: =IFERROR(INDEX(tQueue[ActionCode],MATCH(20,Calc!$C$28:$C$299,0)),"") -> ESCALATE | P29: =IFERROR(INDEX(tQueue[RecommendedAction],MATCH(20,Calc!$C$28:$C$299,0)),"") -> Escalate: high-risk account carrying a 90+ balance. Hold further shipments and agree a payment plan or refer for recovery.
A30: =IF(21>MIN(QueueRowsShown,$F$4),"",21) -> 21 | B30: =IFERROR(INDEX(tQueue[CustomerName],MATCH(21,Calc!$C$28:$C$299,0)),"") -> Northfield School District - Midwest | C30: =IFERROR(INDEX(tQueue[Segment],MATCH(21,Calc!$C$28:$C$299,0)),"") -> Institutional | D30: =IFERROR(INDEX(tQueue[RiskTier],MATCH(21,Calc!$C$28:$C$299,0)),"") -> Low | E30: =IFERROR(INDEX(tQueue[CollectorName],MATCH(21,Calc!$C$28:$C$299,0)),"") -> Priya Natarajan | F30: =IFERROR(INDEX(tQueue[TermsCode],MATCH(21,Calc!$C$28:$C$299,0)),"") -> NET90 | G30: =IFERROR(INDEX(tQueue[OpenBalance],MATCH(21,Calc!$C$28:$C$299,0)),"") -> 65440.55 | H30: =IFERROR(INDEX(tQueue[PastDueBalance],MATCH(21,Calc!$C$28:$C$299,0)),"") -> 31983.14 | I30: =IFERROR(INDEX(tQueue[Balance90Plus],MATCH(21,Calc!$C$28:$C$299,0)),"") -> 0 | J30: =IFERROR(INDEX(tQueue[DisputedBalance],MATCH(21,Calc!$C$28:$C$299,0)),"") -> 0 | K30: =IFERROR(INDEX(tQueue[CollectableExposure],MATCH(21,Calc!$C$28:$C$299,0)),"") -> 7995.79 | L30: =IFERROR(INDEX(tQueue[OldestDaysPastDue],MATCH(21,Calc!$C$28:$C$299,0)),"") -> 24 | M30: =IFERROR(INDEX(tQueue[CreditUtilizationPct],MATCH(21,Calc!$C$28:$C$299,0)),"") -> 28.45 | N30: =IFERROR(INDEX(tQueue[CreditHoldFlag],MATCH(21,Calc!$C$28:$C$299,0)),"") -> 0 | O30: =IFERROR(INDEX(tQueue[ActionCode],MATCH(21,Calc!$C$28:$C$299,0)),"") -> STANDARD_DUNNING | P30: =IFERROR(INDEX(tQueue[RecommendedAction],MATCH(21,Calc!$C$28:$C$299,0)),"") -> Standard dunning letter and follow-up call.
A31: =IF(22>MIN(QueueRowsShown,$F$4),"",22) -> 22 | B31: =IFERROR(INDEX(tQueue[CustomerName],MATCH(22,Calc!$C$28:$C$299,0)),"") -> Keystone Fabrication | C31: =IFERROR(INDEX(tQueue[Segment],MATCH(22,Calc!$C$28:$C$299,0)),"") -> OEM Manufacturer | D31: =IFERROR(INDEX(tQueue[RiskTier],MATCH(22,Calc!$C$28:$C$299,0)),"") -> Medium | E31: =IFERROR(INDEX(tQueue[CollectorName],MATCH(22,Calc!$C$28:$C$299,0)),"") -> Priya Natarajan | F31: =IFERROR(INDEX(tQueue[TermsCode],MATCH(22,Calc!$C$28:$C$299,0)),"") -> NET60 | G31: =IFERROR(INDEX(tQueue[OpenBalance],MATCH(22,Calc!$C$28:$C$299,0)),"") -> 93975.84 | H31: =IFERROR(INDEX(tQueue[PastDueBalance],MATCH(22,Calc!$C$28:$C$299,0)),"") -> 36293.49 | I31: =IFERROR(INDEX(tQueue[Balance90Plus],MATCH(22,Calc!$C$28:$C$299,0)),"") -> 6170.49 | J31: =IFERROR(INDEX(tQueue[DisputedBalance],MATCH(22,Calc!$C$28:$C$299,0)),"") -> 9126.86 | K31: =IFERROR(INDEX(tQueue[CollectableExposure],MATCH(22,Calc!$C$28:$C$299,0)),"") -> 7530.75 | L31: =IFERROR(INDEX(tQueue[OldestDaysPastDue],MATCH(22,Calc!$C$28:$C$299,0)),"") -> 102 | M31: =IFERROR(INDEX(tQueue[CreditUtilizationPct],MATCH(22,Calc!$C$28:$C$299,0)),"") -> 15.66 | N31: =IFERROR(INDEX(tQueue[CreditHoldFlag],MATCH(22,Calc!$C$28:$C$299,0)),"") -> 0 | O31: =IFERROR(INDEX(tQueue[ActionCode],MATCH(22,Calc!$C$28:$C$299,0)),"") -> FINAL_NOTICE | P31: =IFERROR(INDEX(tQueue[RecommendedAction],MATCH(22,Calc!$C$28:$C$299,0)),"") -> Issue a final notice on the 90+ balance and confirm a payment date in writing.
A32: =IF(23>MIN(QueueRowsShown,$F$4),"",23) -> 23 | B32: =IFERROR(INDEX(tQueue[CustomerName],MATCH(23,Calc!$C$28:$C$299,0)),"") -> Stonegate Industries | C32: =IFERROR(INDEX(tQueue[Segment],MATCH(23,Calc!$C$28:$C$299,0)),"") -> OEM Manufacturer | D32: =IFERROR(INDEX(tQueue[RiskTier],MATCH(23,Calc!$C$28:$C$299,0)),"") -> Medium | E32: =IFERROR(INDEX(tQueue[CollectorName],MATCH(23,Calc!$C$28:$C$299,0)),"") -> Priya Natarajan | F32: =IFERROR(INDEX(tQueue[TermsCode],MATCH(23,Calc!$C$28:$C$299,0)),"") -> NET45 | G32: =IFERROR(INDEX(tQueue[OpenBalance],MATCH(23,Calc!$C$28:$C$299,0)),"") -> 78932.51 | H32: =IFERROR(INDEX(tQueue[PastDueBalance],MATCH(23,Calc!$C$28:$C$299,0)),"") -> 29973.52 | I32: =IFERROR(INDEX(tQueue[Balance90Plus],MATCH(23,Calc!$C$28:$C$299,0)),"") -> 1838.06 | J32: =IFERROR(INDEX(tQueue[DisputedBalance],MATCH(23,Calc!$C$28:$C$299,0)),"") -> 0 | K32: =IFERROR(INDEX(tQueue[CollectableExposure],MATCH(23,Calc!$C$28:$C$299,0)),"") -> 7033.87 | L32: =IFERROR(INDEX(tQueue[OldestDaysPastDue],MATCH(23,Calc!$C$28:$C$299,0)),"") -> 185 | M32: =IFERROR(INDEX(tQueue[CreditUtilizationPct],MATCH(23,Calc!$C$28:$C$299,0)),"") -> 19.02 | N32: =IFERROR(INDEX(tQueue[CreditHoldFlag],MATCH(23,Calc!$C$28:$C$299,0)),"") -> 0 | O32: =IFERROR(INDEX(tQueue[ActionCode],MATCH(23,Calc!$C$28:$C$299,0)),"") -> FINAL_NOTICE | P32: =IFERROR(INDEX(tQueue[RecommendedAction],MATCH(23,Calc!$C$28:$C$299,0)),"") -> Issue a final notice on the 90+ balance and confirm a payment date in writing.
A33: =IF(24>MIN(QueueRowsShown,$F$4),"",24) -> 24 | B33: =IFERROR(INDEX(tQueue[CustomerName],MATCH(24,Calc!$C$28:$C$299,0)),"") -> Northfield Machine Works | C33: =IFERROR(INDEX(tQueue[Segment],MATCH(24,Calc!$C$28:$C$299,0)),"") -> OEM Manufacturer | D33: =IFERROR(INDEX(tQueue[RiskTier],MATCH(24,Calc!$C$28:$C$299,0)),"") -> High | E33: =IFERROR(INDEX(tQueue[CollectorName],MATCH(24,Calc!$C$28:$C$299,0)),"") -> Marcus Bell | F33: =IFERROR(INDEX(tQueue[TermsCode],MATCH(24,Calc!$C$28:$C$299,0)),"") -> NET60 | G33: =IFERROR(INDEX(tQueue[OpenBalance],MATCH(24,Calc!$C$28:$C$299,0)),"") -> 50863.84 | H33: =IFERROR(INDEX(tQueue[PastDueBalance],MATCH(24,Calc!$C$28:$C$299,0)),"") -> 21628.98 | I33: =IFERROR(INDEX(tQueue[Balance90Plus],MATCH(24,Calc!$C$28:$C$299,0)),"") -> 0 | J33: =IFERROR(INDEX(tQueue[DisputedBalance],MATCH(24,Calc!$C$28:$C$299,0)),"") -> 16359.42 | K33: =IFERROR(INDEX(tQueue[CollectableExposure],MATCH(24,Calc!$C$28:$C$299,0)),"") -> 6762.21 | L33: =IFERROR(INDEX(tQueue[OldestDaysPastDue],MATCH(24,Calc!$C$28:$C$299,0)),"") -> 33 | M33: =IFERROR(INDEX(tQueue[CreditUtilizationPct],MATCH(24,Calc!$C$28:$C$299,0)),"") -> 31.79 | N33: =IFERROR(INDEX(tQueue[CreditHoldFlag],MATCH(24,Calc!$C$28:$C$299,0)),"") -> 0 | O33: =IFERROR(INDEX(tQueue[ActionCode],MATCH(24,Calc!$C$28:$C$299,0)),"") -> RESOLVE_DISPUTE | P33: =IFERROR(INDEX(tQueue[RecommendedAction],MATCH(24,Calc!$C$28:$C$299,0)),"") -> Route to billing/sales: most of this balance is disputed and will not pay until the dispute closes.
A34: =IF(25>MIN(QueueRowsShown,$F$4),"",25) -> 25 | B34: =IFERROR(INDEX(tQueue[CustomerName],MATCH(25,Calc!$C$28:$C$299,0)),"") -> Ironbridge Medical Center - Northeast | C34: =IFERROR(INDEX(tQueue[Segment],MATCH(25,Calc!$C$28:$C$299,0)),"") -> Institutional | D34: =IFERROR(INDEX(tQueue[RiskTier],MATCH(25,Calc!$C$28:$C$299,0)),"") -> Low | E34: =IFERROR(INDEX(tQueue[CollectorName],MATCH(25,Calc!$C$28:$C$299,0)),"") -> Marcus Bell | F34: =IFERROR(INDEX(tQueue[TermsCode],MATCH(25,Calc!$C$28:$C$299,0)),"") -> NET90 | G34: =IFERROR(INDEX(tQueue[OpenBalance],MATCH(25,Calc!$C$28:$C$299,0)),"") -> 44688.48 | H34: =IFERROR(INDEX(tQueue[PastDueBalance],MATCH(25,Calc!$C$28:$C$299,0)),"") -> 25939.03 | I34: =IFERROR(INDEX(tQueue[Balance90Plus],MATCH(25,Calc!$C$28:$C$299,0)),"") -> 0 | J34: =IFERROR(INDEX(tQueue[DisputedBalance],MATCH(25,Calc!$C$28:$C$299,0)),"") -> 0 | K34: =IFERROR(INDEX(tQueue[CollectableExposure],MATCH(25,Calc!$C$28:$C$299,0)),"") -> 6484.76 | L34: =IFERROR(INDEX(tQueue[OldestDaysPastDue],MATCH(25,Calc!$C$28:$C$299,0)),"") -> 20 | M34: =IFERROR(INDEX(tQueue[CreditUtilizationPct],MATCH(25,Calc!$C$28:$C$299,0)),"") -> 28.83 | N34: =IFERROR(INDEX(tQueue[CreditHoldFlag],MATCH(25,Calc!$C$28:$C$299,0)),"") -> 0 | O34: =IFERROR(INDEX(tQueue[ActionCode],MATCH(25,Calc!$C$28:$C$299,0)),"") -> STANDARD_DUNNING | P34: =IFERROR(INDEX(tQueue[RecommendedAction],MATCH(25,Calc!$C$28:$C$299,0)),"") -> Standard dunning letter and follow-up call.

Sheet Cash Application
A1: CASH APPLICATION WORKLIST
A2: Money already in the bank that nobody has matched to an invoice. Until it is applied, these invoices read as unpaid and the call list will chase customers who have already paid.
B4: Accounts holding unapplied cash | F4: =COUNTA(tCashApp[CustomerID]) -> 97
B5: Cash banked and unmatched | F5: =SUM(tCashApp[UnappliedCash]) -> 419392.13
B6: Of which fully unapplied receipts | F6: =SUM(tCashApp[FullyUnappliedReceipts]) -> 57
B7: Past due that would be WRONGLY chased | F7: =SUM(tCashApp[WronglyChaseable]) -> 409639.85 | H7: ="This is cash Vantage already holds -- recovering it needs no customer conversation at all." -> This is cash Vantage already holds -- recovering it needs no customer conversation at all.
B8: Oldest unmatched receipt (days) | F8: =MAX(tCashApp[OldestUnappliedDays]) -> 679
A10: # | B10: Customer | C10: Segment | D10: Region | E10: Collector | F10: Unapplied cash | G10: Receipts | H10: Fully unapplied | I10: No remittance | J10: Oldest days | K10: Open balance | L10: Past due | M10: Net exposure | N10: Wrongly chaseable | O10: Root cause
A11: =IF(1>COUNTA(tCashApp[CustomerID]),"",1) -> 1 | B11: =IFERROR(INDEX(tCashApp[CustomerName],1),"") -> Pioneer Manufacturing | C11: =IFERROR(INDEX(tCashApp[Segment],1),"") -> OEM Manufacturer | D11: =IFERROR(INDEX(tCashApp[Region],1),"") -> Northeast | E11: =IFERROR(INDEX(tCashApp[CollectorName],1),"") -> Priya Natarajan | F11: =IFERROR(INDEX(tCashApp[UnappliedCash],1),"") -> 3702.23 | G11: =IFERROR(INDEX(tCashApp[UnappliedReceipts],1),"") -> 2 | H11: =IFERROR(INDEX(tCashApp[FullyUnappliedReceipts],1),"") -> 1 | I11: =IFERROR(INDEX(tCashApp[NoRemittanceAdvice],1),"") -> 2 | J11: =IFERROR(INDEX(tCashApp[OldestUnappliedDays],1),"") -> 679 | K11: =IFERROR(INDEX(tCashApp[OpenBalance],1),"") -> 65312.72 | L11: =IFERROR(INDEX(tCashApp[PastDueBalance],1),"") -> 3702.23 | M11: =IFERROR(INDEX(tCashApp[NetExposure],1),"") -> 61610.49 | N11: =IFERROR(INDEX(tCashApp[WronglyChaseable],1),"") -> 3702.23 | O11: =IFERROR(IF(INDEX(tCashApp[NoRemittanceAdvice],1)>0,"No remittance advice -- request it, then apply","Advice received; the cash simply has not been matched"),"") -> No remittance advice -- request it, then apply
A12: =IF(2>COUNTA(tCashApp[CustomerID]),"",2) -> 2 | B12: =IFERROR(INDEX(tCashApp[CustomerName],2),"") -> Silverline Fabrication - Southwest | C12: =IFERROR(INDEX(tCashApp[Segment],2),"") -> OEM Manufacturer | D12: =IFERROR(INDEX(tCashApp[Region],2),"") -> Southwest | E12: =IFERROR(INDEX(tCashApp[CollectorName],2),"") -> Priya Natarajan | F12: =IFERROR(INDEX(tCashApp[UnappliedCash],2),"") -> 10190.22 | G12: =IFERROR(INDEX(tCashApp[UnappliedReceipts],2),"") -> 2 | H12: =IFERROR(INDEX(tCashApp[FullyUnappliedReceipts],2),"") -> 1 | I12: =IFERROR(INDEX(tCashApp[NoRemittanceAdvice],2),"") -> 2 | J12: =IFERROR(INDEX(tCashApp[OldestUnappliedDays],2),"") -> 668 | K12: =IFERROR(INDEX(tCashApp[OpenBalance],2),"") -> 120937.72 | L12: =IFERROR(INDEX(tCashApp[PastDueBalance],2),"") -> 26147.37 | M12: =IFERROR(INDEX(tCashApp[NetExposure],2),"") -> 110747.5 | N12: =IFERROR(INDEX(tCashApp[WronglyChaseable],2),"") -> 10190.22 | O12: =IFERROR(IF(INDEX(tCashApp[NoRemittanceAdvice],2)>0,"No remittance advice -- request it, then apply","Advice received; the cash simply has not been matched"),"") -> No remittance advice -- request it, then apply
A13: =IF(3>COUNTA(tCashApp[CustomerID]),"",3) -> 3 | B13: =IFERROR(INDEX(tCashApp[CustomerName],3),"") -> Granite MRO Services | C13: =IFERROR(INDEX(tCashApp[Segment],3),"") -> MRO Reseller | D13: =IFERROR(INDEX(tCashApp[Region],3),"") -> Southeast | E13: =IFERROR(INDEX(tCashApp[CollectorName],3),"") -> Grace Lindqvist | F13: =IFERROR(INDEX(tCashApp[UnappliedCash],3),"") -> 504.6 | G13: =IFERROR(INDEX(tCashApp[UnappliedReceipts],3),"") -> 1 | H13: =IFERROR(INDEX(tCashApp[FullyUnappliedReceipts],3),"") -> 1 | I13: =IFERROR(INDEX(tCashApp[NoRemittanceAdvice],3),"") -> 1 | J13: =IFERROR(INDEX(tCashApp[OldestUnappliedDays],3),"") -> 652 | K13: =IFERROR(INDEX(tCashApp[OpenBalance],3),"") -> 2847.25 | L13: =IFERROR(INDEX(tCashApp[PastDueBalance],3),"") -> 1339.14 | M13: =IFERROR(INDEX(tCashApp[NetExposure],3),"") -> 2342.65 | N13: =IFERROR(INDEX(tCashApp[WronglyChaseable],3),"") -> 504.6 | O13: =IFERROR(IF(INDEX(tCashApp[NoRemittanceAdvice],3)>0,"No remittance advice -- request it, then apply","Advice received; the cash simply has not been matched"),"") -> No remittance advice -- request it, then apply
A14: =IF(4>COUNTA(tCashApp[CustomerID]),"",4) -> 4 | B14: =IFERROR(INDEX(tCashApp[CustomerName],4),"") -> Lakeshore MRO Services - Midwest | C14: =IFERROR(INDEX(tCashApp[Segment],4),"") -> MRO Reseller | D14: =IFERROR(INDEX(tCashApp[Region],4),"") -> Midwest | E14: =IFERROR(INDEX(tCashApp[CollectorName],4),"") -> Sam Horowitz | F14: =IFERROR(INDEX(tCashApp[UnappliedCash],4),"") -> 4202.45 | G14: =IFERROR(INDEX(tCashApp[UnappliedReceipts],4),"") -> 2 | H14: =IFERROR(INDEX(tCashApp[FullyUnappliedReceipts],4),"") -> 1 | I14: =IFERROR(INDEX(tCashApp[NoRemittanceAdvice],4),"") -> 2 | J14: =IFERROR(INDEX(tCashApp[OldestUnappliedDays],4),"") -> 652 | K14: =IFERROR(INDEX(tCashApp[OpenBalance],4),"") -> 4212.75 | L14: =IFERROR(INDEX(tCashApp[PastDueBalance],4),"") -> 4212.75 | M14: =IFERROR(INDEX(tCashApp[NetExposure],4),"") -> 10.3 | N14: =IFERROR(INDEX(tCashApp[WronglyChaseable],4),"") -> 4202.45 | O14: =IFERROR(IF(INDEX(tCashApp[NoRemittanceAdvice],4)>0,"No remittance advice -- request it, then apply","Advice received; the cash simply has not been matched"),"") -> No remittance advice -- request it, then apply
A15: =IF(5>COUNTA(tCashApp[CustomerID]),"",5) -> 5 | B15: =IFERROR(INDEX(tCashApp[CustomerName],5),"") -> Harbor Fabrication | C15: =IFERROR(INDEX(tCashApp[Segment],5),"") -> OEM Manufacturer | D15: =IFERROR(INDEX(tCashApp[Region],5),"") -> West | E15: =IFERROR(INDEX(tCashApp[CollectorName],5),"") -> Priya Natarajan | F15: =IFERROR(INDEX(tCashApp[UnappliedCash],5),"") -> 12428.36 | G15: =IFERROR(INDEX(tCashApp[UnappliedReceipts],5),"") -> 1 | H15: =IFERROR(INDEX(tCashApp[FullyUnappliedReceipts],5),"") -> 0 | I15: =IFERROR(INDEX(tCashApp[NoRemittanceAdvice],5),"") -> 1 | J15: =IFERROR(INDEX(tCashApp[OldestUnappliedDays],5),"") -> 647 | K15: =IFERROR(INDEX(tCashApp[OpenBalance],5),"") -> 103438.85 | L15: =IFERROR(INDEX(tCashApp[PastDueBalance],5),"") -> 34815.87 | M15: =IFERROR(INDEX(tCashApp[NetExposure],5),"") -> 91010.49 | N15: =IFERROR(INDEX(tCashApp[WronglyChaseable],5),"") -> 12428.36 | O15: =IFERROR(IF(INDEX(tCashApp[NoRemittanceAdvice],5)>0,"No remittance advice -- request it, then apply","Advice received; the cash simply has not been matched"),"") -> No remittance advice -- request it, then apply
A16: =IF(6>COUNTA(tCashApp[CustomerID]),"",6) -> 6 | B16: =IFERROR(INDEX(tCashApp[CustomerName],6),"") -> Apex Industrial Supply - Southwest 3 | C16: =IFERROR(INDEX(tCashApp[Segment],6),"") -> MRO Reseller | D16: =IFERROR(INDEX(tCashApp[Region],6),"") -> Southwest | E16: =IFERROR(INDEX(tCashApp[CollectorName],6),"") -> Grace Lindqvist | F16: =IFERROR(INDEX(tCashApp[UnappliedCash],6),"") -> 302.94 | G16: =IFERROR(INDEX(tCashApp[UnappliedReceipts],6),"") -> 1 | H16: =IFERROR(INDEX(tCashApp[FullyUnappliedReceipts],6),"") -> 0 | I16: =IFERROR(INDEX(tCashApp[NoRemittanceAdvice],6),"") -> 1 | J16: =IFERROR(INDEX(tCashApp[OldestUnappliedDays],6),"") -> 616 | K16: =IFERROR(INDEX(tCashApp[OpenBalance],6),"") -> 7879.38 | L16: =IFERROR(INDEX(tCashApp[PastDueBalance],6),"") -> 871.28 | M16: =IFERROR(INDEX(tCashApp[NetExposure],6),"") -> 7576.44 | N16: =IFERROR(INDEX(tCashApp[WronglyChaseable],6),"") -> 302.94 | O16: =IFERROR(IF(INDEX(tCashApp[NoRemittanceAdvice],6)>0,"No remittance advice -- request it, then apply","Advice received; the cash simply has not been matched"),"") -> No remittance advice -- request it, then apply
A17: =IF(7>COUNTA(tCashApp[CustomerID]),"",7) -> 7 | B17: =IFERROR(INDEX(tCashApp[CustomerName],7),"") -> Stonegate Fabrication | C17: =IFERROR(INDEX(tCashApp[Segment],7),"") -> OEM Manufacturer | D17: =IFERROR(INDEX(tCashApp[Region],7),"") -> West | E17: =IFERROR(INDEX(tCashApp[CollectorName],7),"") -> Marcus Bell | F17: =IFERROR(INDEX(tCashApp[UnappliedCash],7),"") -> 21587.89 | G17: =IFERROR(INDEX(tCashApp[UnappliedReceipts],7),"") -> 3 | H17: =IFERROR(INDEX(tCashApp[FullyUnappliedReceipts],7),"") -> 0 | I17: =IFERROR(INDEX(tCashApp[NoRemittanceAdvice],7),"") -> 3 | J17: =IFERROR(INDEX(tCashApp[OldestUnappliedDays],7),"") -> 612 | K17: =IFERROR(INDEX(tCashApp[OpenBalance],7),"") -> 155416.91 | L17: =IFERROR(INDEX(tCashApp[PastDueBalance],7),"") -> 40638.24 | M17: =IFERROR(INDEX(tCashApp[NetExposure],7),"") -> 133829.02 | N17: =IFERROR(INDEX(tCashApp[WronglyChaseable],7),"") -> 21587.89 | O17: =IFERROR(IF(INDEX(tCashApp[NoRemittanceAdvice],7)>0,"No remittance advice -- request it, then apply","Advice received; the cash simply has not been matched"),"") -> No remittance advice -- request it, then apply
A18: =IF(8>COUNTA(tCashApp[CustomerID]),"",8) -> 8 | B18: =IFERROR(INDEX(tCashApp[CustomerName],8),"") -> Ironbridge Maintenance Supply | C18: =IFERROR(INDEX(tCashApp[Segment],8),"") -> MRO Reseller | D18: =IFERROR(INDEX(tCashApp[Region],8),"") -> Northeast | E18: =IFERROR(INDEX(tCashApp[CollectorName],8),"") -> Sam Horowitz | F18: =IFERROR(INDEX(tCashApp[UnappliedCash],8),"") -> 507.62 | G18: =IFERROR(INDEX(tCashApp[UnappliedReceipts],8),"") -> 1 | H18: =IFERROR(INDEX(tCashApp[FullyUnappliedReceipts],8),"") -> 0 | I18: =IFERROR(INDEX(tCashApp[NoRemittanceAdvice],8),"") -> 1 | J18: =IFERROR(INDEX(tCashApp[OldestUnappliedDays],8),"") -> 603 | K18: =IFERROR(INDEX(tCashApp[OpenBalance],8),"") -> 6558.94 | L18: =IFERROR(INDEX(tCashApp[PastDueBalance],8),"") -> 3571.66 | M18: =IFERROR(INDEX(tCashApp[NetExposure],8),"") -> 6051.32 | N18: =IFERROR(INDEX(tCashApp[WronglyChaseable],8),"") -> 507.62 | O18: =IFERROR(IF(INDEX(tCashApp[NoRemittanceAdvice],8)>0,"No remittance advice -- request it, then apply","Advice received; the cash simply has not been matched"),"") -> No remittance advice -- request it, then apply
A19: =IF(9>COUNTA(tCashApp[CustomerID]),"",9) -> 9 | B19: =IFERROR(INDEX(tCashApp[CustomerName],9),"") -> Granite Construction | C19: =IFERROR(INDEX(tCashApp[Segment],9),"") -> Contractor | D19: =IFERROR(INDEX(tCashApp[Region],9),"") -> Southwest | E19: =IFERROR(INDEX(tCashApp[CollectorName],9),"") -> Elena Ruiz | F19: =IFERROR(INDEX(tCashApp[UnappliedCash],9),"") -> 1741.81 | G19: =IFERROR(INDEX(tCashApp[UnappliedReceipts],9),"") -> 2 | H19: =IFERROR(INDEX(tCashApp[FullyUnappliedReceipts],9),"") -> 0 | I19: =IFERROR(INDEX(tCashApp[NoRemittanceAdvice],9),"") -> 2 | J19: =IFERROR(INDEX(tCashApp[OldestUnappliedDays],9),"") -> 597 | K19: =IFERROR(INDEX(tCashApp[OpenBalance],9),"") -> 11143.4 | L19: =IFERROR(INDEX(tCashApp[PastDueBalance],9),"") -> 4742.58 | M19: =IFERROR(INDEX(tCashApp[NetExposure],9),"") -> 9401.59 | N19: =IFERROR(INDEX(tCashApp[WronglyChaseable],9),"") -> 1741.81 | O19: =IFERROR(IF(INDEX(tCashApp[NoRemittanceAdvice],9)>0,"No remittance advice -- request it, then apply","Advice received; the cash simply has not been matched"),"") -> No remittance advice -- request it, then apply
A20: =IF(10>COUNTA(tCashApp[CustomerID]),"",10) -> 10 | B20: =IFERROR(INDEX(tCashApp[CustomerName],10),"") -> Apex Manufacturing - Northeast | C20: =IFERROR(INDEX(tCashApp[Segment],10),"") -> OEM Manufacturer | D20: =IFERROR(INDEX(tCashApp[Region],10),"") -> Northeast | E20: =IFERROR(INDEX(tCashApp[CollectorName],10),"") -> Marcus Bell | F20: =IFERROR(INDEX(tCashApp[UnappliedCash],10),"") -> 12545.22 | G20: =IFERROR(INDEX(tCashApp[UnappliedReceipts],10),"") -> 2 | H20: =IFERROR(INDEX(tCashApp[FullyUnappliedReceipts],10),"") -> 1 | I20: =IFERROR(INDEX(tCashApp[NoRemittanceAdvice],10),"") -> 1 | J20: =IFERROR(INDEX(tCashApp[OldestUnappliedDays],10),"") -> 581 | K20: =IFERROR(INDEX(tCashApp[OpenBalance],10),"") -> 103119.74 | L20: =IFERROR(INDEX(tCashApp[PastDueBalance],10),"") -> 15008.06 | M20: =IFERROR(INDEX(tCashApp[NetExposure],10),"") -> 90574.52 | N20: =IFERROR(INDEX(tCashApp[WronglyChaseable],10),"") -> 12545.22 | O20: =IFERROR(IF(INDEX(tCashApp[NoRemittanceAdvice],10)>0,"No remittance advice -- request it, then apply","Advice received; the cash simply has not been matched"),"") -> No remittance advice -- request it, then apply
A21: =IF(11>COUNTA(tCashApp[CustomerID]),"",11) -> 11 | B21: =IFERROR(INDEX(tCashApp[CustomerName],11),"") -> Crestview Electric | C21: =IFERROR(INDEX(tCashApp[Segment],11),"") -> Contractor | D21: =IFERROR(INDEX(tCashApp[Region],11),"") -> West | E21: =IFERROR(INDEX(tCashApp[CollectorName],11),"") -> Tomas Okafor | F21: =IFERROR(INDEX(tCashApp[UnappliedCash],11),"") -> 2862.33 | G21: =IFERROR(INDEX(tCashApp[UnappliedReceipts],11),"") -> 1 | H21: =IFERROR(INDEX(tCashApp[FullyUnappliedReceipts],11),"") -> 1 | I21: =IFERROR(INDEX(tCashApp[NoRemittanceAdvice],11),"") -> 1 | J21: =IFERROR(INDEX(tCashApp[OldestUnappliedDays],11),"") -> 580 | K21: =IFERROR(INDEX(tCashApp[OpenBalance],11),"") -> 9910.01 | L21: =IFERROR(INDEX(tCashApp[PastDueBalance],11),"") -> 8585.4 | M21: =IFERROR(INDEX(tCashApp[NetExposure],11),"") -> 7047.68 | N21: =IFERROR(INDEX(tCashApp[WronglyChaseable],11),"") -> 2862.33 | O21: =IFERROR(IF(INDEX(tCashApp[NoRemittanceAdvice],11)>0,"No remittance advice -- request it, then apply","Advice received; the cash simply has not been matched"),"") -> No remittance advice -- request it, then apply
A22: =IF(12>COUNTA(tCashApp[CustomerID]),"",12) -> 12 | B22: =IFERROR(INDEX(tCashApp[CustomerName],12),"") -> Lakeshore Contracting | C22: =IFERROR(INDEX(tCashApp[Segment],12),"") -> Contractor | D22: =IFERROR(INDEX(tCashApp[Region],12),"") -> Southwest | E22: =IFERROR(INDEX(tCashApp[CollectorName],12),"") -> Elena Ruiz | F22: =IFERROR(INDEX(tCashApp[UnappliedCash],12),"") -> 912.02 | G22: =IFERROR(INDEX(tCashApp[UnappliedReceipts],12),"") -> 1 | H22: =IFERROR(INDEX(tCashApp[FullyUnappliedReceipts],12),"") -> 0 | I22: =IFERROR(INDEX(tCashApp[NoRemittanceAdvice],12),"") -> 1 | J22: =IFERROR(INDEX(tCashApp[OldestUnappliedDays],12),"") -> 556 | K22: =IFERROR(INDEX(tCashApp[OpenBalance],12),"") -> 1926.19 | L22: =IFERROR(INDEX(tCashApp[PastDueBalance],12),"") -> 930.63 | M22: =IFERROR(INDEX(tCashApp[NetExposure],12),"") -> 1014.17 | N22: =IFERROR(INDEX(tCashApp[WronglyChaseable],12),"") -> 912.02 | O22: =IFERROR(IF(INDEX(tCashApp[NoRemittanceAdvice],12)>0,"No remittance advice -- request it, then apply","Advice received; the cash simply has not been matched"),"") -> No remittance advice -- request it, then apply
A23: =IF(13>COUNTA(tCashApp[CustomerID]),"",13) -> 13 | B23: =IFERROR(INDEX(tCashApp[CustomerName],13),"") -> Lakeshore Components | C23: =IFERROR(INDEX(tCashApp[Segment],13),"") -> OEM Manufacturer | D23: =IFERROR(INDEX(tCashApp[Region],13),"") -> Midwest | E23: =IFERROR(INDEX(tCashApp[CollectorName],13),"") -> Marcus Bell | F23: =IFERROR(INDEX(tCashApp[UnappliedCash],13),"") -> 25571.1 | G23: =IFERROR(INDEX(tCashApp[UnappliedReceipts],13),"") -> 4 | H23: =IFERROR(INDEX(tCashApp[FullyUnappliedReceipts],13),"") -> 1 | I23: =IFERROR(INDEX(tCashApp[NoRemittanceAdvice],13),"") -> 3 | J23: =IFERROR(INDEX(tCashApp[OldestUnappliedDays],13),"") -> 535 | K23: =IFERROR(INDEX(tCashApp[OpenBalance],13),"") -> 178177.24 | L23: =IFERROR(INDEX(tCashApp[PastDueBalance],13),"") -> 44915.29 | M23: =IFERROR(INDEX(tCashApp[NetExposure],13),"") -> 152606.14 | N23: =IFERROR(INDEX(tCashApp[WronglyChaseable],13),"") -> 25571.1 | O23: =IFERROR(IF(INDEX(tCashApp[NoRemittanceAdvice],13)>0,"No remittance advice -- request it, then apply","Advice received; the cash simply has not been matched"),"") -> No remittance advice -- request it, then apply
A24: =IF(14>COUNTA(tCashApp[CustomerID]),"",14) -> 14 | B24: =IFERROR(INDEX(tCashApp[CustomerName],14),"") -> Lakeshore Parts & Service | C24: =IFERROR(INDEX(tCashApp[Segment],14),"") -> MRO Reseller | D24: =IFERROR(INDEX(tCashApp[Region],14),"") -> Midwest | E24: =IFERROR(INDEX(tCashApp[CollectorName],14),"") -> Sam Horowitz | F24: =IFERROR(INDEX(tCashApp[UnappliedCash],14),"") -> 574.59 | G24: =IFERROR(INDEX(tCashApp[UnappliedReceipts],14),"") -> 1 | H24: =IFERROR(INDEX(tCashApp[FullyUnappliedReceipts],14),"") -> 1 | I24: =IFERROR(INDEX(tCashApp[NoRemittanceAdvice],14),"") -> 1 | J24: =IFERROR(INDEX(tCashApp[OldestUnappliedDays],14),"") -> 516 | K24: =IFERROR(INDEX(tCashApp[OpenBalance],14),"") -> 5031.57 | L24: =IFERROR(INDEX(tCashApp[PastDueBalance],14),"") -> 574.59 | M24: =IFERROR(INDEX(tCashApp[NetExposure],14),"") -> 4456.98 | N24: =IFERROR(INDEX(tCashApp[WronglyChaseable],14),"") -> 574.59 | O24: =IFERROR(IF(INDEX(tCashApp[NoRemittanceAdvice],14)>0,"No remittance advice -- request it, then apply","Advice received; the cash simply has not been matched"),"") -> No remittance advice -- request it, then apply
A25: =IF(15>COUNTA(tCashApp[CustomerID]),"",15) -> 15 | B25: =IFERROR(INDEX(tCashApp[CustomerName],15),"") -> Harbor Construction - Southwest | C25: =IFERROR(INDEX(tCashApp[Segment],15),"") -> Contractor | D25: =IFERROR(INDEX(tCashApp[Region],15),"") -> Southwest | E25: =IFERROR(INDEX(tCashApp[CollectorName],15),"") -> Tomas Okafor | F25: =IFERROR(INDEX(tCashApp[UnappliedCash],15),"") -> 3195.97 | G25: =IFERROR(INDEX(tCashApp[UnappliedReceipts],15),"") -> 1 | H25: =IFERROR(INDEX(tCashApp[FullyUnappliedReceipts],15),"") -> 1 | I25: =IFERROR(INDEX(tCashApp[NoRemittanceAdvice],15),"") -> 1 | J25: =IFERROR(INDEX(tCashApp[OldestUnappliedDays],15),"") -> 503 | K25: =IFERROR(INDEX(tCashApp[OpenBalance],15),"") -> 34035.98 | L25: =IFERROR(INDEX(tCashApp[PastDueBalance],15),"") -> 12020.78 | M25: =IFERROR(INDEX(tCashApp[NetExposure],15),"") -> 30840.01 | N25: =IFERROR(INDEX(tCashApp[WronglyChaseable],15),"") -> 3195.97 | O25: =IFERROR(IF(INDEX(tCashApp[NoRemittanceAdvice],15)>0,"No remittance advice -- request it, then apply","Advice received; the cash simply has not been matched"),"") -> No remittance advice -- request it, then apply
A26: =IF(16>COUNTA(tCashApp[CustomerID]),"",16) -> 16 | B26: =IFERROR(INDEX(tCashApp[CustomerName],16),"") -> Ironbridge Contracting | C26: =IFERROR(INDEX(tCashApp[Segment],16),"") -> Contractor | D26: =IFERROR(INDEX(tCashApp[Region],16),"") -> Northeast | E26: =IFERROR(INDEX(tCashApp[CollectorName],16),"") -> Elena Ruiz | F26: =IFERROR(INDEX(tCashApp[UnappliedCash],16),"") -> 1417 | G26: =IFERROR(INDEX(tCashApp[UnappliedReceipts],16),"") -> 1 | H26: =IFERROR(INDEX(tCashApp[FullyUnappliedReceipts],16),"") -> 0 | I26: =IFERROR(INDEX(tCashApp[NoRemittanceAdvice],16),"") -> 1 | J26: =IFERROR(INDEX(tCashApp[OldestUnappliedDays],16),"") -> 502 | K26: =IFERROR(INDEX(tCashApp[OpenBalance],16),"") -> 6886.48 | L26: =IFERROR(INDEX(tCashApp[PastDueBalance],16),"") -> 1417 | M26: =IFERROR(INDEX(tCashApp[NetExposure],16),"") -> 5469.48 | N26: =IFERROR(INDEX(tCashApp[WronglyChaseable],16),"") -> 1417 | O26: =IFERROR(IF(INDEX(tCashApp[NoRemittanceAdvice],16)>0,"No remittance advice -- request it, then apply","Advice received; the cash simply has not been matched"),"") -> No remittance advice -- request it, then apply
A27: =IF(17>COUNTA(tCashApp[CustomerID]),"",17) -> 17 | B27: =IFERROR(INDEX(tCashApp[CustomerName],17),"") -> Riverbend MRO Services - Northeast 3 | C27: =IFERROR(INDEX(tCashApp[Segment],17),"") -> MRO Reseller | D27: =IFERROR(INDEX(tCashApp[Region],17),"") -> Northeast | E27: =IFERROR(INDEX(tCashApp[CollectorName],17),"") -> Grace Lindqvist | F27: =IFERROR(INDEX(tCashApp[UnappliedCash],17),"") -> 3099.81 | G27: =IFERROR(INDEX(tCashApp[UnappliedReceipts],17),"") -> 2 | H27: =IFERROR(INDEX(tCashApp[FullyUnappliedReceipts],17),"") -> 1 | I27: =IFERROR(INDEX(tCashApp[NoRemittanceAdvice],17),"") -> 1 | J27: =IFERROR(INDEX(tCashApp[OldestUnappliedDays],17),"") -> 500 | K27: =IFERROR(INDEX(tCashApp[OpenBalance],17),"") -> 8215.01 | L27: =IFERROR(INDEX(tCashApp[PastDueBalance],17),"") -> 2414.29 | M27: =IFERROR(INDEX(tCashApp[NetExposure],17),"") -> 5115.2 | N27: =IFERROR(INDEX(tCashApp[WronglyChaseable],17),"") -> 2414.29 | O27: =IFERROR(IF(INDEX(tCashApp[NoRemittanceAdvice],17)>0,"No remittance advice -- request it, then apply","Advice received; the cash simply has not been matched"),"") -> No remittance advice -- request it, then apply
A28: =IF(18>COUNTA(tCashApp[CustomerID]),"",18) -> 18 | B28: =IFERROR(INDEX(tCashApp[CustomerName],18),"") -> Silverline Medical Center | C28: =IFERROR(INDEX(tCashApp[Segment],18),"") -> Institutional | D28: =IFERROR(INDEX(tCashApp[Region],18),"") -> Southeast | E28: =IFERROR(INDEX(tCashApp[CollectorName],18),"") -> Marcus Bell | F28: =IFERROR(INDEX(tCashApp[UnappliedCash],18),"") -> 4011.74 | G28: =IFERROR(INDEX(tCashApp[UnappliedReceipts],18),"") -> 1 | H28: =IFERROR(INDEX(tCashApp[FullyUnappliedReceipts],18),"") -> 0 | I28: =IFERROR(INDEX(tCashApp[NoRemittanceAdvice],18),"") -> 1 | J28: =IFERROR(INDEX(tCashApp[OldestUnappliedDays],18),"") -> 499 | K28: =IFERROR(INDEX(tCashApp[OpenBalance],18),"") -> 8153.48 | L28: =IFERROR(INDEX(tCashApp[PastDueBalance],18),"") -> 6605.52 | M28: =IFERROR(INDEX(tCashApp[NetExposure],18),"") -> 4141.74 | N28: =IFERROR(INDEX(tCashApp[WronglyChaseable],18),"") -> 4011.74 | O28: =IFERROR(IF(INDEX(tCashApp[NoRemittanceAdvice],18)>0,"No remittance advice -- request it, then apply","Advice received; the cash simply has not been matched"),"") -> No remittance advice -- request it, then apply
A29: =IF(19>COUNTA(tCashApp[CustomerID]),"",19) -> 19 | B29: =IFERROR(INDEX(tCashApp[CustomerName],19),"") -> Silverline Mechanical - Southwest | C29: =IFERROR(INDEX(tCashApp[Segment],19),"") -> Contractor | D29: =IFERROR(INDEX(tCashApp[Region],19),"") -> Southwest | E29: =IFERROR(INDEX(tCashApp[CollectorName],19),"") -> Tomas Okafor | F29: =IFERROR(INDEX(tCashApp[UnappliedCash],19),"") -> 4065.66 | G29: =IFERROR(INDEX(tCashApp[UnappliedReceipts],19),"") -> 2 | H29: =IFERROR(INDEX(tCashApp[FullyUnappliedReceipts],19),"") -> 2 | I29: =IFERROR(INDEX(tCashApp[NoRemittanceAdvice],19),"") -> 1 | J29: =IFERROR(INDEX(tCashApp[OldestUnappliedDays],19),"") -> 498 | K29: =IFERROR(INDEX(tCashApp[OpenBalance],19),"") -> 13038.52 | L29: =IFERROR(INDEX(tCashApp[PastDueBalance],19),"") -> 4924.6 | M29: =IFERROR(INDEX(tCashApp[NetExposure],19),"") -> 8972.86 | N29: =IFERROR(INDEX(tCashApp[WronglyChaseable],19),"") -> 4065.66 | O29: =IFERROR(IF(INDEX(tCashApp[NoRemittanceAdvice],19)>0,"No remittance advice -- request it, then apply","Advice received; the cash simply has not been matched"),"") -> No remittance advice -- request it, then apply
A30: =IF(20>COUNTA(tCashApp[CustomerID]),"",20) -> 20 | B30: =IFERROR(INDEX(tCashApp[CustomerName],20),"") -> Lakeshore Industrial Supply | C30: =IFERROR(INDEX(tCashApp[Segment],20),"") -> MRO Reseller | D30: =IFERROR(INDEX(tCashApp[Region],20),"") -> Southeast | E30: =IFERROR(INDEX(tCashApp[CollectorName],20),"") -> Sam Horowitz | F30: =IFERROR(INDEX(tCashApp[UnappliedCash],20),"") -> 471.72 | G30: =IFERROR(INDEX(tCashApp[UnappliedReceipts],20),"") -> 1 | H30: =IFERROR(INDEX(tCashApp[FullyUnappliedReceipts],20),"") -> 0 | I30: =IFERROR(INDEX(tCashApp[NoRemittanceAdvice],20),"") -> 1 | J30: =IFERROR(INDEX(tCashApp[OldestUnappliedDays],20),"") -> 487 | K30: =IFERROR(INDEX(tCashApp[OpenBalance],20),"") -> 14261.24 | L30: =IFERROR(INDEX(tCashApp[PastDueBalance],20),"") -> 1502.17 | M30: =IFERROR(INDEX(tCashApp[NetExposure],20),"") -> 13789.52 | N30: =IFERROR(INDEX(tCashApp[WronglyChaseable],20),"") -> 471.72 | O30: =IFERROR(IF(INDEX(tCashApp[NoRemittanceAdvice],20)>0,"No remittance advice -- request it, then apply","Advice received; the cash simply has not been matched"),"") -> No remittance advice -- request it, then apply
A31: =IF(21>COUNTA(tCashApp[CustomerID]),"",21) -> 21 | B31: =IFERROR(INDEX(tCashApp[CustomerName],21),"") -> Oakmont Manufacturing | C31: =IFERROR(INDEX(tCashApp[Segment],21),"") -> OEM Manufacturer | D31: =IFERROR(INDEX(tCashApp[Region],21),"") -> Southeast | E31: =IFERROR(INDEX(tCashApp[CollectorName],21),"") -> Priya Natarajan | F31: =IFERROR(INDEX(tCashApp[UnappliedCash],21),"") -> 5843.74 | G31: =IFERROR(INDEX(tCashApp[UnappliedReceipts],21),"") -> 2 | H31: =IFERROR(INDEX(tCashApp[FullyUnappliedReceipts],21),"") -> 0 | I31: =IFERROR(INDEX(tCashApp[NoRemittanceAdvice],21),"") -> 2 | J31: =IFERROR(INDEX(tCashApp[OldestUnappliedDays],21),"") -> 479 | K31: =IFERROR(INDEX(tCashApp[OpenBalance],21),"") -> 84060.86 | L31: =IFERROR(INDEX(tCashApp[PastDueBalance],21),"") -> 20774.67 | M31: =IFERROR(INDEX(tCashApp[NetExposure],21),"") -> 78217.12 | N31: =IFERROR(INDEX(tCashApp[WronglyChaseable],21),"") -> 5843.74 | O31: =IFERROR(IF(INDEX(tCashApp[NoRemittanceAdvice],21)>0,"No remittance advice -- request it, then apply","Advice received; the cash simply has not been matched"),"") -> No remittance advice -- request it, then apply
A32: =IF(22>COUNTA(tCashApp[CustomerID]),"",22) -> 22 | B32: =IFERROR(INDEX(tCashApp[CustomerName],22),"") -> Bluewater Industries | C32: =IFERROR(INDEX(tCashApp[Segment],22),"") -> OEM Manufacturer | D32: =IFERROR(INDEX(tCashApp[Region],22),"") -> Southwest | E32: =IFERROR(INDEX(tCashApp[CollectorName],22),"") -> Priya Natarajan | F32: =IFERROR(INDEX(tCashApp[UnappliedCash],22),"") -> 3658.04 | G32: =IFERROR(INDEX(tCashApp[UnappliedReceipts],22),"") -> 1 | H32: =IFERROR(INDEX(tCashApp[FullyUnappliedReceipts],22),"") -> 0 | I32: =IFERROR(INDEX(tCashApp[NoRemittanceAdvice],22),"") -> 1 | J32: =IFERROR(INDEX(tCashApp[OldestUnappliedDays],22),"") -> 479 | K32: =IFERROR(INDEX(tCashApp[OpenBalance],22),"") -> 93887.29 | L32: =IFERROR(INDEX(tCashApp[PastDueBalance],22),"") -> 53541.39 | M32: =IFERROR(INDEX(tCashApp[NetExposure],22),"") -> 90229.25 | N32: =IFERROR(INDEX(tCashApp[WronglyChaseable],22),"") -> 3658.04 | O32: =IFERROR(IF(INDEX(tCashApp[NoRemittanceAdvice],22)>0,"No remittance advice -- request it, then apply","Advice received; the cash simply has not been matched"),"") -> No remittance advice -- request it, then apply
A33: =IF(23>COUNTA(tCashApp[CustomerID]),"",23) -> 23 | B33: =IFERROR(INDEX(tCashApp[CustomerName],23),"") -> Cedar Ridge Contracting - Northeast | C33: =IFERROR(INDEX(tCashApp[Segment],23),"") -> Contractor | D33: =IFERROR(INDEX(tCashApp[Region],23),"") -> Northeast | E33: =IFERROR(INDEX(tCashApp[CollectorName],23),"") -> Priya Natarajan | F33: =IFERROR(INDEX(tCashApp[UnappliedCash],23),"") -> 1591.96 | G33: =IFERROR(INDEX(tCashApp[UnappliedReceipts],23),"") -> 2 | H33: =IFERROR(INDEX(tCashApp[FullyUnappliedReceipts],23),"") -> 2 | I33: =IFERROR(INDEX(tCashApp[NoRemittanceAdvice],23),"") -> 1 | J33: =IFERROR(INDEX(tCashApp[OldestUnappliedDays],23),"") -> 456 | K33: =IFERROR(INDEX(tCashApp[OpenBalance],23),"") -> 11454.01 | L33: =IFERROR(INDEX(tCashApp[PastDueBalance],23),"") -> 1857.57 | M33: =IFERROR(INDEX(tCashApp[NetExposure],23),"") -> 9862.05 | N33: =IFERROR(INDEX(tCashApp[WronglyChaseable],23),"") -> 1591.96 | O33: =IFERROR(IF(INDEX(tCashApp[NoRemittanceAdvice],23)>0,"No remittance advice -- request it, then apply","Advice received; the cash simply has not been matched"),"") -> No remittance advice -- request it, then apply
A34: =IF(24>COUNTA(tCashApp[CustomerID]),"",24) -> 24 | B34: =IFERROR(INDEX(tCashApp[CustomerName],24),"") -> Lakeshore Builders | C34: =IFERROR(INDEX(tCashApp[Segment],24),"") -> Contractor | D34: =IFERROR(INDEX(tCashApp[Region],24),"") -> Southwest | E34: =IFERROR(INDEX(tCashApp[CollectorName],24),"") -> Elena Ruiz | F34: =IFERROR(INDEX(tCashApp[UnappliedCash],24),"") -> 1653.18 | G34: =IFERROR(INDEX(tCashApp[UnappliedReceipts],24),"") -> 1 | H34: =IFERROR(INDEX(tCashApp[FullyUnappliedReceipts],24),"") -> 0 | I34: =IFERROR(INDEX(tCashApp[NoRemittanceAdvice],24),"") -> 1 | J34: =IFERROR(INDEX(tCashApp[OldestUnappliedDays],24),"") -> 455 | K34: =IFERROR(INDEX(tCashApp[OpenBalance],24),"") -> 12680.1 | L34: =IFERROR(INDEX(tCashApp[PastDueBalance],24),"") -> 1653.18 | M34: =IFERROR(INDEX(tCashApp[NetExposure],24),"") -> 11026.92 | N34: =IFERROR(INDEX(tCashApp[WronglyChaseable],24),"") -> 1653.18 | O34: =IFERROR(IF(INDEX(tCashApp[NoRemittanceAdvice],24)>0,"No remittance advice -- request it, then apply","Advice received; the cash simply has not been matched"),"") -> No remittance advice -- request it, then apply
A35: =IF(25>COUNTA(tCashApp[CustomerID]),"",25) -> 25 | B35: =IFERROR(INDEX(tCashApp[CustomerName],25),"") -> Harbor Industries | C35: =IFERROR(INDEX(tCashApp[Segment],25),"") -> OEM Manufacturer | D35: =IFERROR(INDEX(tCashApp[Region],25),"") -> Southwest | E35: =IFERROR(INDEX(tCashApp[CollectorName],25),"") -> Priya Natarajan | F35: =IFERROR(INDEX(tCashApp[UnappliedCash],25),"") -> 11304.99 | G35: =IFERROR(INDEX(tCashApp[UnappliedReceipts],25),"") -> 3 | H35: =IFERROR(INDEX(tCashApp[FullyUnappliedReceipts],25),"") -> 0 | I35: =IFERROR(INDEX(tCashApp[NoRemittanceAdvice],25),"") -> 3 | J35: =IFERROR(INDEX(tCashApp[OldestUnappliedDays],25),"") -> 454 | K35: =IFERROR(INDEX(tCashApp[OpenBalance],25),"") -> 150420.44 | L35: =IFERROR(INDEX(tCashApp[PastDueBalance],25),"") -> 32505.92 | M35: =IFERROR(INDEX(tCashApp[NetExposure],25),"") -> 139115.45 | N35: =IFERROR(INDEX(tCashApp[WronglyChaseable],25),"") -> 11304.99 | O35: =IFERROR(IF(INDEX(tCashApp[NoRemittanceAdvice],25)>0,"No remittance advice -- request it, then apply","Advice received; the cash simply has not been matched"),"") -> No remittance advice -- request it, then apply
A36: =IF(26>COUNTA(tCashApp[CustomerID]),"",26) -> 26 | B36: =IFERROR(INDEX(tCashApp[CustomerName],26),"") -> Titan Industries | C36: =IFERROR(INDEX(tCashApp[Segment],26),"") -> OEM Manufacturer | D36: =IFERROR(INDEX(tCashApp[Region],26),"") -> Northeast | E36: =IFERROR(INDEX(tCashApp[CollectorName],26),"") -> Priya Natarajan | F36: =IFERROR(INDEX(tCashApp[UnappliedCash],26),"") -> 1529.01 | G36: =IFERROR(INDEX(tCashApp[UnappliedReceipts],26),"") -> 1 | H36: =IFERROR(INDEX(tCashApp[FullyUnappliedReceipts],26),"") -> 0 | I36: =IFERROR(INDEX(tCashApp[NoRemittanceAdvice],26),"") -> 1 | J36: =IFERROR(INDEX(tCashApp[OldestUnappliedDays],26),"") -> 426 | K36: =IFERROR(INDEX(tCashApp[OpenBalance],26),"") -> 122676.78 | L36: =IFERROR(INDEX(tCashApp[PastDueBalance],26),"") -> 1529.01 | M36: =IFERROR(INDEX(tCashApp[NetExposure],26),"") -> 121147.77 | N36: =IFERROR(INDEX(tCashApp[WronglyChaseable],26),"") -> 1529.01 | O36: =IFERROR(IF(INDEX(tCashApp[NoRemittanceAdvice],26)>0,"No remittance advice -- request it, then apply","Advice received; the cash simply has not been matched"),"") -> No remittance advice -- request it, then apply
A37: =IF(27>COUNTA(tCashApp[CustomerID]),"",27) -> 27 | B37: =IFERROR(INDEX(tCashApp[CustomerName],27),"") -> Westbrook Industries | C37: =IFERROR(INDEX(tCashApp[Segment],27),"") -> OEM Manufacturer | D37: =IFERROR(INDEX(tCashApp[Region],27),"") -> Midwest | E37: =IFERROR(INDEX(tCashApp[CollectorName],27),"") -> Priya Natarajan | F37: =IFERROR(INDEX(tCashApp[UnappliedCash],27),"") -> 3169.41 | G37: =IFERROR(INDEX(tCashApp[UnappliedReceipts],27),"") -> 1 | H37: =IFERROR(INDEX(tCashApp[FullyUnappliedReceipts],27),"") -> 0 | I37: =IFERROR(INDEX(tCashApp[NoRemittanceAdvice],27),"") -> 1 | J37: =IFERROR(INDEX(tCashApp[OldestUnappliedDays],27),"") -> 409 | K37: =IFERROR(INDEX(tCashApp[OpenBalance],27),"") -> 73047.34 | L37: =IFERROR(INDEX(tCashApp[PastDueBalance],27),"") -> 5883.67 | M37: =IFERROR(INDEX(tCashApp[NetExposure],27),"") -> 69877.93 | N37: =IFERROR(INDEX(tCashApp[WronglyChaseable],27),"") -> 3169.41 | O37: =IFERROR(IF(INDEX(tCashApp[NoRemittanceAdvice],27)>0,"No remittance advice -- request it, then apply","Advice received; the cash simply has not been matched"),"") -> No remittance advice -- request it, then apply
A38: =IF(28>COUNTA(tCashApp[CustomerID]),"",28) -> 28 | B38: =IFERROR(INDEX(tCashApp[CustomerName],28),"") -> Crestview Contracting | C38: =IFERROR(INDEX(tCashApp[Segment],28),"") -> Contractor | D38: =IFERROR(INDEX(tCashApp[Region],28),"") -> Southwest | E38: =IFERROR(INDEX(tCashApp[CollectorName],28),"") -> Tomas Okafor | F38: =IFERROR(INDEX(tCashApp[UnappliedCash],28),"") -> 1402.84 | G38: =IFERROR(INDEX(tCashApp[UnappliedReceipts],28),"") -> 1 | H38: =IFERROR(INDEX(tCashApp[FullyUnappliedReceipts],28),"") -> 1 | I38: =IFERROR(INDEX(tCashApp[NoRemittanceAdvice],28),"") -> 1 | J38: =IFERROR(INDEX(tCashApp[OldestUnappliedDays],28),"") -> 394 | K38: =IFERROR(INDEX(tCashApp[OpenBalance],28),"") -> 4962.52 | L38: =IFERROR(INDEX(tCashApp[PastDueBalance],28),"") -> 1402.84 | M38: =IFERROR(INDEX(tCashApp[NetExposure],28),"") -> 3559.68 | N38: =IFERROR(INDEX(tCashApp[WronglyChaseable],28),"") -> 1402.84 | O38: =IFERROR(IF(INDEX(tCashApp[NoRemittanceAdvice],28)>0,"No remittance advice -- request it, then apply","Advice received; the cash simply has not been matched"),"") -> No remittance advice -- request it, then apply
A39: =IF(29>COUNTA(tCashApp[CustomerID]),"",29) -> 29 | B39: =IFERROR(INDEX(tCashApp[CustomerName],29),"") -> Silverline Mechanical | C39: =IFERROR(INDEX(tCashApp[Segment],29),"") -> Contractor | D39: =IFERROR(INDEX(tCashApp[Region],29),"") -> Southeast | E39: =IFERROR(INDEX(tCashApp[CollectorName],29),"") -> Elena Ruiz | F39: =IFERROR(INDEX(tCashApp[UnappliedCash],29),"") -> 4840.27 | G39: =IFERROR(INDEX(tCashApp[UnappliedReceipts],29),"") -> 1 | H39: =IFERROR(INDEX(tCashApp[FullyUnappliedReceipts],29),"") -> 0 | I39: =IFERROR(INDEX(tCashApp[NoRemittanceAdvice],29),"") -> 1 | J39: =IFERROR(INDEX(tCashApp[OldestUnappliedDays],29),"") -> 392 | K39: =IFERROR(INDEX(tCashApp[OpenBalance],29),"") -> 7599.96 | L39: =IFERROR(INDEX(tCashApp[PastDueBalance],29),"") -> 4939.05 | M39: =IFERROR(INDEX(tCashApp[NetExposure],29),"") -> 2759.69 | N39: =IFERROR(INDEX(tCashApp[WronglyChaseable],29),"") -> 4840.27 | O39: =IFERROR(IF(INDEX(tCashApp[NoRemittanceAdvice],29)>0,"No remittance advice -- request it, then apply","Advice received; the cash simply has not been matched"),"") -> No remittance advice -- request it, then apply
A40: =IF(30>COUNTA(tCashApp[CustomerID]),"",30) -> 30 | B40: =IFERROR(INDEX(tCashApp[CustomerName],30),"") -> Titan Builders - Midwest 4 | C40: =IFERROR(INDEX(tCashApp[Segment],30),"") -> Contractor | D40: =IFERROR(INDEX(tCashApp[Region],30),"") -> Midwest | E40: =IFERROR(INDEX(tCashApp[CollectorName],30),"") -> Elena Ruiz | F40: =IFERROR(INDEX(tCashApp[UnappliedCash],30),"") -> 2303.59 | G40: =IFERROR(INDEX(tCashApp[UnappliedReceipts],30),"") -> 1 | H40: =IFERROR(INDEX(tCashApp[FullyUnappliedReceipts],30),"") -> 1 | I40: =IFERROR(INDEX(tCashApp[NoRemittanceAdvice],30),"") -> 1 | J40: =IFERROR(INDEX(tCashApp[OldestUnappliedDays],30),"") -> 391 | K40: =IFERROR(INDEX(tCashApp[OpenBalance],30),"") -> 10973.06 | L40: =IFERROR(INDEX(tCashApp[PastDueBalance],30),"") -> 6878.46 | M40: =IFERROR(INDEX(tCashApp[NetExposure],30),"") -> 8669.47 | N40: =IFERROR(INDEX(tCashApp[WronglyChaseable],30),"") -> 2303.59 | O40: =IFERROR(IF(INDEX(tCashApp[NoRemittanceAdvice],30)>0,"No remittance advice -- request it, then apply","Advice received; the cash simply has not been matched"),"") -> No remittance advice -- request it, then apply

Sheet Ageing Matrix
A1: AGEING MATRIX
A2: Pick a dimension. SUMIFS resolves the criteria column by name, so one set of formulas serves every cut.
B4: Cut by | C4: Segment
A6: Value | B6: =INDEX(tBuckets[BucketName],1) -> Current | C6: =INDEX(tBuckets[BucketName],2) -> 1-30 | D6: =INDEX(tBuckets[BucketName],3) -> 31-60 | E6: =INDEX(tBuckets[BucketName],4) -> 61-90 | F6: =INDEX(tBuckets[BucketName],5) -> 90+ | G6: Total | H6: Past due | I6: Share past due
A7: =IFERROR(INDEX(Calc!$N$5:$S$10,1,MATCH($C$4,Calc!$N$4:$S$4,0)),"") -> Contractor | B7: =IF($A7="","",SUMIFS(tOpenItems[OpenBalance],INDEX(tOpenItems[],0,MATCH($C$4,tOpenItems[#Headers],0)),$A7,tOpenItems[DaysPastDue],">="&INDEX(tBuckets[MinDaysPastDue],1),tOpenItems[DaysPastDue],"<="&INDEX(tBuckets[MaxDaysPastDue],1))) -> 1556763.2 | C7: =IF($A7="","",SUMIFS(tOpenItems[OpenBalance],INDEX(tOpenItems[],0,MATCH($C$4,tOpenItems[#Headers],0)),$A7,tOpenItems[DaysPastDue],">="&INDEX(tBuckets[MinDaysPastDue],2),tOpenItems[DaysPastDue],"<="&INDEX(tBuckets[MaxDaysPastDue],2))) -> 363595.4 | D7: =IF($A7="","",SUMIFS(tOpenItems[OpenBalance],INDEX(tOpenItems[],0,MATCH($C$4,tOpenItems[#Headers],0)),$A7,tOpenItems[DaysPastDue],">="&INDEX(tBuckets[MinDaysPastDue],3),tOpenItems[DaysPastDue],"<="&INDEX(tBuckets[MaxDaysPastDue],3))) -> 113580.1 | E7: =IF($A7="","",SUMIFS(tOpenItems[OpenBalance],INDEX(tOpenItems[],0,MATCH($C$4,tOpenItems[#Headers],0)),$A7,tOpenItems[DaysPastDue],">="&INDEX(tBuckets[MinDaysPastDue],4),tOpenItems[DaysPastDue],"<="&INDEX(tBuckets[MaxDaysPastDue],4))) -> 75795.76 | F7: =IF($A7="","",SUMIFS(tOpenItems[OpenBalance],INDEX(tOpenItems[],0,MATCH($C$4,tOpenItems[#Headers],0)),$A7,tOpenItems[DaysPastDue],">="&INDEX(tBuckets[MinDaysPastDue],5),tOpenItems[DaysPastDue],"<="&INDEX(tBuckets[MaxDaysPastDue],5))) -> 183978.42 | G7: =IF($A7="","",SUM(B7:F7)) -> 2293712.9 | H7: =IF($A7="","",SUM(C7:F7)) -> 736949.68 | I7: =IF(OR($A7="",G7=0),"",H7/G7) -> 0.32129116
A8: =IFERROR(INDEX(Calc!$N$5:$S$10,2,MATCH($C$4,Calc!$N$4:$S$4,0)),"") -> Institutional | B8: =IF($A8="","",SUMIFS(tOpenItems[OpenBalance],INDEX(tOpenItems[],0,MATCH($C$4,tOpenItems[#Headers],0)),$A8,tOpenItems[DaysPastDue],">="&INDEX(tBuckets[MinDaysPastDue],1),tOpenItems[DaysPastDue],"<="&INDEX(tBuckets[MaxDaysPastDue],1))) -> 917148.81 | C8: =IF($A8="","",SUMIFS(tOpenItems[OpenBalance],INDEX(tOpenItems[],0,MATCH($C$4,tOpenItems[#Headers],0)),$A8,tOpenItems[DaysPastDue],">="&INDEX(tBuckets[MinDaysPastDue],2),tOpenItems[DaysPastDue],"<="&INDEX(tBuckets[MaxDaysPastDue],2))) -> 266116.11 | D8: =IF($A8="","",SUMIFS(tOpenItems[OpenBalance],INDEX(tOpenItems[],0,MATCH($C$4,tOpenItems[#Headers],0)),$A8,tOpenItems[DaysPastDue],">="&INDEX(tBuckets[MinDaysPastDue],3),tOpenItems[DaysPastDue],"<="&INDEX(tBuckets[MaxDaysPastDue],3))) -> 10338.43 | E8: =IF($A8="","",SUMIFS(tOpenItems[OpenBalance],INDEX(tOpenItems[],0,MATCH($C$4,tOpenItems[#Headers],0)),$A8,tOpenItems[DaysPastDue],">="&INDEX(tBuckets[MinDaysPastDue],4),tOpenItems[DaysPastDue],"<="&INDEX(tBuckets[MaxDaysPastDue],4))) -> 0 | F8: =IF($A8="","",SUMIFS(tOpenItems[OpenBalance],INDEX(tOpenItems[],0,MATCH($C$4,tOpenItems[#Headers],0)),$A8,tOpenItems[DaysPastDue],">="&INDEX(tBuckets[MinDaysPastDue],5),tOpenItems[DaysPastDue],"<="&INDEX(tBuckets[MaxDaysPastDue],5))) -> 4011.74 | G8: =IF($A8="","",SUM(B8:F8)) -> 1197615.1 | H8: =IF($A8="","",SUM(C8:F8)) -> 280466.28 | I8: =IF(OR($A8="",G8=0),"",H8/G8) -> 0.23418733
A9: =IFERROR(INDEX(Calc!$N$5:$S$10,3,MATCH($C$4,Calc!$N$4:$S$4,0)),"") -> MRO Reseller | B9: =IF($A9="","",SUMIFS(tOpenItems[OpenBalance],INDEX(tOpenItems[],0,MATCH($C$4,tOpenItems[#Headers],0)),$A9,tOpenItems[DaysPastDue],">="&INDEX(tBuckets[MinDaysPastDue],1),tOpenItems[DaysPastDue],"<="&INDEX(tBuckets[MaxDaysPastDue],1))) -> 672881.05 | C9: =IF($A9="","",SUMIFS(tOpenItems[OpenBalance],INDEX(tOpenItems[],0,MATCH($C$4,tOpenItems[#Headers],0)),$A9,tOpenItems[DaysPastDue],">="&INDEX(tBuckets[MinDaysPastDue],2),tOpenItems[DaysPastDue],"<="&INDEX(tBuckets[MaxDaysPastDue],2))) -> 163137.68 | D9: =IF($A9="","",SUMIFS(tOpenItems[OpenBalance],INDEX(tOpenItems[],0,MATCH($C$4,tOpenItems[#Headers],0)),$A9,tOpenItems[DaysPastDue],">="&INDEX(tBuckets[MinDaysPastDue],3),tOpenItems[DaysPastDue],"<="&INDEX(tBuckets[MaxDaysPastDue],3))) -> 9606.6 | E9: =IF($A9="","",SUMIFS(tOpenItems[OpenBalance],INDEX(tOpenItems[],0,MATCH($C$4,tOpenItems[#Headers],0)),$A9,tOpenItems[DaysPastDue],">="&INDEX(tBuckets[MinDaysPastDue],4),tOpenItems[DaysPastDue],"<="&INDEX(tBuckets[MaxDaysPastDue],4))) -> 6652.9 | F9: =IF($A9="","",SUMIFS(tOpenItems[OpenBalance],INDEX(tOpenItems[],0,MATCH($C$4,tOpenItems[#Headers],0)),$A9,tOpenItems[DaysPastDue],">="&INDEX(tBuckets[MinDaysPastDue],5),tOpenItems[DaysPastDue],"<="&INDEX(tBuckets[MaxDaysPastDue],5))) -> 21401.09 | G9: =IF($A9="","",SUM(B9:F9)) -> 873679.32 | H9: =IF($A9="","",SUM(C9:F9)) -> 200798.27 | I9: =IF(OR($A9="",G9=0),"",H9/G9) -> 0.22983063
A10: =IFERROR(INDEX(Calc!$N$5:$S$10,4,MATCH($C$4,Calc!$N$4:$S$4,0)),"") -> OEM Manufacturer | B10: =IF($A10="","",SUMIFS(tOpenItems[OpenBalance],INDEX(tOpenItems[],0,MATCH($C$4,tOpenItems[#Headers],0)),$A10,tOpenItems[DaysPastDue],">="&INDEX(tBuckets[MinDaysPastDue],1),tOpenItems[DaysPastDue],"<="&INDEX(tBuckets[MaxDaysPastDue],1))) -> 4949000.7 | C10: =IF($A10="","",SUMIFS(tOpenItems[OpenBalance],INDEX(tOpenItems[],0,MATCH($C$4,tOpenItems[#Headers],0)),$A10,tOpenItems[DaysPastDue],">="&INDEX(tBuckets[MinDaysPastDue],2),tOpenItems[DaysPastDue],"<="&INDEX(tBuckets[MaxDaysPastDue],2))) -> 1046670.2 | D10: =IF($A10="","",SUMIFS(tOpenItems[OpenBalance],INDEX(tOpenItems[],0,MATCH($C$4,tOpenItems[#Headers],0)),$A10,tOpenItems[DaysPastDue],">="&INDEX(tBuckets[MinDaysPastDue],3),tOpenItems[DaysPastDue],"<="&INDEX(tBuckets[MaxDaysPastDue],3))) -> 272413 | E10: =IF($A10="","",SUMIFS(tOpenItems[OpenBalance],INDEX(tOpenItems[],0,MATCH($C$4,tOpenItems[#Headers],0)),$A10,tOpenItems[DaysPastDue],">="&INDEX(tBuckets[MinDaysPastDue],4),tOpenItems[DaysPastDue],"<="&INDEX(tBuckets[MaxDaysPastDue],4))) -> 60517.73 | F10: =IF($A10="","",SUMIFS(tOpenItems[OpenBalance],INDEX(tOpenItems[],0,MATCH($C$4,tOpenItems[#Headers],0)),$A10,tOpenItems[DaysPastDue],">="&INDEX(tBuckets[MinDaysPastDue],5),tOpenItems[DaysPastDue],"<="&INDEX(tBuckets[MaxDaysPastDue],5))) -> 153472.53 | G10: =IF($A10="","",SUM(B10:F10)) -> 6482074.2 | H10: =IF($A10="","",SUM(C10:F10)) -> 1533073.5 | I10: =IF(OR($A10="",G10=0),"",H10/G10) -> 0.23650971
A11: =IFERROR(INDEX(Calc!$N$5:$S$10,5,MATCH($C$4,Calc!$N$4:$S$4,0)),"") -> 0 | B11: =IF($A11="","",SUMIFS(tOpenItems[OpenBalance],INDEX(tOpenItems[],0,MATCH($C$4,tOpenItems[#Headers],0)),$A11,tOpenItems[DaysPastDue],">="&INDEX(tBuckets[MinDaysPastDue],1),tOpenItems[DaysPastDue],"<="&INDEX(tBuckets[MaxDaysPastDue],1))) -> 0 | C11: =IF($A11="","",SUMIFS(tOpenItems[OpenBalance],INDEX(tOpenItems[],0,MATCH($C$4,tOpenItems[#Headers],0)),$A11,tOpenItems[DaysPastDue],">="&INDEX(tBuckets[MinDaysPastDue],2),tOpenItems[DaysPastDue],"<="&INDEX(tBuckets[MaxDaysPastDue],2))) -> 0 | D11: =IF($A11="","",SUMIFS(tOpenItems[OpenBalance],INDEX(tOpenItems[],0,MATCH($C$4,tOpenItems[#Headers],0)),$A11,tOpenItems[DaysPastDue],">="&INDEX(tBuckets[MinDaysPastDue],3),tOpenItems[DaysPastDue],"<="&INDEX(tBuckets[MaxDaysPastDue],3))) -> 0 | E11: =IF($A11="","",SUMIFS(tOpenItems[OpenBalance],INDEX(tOpenItems[],0,MATCH($C$4,tOpenItems[#Headers],0)),$A11,tOpenItems[DaysPastDue],">="&INDEX(tBuckets[MinDaysPastDue],4),tOpenItems[DaysPastDue],"<="&INDEX(tBuckets[MaxDaysPastDue],4))) -> 0 | F11: =IF($A11="","",SUMIFS(tOpenItems[OpenBalance],INDEX(tOpenItems[],0,MATCH($C$4,tOpenItems[#Headers],0)),$A11,tOpenItems[DaysPastDue],">="&INDEX(tBuckets[MinDaysPastDue],5),tOpenItems[DaysPastDue],"<="&INDEX(tBuckets[MaxDaysPastDue],5))) -> 0 | G11: =IF($A11="","",SUM(B11:F11)) -> 0 | H11: =IF($A11="","",SUM(C11:F11)) -> 0 | I11: =IF(OR($A11="",G11=0),"",H11/G11)
A12: =IFERROR(INDEX(Calc!$N$5:$S$10,6,MATCH($C$4,Calc!$N$4:$S$4,0)),"") -> 0 | B12: =IF($A12="","",SUMIFS(tOpenItems[OpenBalance],INDEX(tOpenItems[],0,MATCH($C$4,tOpenItems[#Headers],0)),$A12,tOpenItems[DaysPastDue],">="&INDEX(tBuckets[MinDaysPastDue],1),tOpenItems[DaysPastDue],"<="&INDEX(tBuckets[MaxDaysPastDue],1))) -> 0 | C12: =IF($A12="","",SUMIFS(tOpenItems[OpenBalance],INDEX(tOpenItems[],0,MATCH($C$4,tOpenItems[#Headers],0)),$A12,tOpenItems[DaysPastDue],">="&INDEX(tBuckets[MinDaysPastDue],2),tOpenItems[DaysPastDue],"<="&INDEX(tBuckets[MaxDaysPastDue],2))) -> 0 | D12: =IF($A12="","",SUMIFS(tOpenItems[OpenBalance],INDEX(tOpenItems[],0,MATCH($C$4,tOpenItems[#Headers],0)),$A12,tOpenItems[DaysPastDue],">="&INDEX(tBuckets[MinDaysPastDue],3),tOpenItems[DaysPastDue],"<="&INDEX(tBuckets[MaxDaysPastDue],3))) -> 0 | E12: =IF($A12="","",SUMIFS(tOpenItems[OpenBalance],INDEX(tOpenItems[],0,MATCH($C$4,tOpenItems[#Headers],0)),$A12,tOpenItems[DaysPastDue],">="&INDEX(tBuckets[MinDaysPastDue],4),tOpenItems[DaysPastDue],"<="&INDEX(tBuckets[MaxDaysPastDue],4))) -> 0 | F12: =IF($A12="","",SUMIFS(tOpenItems[OpenBalance],INDEX(tOpenItems[],0,MATCH($C$4,tOpenItems[#Headers],0)),$A12,tOpenItems[DaysPastDue],">="&INDEX(tBuckets[MinDaysPastDue],5),tOpenItems[DaysPastDue],"<="&INDEX(tBuckets[MaxDaysPastDue],5))) -> 0 | G12: =IF($A12="","",SUM(B12:F12)) -> 0 | H12: =IF($A12="","",SUM(C12:F12)) -> 0 | I12: =IF(OR($A12="",G12=0),"",H12/G12)
A13: TOTAL | B13: =SUM(B7:B12) -> 8095793.8 | C13: =SUM(C7:C12) -> 1839519.4 | D13: =SUM(D7:D12) -> 405938.13 | E13: =SUM(E7:E12) -> 142966.39 | F13: =SUM(F7:F12) -> 362863.78 | G13: =SUM(G7:G12) -> 10847081 | H13: =SUM(H7:H12) -> 2751287.7 | I13: =IF(G13=0,"",H13/G13) -> 0.25364313

Sheet Validation
A1: CROSS-IMPLEMENTATION VALIDATION
A2: Each figure below was computed twice: once in T-SQL against the database, once in Excel formulas against the extract. A dashboard that only displays what the database told it cannot detect that the database was wrong.
A4: # | B4: Figure | C4: SQL | D4: Excel | E4: Difference | F4: Result
A5: 1 | B5: Total open AR | C5: =INDEX(tKPI[EndAR],MATCH(MAX(tKPI[AsOfDate]),tKPI[AsOfDate],0)) -> 10847081 | D5: =Dashboard!$C$8 -> 10847081 | E5: =C5-D5 -> 0 | F5: =IF(ABS(E5)<=0.005,"MATCH","DIFFERS") -> MATCH
A6: 2 | B6: Not yet due | C6: =INDEX(tKPI[EndCurrentAR],MATCH(MAX(tKPI[AsOfDate]),tKPI[AsOfDate],0)) -> 8095793.8 | D6: =Dashboard!$C$9 -> 8095793.8 | E6: =C6-D6 -> 1.2107193e-08 | F6: =IF(ABS(E6)<=0.005,"MATCH","DIFFERS") -> MATCH
A7: 3 | B7: Past due AR | C7: =INDEX(tKPI[PastDueAR],MATCH(MAX(tKPI[AsOfDate]),tKPI[AsOfDate],0)) -> 2751287.7 | D7: =Dashboard!$C$10+Dashboard!$C$11 -> 2751287.7 | E7: =C7-D7 -> 0 | F7: =IF(ABS(E7)<=0.005,"MATCH","DIFFERS") -> MATCH
A8: 4 | B8: 90+ AR | C8: =INDEX(tKPI[AR90Plus],MATCH(MAX(tKPI[AsOfDate]),tKPI[AsOfDate],0)) -> 362863.78 | D8: =Dashboard!$C$12 -> 362863.78 | E8: =C8-D8 -> 0 | F8: =IF(ABS(E8)<=0.005,"MATCH","DIFFERS") -> MATCH
A9: 5 | B9: Open invoice count | C9: =INDEX(tKPI[OpenInvoices],MATCH(MAX(tKPI[AsOfDate]),tKPI[AsOfDate],0)) -> 2346 | D9: =Dashboard!$C$13 -> 2346 | E9: =C9-D9 -> 0 | F9: =IF(ABS(E9)<=0.5,"MATCH","DIFFERS") -> MATCH
A10: 6 | B10: Credit sales per day | C10: =INDEX(tBridge[SalesPerDay],MATCH(MAX(tBridge[AsOfDate]),tBridge[AsOfDate],0)) -> 176118.33 | D10: =Dashboard!$C$16 -> 176118.33 | E10: =C10-D10 -> 0.0027945206 | F10: =IF(ABS(E10)<=0.005,"MATCH","DIFFERS") -> MATCH
A11: 7 | B11: Classic DSO | C11: =INDEX(tBridge[DSO_Classic],MATCH(MAX(tBridge[AsOfDate]),tBridge[AsOfDate],0)) -> 61.59 | D11: =Dashboard!$F$12 -> 61.589737 | E11: =C11-D11 -> 0.00026279256 | F11: =IF(ABS(E11)<=0.005,"MATCH","DIFFERS") -> MATCH
A12: 8 | B12: Countback DSO | C12: =INDEX(tKPI[DSO_Countback],MATCH(MAX(tKPI[AsOfDate]),tKPI[AsOfDate],0)) -> 63.07 | D12: =xlDSOCountback -> 63.071066 | E12: =C12-D12 -> -0.0010659811 | F12: =IF(ABS(E12)<=0.005,"MATCH","DIFFERS") -> MATCH
A13: 9 | B13: Best possible DSO | C13: =INDEX(tKPI[BPDSO_Countback],MATCH(MAX(tKPI[AsOfDate]),tKPI[AsOfDate],0)) -> 46.27 | D13: =xlBPDSO -> 46.265766 | E13: =C13-D13 -> 0.0042335741 | F13: =IF(ABS(E13)<=0.005,"MATCH","DIFFERS") -> MATCH
A14: 10 | B14: Average days delinquent | C14: =INDEX(tKPI[AvgDaysDelinquent],MATCH(MAX(tKPI[AsOfDate]),tKPI[AsOfDate],0)) -> 16.8 | D14: =xlADD -> 16.8 | E14: =C14-D14 -> 0 | F14: =IF(ABS(E14)<=0.005,"MATCH","DIFFERS") -> MATCH
A15: 11 | B15: Granted days | C15: =INDEX(tBridge[GrantedDays],MATCH(MAX(tBridge[AsOfDate]),tBridge[AsOfDate],0)) -> 45.97 | D15: =Dashboard!$F$9 -> 45.967923 | E15: =C15-D15 -> 0.0020765677 | F15: =IF(ABS(E15)<=0.005,"MATCH","DIFFERS") -> MATCH
A16: 12 | B16: Dispute days | C16: =INDEX(tBridge[DisputeDays],MATCH(MAX(tBridge[AsOfDate]),tBridge[AsOfDate],0)) -> 0.88 | D16: =Dashboard!$F$10 -> 0.87932194 | E16: =C16-D16 -> 0.00067805516 | F16: =IF(ABS(E16)<=0.005,"MATCH","DIFFERS") -> MATCH
A17: 13 | B17: Lateness days | C17: =INDEX(tBridge[LatenessDays],MATCH(MAX(tBridge[AsOfDate]),tBridge[AsOfDate],0)) -> 14.74 | D17: =Dashboard!$F$11 -> 14.742492 | E17: =C17-D17 -> -0.0024918303 | F17: =IF(ABS(E17)<=0.005,"MATCH","DIFFERS") -> MATCH
A18: 14 | B18: Weighted average terms | C18: =INDEX(tBridge[WeightedAvgTermsDays],MATCH(MAX(tBridge[AsOfDate]),tBridge[AsOfDate],0)) -> 46.68 | D18: =Dashboard!$F$14 -> 46.675073 | E18: =C18-D18 -> 0.0049267522 | F18: =IF(ABS(E18)<=0.005,"MATCH","DIFFERS") -> MATCH
A19: 15 | B19: Past due % of AR | C19: =INDEX(tKPI[PctPastDue],MATCH(MAX(tKPI[AsOfDate]),tKPI[AsOfDate],0)) -> 25.36 | D19: =Dashboard!$B$24 -> 25.364313 | E19: =C19-D19 -> -0.0043130877 | F19: =IF(ABS(E19)<=0.005,"MATCH","DIFFERS") -> MATCH
A20: 16 | B20: 90+ % of AR | C20: =INDEX(tKPI[Pct90Plus],MATCH(MAX(tKPI[AsOfDate]),tKPI[AsOfDate],0)) -> 3.35 | D20: =Dashboard!$B$25 -> 3.3452665 | E20: =C20-D20 -> 0.0047335305 | F20: =IF(ABS(E20)<=0.005,"MATCH","DIFFERS") -> MATCH
A21: 17 | B21: Unapplied cash | C21: =INDEX(tKPI[UnappliedCash],MATCH(MAX(tKPI[AsOfDate]),tKPI[AsOfDate],0)) -> 419392.13 | D21: =SUM(tCashApp[UnappliedCash]) -> 419392.13 | E21: =C21-D21 -> 0 | F21: =IF(ABS(E21)<=0.005,"MATCH","DIFFERS") -> MATCH
A22: 18 | B22: Unapplied cash % of AR | C22: =INDEX(tKPI[UnappliedCashPct],MATCH(MAX(tKPI[AsOfDate]),tKPI[AsOfDate],0)) -> 3.87 | D22: =Dashboard!$B$27 -> 3.8664053 | E22: =C22-D22 -> 0.0035947334 | F22: =IF(ABS(E22)<=0.005,"MATCH","DIFFERS") -> MATCH
A23: 19 | B23: Billing lag (days) | C23: =INDEX(tBridge[BillingLagDays],MATCH(MAX(tBridge[AsOfDate]),tBridge[AsOfDate],0)) -> 1.78 | D23: =Dashboard!$B$28 -> 1.7841244 | E23: =C23-D23 -> -0.0041244387 | F23: =IF(ABS(E23)<=0.01,"MATCH","DIFFERS") -> MATCH
A24: 20 | B24: True cash cycle (days) | C24: =INDEX(tBridge[CashCycleDays],MATCH(MAX(tBridge[AsOfDate]),tBridge[AsOfDate],0)) -> 63.37 | D24: =Dashboard!$F$18 -> 63.373862 | E24: =C24-D24 -> -0.0038616462 | F24: =IF(ABS(E24)<=0.01,"MATCH","DIFFERS") -> MATCH
A25: 21 | B25: Net exposure (AR less cash held) | C25: =INDEX(tKPI[EndAR],MATCH(MAX(tKPI[AsOfDate]),tKPI[AsOfDate],0))-INDEX(tKPI[UnappliedCash],MATCH(MAX(tKPI[AsOfDate]),tKPI[AsOfDate],0)) -> 10427689 | D25: =Dashboard!$C$8-SUM(tCashApp[UnappliedCash]) -> 10427689 | E25: =C25-D25 -> 0 | F25: =IF(ABS(E25)<=0.005,"MATCH","DIFFERS") -> MATCH
A26: 22 | B26: ="Bucket: "&INDEX(tBuckets[BucketName],1) -> Bucket: Current | C26: =SUMIFS(tOpenItems[OpenBalance],tOpenItems[BucketKey],1) -> 8095793.8 | D26: =SUMIFS(tOpenItems[OpenBalance],tOpenItems[DaysPastDue],">="&INDEX(tBuckets[MinDaysPastDue],1),tOpenItems[DaysPastDue],"<="&INDEX(tBuckets[MaxDaysPastDue],1)) -> 8095793.8 | E26: =C26-D26 -> 0 | F26: =IF(ABS(E26)<=0.005,"MATCH","DIFFERS") -> MATCH
A27: 23 | B27: ="Bucket: "&INDEX(tBuckets[BucketName],2) -> Bucket: 1-30 | C27: =SUMIFS(tOpenItems[OpenBalance],tOpenItems[BucketKey],2) -> 1839519.4 | D27: =SUMIFS(tOpenItems[OpenBalance],tOpenItems[DaysPastDue],">="&INDEX(tBuckets[MinDaysPastDue],2),tOpenItems[DaysPastDue],"<="&INDEX(tBuckets[MaxDaysPastDue],2)) -> 1839519.4 | E27: =C27-D27 -> 0 | F27: =IF(ABS(E27)<=0.005,"MATCH","DIFFERS") -> MATCH
A28: 24 | B28: ="Bucket: "&INDEX(tBuckets[BucketName],3) -> Bucket: 31-60 | C28: =SUMIFS(tOpenItems[OpenBalance],tOpenItems[BucketKey],3) -> 405938.13 | D28: =SUMIFS(tOpenItems[OpenBalance],tOpenItems[DaysPastDue],">="&INDEX(tBuckets[MinDaysPastDue],3),tOpenItems[DaysPastDue],"<="&INDEX(tBuckets[MaxDaysPastDue],3)) -> 405938.13 | E28: =C28-D28 -> 0 | F28: =IF(ABS(E28)<=0.005,"MATCH","DIFFERS") -> MATCH
A29: 25 | B29: ="Bucket: "&INDEX(tBuckets[BucketName],4) -> Bucket: 61-90 | C29: =SUMIFS(tOpenItems[OpenBalance],tOpenItems[BucketKey],4) -> 142966.39 | D29: =SUMIFS(tOpenItems[OpenBalance],tOpenItems[DaysPastDue],">="&INDEX(tBuckets[MinDaysPastDue],4),tOpenItems[DaysPastDue],"<="&INDEX(tBuckets[MaxDaysPastDue],4)) -> 142966.39 | E29: =C29-D29 -> 0 | F29: =IF(ABS(E29)<=0.005,"MATCH","DIFFERS") -> MATCH
A30: 26 | B30: ="Bucket: "&INDEX(tBuckets[BucketName],5) -> Bucket: 90+ | C30: =SUMIFS(tOpenItems[OpenBalance],tOpenItems[BucketKey],5) -> 362863.78 | D30: =SUMIFS(tOpenItems[OpenBalance],tOpenItems[DaysPastDue],">="&INDEX(tBuckets[MinDaysPastDue],5),tOpenItems[DaysPastDue],"<="&INDEX(tBuckets[MaxDaysPastDue],5)) -> 362863.78 | E30: =C30-D30 -> 0 | F30: =IF(ABS(E30)<=0.005,"MATCH","DIFFERS") -> MATCH
A31: 27 | B31: Days past due (sum, re-derived from dates) | C31: =SUM(tOpenItems[DaysPastDue]) -> 1906 | D31: =SUMPRODUCT(AsOfDate-tOpenItems[DueDate]) -> 1906 | E31: =C31-D31 -> 0 | F31: =IF(ABS(E31)<=0.5,"MATCH","DIFFERS") -> MATCH
B33: Checks reconciling | C33: =COUNTIF($F$5:$F$31,"MATCH")&" of "&COUNTA($F$5:$F$31) -> 27 of 27
B34: =IF(COUNTIF($F$5:$F$31,"DIFFERS")=0,"All figures reconcile between the two independent implementations.","RECONCILIATION FAILED -- do not publish these figures.") -> All figures reconcile between the two independent implementations.

Sheet Calc
A1: WORKING -- countback DSO and queue ranking
A2: Nothing here is decorative. The Dashboard reads these cells.
N3: DIMENSION VALUE LISTS (used by the Ageing Matrix)
A4: COUNTBACK DSO -- consume the open balance against the most recent months of sales | N4: Segment | O4: Region | P4: RiskTier | Q4: TermsCode | R4: CollectorName | S4: Team
A5: Month end | B5: Credit sales | C5: Days in month | D5: Cumulative sales | E5: Cumulative days | F5: Sales before this month | G5: Days before this month | H5: Covers total AR? | I5: Covers current AR? | N5: Contractor | O5: Midwest | P5: High | Q5: 2/10NET30 | R5: Elena Ruiz | S5: Commercial
A6: =_xlfn.AGGREGATE(14,6,tSales[MonthEndDate]/(tSales[MonthEndDate]<=AsOfDate),1) -> 46022 | B6: =SUMIFS(tSales[CreditSales],tSales[MonthEndDate],$A6) -> 5648631.9 | C6: =SUMIFS(tSales[DaysInMonth],tSales[MonthEndDate],$A6) -> 31 | D6: =SUM($B$6:$B6) -> 5648631.9 | E6: =SUM($C$6:$C6) -> 31 | F6: =$D6-$B6 -> 0 | G6: =$E6-$C6 -> 0 | H6: =IF($D6>=Dashboard!$C$8,1,0) -> 0 | I6: =IF($D6>=Dashboard!$C$9,1,0) -> 0 | N6: Institutional | O6: Northeast | P6: Low | Q6: NET30 | R6: Grace Lindqvist | S6: Small Business
A7: =_xlfn.AGGREGATE(14,6,tSales[MonthEndDate]/(tSales[MonthEndDate]<=AsOfDate),2) -> 45991 | B7: =SUMIFS(tSales[CreditSales],tSales[MonthEndDate],$A7) -> 4809117 | C7: =SUMIFS(tSales[DaysInMonth],tSales[MonthEndDate],$A7) -> 30 | D7: =SUM($B$6:$B7) -> 10457749 | E7: =SUM($C$6:$C7) -> 61 | F7: =$D7-$B7 -> 5648631.9 | G7: =$E7-$C7 -> 31 | H7: =IF($D7>=Dashboard!$C$8,1,0) -> 0 | I7: =IF($D7>=Dashboard!$C$9,1,0) -> 1 | N7: MRO Reseller | O7: Southeast | P7: Medium | Q7: NET45 | R7: Marcus Bell | S7: Strategic Accounts
A8: =_xlfn.AGGREGATE(14,6,tSales[MonthEndDate]/(tSales[MonthEndDate]<=AsOfDate),3) -> 45961 | B8: =SUMIFS(tSales[CreditSales],tSales[MonthEndDate],$A8) -> 5827583.5 | C8: =SUMIFS(tSales[DaysInMonth],tSales[MonthEndDate],$A8) -> 31 | D8: =SUM($B$6:$B8) -> 16285332 | E8: =SUM($C$6:$C8) -> 92 | F8: =$D8-$B8 -> 10457749 | G8: =$E8-$C8 -> 61 | H8: =IF($D8>=Dashboard!$C$8,1,0) -> 1 | I8: =IF($D8>=Dashboard!$C$9,1,0) -> 1 | N8: OEM Manufacturer | O8: Southwest | Q8: NET60 | R8: Priya Natarajan
A9: =_xlfn.AGGREGATE(14,6,tSales[MonthEndDate]/(tSales[MonthEndDate]<=AsOfDate),4) -> 45930 | B9: =SUMIFS(tSales[CreditSales],tSales[MonthEndDate],$A9) -> 5729864 | C9: =SUMIFS(tSales[DaysInMonth],tSales[MonthEndDate],$A9) -> 30 | D9: =SUM($B$6:$B9) -> 22015196 | E9: =SUM($C$6:$C9) -> 122 | F9: =$D9-$B9 -> 16285332 | G9: =$E9-$C9 -> 92 | H9: =IF($D9>=Dashboard!$C$8,1,0) -> 1 | I9: =IF($D9>=Dashboard!$C$9,1,0) -> 1 | O9: West | Q9: NET90 | R9: Sam Horowitz
A10: =_xlfn.AGGREGATE(14,6,tSales[MonthEndDate]/(tSales[MonthEndDate]<=AsOfDate),5) -> 45900 | B10: =SUMIFS(tSales[CreditSales],tSales[MonthEndDate],$A10) -> 5449542.7 | C10: =SUMIFS(tSales[DaysInMonth],tSales[MonthEndDate],$A10) -> 31 | D10: =SUM($B$6:$B10) -> 27464739 | E10: =SUM($C$6:$C10) -> 153 | F10: =$D10-$B10 -> 22015196 | G10: =$E10-$C10 -> 122 | H10: =IF($D10>=Dashboard!$C$8,1,0) -> 1 | I10: =IF($D10>=Dashboard!$C$9,1,0) -> 1 | R10: Tomas Okafor
A11: =_xlfn.AGGREGATE(14,6,tSales[MonthEndDate]/(tSales[MonthEndDate]<=AsOfDate),6) -> 45869 | B11: =SUMIFS(tSales[CreditSales],tSales[MonthEndDate],$A11) -> 6059943.3 | C11: =SUMIFS(tSales[DaysInMonth],tSales[MonthEndDate],$A11) -> 31 | D11: =SUM($B$6:$B11) -> 33524682 | E11: =SUM($C$6:$C11) -> 184 | F11: =$D11-$B11 -> 27464739 | G11: =$E11-$C11 -> 153 | H11: =IF($D11>=Dashboard!$C$8,1,0) -> 1 | I11: =IF($D11>=Dashboard!$C$9,1,0) -> 1
A12: =_xlfn.AGGREGATE(14,6,tSales[MonthEndDate]/(tSales[MonthEndDate]<=AsOfDate),7) -> 45838 | B12: =SUMIFS(tSales[CreditSales],tSales[MonthEndDate],$A12) -> 5170792.4 | C12: =SUMIFS(tSales[DaysInMonth],tSales[MonthEndDate],$A12) -> 30 | D12: =SUM($B$6:$B12) -> 38695475 | E12: =SUM($C$6:$C12) -> 214 | F12: =$D12-$B12 -> 33524682 | G12: =$E12-$C12 -> 184 | H12: =IF($D12>=Dashboard!$C$8,1,0) -> 1 | I12: =IF($D12>=Dashboard!$C$9,1,0) -> 1
A13: =_xlfn.AGGREGATE(14,6,tSales[MonthEndDate]/(tSales[MonthEndDate]<=AsOfDate),8) -> 45808 | B13: =SUMIFS(tSales[CreditSales],tSales[MonthEndDate],$A13) -> 5630994.2 | C13: =SUMIFS(tSales[DaysInMonth],tSales[MonthEndDate],$A13) -> 31 | D13: =SUM($B$6:$B13) -> 44326469 | E13: =SUM($C$6:$C13) -> 245 | F13: =$D13-$B13 -> 38695475 | G13: =$E13-$C13 -> 214 | H13: =IF($D13>=Dashboard!$C$8,1,0) -> 1 | I13: =IF($D13>=Dashboard!$C$9,1,0) -> 1
A14: =_xlfn.AGGREGATE(14,6,tSales[MonthEndDate]/(tSales[MonthEndDate]<=AsOfDate),9) -> 45777 | B14: =SUMIFS(tSales[CreditSales],tSales[MonthEndDate],$A14) -> 5478895.9 | C14: =SUMIFS(tSales[DaysInMonth],tSales[MonthEndDate],$A14) -> 30 | D14: =SUM($B$6:$B14) -> 49805365 | E14: =SUM($C$6:$C14) -> 275 | F14: =$D14-$B14 -> 44326469 | G14: =$E14-$C14 -> 245 | H14: =IF($D14>=Dashboard!$C$8,1,0) -> 1 | I14: =IF($D14>=Dashboard!$C$9,1,0) -> 1
A15: =_xlfn.AGGREGATE(14,6,tSales[MonthEndDate]/(tSales[MonthEndDate]<=AsOfDate),10) -> 45747 | B15: =SUMIFS(tSales[CreditSales],tSales[MonthEndDate],$A15) -> 5098561.4 | C15: =SUMIFS(tSales[DaysInMonth],tSales[MonthEndDate],$A15) -> 31 | D15: =SUM($B$6:$B15) -> 54903926 | E15: =SUM($C$6:$C15) -> 306 | F15: =$D15-$B15 -> 49805365 | G15: =$E15-$C15 -> 275 | H15: =IF($D15>=Dashboard!$C$8,1,0) -> 1 | I15: =IF($D15>=Dashboard!$C$9,1,0) -> 1
A16: =_xlfn.AGGREGATE(14,6,tSales[MonthEndDate]/(tSales[MonthEndDate]<=AsOfDate),11) -> 45716 | B16: =SUMIFS(tSales[CreditSales],tSales[MonthEndDate],$A16) -> 4316123.2 | C16: =SUMIFS(tSales[DaysInMonth],tSales[MonthEndDate],$A16) -> 28 | D16: =SUM($B$6:$B16) -> 59220050 | E16: =SUM($C$6:$C16) -> 334 | F16: =$D16-$B16 -> 54903926 | G16: =$E16-$C16 -> 306 | H16: =IF($D16>=Dashboard!$C$8,1,0) -> 1 | I16: =IF($D16>=Dashboard!$C$9,1,0) -> 1
A17: =_xlfn.AGGREGATE(14,6,tSales[MonthEndDate]/(tSales[MonthEndDate]<=AsOfDate),12) -> 45688 | B17: =SUMIFS(tSales[CreditSales],tSales[MonthEndDate],$A17) -> 5063139.8 | C17: =SUMIFS(tSales[DaysInMonth],tSales[MonthEndDate],$A17) -> 31 | D17: =SUM($B$6:$B17) -> 64283189 | E17: =SUM($C$6:$C17) -> 365 | F17: =$D17-$B17 -> 59220050 | G17: =$E17-$C17 -> 334 | H17: =IF($D17>=Dashboard!$C$8,1,0) -> 1 | I17: =IF($D17>=Dashboard!$C$9,1,0) -> 1
A19: Month that exhausts total AR | C19: =MATCH(1,$H$6:$H$17,0) -> 3
A20: Countback DSO (days) | C20: =INDEX($G$6:$G$17,$C$19)+(Dashboard!$C$8-INDEX($F$6:$F$17,$C$19))/INDEX($B$6:$B$17,$C$19)*INDEX($C$6:$C$17,$C$19) -> 63.071066
A21: Month that exhausts current AR | C21: =MATCH(1,$I$6:$I$17,0) -> 2
A22: Best Possible DSO (days) | C22: =INDEX($G$6:$G$17,$C$21)+(Dashboard!$C$9-INDEX($F$6:$F$17,$C$21))/INDEX($B$6:$B$17,$C$21)*INDEX($C$6:$C$17,$C$21) -> 46.265766
A23: Average Days Delinquent (days) | C23: =ROUND(C20,2)-ROUND(C22,2) -> 16.8
A26: QUEUE RANKING -- re-ranks the SQL queue under whatever filters the Priority Queue sheet has set
A27: Row | B27: Matches filters | C27: Rank within filter
A28: 1 | B28: =IF(AND(OR('Priority Queue'!$C$4="(All)",INDEX(tQueue[CollectorName],1)='Priority Queue'!$C$4),OR('Priority Queue'!$C$5="(All)",INDEX(tQueue[ActionCode],1)='Priority Queue'!$C$5),OR('Priority Queue'!$C$6="No",INDEX(tQueue[IsTodaysWorklist],1)=1),INDEX(tQueue[PastDueBalance],1)>='Priority Queue'!$C$7),1,0) -> 1 | C28: =IF($B28=0,"",SUMPRODUCT(($B$28:$B$299=1)*(tQueue[PriorityRank]<INDEX(tQueue[PriorityRank],1)))+1) -> 1
A29: 2 | B29: =IF(AND(OR('Priority Queue'!$C$4="(All)",INDEX(tQueue[CollectorName],2)='Priority Queue'!$C$4),OR('Priority Queue'!$C$5="(All)",INDEX(tQueue[ActionCode],2)='Priority Queue'!$C$5),OR('Priority Queue'!$C$6="No",INDEX(tQueue[IsTodaysWorklist],2)=1),INDEX(tQueue[PastDueBalance],2)>='Priority Queue'!$C$7),1,0) -> 1 | C29: =IF($B29=0,"",SUMPRODUCT(($B$28:$B$299=1)*(tQueue[PriorityRank]<INDEX(tQueue[PriorityRank],2)))+1) -> 2
A30: 3 | B30: =IF(AND(OR('Priority Queue'!$C$4="(All)",INDEX(tQueue[CollectorName],3)='Priority Queue'!$C$4),OR('Priority Queue'!$C$5="(All)",INDEX(tQueue[ActionCode],3)='Priority Queue'!$C$5),OR('Priority Queue'!$C$6="No",INDEX(tQueue[IsTodaysWorklist],3)=1),INDEX(tQueue[PastDueBalance],3)>='Priority Queue'!$C$7),1,0) -> 1 | C30: =IF($B30=0,"",SUMPRODUCT(($B$28:$B$299=1)*(tQueue[PriorityRank]<INDEX(tQueue[PriorityRank],3)))+1) -> 3
A31: 4 | B31: =IF(AND(OR('Priority Queue'!$C$4="(All)",INDEX(tQueue[CollectorName],4)='Priority Queue'!$C$4),OR('Priority Queue'!$C$5="(All)",INDEX(tQueue[ActionCode],4)='Priority Queue'!$C$5),OR('Priority Queue'!$C$6="No",INDEX(tQueue[IsTodaysWorklist],4)=1),INDEX(tQueue[PastDueBalance],4)>='Priority Queue'!$C$7),1,0) -> 1 | C31: =IF($B31=0,"",SUMPRODUCT(($B$28:$B$299=1)*(tQueue[PriorityRank]<INDEX(tQueue[PriorityRank],4)))+1) -> 4
A32: 5 | B32: =IF(AND(OR('Priority Queue'!$C$4="(All)",INDEX(tQueue[CollectorName],5)='Priority Queue'!$C$4),OR('Priority Queue'!$C$5="(All)",INDEX(tQueue[ActionCode],5)='Priority Queue'!$C$5),OR('Priority Queue'!$C$6="No",INDEX(tQueue[IsTodaysWorklist],5)=1),INDEX(tQueue[PastDueBalance],5)>='Priority Queue'!$C$7),1,0) -> 1 | C32: =IF($B32=0,"",SUMPRODUCT(($B$28:$B$299=1)*(tQueue[PriorityRank]<INDEX(tQueue[PriorityRank],5)))+1) -> 5
A33: 6 | B33: =IF(AND(OR('Priority Queue'!$C$4="(All)",INDEX(tQueue[CollectorName],6)='Priority Queue'!$C$4),OR('Priority Queue'!$C$5="(All)",INDEX(tQueue[ActionCode],6)='Priority Queue'!$C$5),OR('Priority Queue'!$C$6="No",INDEX(tQueue[IsTodaysWorklist],6)=1),INDEX(tQueue[PastDueBalance],6)>='Priority Queue'!$C$7),1,0) -> 1 | C33: =IF($B33=0,"",SUMPRODUCT(($B$28:$B$299=1)*(tQueue[PriorityRank]<INDEX(tQueue[PriorityRank],6)))+1) -> 6
A34: 7 | B34: =IF(AND(OR('Priority Queue'!$C$4="(All)",INDEX(tQueue[CollectorName],7)='Priority Queue'!$C$4),OR('Priority Queue'!$C$5="(All)",INDEX(tQueue[ActionCode],7)='Priority Queue'!$C$5),OR('Priority Queue'!$C$6="No",INDEX(tQueue[IsTodaysWorklist],7)=1),INDEX(tQueue[PastDueBalance],7)>='Priority Queue'!$C$7),1,0) -> 1 | C34: =IF($B34=0,"",SUMPRODUCT(($B$28:$B$299=1)*(tQueue[PriorityRank]<INDEX(tQueue[PriorityRank],7)))+1) -> 7
A35: 8 | B35: =IF(AND(OR('Priority Queue'!$C$4="(All)",INDEX(tQueue[CollectorName],8)='Priority Queue'!$C$4),OR('Priority Queue'!$C$5="(All)",INDEX(tQueue[ActionCode],8)='Priority Queue'!$C$5),OR('Priority Queue'!$C$6="No",INDEX(tQueue[IsTodaysWorklist],8)=1),INDEX(tQueue[PastDueBalance],8)>='Priority Queue'!$C$7),1,0) -> 1 | C35: =IF($B35=0,"",SUMPRODUCT(($B$28:$B$299=1)*(tQueue[PriorityRank]<INDEX(tQueue[PriorityRank],8)))+1) -> 8
A36: 9 | B36: =IF(AND(OR('Priority Queue'!$C$4="(All)",INDEX(tQueue[CollectorName],9)='Priority Queue'!$C$4),OR('Priority Queue'!$C$5="(All)",INDEX(tQueue[ActionCode],9)='Priority Queue'!$C$5),OR('Priority Queue'!$C$6="No",INDEX(tQueue[IsTodaysWorklist],9)=1),INDEX(tQueue[PastDueBalance],9)>='Priority Queue'!$C$7),1,0) -> 1 | C36: =IF($B36=0,"",SUMPRODUCT(($B$28:$B$299=1)*(tQueue[PriorityRank]<INDEX(tQueue[PriorityRank],9)))+1) -> 9
A37: 10 | B37: =IF(AND(OR('Priority Queue'!$C$4="(All)",INDEX(tQueue[CollectorName],10)='Priority Queue'!$C$4),OR('Priority Queue'!$C$5="(All)",INDEX(tQueue[ActionCode],10)='Priority Queue'!$C$5),OR('Priority Queue'!$C$6="No",INDEX(tQueue[IsTodaysWorklist],10)=1),INDEX(tQueue[PastDueBalance],10)>='Priority Queue'!$C$7),1,0) -> 1 | C37: =IF($B37=0,"",SUMPRODUCT(($B$28:$B$299=1)*(tQueue[PriorityRank]<INDEX(tQueue[PriorityRank],10)))+1) -> 10
A38: 11 | B38: =IF(AND(OR('Priority Queue'!$C$4="(All)",INDEX(tQueue[CollectorName],11)='Priority Queue'!$C$4),OR('Priority Queue'!$C$5="(All)",INDEX(tQueue[ActionCode],11)='Priority Queue'!$C$5),OR('Priority Queue'!$C$6="No",INDEX(tQueue[IsTodaysWorklist],11)=1),INDEX(tQueue[PastDueBalance],11)>='Priority Queue'!$C$7),1,0) -> 1 | C38: =IF($B38=0,"",SUMPRODUCT(($B$28:$B$299=1)*(tQueue[PriorityRank]<INDEX(tQueue[PriorityRank],11)))+1) -> 11
A39: 12 | B39: =IF(AND(OR('Priority Queue'!$C$4="(All)",INDEX(tQueue[CollectorName],12)='Priority Queue'!$C$4),OR('Priority Queue'!$C$5="(All)",INDEX(tQueue[ActionCode],12)='Priority Queue'!$C$5),OR('Priority Queue'!$C$6="No",INDEX(tQueue[IsTodaysWorklist],12)=1),INDEX(tQueue[PastDueBalance],12)>='Priority Queue'!$C$7),1,0) -> 1 | C39: =IF($B39=0,"",SUMPRODUCT(($B$28:$B$299=1)*(tQueue[PriorityRank]<INDEX(tQueue[PriorityRank],12)))+1) -> 12
A40: 13 | B40: =IF(AND(OR('Priority Queue'!$C$4="(All)",INDEX(tQueue[CollectorName],13)='Priority Queue'!$C$4),OR('Priority Queue'!$C$5="(All)",INDEX(tQueue[ActionCode],13)='Priority Queue'!$C$5),OR('Priority Queue'!$C$6="No",INDEX(tQueue[IsTodaysWorklist],13)=1),INDEX(tQueue[PastDueBalance],13)>='Priority Queue'!$C$7),1,0) -> 1 | C40: =IF($B40=0,"",SUMPRODUCT(($B$28:$B$299=1)*(tQueue[PriorityRank]<INDEX(tQueue[PriorityRank],13)))+1) -> 13
A41: 14 | B41: =IF(AND(OR('Priority Queue'!$C$4="(All)",INDEX(tQueue[CollectorName],14)='Priority Queue'!$C$4),OR('Priority Queue'!$C$5="(All)",INDEX(tQueue[ActionCode],14)='Priority Queue'!$C$5),OR('Priority Queue'!$C$6="No",INDEX(tQueue[IsTodaysWorklist],14)=1),INDEX(tQueue[PastDueBalance],14)>='Priority Queue'!$C$7),1,0) -> 1 | C41: =IF($B41=0,"",SUMPRODUCT(($B$28:$B$299=1)*(tQueue[PriorityRank]<INDEX(tQueue[PriorityRank],14)))+1) -> 14
A42: 15 | B42: =IF(AND(OR('Priority Queue'!$C$4="(All)",INDEX(tQueue[CollectorName],15)='Priority Queue'!$C$4),OR('Priority Queue'!$C$5="(All)",INDEX(tQueue[ActionCode],15)='Priority Queue'!$C$5),OR('Priority Queue'!$C$6="No",INDEX(tQueue[IsTodaysWorklist],15)=1),INDEX(tQueue[PastDueBalance],15)>='Priority Queue'!$C$7),1,0) -> 1 | C42: =IF($B42=0,"",SUMPRODUCT(($B$28:$B$299=1)*(tQueue[PriorityRank]<INDEX(tQueue[PriorityRank],15)))+1) -> 15
A43: 16 | B43: =IF(AND(OR('Priority Queue'!$C$4="(All)",INDEX(tQueue[CollectorName],16)='Priority Queue'!$C$4),OR('Priority Queue'!$C$5="(All)",INDEX(tQueue[ActionCode],16)='Priority Queue'!$C$5),OR('Priority Queue'!$C$6="No",INDEX(tQueue[IsTodaysWorklist],16)=1),INDEX(tQueue[PastDueBalance],16)>='Priority Queue'!$C$7),1,0) -> 1 | C43: =IF($B43=0,"",SUMPRODUCT(($B$28:$B$299=1)*(tQueue[PriorityRank]<INDEX(tQueue[PriorityRank],16)))+1) -> 16
A44: 17 | B44: =IF(AND(OR('Priority Queue'!$C$4="(All)",INDEX(tQueue[CollectorName],17)='Priority Queue'!$C$4),OR('Priority Queue'!$C$5="(All)",INDEX(tQueue[ActionCode],17)='Priority Queue'!$C$5),OR('Priority Queue'!$C$6="No",INDEX(tQueue[IsTodaysWorklist],17)=1),INDEX(tQueue[PastDueBalance],17)>='Priority Queue'!$C$7),1,0) -> 1 | C44: =IF($B44=0,"",SUMPRODUCT(($B$28:$B$299=1)*(tQueue[PriorityRank]<INDEX(tQueue[PriorityRank],17)))+1) -> 17
A45: 18 | B45: =IF(AND(OR('Priority Queue'!$C$4="(All)",INDEX(tQueue[CollectorName],18)='Priority Queue'!$C$4),OR('Priority Queue'!$C$5="(All)",INDEX(tQueue[ActionCode],18)='Priority Queue'!$C$5),OR('Priority Queue'!$C$6="No",INDEX(tQueue[IsTodaysWorklist],18)=1),INDEX(tQueue[PastDueBalance],18)>='Priority Queue'!$C$7),1,0) -> 1 | C45: =IF($B45=0,"",SUMPRODUCT(($B$28:$B$299=1)*(tQueue[PriorityRank]<INDEX(tQueue[PriorityRank],18)))+1) -> 18
A46: 19 | B46: =IF(AND(OR('Priority Queue'!$C$4="(All)",INDEX(tQueue[CollectorName],19)='Priority Queue'!$C$4),OR('Priority Queue'!$C$5="(All)",INDEX(tQueue[ActionCode],19)='Priority Queue'!$C$5),OR('Priority Queue'!$C$6="No",INDEX(tQueue[IsTodaysWorklist],19)=1),INDEX(tQueue[PastDueBalance],19)>='Priority Queue'!$C$7),1,0) -> 1 | C46: =IF($B46=0,"",SUMPRODUCT(($B$28:$B$299=1)*(tQueue[PriorityRank]<INDEX(tQueue[PriorityRank],19)))+1) -> 19
A47: 20 | B47: =IF(AND(OR('Priority Queue'!$C$4="(All)",INDEX(tQueue[CollectorName],20)='Priority Queue'!$C$4),OR('Priority Queue'!$C$5="(All)",INDEX(tQueue[ActionCode],20)='Priority Queue'!$C$5),OR('Priority Queue'!$C$6="No",INDEX(tQueue[IsTodaysWorklist],20)=1),INDEX(tQueue[PastDueBalance],20)>='Priority Queue'!$C$7),1,0) -> 1 | C47: =IF($B47=0,"",SUMPRODUCT(($B$28:$B$299=1)*(tQueue[PriorityRank]<INDEX(tQueue[PriorityRank],20)))+1) -> 20
A48: 21 | B48: =IF(AND(OR('Priority Queue'!$C$4="(All)",INDEX(tQueue[CollectorName],21)='Priority Queue'!$C$4),OR('Priority Queue'!$C$5="(All)",INDEX(tQueue[ActionCode],21)='Priority Queue'!$C$5),OR('Priority Queue'!$C$6="No",INDEX(tQueue[IsTodaysWorklist],21)=1),INDEX(tQueue[PastDueBalance],21)>='Priority Queue'!$C$7),1,0) -> 1 | C48: =IF($B48=0,"",SUMPRODUCT(($B$28:$B$299=1)*(tQueue[PriorityRank]<INDEX(tQueue[PriorityRank],21)))+1) -> 21
A49: 22 | B49: =IF(AND(OR('Priority Queue'!$C$4="(All)",INDEX(tQueue[CollectorName],22)='Priority Queue'!$C$4),OR('Priority Queue'!$C$5="(All)",INDEX(tQueue[ActionCode],22)='Priority Queue'!$C$5),OR('Priority Queue'!$C$6="No",INDEX(tQueue[IsTodaysWorklist],22)=1),INDEX(tQueue[PastDueBalance],22)>='Priority Queue'!$C$7),1,0) -> 1 | C49: =IF($B49=0,"",SUMPRODUCT(($B$28:$B$299=1)*(tQueue[PriorityRank]<INDEX(tQueue[PriorityRank],22)))+1) -> 22
A50: 23 | B50: =IF(AND(OR('Priority Queue'!$C$4="(All)",INDEX(tQueue[CollectorName],23)='Priority Queue'!$C$4),OR('Priority Queue'!$C$5="(All)",INDEX(tQueue[ActionCode],23)='Priority Queue'!$C$5),OR('Priority Queue'!$C$6="No",INDEX(tQueue[IsTodaysWorklist],23)=1),INDEX(tQueue[PastDueBalance],23)>='Priority Queue'!$C$7),1,0) -> 1 | C50: =IF($B50=0,"",SUMPRODUCT(($B$28:$B$299=1)*(tQueue[PriorityRank]<INDEX(tQueue[PriorityRank],23)))+1) -> 23
A51: 24 | B51: =IF(AND(OR('Priority Queue'!$C$4="(All)",INDEX(tQueue[CollectorName],24)='Priority Queue'!$C$4),OR('Priority Queue'!$C$5="(All)",INDEX(tQueue[ActionCode],24)='Priority Queue'!$C$5),OR('Priority Queue'!$C$6="No",INDEX(tQueue[IsTodaysWorklist],24)=1),INDEX(tQueue[PastDueBalance],24)>='Priority Queue'!$C$7),1,0) -> 1 | C51: =IF($B51=0,"",SUMPRODUCT(($B$28:$B$299=1)*(tQueue[PriorityRank]<INDEX(tQueue[PriorityRank],24)))+1) -> 24
A52: 25 | B52: =IF(AND(OR('Priority Queue'!$C$4="(All)",INDEX(tQueue[CollectorName],25)='Priority Queue'!$C$4),OR('Priority Queue'!$C$5="(All)",INDEX(tQueue[ActionCode],25)='Priority Queue'!$C$5),OR('Priority Queue'!$C$6="No",INDEX(tQueue[IsTodaysWorklist],25)=1),INDEX(tQueue[PastDueBalance],25)>='Priority Queue'!$C$7),1,0) -> 1 | C52: =IF($B52=0,"",SUMPRODUCT(($B$28:$B$299=1)*(tQueue[PriorityRank]<INDEX(tQueue[PriorityRank],25)))+1) -> 25
A53: 26 | B53: =IF(AND(OR('Priority Queue'!$C$4="(All)",INDEX(tQueue[CollectorName],26)='Priority Queue'!$C$4),OR('Priority Queue'!$C$5="(All)",INDEX(tQueue[ActionCode],26)='Priority Queue'!$C$5),OR('Priority Queue'!$C$6="No",INDEX(tQueue[IsTodaysWorklist],26)=1),INDEX(tQueue[PastDueBalance],26)>='Priority Queue'!$C$7),1,0) -> 1 | C53: =IF($B53=0,"",SUMPRODUCT(($B$28:$B$299=1)*(tQueue[PriorityRank]<INDEX(tQueue[PriorityRank],26)))+1) -> 26
A54: 27 | B54: =IF(AND(OR('Priority Queue'!$C$4="(All)",INDEX(tQueue[CollectorName],27)='Priority Queue'!$C$4),OR('Priority Queue'!$C$5="(All)",INDEX(tQueue[ActionCode],27)='Priority Queue'!$C$5),OR('Priority Queue'!$C$6="No",INDEX(tQueue[IsTodaysWorklist],27)=1),INDEX(tQueue[PastDueBalance],27)>='Priority Queue'!$C$7),1,0) -> 1 | C54: =IF($B54=0,"",SUMPRODUCT(($B$28:$B$299=1)*(tQueue[PriorityRank]<INDEX(tQueue[PriorityRank],27)))+1) -> 27
A55: 28 | B55: =IF(AND(OR('Priority Queue'!$C$4="(All)",INDEX(tQueue[CollectorName],28)='Priority Queue'!$C$4),OR('Priority Queue'!$C$5="(All)",INDEX(tQueue[ActionCode],28)='Priority Queue'!$C$5),OR('Priority Queue'!$C$6="No",INDEX(tQueue[IsTodaysWorklist],28)=1),INDEX(tQueue[PastDueBalance],28)>='Priority Queue'!$C$7),1,0) -> 0 | C55: =IF($B55=0,"",SUMPRODUCT(($B$28:$B$299=1)*(tQueue[PriorityRank]<INDEX(tQueue[PriorityRank],28)))+1)
A56: 29 | B56: =IF(AND(OR('Priority Queue'!$C$4="(All)",INDEX(tQueue[CollectorName],29)='Priority Queue'!$C$4),OR('Priority Queue'!$C$5="(All)",INDEX(tQueue[ActionCode],29)='Priority Queue'!$C$5),OR('Priority Queue'!$C$6="No",INDEX(tQueue[IsTodaysWorklist],29)=1),INDEX(tQueue[PastDueBalance],29)>='Priority Queue'!$C$7),1,0) -> 1 | C56: =IF($B56=0,"",SUMPRODUCT(($B$28:$B$299=1)*(tQueue[PriorityRank]<INDEX(tQueue[PriorityRank],29)))+1) -> 28
A57: 30 | B57: =IF(AND(OR('Priority Queue'!$C$4="(All)",INDEX(tQueue[CollectorName],30)='Priority Queue'!$C$4),OR('Priority Queue'!$C$5="(All)",INDEX(tQueue[ActionCode],30)='Priority Queue'!$C$5),OR('Priority Queue'!$C$6="No",INDEX(tQueue[IsTodaysWorklist],30)=1),INDEX(tQueue[PastDueBalance],30)>='Priority Queue'!$C$7),1,0) -> 0 | C57: =IF($B57=0,"",SUMPRODUCT(($B$28:$B$299=1)*(tQueue[PriorityRank]<INDEX(tQueue[PriorityRank],30)))+1)
A58: 31 | B58: =IF(AND(OR('Priority Queue'!$C$4="(All)",INDEX(tQueue[CollectorName],31)='Priority Queue'!$C$4),OR('Priority Queue'!$C$5="(All)",INDEX(tQueue[ActionCode],31)='Priority Queue'!$C$5),OR('Priority Queue'!$C$6="No",INDEX(tQueue[IsTodaysWorklist],31)=1),INDEX(tQueue[PastDueBalance],31)>='Priority Queue'!$C$7),1,0) -> 1 | C58: =IF($B58=0,"",SUMPRODUCT(($B$28:$B$299=1)*(tQueue[PriorityRank]<INDEX(tQueue[PriorityRank],31)))+1) -> 29
A59: 32 | B59: =IF(AND(OR('Priority Queue'!$C$4="(All)",INDEX(tQueue[CollectorName],32)='Priority Queue'!$C$4),OR('Priority Queue'!$C$5="(All)",INDEX(tQueue[ActionCode],32)='Priority Queue'!$C$5),OR('Priority Queue'!$C$6="No",INDEX(tQueue[IsTodaysWorklist],32)=1),INDEX(tQueue[PastDueBalance],32)>='Priority Queue'!$C$7),1,0) -> 1 | C59: =IF($B59=0,"",SUMPRODUCT(($B$28:$B$299=1)*(tQueue[PriorityRank]<INDEX(tQueue[PriorityRank],32)))+1) -> 30
A60: 33 | B60: =IF(AND(OR('Priority Queue'!$C$4="(All)",INDEX(tQueue[CollectorName],33)='Priority Queue'!$C$4),OR('Priority Queue'!$C$5="(All)",INDEX(tQueue[ActionCode],33)='Priority Queue'!$C$5),OR('Priority Queue'!$C$6="No",INDEX(tQueue[IsTodaysWorklist],33)=1),INDEX(tQueue[PastDueBalance],33)>='Priority Queue'!$C$7),1,0) -> 0 | C60: =IF($B60=0,"",SUMPRODUCT(($B$28:$B$299=1)*(tQueue[PriorityRank]<INDEX(tQueue[PriorityRank],33)))+1)
A61: 34 | B61: =IF(AND(OR('Priority Queue'!$C$4="(All)",INDEX(tQueue[CollectorName],34)='Priority Queue'!$C$4),OR('Priority Queue'!$C$5="(All)",INDEX(tQueue[ActionCode],34)='Priority Queue'!$C$5),OR('Priority Queue'!$C$6="No",INDEX(tQueue[IsTodaysWorklist],34)=1),INDEX(tQueue[PastDueBalance],34)>='Priority Queue'!$C$7),1,0) -> 0 | C61: =IF($B61=0,"",SUMPRODUCT(($B$28:$B$299=1)*(tQueue[PriorityRank]<INDEX(tQueue[PriorityRank],34)))+1)
A62: 35 | B62: =IF(AND(OR('Priority Queue'!$C$4="(All)",INDEX(tQueue[CollectorName],35)='Priority Queue'!$C$4),OR('Priority Queue'!$C$5="(All)",INDEX(tQueue[ActionCode],35)='Priority Queue'!$C$5),OR('Priority Queue'!$C$6="No",INDEX(tQueue[IsTodaysWorklist],35)=1),INDEX(tQueue[PastDueBalance],35)>='Priority Queue'!$C$7),1,0) -> 0 | C62: =IF($B62=0,"",SUMPRODUCT(($B$28:$B$299=1)*(tQueue[PriorityRank]<INDEX(tQueue[PriorityRank],35)))+1)
A63: 36 | B63: =IF(AND(OR('Priority Queue'!$C$4="(All)",INDEX(tQueue[CollectorName],36)='Priority Queue'!$C$4),OR('Priority Queue'!$C$5="(All)",INDEX(tQueue[ActionCode],36)='Priority Queue'!$C$5),OR('Priority Queue'!$C$6="No",INDEX(tQueue[IsTodaysWorklist],36)=1),INDEX(tQueue[PastDueBalance],36)>='Priority Queue'!$C$7),1,0) -> 1 | C63: =IF($B63=0,"",SUMPRODUCT(($B$28:$B$299=1)*(tQueue[PriorityRank]<INDEX(tQueue[PriorityRank],36)))+1) -> 31
A64: 37 | B64: =IF(AND(OR('Priority Queue'!$C$4="(All)",INDEX(tQueue[CollectorName],37)='Priority Queue'!$C$4),OR('Priority Queue'!$C$5="(All)",INDEX(tQueue[ActionCode],37)='Priority Queue'!$C$5),OR('Priority Queue'!$C$6="No",INDEX(tQueue[IsTodaysWorklist],37)=1),INDEX(tQueue[PastDueBalance],37)>='Priority Queue'!$C$7),1,0) -> 0 | C64: =IF($B64=0,"",SUMPRODUCT(($B$28:$B$299=1)*(tQueue[PriorityRank]<INDEX(tQueue[PriorityRank],37)))+1)
A65: 38 | B65: =IF(AND(OR('Priority Queue'!$C$4="(All)",INDEX(tQueue[CollectorName],38)='Priority Queue'!$C$4),OR('Priority Queue'!$C$5="(All)",INDEX(tQueue[ActionCode],38)='Priority Queue'!$C$5),OR('Priority Queue'!$C$6="No",INDEX(tQueue[IsTodaysWorklist],38)=1),INDEX(tQueue[PastDueBalance],38)>='Priority Queue'!$C$7),1,0) -> 0 | C65: =IF($B65=0,"",SUMPRODUCT(($B$28:$B$299=1)*(tQueue[PriorityRank]<INDEX(tQueue[PriorityRank],38)))+1)
A66: 39 | B66: =IF(AND(OR('Priority Queue'!$C$4="(All)",INDEX(tQueue[CollectorName],39)='Priority Queue'!$C$4),OR('Priority Queue'!$C$5="(All)",INDEX(tQueue[ActionCode],39)='Priority Queue'!$C$5),OR('Priority Queue'!$C$6="No",INDEX(tQueue[IsTodaysWorklist],39)=1),INDEX(tQueue[PastDueBalance],39)>='Priority Queue'!$C$7),1,0) -> 0 | C66: =IF($B66=0,"",SUMPRODUCT(($B$28:$B$299=1)*(tQueue[PriorityRank]<INDEX(tQueue[PriorityRank],39)))+1)
A67: 40 | B67: =IF(AND(OR('Priority Queue'!$C$4="(All)",INDEX(tQueue[CollectorName],40)='Priority Queue'!$C$4),OR('Priority Queue'!$C$5="(All)",INDEX(tQueue[ActionCode],40)='Priority Queue'!$C$5),OR('Priority Queue'!$C$6="No",INDEX(tQueue[IsTodaysWorklist],40)=1),INDEX(tQueue[PastDueBalance],40)>='Priority Queue'!$C$7),1,0) -> 1 | C67: =IF($B67=0,"",SUMPRODUCT(($B$28:$B$299=1)*(tQueue[PriorityRank]<INDEX(tQueue[PriorityRank],40)))+1) -> 32
A68: 41 | B68: =IF(AND(OR('Priority Queue'!$C$4="(All)",INDEX(tQueue[CollectorName],41)='Priority Queue'!$C$4),OR('Priority Queue'!$C$5="(All)",INDEX(tQueue[ActionCode],41)='Priority Queue'!$C$5),OR('Priority Queue'!$C$6="No",INDEX(tQueue[IsTodaysWorklist],41)=1),INDEX(tQueue[PastDueBalance],41)>='Priority Queue'!$C$7),1,0) -> 1 | C68: =IF($B68=0,"",SUMPRODUCT(($B$28:$B$299=1)*(tQueue[PriorityRank]<INDEX(tQueue[PriorityRank],41)))+1) -> 33
A69: 42 | B69: =IF(AND(OR('Priority Queue'!$C$4="(All)",INDEX(tQueue[CollectorName],42)='Priority Queue'!$C$4),OR('Priority Queue'!$C$5="(All)",INDEX(tQueue[ActionCode],42)='Priority Queue'!$C$5),OR('Priority Queue'!$C$6="No",INDEX(tQueue[IsTodaysWorklist],42)=1),INDEX(tQueue[PastDueBalance],42)>='Priority Queue'!$C$7),1,0) -> 1 | C69: =IF($B69=0,"",SUMPRODUCT(($B$28:$B$299=1)*(tQueue[PriorityRank]<INDEX(tQueue[PriorityRank],42)))+1) -> 34
A70: 43 | B70: =IF(AND(OR('Priority Queue'!$C$4="(All)",INDEX(tQueue[CollectorName],43)='Priority Queue'!$C$4),OR('Priority Queue'!$C$5="(All)",INDEX(tQueue[ActionCode],43)='Priority Queue'!$C$5),OR('Priority Queue'!$C$6="No",INDEX(tQueue[IsTodaysWorklist],43)=1),INDEX(tQueue[PastDueBalance],43)>='Priority Queue'!$C$7),1,0) -> 0 | C70: =IF($B70=0,"",SUMPRODUCT(($B$28:$B$299=1)*(tQueue[PriorityRank]<INDEX(tQueue[PriorityRank],43)))+1)
A71: 44 | B71: =IF(AND(OR('Priority Queue'!$C$4="(All)",INDEX(tQueue[CollectorName],44)='Priority Queue'!$C$4),OR('Priority Queue'!$C$5="(All)",INDEX(tQueue[ActionCode],44)='Priority Queue'!$C$5),OR('Priority Queue'!$C$6="No",INDEX(tQueue[IsTodaysWorklist],44)=1),INDEX(tQueue[PastDueBalance],44)>='Priority Queue'!$C$7),1,0) -> 0 | C71: =IF($B71=0,"",SUMPRODUCT(($B$28:$B$299=1)*(tQueue[PriorityRank]<INDEX(tQueue[PriorityRank],44)))+1)
A72: 45 | B72: =IF(AND(OR('Priority Queue'!$C$4="(All)",INDEX(tQueue[CollectorName],45)='Priority Queue'!$C$4),OR('Priority Queue'!$C$5="(All)",INDEX(tQueue[ActionCode],45)='Priority Queue'!$C$5),OR('Priority Queue'!$C$6="No",INDEX(tQueue[IsTodaysWorklist],45)=1),INDEX(tQueue[PastDueBalance],45)>='Priority Queue'!$C$7),1,0) -> 1 | C72: =IF($B72=0,"",SUMPRODUCT(($B$28:$B$299=1)*(tQueue[PriorityRank]<INDEX(tQueue[PriorityRank],45)))+1) -> 35
A73: 46 | B73: =IF(AND(OR('Priority Queue'!$C$4="(All)",INDEX(tQueue[CollectorName],46)='Priority Queue'!$C$4),OR('Priority Queue'!$C$5="(All)",INDEX(tQueue[ActionCode],46)='Priority Queue'!$C$5),OR('Priority Queue'!$C$6="No",INDEX(tQueue[IsTodaysWorklist],46)=1),INDEX(tQueue[PastDueBalance],46)>='Priority Queue'!$C$7),1,0) -> 1 | C73: =IF($B73=0,"",SUMPRODUCT(($B$28:$B$299=1)*(tQueue[PriorityRank]<INDEX(tQueue[PriorityRank],46)))+1) -> 36
A74: 47 | B74: =IF(AND(OR('Priority Queue'!$C$4="(All)",INDEX(tQueue[CollectorName],47)='Priority Queue'!$C$4),OR('Priority Queue'!$C$5="(All)",INDEX(tQueue[ActionCode],47)='Priority Queue'!$C$5),OR('Priority Queue'!$C$6="No",INDEX(tQueue[IsTodaysWorklist],47)=1),INDEX(tQueue[PastDueBalance],47)>='Priority Queue'!$C$7),1,0) -> 0 | C74: =IF($B74=0,"",SUMPRODUCT(($B$28:$B$299=1)*(tQueue[PriorityRank]<INDEX(tQueue[PriorityRank],47)))+1)
A75: 48 | B75: =IF(AND(OR('Priority Queue'!$C$4="(All)",INDEX(tQueue[CollectorName],48)='Priority Queue'!$C$4),OR('Priority Queue'!$C$5="(All)",INDEX(tQueue[ActionCode],48)='Priority Queue'!$C$5),OR('Priority Queue'!$C$6="No",INDEX(tQueue[IsTodaysWorklist],48)=1),INDEX(tQueue[PastDueBalance],48)>='Priority Queue'!$C$7),1,0) -> 0 | C75: =IF($B75=0,"",SUMPRODUCT(($B$28:$B$299=1)*(tQueue[PriorityRank]<INDEX(tQueue[PriorityRank],48)))+1)
A76: 49 | B76: =IF(AND(OR('Priority Queue'!$C$4="(All)",INDEX(tQueue[CollectorName],49)='Priority Queue'!$C$4),OR('Priority Queue'!$C$5="(All)",INDEX(tQueue[ActionCode],49)='Priority Queue'!$C$5),OR('Priority Queue'!$C$6="No",INDEX(tQueue[IsTodaysWorklist],49)=1),INDEX(tQueue[PastDueBalance],49)>='Priority Queue'!$C$7),1,0) -> 1 | C76: =IF($B76=0,"",SUMPRODUCT(($B$28:$B$299=1)*(tQueue[PriorityRank]<INDEX(tQueue[PriorityRank],49)))+1) -> 37
A77: 50 | B77: =IF(AND(OR('Priority Queue'!$C$4="(All)",INDEX(tQueue[CollectorName],50)='Priority Queue'!$C$4),OR('Priority Queue'!$C$5="(All)",INDEX(tQueue[ActionCode],50)='Priority Queue'!$C$5),OR('Priority Queue'!$C$6="No",INDEX(tQueue[IsTodaysWorklist],50)=1),INDEX(tQueue[PastDueBalance],50)>='Priority Queue'!$C$7),1,0) -> 0 | C77: =IF($B77=0,"",SUMPRODUCT(($B$28:$B$299=1)*(tQueue[PriorityRank]<INDEX(tQueue[PriorityRank],50)))+1)
A78: 51 | B78: =IF(AND(OR('Priority Queue'!$C$4="(All)",INDEX(tQueue[CollectorName],51)='Priority Queue'!$C$4),OR('Priority Queue'!$C$5="(All)",INDEX(tQueue[ActionCode],51)='Priority Queue'!$C$5),OR('Priority Queue'!$C$6="No",INDEX(tQueue[IsTodaysWorklist],51)=1),INDEX(tQueue[PastDueBalance],51)>='Priority Queue'!$C$7),1,0) -> 1 | C78: =IF($B78=0,"",SUMPRODUCT(($B$28:$B$299=1)*(tQueue[PriorityRank]<INDEX(tQueue[PriorityRank],51)))+1) -> 38
A79: 52 | B79: =IF(AND(OR('Priority Queue'!$C$4="(All)",INDEX(tQueue[CollectorName],52)='Priority Queue'!$C$4),OR('Priority Queue'!$C$5="(All)",INDEX(tQueue[ActionCode],52)='Priority Queue'!$C$5),OR('Priority Queue'!$C$6="No",INDEX(tQueue[IsTodaysWorklist],52)=1),INDEX(tQueue[PastDueBalance],52)>='Priority Queue'!$C$7),1,0) -> 0 | C79: =IF($B79=0,"",SUMPRODUCT(($B$28:$B$299=1)*(tQueue[PriorityRank]<INDEX(tQueue[PriorityRank],52)))+1)
A80: 53 | B80: =IF(AND(OR('Priority Queue'!$C$4="(All)",INDEX(tQueue[CollectorName],53)='Priority Queue'!$C$4),OR('Priority Queue'!$C$5="(All)",INDEX(tQueue[ActionCode],53)='Priority Queue'!$C$5),OR('Priority Queue'!$C$6="No",INDEX(tQueue[IsTodaysWorklist],53)=1),INDEX(tQueue[PastDueBalance],53)>='Priority Queue'!$C$7),1,0) -> 1 | C80: =IF($B80=0,"",SUMPRODUCT(($B$28:$B$299=1)*(tQueue[PriorityRank]<INDEX(tQueue[PriorityRank],53)))+1) -> 39
A81: 54 | B81: =IF(AND(OR('Priority Queue'!$C$4="(All)",INDEX(tQueue[CollectorName],54)='Priority Queue'!$C$4),OR('Priority Queue'!$C$5="(All)",INDEX(tQueue[ActionCode],54)='Priority Queue'!$C$5),OR('Priority Queue'!$C$6="No",INDEX(tQueue[IsTodaysWorklist],54)=1),INDEX(tQueue[PastDueBalance],54)>='Priority Queue'!$C$7),1,0) -> 1 | C81: =IF($B81=0,"",SUMPRODUCT(($B$28:$B$299=1)*(tQueue[PriorityRank]<INDEX(tQueue[PriorityRank],54)))+1) -> 40
A82: 55 | B82: =IF(AND(OR('Priority Queue'!$C$4="(All)",INDEX(tQueue[CollectorName],55)='Priority Queue'!$C$4),OR('Priority Queue'!$C$5="(All)",INDEX(tQueue[ActionCode],55)='Priority Queue'!$C$5),OR('Priority Queue'!$C$6="No",INDEX(tQueue[IsTodaysWorklist],55)=1),INDEX(tQueue[PastDueBalance],55)>='Priority Queue'!$C$7),1,0) -> 0 | C82: =IF($B82=0,"",SUMPRODUCT(($B$28:$B$299=1)*(tQueue[PriorityRank]<INDEX(tQueue[PriorityRank],55)))+1)
A83: 56 | B83: =IF(AND(OR('Priority Queue'!$C$4="(All)",INDEX(tQueue[CollectorName],56)='Priority Queue'!$C$4),OR('Priority Queue'!$C$5="(All)",INDEX(tQueue[ActionCode],56)='Priority Queue'!$C$5),OR('Priority Queue'!$C$6="No",INDEX(tQueue[IsTodaysWorklist],56)=1),INDEX(tQueue[PastDueBalance],56)>='Priority Queue'!$C$7),1,0) -> 1 | C83: =IF($B83=0,"",SUMPRODUCT(($B$28:$B$299=1)*(tQueue[PriorityRank]<INDEX(tQueue[PriorityRank],56)))+1) -> 41
A84: 57 | B84: =IF(AND(OR('Priority Queue'!$C$4="(All)",INDEX(tQueue[CollectorName],57)='Priority Queue'!$C$4),OR('Priority Queue'!$C$5="(All)",INDEX(tQueue[ActionCode],57)='Priority Queue'!$C$5),OR('Priority Queue'!$C$6="No",INDEX(tQueue[IsTodaysWorklist],57)=1),INDEX(tQueue[PastDueBalance],57)>='Priority Queue'!$C$7),1,0) -> 1 | C84: =IF($B84=0,"",SUMPRODUCT(($B$28:$B$299=1)*(tQueue[PriorityRank]<INDEX(tQueue[PriorityRank],57)))+1) -> 42
A85: 58 | B85: =IF(AND(OR('Priority Queue'!$C$4="(All)",INDEX(tQueue[CollectorName],58)='Priority Queue'!$C$4),OR('Priority Queue'!$C$5="(All)",INDEX(tQueue[ActionCode],58)='Priority Queue'!$C$5),OR('Priority Queue'!$C$6="No",INDEX(tQueue[IsTodaysWorklist],58)=1),INDEX(tQueue[PastDueBalance],58)>='Priority Queue'!$C$7),1,0) -> 1 | C85: =IF($B85=0,"",SUMPRODUCT(($B$28:$B$299=1)*(tQueue[PriorityRank]<INDEX(tQueue[PriorityRank],58)))+1) -> 43
A86: 59 | B86: =IF(AND(OR('Priority Queue'!$C$4="(All)",INDEX(tQueue[CollectorName],59)='Priority Queue'!$C$4),OR('Priority Queue'!$C$5="(All)",INDEX(tQueue[ActionCode],59)='Priority Queue'!$C$5),OR('Priority Queue'!$C$6="No",INDEX(tQueue[IsTodaysWorklist],59)=1),INDEX(tQueue[PastDueBalance],59)>='Priority Queue'!$C$7),1,0) -> 0 | C86: =IF($B86=0,"",SUMPRODUCT(($B$28:$B$299=1)*(tQueue[PriorityRank]<INDEX(tQueue[PriorityRank],59)))+1)
A87: 60 | B87: =IF(AND(OR('Priority Queue'!$C$4="(All)",INDEX(tQueue[CollectorName],60)='Priority Queue'!$C$4),OR('Priority Queue'!$C$5="(All)",INDEX(tQueue[ActionCode],60)='Priority Queue'!$C$5),OR('Priority Queue'!$C$6="No",INDEX(tQueue[IsTodaysWorklist],60)=1),INDEX(tQueue[PastDueBalance],60)>='Priority Queue'!$C$7),1,0) -> 0 | C87: =IF($B87=0,"",SUMPRODUCT(($B$28:$B$299=1)*(tQueue[PriorityRank]<INDEX(tQueue[PriorityRank],60)))+1)
A88: 61 | B88: =IF(AND(OR('Priority Queue'!$C$4="(All)",INDEX(tQueue[CollectorName],61)='Priority Queue'!$C$4),OR('Priority Queue'!$C$5="(All)",INDEX(tQueue[ActionCode],61)='Priority Queue'!$C$5),OR('Priority Queue'!$C$6="No",INDEX(tQueue[IsTodaysWorklist],61)=1),INDEX(tQueue[PastDueBalance],61)>='Priority Queue'!$C$7),1,0) -> 1 | C88: =IF($B88=0,"",SUMPRODUCT(($B$28:$B$299=1)*(tQueue[PriorityRank]<INDEX(tQueue[PriorityRank],61)))+1) -> 44
A89: 62 | B89: =IF(AND(OR('Priority Queue'!$C$4="(All)",INDEX(tQueue[CollectorName],62)='Priority Queue'!$C$4),OR('Priority Queue'!$C$5="(All)",INDEX(tQueue[ActionCode],62)='Priority Queue'!$C$5),OR('Priority Queue'!$C$6="No",INDEX(tQueue[IsTodaysWorklist],62)=1),INDEX(tQueue[PastDueBalance],62)>='Priority Queue'!$C$7),1,0) -> 0 | C89: =IF($B89=0,"",SUMPRODUCT(($B$28:$B$299=1)*(tQueue[PriorityRank]<INDEX(tQueue[PriorityRank],62)))+1)
A90: 63 | B90: =IF(AND(OR('Priority Queue'!$C$4="(All)",INDEX(tQueue[CollectorName],63)='Priority Queue'!$C$4),OR('Priority Queue'!$C$5="(All)",INDEX(tQueue[ActionCode],63)='Priority Queue'!$C$5),OR('Priority Queue'!$C$6="No",INDEX(tQueue[IsTodaysWorklist],63)=1),INDEX(tQueue[PastDueBalance],63)>='Priority Queue'!$C$7),1,0) -> 0 | C90: =IF($B90=0,"",SUMPRODUCT(($B$28:$B$299=1)*(tQueue[PriorityRank]<INDEX(tQueue[PriorityRank],63)))+1)
A91: 64 | B91: =IF(AND(OR('Priority Queue'!$C$4="(All)",INDEX(tQueue[CollectorName],64)='Priority Queue'!$C$4),OR('Priority Queue'!$C$5="(All)",INDEX(tQueue[ActionCode],64)='Priority Queue'!$C$5),OR('Priority Queue'!$C$6="No",INDEX(tQueue[IsTodaysWorklist],64)=1),INDEX(tQueue[PastDueBalance],64)>='Priority Queue'!$C$7),1,0) -> 0 | C91: =IF($B91=0,"",SUMPRODUCT(($B$28:$B$299=1)*(tQueue[PriorityRank]<INDEX(tQueue[PriorityRank],64)))+1)
A92: 65 | B92: =IF(AND(OR('Priority Queue'!$C$4="(All)",INDEX(tQueue[CollectorName],65)='Priority Queue'!$C$4),OR('Priority Queue'!$C$5="(All)",INDEX(tQueue[ActionCode],65)='Priority Queue'!$C$5),OR('Priority Queue'!$C$6="No",INDEX(tQueue[IsTodaysWorklist],65)=1),INDEX(tQueue[PastDueBalance],65)>='Priority Queue'!$C$7),1,0) -> 0 | C92: =IF($B92=0,"",SUMPRODUCT(($B$28:$B$299=1)*(tQueue[PriorityRank]<INDEX(tQueue[PriorityRank],65)))+1)
A93: 66 | B93: =IF(AND(OR('Priority Queue'!$C$4="(All)",INDEX(tQueue[CollectorName],66)='Priority Queue'!$C$4),OR('Priority Queue'!$C$5="(All)",INDEX(tQueue[ActionCode],66)='Priority Queue'!$C$5),OR('Priority Queue'!$C$6="No",INDEX(tQueue[IsTodaysWorklist],66)=1),INDEX(tQueue[PastDueBalance],66)>='Priority Queue'!$C$7),1,0) -> 1 | C93: =IF($B93=0,"",SUMPRODUCT(($B$28:$B$299=1)*(tQueue[PriorityRank]<INDEX(tQueue[PriorityRank],66)))+1) -> 45
A94: 67 | B94: =IF(AND(OR('Priority Queue'!$C$4="(All)",INDEX(tQueue[CollectorName],67)='Priority Queue'!$C$4),OR('Priority Queue'!$C$5="(All)",INDEX(tQueue[ActionCode],67)='Priority Queue'!$C$5),OR('Priority Queue'!$C$6="No",INDEX(tQueue[IsTodaysWorklist],67)=1),INDEX(tQueue[PastDueBalance],67)>='Priority Queue'!$C$7),1,0) -> 1 | C94: =IF($B94=0,"",SUMPRODUCT(($B$28:$B$299=1)*(tQueue[PriorityRank]<INDEX(tQueue[PriorityRank],67)))+1) -> 46
A95: 68 | B95: =IF(AND(OR('Priority Queue'!$C$4="(All)",INDEX(tQueue[CollectorName],68)='Priority Queue'!$C$4),OR('Priority Queue'!$C$5="(All)",INDEX(tQueue[ActionCode],68)='Priority Queue'!$C$5),OR('Priority Queue'!$C$6="No",INDEX(tQueue[IsTodaysWorklist],68)=1),INDEX(tQueue[PastDueBalance],68)>='Priority Queue'!$C$7),1,0) -> 0 | C95: =IF($B95=0,"",SUMPRODUCT(($B$28:$B$299=1)*(tQueue[PriorityRank]<INDEX(tQueue[PriorityRank],68)))+1)
A96: 69 | B96: =IF(AND(OR('Priority Queue'!$C$4="(All)",INDEX(tQueue[CollectorName],69)='Priority Queue'!$C$4),OR('Priority Queue'!$C$5="(All)",INDEX(tQueue[ActionCode],69)='Priority Queue'!$C$5),OR('Priority Queue'!$C$6="No",INDEX(tQueue[IsTodaysWorklist],69)=1),INDEX(tQueue[PastDueBalance],69)>='Priority Queue'!$C$7),1,0) -> 1 | C96: =IF($B96=0,"",SUMPRODUCT(($B$28:$B$299=1)*(tQueue[PriorityRank]<INDEX(tQueue[PriorityRank],69)))+1) -> 47
A97: 70 | B97: =IF(AND(OR('Priority Queue'!$C$4="(All)",INDEX(tQueue[CollectorName],70)='Priority Queue'!$C$4),OR('Priority Queue'!$C$5="(All)",INDEX(tQueue[ActionCode],70)='Priority Queue'!$C$5),OR('Priority Queue'!$C$6="No",INDEX(tQueue[IsTodaysWorklist],70)=1),INDEX(tQueue[PastDueBalance],70)>='Priority Queue'!$C$7),1,0) -> 0 | C97: =IF($B97=0,"",SUMPRODUCT(($B$28:$B$299=1)*(tQueue[PriorityRank]<INDEX(tQueue[PriorityRank],70)))+1)
A98: 71 | B98: =IF(AND(OR('Priority Queue'!$C$4="(All)",INDEX(tQueue[CollectorName],71)='Priority Queue'!$C$4),OR('Priority Queue'!$C$5="(All)",INDEX(tQueue[ActionCode],71)='Priority Queue'!$C$5),OR('Priority Queue'!$C$6="No",INDEX(tQueue[IsTodaysWorklist],71)=1),INDEX(tQueue[PastDueBalance],71)>='Priority Queue'!$C$7),1,0) -> 0 | C98: =IF($B98=0,"",SUMPRODUCT(($B$28:$B$299=1)*(tQueue[PriorityRank]<INDEX(tQueue[PriorityRank],71)))+1)
A99: 72 | B99: =IF(AND(OR('Priority Queue'!$C$4="(All)",INDEX(tQueue[CollectorName],72)='Priority Queue'!$C$4),OR('Priority Queue'!$C$5="(All)",INDEX(tQueue[ActionCode],72)='Priority Queue'!$C$5),OR('Priority Queue'!$C$6="No",INDEX(tQueue[IsTodaysWorklist],72)=1),INDEX(tQueue[PastDueBalance],72)>='Priority Queue'!$C$7),1,0) -> 0 | C99: =IF($B99=0,"",SUMPRODUCT(($B$28:$B$299=1)*(tQueue[PriorityRank]<INDEX(tQueue[PriorityRank],72)))+1)
A100: 73 | B100: =IF(AND(OR('Priority Queue'!$C$4="(All)",INDEX(tQueue[CollectorName],73)='Priority Queue'!$C$4),OR('Priority Queue'!$C$5="(All)",INDEX(tQueue[ActionCode],73)='Priority Queue'!$C$5),OR('Priority Queue'!$C$6="No",INDEX(tQueue[IsTodaysWorklist],73)=1),INDEX(tQueue[PastDueBalance],73)>='Priority Queue'!$C$7),1,0) -> 0 | C100: =IF($B100=0,"",SUMPRODUCT(($B$28:$B$299=1)*(tQueue[PriorityRank]<INDEX(tQueue[PriorityRank],73)))+1)
A101: 74 | B101: =IF(AND(OR('Priority Queue'!$C$4="(All)",INDEX(tQueue[CollectorName],74)='Priority Queue'!$C$4),OR('Priority Queue'!$C$5="(All)",INDEX(tQueue[ActionCode],74)='Priority Queue'!$C$5),OR('Priority Queue'!$C$6="No",INDEX(tQueue[IsTodaysWorklist],74)=1),INDEX(tQueue[PastDueBalance],74)>='Priority Queue'!$C$7),1,0) -> 0 | C101: =IF($B101=0,"",SUMPRODUCT(($B$28:$B$299=1)*(tQueue[PriorityRank]<INDEX(tQueue[PriorityRank],74)))+1)
A102: 75 | B102: =IF(AND(OR('Priority Queue'!$C$4="(All)",INDEX(tQueue[CollectorName],75)='Priority Queue'!$C$4),OR('Priority Queue'!$C$5="(All)",INDEX(tQueue[ActionCode],75)='Priority Queue'!$C$5),OR('Priority Queue'!$C$6="No",INDEX(tQueue[IsTodaysWorklist],75)=1),INDEX(tQueue[PastDueBalance],75)>='Priority Queue'!$C$7),1,0) -> 1 | C102: =IF($B102=0,"",SUMPRODUCT(($B$28:$B$299=1)*(tQueue[PriorityRank]<INDEX(tQueue[PriorityRank],75)))+1) -> 48
A103: 76 | B103: =IF(AND(OR('Priority Queue'!$C$4="(All)",INDEX(tQueue[CollectorName],76)='Priority Queue'!$C$4),OR('Priority Queue'!$C$5="(All)",INDEX(tQueue[ActionCode],76)='Priority Queue'!$C$5),OR('Priority Queue'!$C$6="No",INDEX(tQueue[IsTodaysWorklist],76)=1),INDEX(tQueue[PastDueBalance],76)>='Priority Queue'!$C$7),1,0) -> 0 | C103: =IF($B103=0,"",SUMPRODUCT(($B$28:$B$299=1)*(tQueue[PriorityRank]<INDEX(tQueue[PriorityRank],76)))+1)
...

Sheet Control
A1: VANTAGE WHOLESALE SUPPLY -- RECEIVABLES CONTROL
A2: Control panel. Every sheet in this workbook reads its parameters from the cells below.
A4: PARAMETER | B4: VALUE | C4: WHAT IT CONTROLS
A5: Reporting date | B5: =DATE(2025,12,31) -> 46022 | C5: The as-of date for every balance, ageing bucket and KPI.
A6: Extract folder | B6: =IF(OR(CELL("filename")="",LEFT(CELL("filename"),4)="http"),"Set this cell to the full path of the erp_extracts folder, then Data > Refresh All",LEFT(CELL("filename"),FIND("[",CELL("filename"))-1)&"..\erp_extracts") -> Set this cell to the full path of the erp_extracts folder, then Data > Refresh All | C6: Resolves from this workbook's own location so the repo can be cloned anywhere. On OneDrive, Excel reports a URL rather than a path, so set the folder here by hand. The workbook ships with its data already loaded, so this only matters when you refresh.
A7: Calls per collector | B7: 10 | C7: Capacity assumption behind the daily worklist. Raising it lengthens every collector's list.
A8: Dispute discount | B8: 0.75 | C8: How much of a disputed balance is treated as un-chaseable by a phone call.
A9: 90+ threshold (days) | B9: 90 | C9: Days past due at which a balance counts as seriously delinquent.
A10: Queue rows shown | B10: 25 | C10: How many ranked accounts the Priority Queue sheet displays.
A13: DATA DISCLOSURE
A14: Vantage Wholesale Supply is a fictional company. All data in this workbook is synthetic and generated by the scripts in the sql\ folder. No confidential data is used and no claim is made about any production system.

Sheet Data_OpenItems
A1: InvoiceNo | B1: CustomerID | C1: CustomerName | D1: Segment | E1: Region | F1: SalesRep | G1: RiskTier | H1: CreditLimit | I1: CollectorID | J1: CollectorName | K1: Team | L1: TermsCode | M1: NetDays | N1: DiscountPct | O1: InvoiceDate | P1: DueDate | Q1: InvoiceAmount | R1: PaidToDate | S1: DiscountToDate | T1: CreditMemoToDate | U1: WriteOffToDate | V1: OpenBalance | W1: OverAppliedAmount | X1: IsOpen | Y1: IsPastDue | Z1: DaysPastDue | AA1: BucketKey | AB1: BucketName | AC1: RiskWeight | AD1: IsDisputedOpen | AE1: DisputeReason
A2: INV-000153 | B2: C0378 | C2: Silverline Fabrication - Southwest | D2: OEM Manufacturer | E2: Southwest | F2: Rosa Delgado | G2: Medium | H2: 585000 | I2: COL-01 | J2: Priya Natarajan | K2: Strategic Accounts | L2: NET45 | M2: 45 | N2: 0 | O2: 45294 | P2: 45339 | Q2: 8016.67 | R2: 0 | S2: 0 | T2: 0 | U2: 0 | V2: 8016.67 | W2: 0 | X2: 1 | Y2: 1 | Z2: 683 | AA2: 5 | AB2: 90+ | AC2: 1 | AD2: 0
A3: INV-000196 | B3: C0326 | C3: Pioneer Manufacturing | D3: OEM Manufacturer | E3: Northeast | F3: Adrian Cole | G3: Low | H3: 315000 | I3: COL-01 | J3: Priya Natarajan | K3: Strategic Accounts | L3: NET45 | M3: 45 | N3: 0 | O3: 45295 | P3: 45340 | Q3: 3019.28 | R3: 0 | S3: 0 | T3: 0 | U3: 0 | V3: 3019.28 | W3: 0 | X3: 1 | Y3: 1 | Z3: 682 | AA3: 5 | AB3: 90+ | AC3: 1 | AD3: 0
A4: INV-001056 | B4: C0190 | C4: Harbor Fabrication | D4: OEM Manufacturer | E4: West | F4: Owen Price | G4: Medium | H4: 580000 | I4: COL-01 | J4: Priya Natarajan | K4: Strategic Accounts | L4: NET45 | M4: 45 | N4: 0 | O4: 45321 | P4: 45366 | Q4: 12428.36 | R4: 0 | S4: 0 | T4: 0 | U4: 0 | V4: 12428.36 | W4: 0 | X4: 1 | Y4: 1 | Z4: 656 | AA4: 5 | AB4: 90+ | AC4: 1 | AD4: 0
A5: INV-001631 | B5: C0196 | C5: Lakeshore MRO Services - Midwest | D5: MRO Reseller | E5: Midwest | F5: Hana Sato | G5: Low | H5: 75000 | I5: COL-06 | J5: Sam Horowitz | K5: Small Business | L5: 2/10NET30 | M5: 30 | N5: 2 | O5: 45337 | P5: 45367 | Q5: 3697.77 | R5: 0 | S5: 0 | T5: 0 | U5: 0 | V5: 3697.77 | W5: 0 | X5: 1 | Y5: 1 | Z5: 655 | AA5: 5 | AB5: 90+ | AC5: 1 | AD5: 0
A6: INV-001887 | B6: C0095 | C6: Stonegate Fabrication | D6: OEM Manufacturer | E6: West | F6: Owen Price | G6: Low | H6: 600000 | I6: COL-02 | J6: Marcus Bell | K6: Strategic Accounts | L6: NET60 | M6: 60 | N6: 0 | O6: 45344 | P6: 45404 | Q6: 15952.24 | R6: 0 | S6: 0 | T6: 0 | U6: 0 | V6: 15952.24 | W6: 0 | X6: 1 | Y6: 1 | Z6: 618 | AA6: 5 | AB6: 90+ | AC6: 1 | AD6: 0
A7: INV-001929 | B7: C0392 | C7: Apex Industrial Supply - Southwest 3 | D7: MRO Reseller | E7: Southwest | F7: Rosa Delgado | G7: High | H7: 95000 | I7: COL-05 | J7: Grace Lindqvist | K7: Small Business | L7: NET30 | M7: 30 | N7: 0 | O7: 45344 | P7: 45374 | Q7: 504.9 | R7: 201.96 | S7: 0 | T7: 0 | U7: 0 | V7: 302.94 | W7: 0 | X7: 1 | Y7: 1 | Z7: 648 | AA7: 5 | AB7: 90+ | AC7: 1 | AD7: 0
A8: INV-002573 | B8: C0118 | C8: Granite MRO Services | D8: MRO Reseller | E8: Southeast | F8: Dana Whitfield | G8: Low | H8: 60000 | I8: COL-05 | J8: Grace Lindqvist | K8: Small Business | L8: 2/10NET30 | M8: 30 | N8: 2 | O8: 45363 | P8: 45393 | Q8: 514.9 | R8: 0 | S8: 0 | T8: 0 | U8: 0 | V8: 514.9 | W8: 0 | X8: 1 | Y8: 1 | Z8: 629 | AA8: 5 | AB8: 90+ | AC8: 1 | AD8: 0
A9: INV-002698 | B9: C0172 | C9: Crestview Electric | D9: Contractor | E9: West | F9: Owen Price | G9: Medium | H9: 120000 | I9: COL-04 | J9: Tomas Okafor | K9: Commercial | L9: 2/10NET30 | M9: 30 | N9: 2 | O9: 45365 | P9: 45395 | Q9: 7155.82 | R9: 4293.49 | S9: 0 | T9: 0 | U9: 0 | V9: 2862.33 | W9: 0 | X9: 1 | Y9: 1 | Z9: 627 | AA9: 5 | AB9: 90+ | AC9: 1 | AD9: 0
A10: INV-003672 | B10: C0147 | C10: Apex Manufacturing - Northeast | D10: OEM Manufacturer | E10: Northeast | F10: Nadia Farouk | G10: Low | H10: 455000 | I10: COL-02 | J10: Marcus Bell | K10: Strategic Accounts | L10: NET45 | M10: 45 | N10: 0 | O10: 45390 | P10: 45435 | Q10: 1792.87 | R10: 0 | S10: 0 | T10: 0 | U10: 0 | V10: 1792.87 | W10: 0 | X10: 1 | Y10: 1 | Z10: 587 | AA10: 5 | AB10: 90+ | AC10: 1 | AD10: 0
A11: INV-004341 | B11: C0369 | C11: Lakeshore Components | D11: OEM Manufacturer | E11: Midwest | F11: Hana Sato | G11: High | H11: 545000 | I11: COL-02 | J11: Marcus Bell | K11: Strategic Accounts | L11: NET60 | M11: 60 | N11: 0 | O11: 45404 | P11: 45464 | Q11: 1876.3 | R11: 0 | S11: 0 | T11: 0 | U11: 0 | V11: 1876.3 | W11: 0 | X11: 1 | Y11: 1 | Z11: 558 | AA11: 5 | AB11: 90+ | AC11: 1 | AD11: 0
A12: INV-004785 | B12: C0295 | C12: Ironbridge Maintenance Supply | D12: MRO Reseller | E12: Northeast | F12: Nadia Farouk | G12: Low | H12: 85000 | I12: COL-06 | J12: Sam Horowitz | K12: Small Business | L12: 2/10NET30 | M12: 30 | N12: 2 | O12: 45414 | P12: 45444 | Q12: 517.98 | R12: 0 | S12: 0 | T12: 0 | U12: 0 | V12: 517.98 | W12: 0 | X12: 1 | Y12: 1 | Z12: 578 | AA12: 5 | AB12: 90+ | AC12: 1 | AD12: 0
A13: INV-004996 | B13: C0084 | C13: Granite Construction | D13: Contractor | E13: Southwest | F13: Rosa Delgado | G13: Medium | H13: 145000 | I13: COL-03 | J13: Elena Ruiz | K13: Commercial | L13: 2/10NET30 | M13: 30 | N13: 2 | O13: 45420 | P13: 45450 | Q13: 919.96 | R13: 0 | S13: 0 | T13: 0 | U13: 0 | V13: 919.96 | W13: 0 | X13: 1 | Y13: 1 | Z13: 572 | AA13: 5 | AB13: 90+ | AC13: 1 | AD13: 0
... A109: INV-023767 | B109: C0302 | C109: Crestview Contracting - Northeast 3 | D109: Contractor | E109: Northeast | F109: Nadia Farouk | G109: High | H109: 125000 | I109: COL-04 | J109: Tomas Okafor | K109: Commercial | L109: 2/10NET30 | M109: 30 | N109: 2 | O109: 45875 | P109: 45905 | Q109: 1084.68 | R109: 0 | S109: 0 | T109: 0 | U109: 0 | V109: 1084.68 | W109: 0 | X109: 1 | Y109: 1 | Z109: 117 | AA109: 5 | AB109: 90+ | AC109: 1 | AD109: 0
A110: INV-023845 | B110: C0386 | C110: Bluewater Electric | D110: Contractor | E110: West | F110: Maya Brennan | G110: High | H110: 100000 | I110: COL-03 | J110: Elena Ruiz | K110: Commercial | L110: NET60 | M110: 60 | N110: 0 | O110: 45876 | P110: 45936 | Q110: 5958.39 | R110: 0 | S110: 0 | T110: 0 | U110: 0 | V110: 5958.39 | W110: 0 | X110: 1 | Y110: 1 | Z110: 86 | AA110: 4 | AB110: 61-90 | AC110: 0.75 | AD110: 0 | AE110: PO Mismatch
A111: INV-023860 | B111: C0059 | C111: Apex Mechanical | D111: Contractor | E111: Midwest | F111: Ben Kowalczyk | G111: High | H111: 150000 | I111: COL-02 | J111: Marcus Bell | K111: Strategic Accounts | L111: NET30 | M111: 30 | N111: 0 | O111: 45877 | P111: 45907 | Q111: 2340.72 | R111: 0 | S111: 0 | T111: 0 | U111: 0 | V111: 2340.72 | W111: 0 | X111: 1 | Y111: 1 | Z111: 115 | AA111: 5 | AB111: 90+ | AC111: 1 | AD111: 0
A112: INV-023884 | B112: C0232 | C112: Titan Builders - Southwest | D112: Contractor | E112: Southwest | F112: Kevin Ames | G112: High | H112: 105000 | I112: COL-04 | J112: Tomas Okafor | K112: Commercial | L112: 2/10NET30 | M112: 30 | N112: 2 | O112: 45877 | P112: 45907 | Q112: 913.88 | R112: 0 | S112: 0 | T112: 0 | U112: 0 | V112: 913.88 | W112: 0 | X112: 1 | Y112: 1 | Z112: 115 | AA112: 5 | AB112: 90+ | AC112: 1 | AD112: 0
A113: INV-023889 | B113: C0271 | C113: Riverbend Electric - Midwest 3 | D113: Contractor | E113: Midwest | F113: Hana Sato | G113: High | H113: 140000 | I113: COL-03 | J113: Elena Ruiz | K113: Commercial | L113: 2/10NET30 | M113: 30 | N113: 2 | O113: 45877 | P113: 45907 | Q113: 1516.96 | R113: 0 | S113: 0 | T113: 0 | U113: 0 | V113: 1516.96 | W113: 0 | X113: 1 | Y113: 1 | Z113: 115 | AA113: 5 | AB113: 90+ | AC113: 1 | AD113: 0
A114: INV-023952 | B114: C0297 | C114: Apex Mechanical - Southeast 3 | D114: Contractor | E114: Southeast | F114: Dana Whitfield | G114: High | H114: 30000 | I114: COL-04 | J114: Tomas Okafor | K114: Commercial | L114: NET30 | M114: 30 | N114: 0 | O114: 45880 | P114: 45910 | Q114: 6073.46 | R114: 0 | S114: 0 | T114: 0 | U114: 0 | V114: 6073.46 | W114: 0 | X114: 1 | Y114: 1 | Z114: 112 | AA114: 5 | AB114: 90+ | AC114: 1 | AD114: 0
A115: INV-023954 | B115: C0302 | C115: Crestview Contracting - Northeast 3 | D115: Contractor | E115: Northeast | F115: Nadia Farouk | G115: High | H115: 125000 | I115: COL-04 | J115: Tomas Okafor | K115: Commercial | L115: 2/10NET30 | M115: 30 | N115: 2 | O115: 45880 | P115: 45910 | Q115: 1046.01 | R115: 0 | S115: 0 | T115: 0 | U115: 0 | V115: 1046.01 | W115: 0 | X115: 1 | Y115: 1 | Z115: 112 | AA115: 5 | AB115: 90+ | AC115: 1 | AD115: 0
A116: INV-024004 | B116: C0232 | C116: Titan Builders - Southwest | D116: Contractor | E116: Southwest | F116: Kevin Ames | G116: High | H116: 105000 | I116: COL-04 | J116: Tomas Okafor | K116: Commercial | L116: 2/10NET30 | M116: 30 | N116: 2 | O116: 45881 | P116: 45911 | Q116: 6219.33 | R116: 0 | S116: 0 | T116: 0 | U116: 0 | V116: 6219.33 | W116: 0 | X116: 1 | Y116: 1 | Z116: 111 | AA116: 5 | AB116: 90+ | AC116: 1 | AD116: 0
A117: INV-024014 | B117: C0271 | C117: Riverbend Electric - Midwest 3 | D117: Contractor | E117: Midwest | F117: Hana Sato | G117: High | H117: 140000 | I117: COL-03 | J117: Elena Ruiz | K117: Commercial | L117: 2/10NET30 | M117: 30 | N117: 2 | O117: 45881 | P117: 45911 | Q117: 2247.11 | R117: 0 | S117: 0 | T117: 0 | U117: 0 | V117: 2247.11 | W117: 0 | X117: 1 | Y117: 1 | Z117: 111 | AA117: 5 | AB117: 90+ | AC117: 1 | AD117: 0
A118: INV-024015 | B118: C0277 | C118: Lakeshore Construction - West | D118: Contractor | E118: West | F118: Maya Brennan | G118: High | H118: 25000 | I118: COL-04 | J118: Tomas Okafor | K118: Commercial | L118: 2/10NET30 | M118: 30 | N118: 2 | O118: 45881 | P118: 45911 | Q118: 4672.34 | R118: 0 | S118: 0 | T118: 0 | U118: 0 | V118: 4672.34 | W118: 0 | X118: 1 | Y118: 1 | Z118: 111 | AA118: 5 | AB118: 90+ | AC118: 1 | AD118: 0
A119: INV-024036 | B119: C0386 | C119: Bluewater Electric | D119: Contractor | E119: West | F119: Maya Brennan | G119: High | H119: 100000 | I119: COL-03 | J119: Elena Ruiz | K119: Commercial | L119: NET60 | M119: 60 | N119: 0 | O119: 45881 | P119: 45941 | Q119: 1601.7 | R119: 0 | S119: 0 | T119: 0 | U119: 0 | V119: 1601.7 | W119: 0 | X119: 1 | Y119: 1 | Z119: 81 | AA119: 4 | AB119: 61-90 | AC119: 0.75 | AD119: 0
A120: INV-024037 | B120: C0391 | C120: Keystone MRO Services - Northeast | D120: MRO Reseller | E120: Northeast | F120: Adrian Cole | G120: Low | H120: 30000 | I120: COL-05 | J120: Grace Lindqvist | K120: Small Business | L120: NET30 | M120: 30 | N120: 0 | O120: 45881 | P120: 45911 | Q120: 3595.83 | R120: 0 | S120: 0 | T120: 0 | U120: 0 | V120: 3595.83 | W120: 0 | X120: 1 | Y120: 1 | Z120: 111 | AA120: 5 | AB120: 90+ | AC120: 1 | AD120: 0
A121: INV-024049 | B121: C0059 | C121: Apex Mechanical | D121: Contractor | E121: Midwest | F121: Ben Kowalczyk | G121: High | H121: 150000 | I121: COL-02 | J121: Marcus Bell | K121: Strategic Accounts | L121: NET30 | M121: 30 | N121: 0 | O121: 45882 | P121: 45912 | Q121: 7727.08 | R121: 0 | S121: 0 | T121: 0 | U121: 0 | V121: 7727.08 | W121: 0 | X121: 1 | Y121: 1 | Z121: 110 | AA121: 5 | AB121: 90+ | AC121: 1 | AD121: 0
A122: INV-024054 | B122: C0132 | C122: Keystone Contracting | D122: Contractor | E122: West | F122: Maya Brennan | G122: High | H122: 105000 | I122: COL-04 | J122: Tomas Okafor | K122: Commercial | L122: NET60 | M122: 60 | N122: 0 | O122: 45882 | P122: 45942 | Q122: 2630.48 | R122: 0 | S122: 0 | T122: 0 | U122: 0 | V122: 2630.48 | W122: 0 | X122: 1 | Y122: 1 | Z122: 80 | AA122: 4 | AB122: 61-90 | AC122: 0.75 | AD122: 0
... A127: INV-024224 | B127: C0059 | C127: Apex Mechanical | D127: Contractor | E127: Midwest | F127: Ben Kowalczyk | G127: High | H127: 150000 | I127: COL-02 | J127: Marcus Bell | K127: Strategic Accounts | L127: NET30 | M127: 30 | N127: 0 | O127: 45887 | P127: 45917 | Q127: 1756.99 | R127: 0 | S127: 0 | T127: 0 | U127: 0 | V127: 1756.99 | W127: 0 | X127: 1 | Y127: 1 | Z127: 105 | AA127: 5 | AB127: 90+ | AC127: 1 | AD127: 0
A128: INV-024258 | B128: C0273 | C128: Oakmont Fabrication | D128: OEM Manufacturer | E128: Southeast | F128: Dana Whitfield | G128: Medium | H128: 395000 | I128: COL-01 | J128: Priya Natarajan | K128: Strategic Accounts | L128: NET45 | M128: 45 | N128: 0 | O128: 45887 | P128: 45932 | Q128: 1820.06 | R128: 873.63 | S128: 0 | T128: 364.01 | U128: 0 | V128: 582.42 | W128: 0 | X128: 1 | Y128: 1 | Z128: 90 | AA128: 4 | AB128: 61-90 | AC128: 0.75 | AD128: 0 | AE128: Pricing
A129: INV-024269 | B129: C0351 | C129: Ironbridge Components | D129: OEM Manufacturer | E129: Midwest | F129: Hana Sato | G129: High | H129: 450000 | I129: COL-01 | J129: Priya Natarajan | K129: Strategic Accounts | L129: NET45 | M129: 45 | N129: 0 | O129: 45887 | P129: 45932 | Q129: 13256.78 | R129: 0 | S129: 0 | T129: 0 | U129: 0 | V129: 13256.78 | W129: 0 | X129: 1 | Y129: 1 | Z129: 90 | AA129: 4 | AB129: 61-90 | AC129: 0.75 | AD129: 0
A130: INV-024290 | B130: C0132 | C130: Keystone Contracting | D130: Contractor | E130: West | F130: Maya Brennan | G130: High | H130: 105000 | I130: COL-04 | J130: Tomas Okafor | K130: Commercial | L130: NET60 | M130: 60 | N130: 0 | O130: 45888 | P130: 45948 | Q130: 5565.47 | R130: 0 | S130: 0 | T130: 0 | U130: 0 | V130: 5565.47 | W130: 0 | X130: 1 | Y130: 1 | Z130: 74 | AA130: 4 | AB130: 61-90 | AC130: 0.75 | AD130: 0
A131: INV-024336 | B131: C0059 | C131: Apex Mechanical | D131: Contractor | E131: Midwest | F131: Ben Kowalczyk | G131: High | H131: 150000 | I131: COL-02 | J131: Marcus Bell | K131: Strategic Accounts | L131: NET30 | M131: 30 | N131: 0 | O131: 45889 | P131: 45919 | Q131: 801.98 | R131: 0 | S131: 0 | T131: 0 | U131: 0 | V131: 801.98 | W131: 0 | X131: 1 | Y131: 1 | Z131: 103 | AA131: 5 | AB131: 90+ | AC131: 1 | AD131: 0
A132: INV-024436 | B132: C0302 | C132: Crestview Contracting - Northeast 3 | D132: Contractor | E132: Northeast | F132: Nadia Farouk | G132: High | H132: 125000 | I132: COL-04 | J132: Tomas Okafor | K132: Commercial | L132: 2/10NET30 | M132: 30 | N132: 2 | O132: 45890 | P132: 45920 | Q132: 884.67 | R132: 0 | S132: 0 | T132: 0 | U132: 0 | V132: 884.67 | W132: 0 | X132: 1 | Y132: 1 | Z132: 102 | AA132: 5 | AB132: 90+ | AC132: 1 | AD132: 0
A133: INV-024446 | B133: C0386 | C133: Bluewater Electric | D133: Contractor | E133: West | F133: Maya Brennan | G133: High | H133: 100000 | I133: COL-03 | J133: Elena Ruiz | K133: Commercial | L133: NET60 | M133: 60 | N133: 0 | O133: 45890 | P133: 45950 | Q133: 7354.36 | R133: 0 | S133: 0 | T133: 0 | U133: 0 | V133: 7354.36 | W133: 0 | X133: 1 | Y133: 1 | Z133: 72 | AA133: 4 | AB133: 61-90 | AC133: 0.75 | AD133: 0
A134: INV-024496 | B134: C0294 | C134: Titan Components | D134: OEM Manufacturer | E134: Northeast | F134: Adrian Cole | G134: Low | H134: 215000 | I134: COL-01 | J134: Priya Natarajan | K134: Strategic Accounts | L134: NET60 | M134: 60 | N134: 0 | O134: 45891 | P134: 45951 | Q134: 2883.43 | R134: 0 | S134: 0 | T134: 0 | U134: 0 | V134: 2883.43 | W134: 0 | X134: 1 | Y134: 1 | Z134: 71 | AA134: 4 | AB134: 61-90 | AC134: 0.75 | AD134: 0
A135: INV-024564 | B135: C0324 | C135: Pioneer Construction | D135: Contractor | E135: Southeast | F135: Dana Whitfield | G135: High | H135: 145000 | I135: COL-03 | J135: Elena Ruiz | K135: Commercial | L135: 2/10NET30 | M135: 30 | N135: 2 | O135: 45894 | P135: 45924 | Q135: 2695.12 | R135: 0 | S135: 0 | T135: 0 | U135: 0 | V135: 2695.12 | W135: 0 | X135: 1 | Y135: 1 | Z135: 98 | AA135: 5 | AB135: 90+ | AC135: 1 | AD135: 0
A136: INV-024575 | B136: C0366 | C136: Westbrook Industries - West | D136: OEM Manufacturer | E136: West | F136: Owen Price | G136: Medium | H136: 320000 | I136: COL-02 | J136: Marcus Bell | K136: Strategic Accounts | L136: NET60 | M136: 60 | N136: 0 | O136: 45894 | P136: 45954 | Q136: 10923.61 | R136: 0 | S136: 0 | T136: 0 | U136: 0 | V136: 10923.61 | W136: 0 | X136: 1 | Y136: 1 | Z136: 68 | AA136: 4 | AB136: 61-90 | AC136: 0.75 | AD136: 0
A137: INV-024665 | B137: C0080 | C137: Frontier Maintenance Supply | D137: MRO Reseller | E137: Northeast | F137: Adrian Cole | G137: Medium | H137: 50000 | I137: COL-05 | J137: Grace Lindqvist | K137: Small Business | L137: NET30 | M137: 30 | N137: 0 | O137: 45896 | P137: 45926 | Q137: 1576.11 | R137: 0 | S137: 0 | T137: 0 | U137: 0 | V137: 1576.11 | W137: 0 | X137: 1 | Y137: 1 | Z137: 96 | AA137: 5 | AB137: 90+ | AC137: 1 | AD137: 0
A138: INV-024707 | B138: C0386 | C138: Bluewater Electric | D138: Contractor | E138: West | F138: Maya Brennan | G138: High | H138: 100000 | I138: COL-03 | J138: Elena Ruiz | K138: Commercial | L138: NET60 | M138: 60 | N138: 0 | O138: 45896 | P138: 45956 | Q138: 1851.58 | R138: 0 | S138: 0 | T138: 0 | U138: 0 | V138: 1851.58 | W138: 0 | X138: 1 | Y138: 1 | Z138: 66 | AA138: 4 | AB138: 61-90 | AC138: 0.75 | AD138: 0
A139: INV-024767 | B139: C0386 | C139: Bluewater Electric | D139: Contractor | E139: West | F139: Maya Brennan | G139: High | H139: 100000 | I139: COL-03 | J139: Elena Ruiz | K139: Commercial | L139: NET60 | M139: 60 | N139: 0 | O139: 45897 | P139: 45957 | Q139: 1471.66 | R139: 0 | S139: 0 | T139: 0 | U139: 0 | V139: 1471.66 | W139: 0 | X139: 1 | Y139: 1 | Z139: 65 | AA139: 4 | AB139: 61-90 | AC139: 0.75 | AD139: 0
A140: INV-024818 | B140: C0277 | C140: Lakeshore Construction - West | D140: Contractor | E140: West | F140: Maya Brennan | G140: High | H140: 25000 | I140: COL-04 | J140: Tomas Okafor | K140: Commercial | L140: 2/10NET30 | M140: 30 | N140: 2 | O140: 45898 | P140: 45928 | Q140: 3453.68 | R140: 0 | S140: 0 | T140: 0 | U140: 0 | V140: 3453.68 | W140: 0 | X140: 1 | Y140: 1 | Z140: 94 | AA140: 5 | AB140: 90+ | AC140: 1 | AD140: 0
... A173: INV-025561 | B173: C0324 | C173: Pioneer Construction | D173: Contractor | E173: Southeast | F173: Dana Whitfield | G173: High | H173: 145000 | I173: COL-03 | J173: Elena Ruiz | K173: Commercial | L173: 2/10NET30 | M173: 30 | N173: 2 | O173: 45916 | P173: 45946 | Q173: 3050.92 | R173: 0 | S173: 0 | T173: 0 | U173: 0 | V173: 3050.92 | W173: 0 | X173: 1 | Y173: 1 | Z173: 76 | AA173: 4 | AB173: 61-90 | AC173: 0.75 | AD173: 0
A174: INV-025563 | B174: C0333 | C174: Oakmont Maintenance Supply - Southwest | D174: MRO Reseller | E174: Southwest | F174: Kevin Ames | G174: Medium | H174: 75000 | I174: COL-05 | J174: Grace Lindqvist | K174: Small Business | L174: NET30 | M174: 30 | N174: 0 | O174: 45916 | P174: 45946 | Q174: 3910.97 | R174: 0 | S174: 0 | T174: 469.32 | U174: 0 | V174: 3441.65 | W174: 0 | X174: 1 | Y174: 1 | Z174: 76 | AA174: 4 | AB174: 61-90 | AC174: 0.75 | AD174: 0 | AE174: Damaged Goods
A175: INV-025609 | B175: C0234 | C175: Redline University Facilities - Midwest 3 | D175: Institutional | E175: Midwest | F175: Ben Kowalczyk | G175: Low | H175: 145000 | I175: COL-04 | J175: Tomas Okafor | K175: Commercial | L175: NET90 | M175: 90 | N175: 0 | O175: 45917 | P175: 46007 | Q175: 8221.59 | R175: 0 | S175: 0 | T175: 0 | U175: 0 | V175: 8221.59 | W175: 0 | X175: 1 | Y175: 1 | Z175: 15 | AA175: 2 | AB175: 1-30 | AC175: 0.25 | AD175: 0
A176: INV-025619 | B176: C0279 | C176: Ironbridge Medical Center - Northeast | D176: Institutional | E176: Northeast | F176: Nadia Farouk | G176: Low | H176: 155000 | I176: COL-02 | J176: Marcus Bell | K176: Strategic Accounts | L176: NET90 | M176: 90 | N176: 0 | O176: 45917 | P176: 46007 | Q176: 10673.05 | R176: 0 | S176: 0 | T176: 0 | U176: 0 | V176: 10673.05 | W176: 0 | X176: 1 | Y176: 1 | Z176: 15 | AA176: 2 | AB176: 1-30 | AC176: 0.25 | AD176: 0
A177: INV-025624 | B177: C0324 | C177: Pioneer Construction | D177: Contractor | E177: Southeast | F177: Dana Whitfield | G177: High | H177: 145000 | I177: COL-03 | J177: Elena Ruiz | K177: Commercial | L177: 2/10NET30 | M177: 30 | N177: 2 | O177: 45917 | P177: 45947 | Q177: 1392.52 | R177: 0 | S177: 0 | T177: 0 | U177: 0 | V177: 1392.52 | W177: 0 | X177: 1 | Y177: 1 | Z177: 75 | AA177: 4 | AB177: 61-90 | AC177: 0.75 | AD177: 0
A178: INV-025633 | B178: C0376 | C178: Summit Components - Midwest | D178: OEM Manufacturer | E178: Midwest | F178: Hana Sato | G178: High | H178: 565000 | I178: COL-01 | J178: Priya Natarajan | K178: Strategic Accounts | L178: NET45 | M178: 45 | N178: 0 | O178: 45917 | P178: 45962 | Q178: 1902.49 | R178: 0 | S178: 0 | T178: 0 | U178: 0 | V178: 1902.49 | W178: 0 | X178: 1 | Y178: 1 | Z178: 60 | AA178: 3 | AB178: 31-60 | AC178: 0.5 | AD178: 1 | AE178: Damaged Goods
A179: INV-025637 | B179: C0386 | C179: Bluewater Electric | D179: Contractor | E179: West | F179: Maya Brennan | G179: High | H179: 100000 | I179: COL-03 | J179: Elena Ruiz | K179: Commercial | L179: NET60 | M179: 60 | N179: 0 | O179: 45917 | P179: 45977 | Q179: 3282.49 | R179: 0 | S179: 0 | T179: 0 | U179: 0 | V179: 3282.49 | W179: 0 | X179: 1 | Y179: 1 | Z179: 45 | AA179: 3 | AB179: 31-60 | AC179: 0.5 | AD179: 0
A180: INV-025694 | B180: C0329 | C180: Northfield School District - Midwest | D180: Institutional | E180: Midwest | F180: Hana Sato | G180: Low | H180: 230000 | I180: COL-01 | J180: Priya Natarajan | K180: Strategic Accounts | L180: NET90 | M180: 90 | N180: 0 | O180: 45918 | P180: 46008 | Q180: 11054.29 | R180: 0 | S180: 0 | T180: 0 | U180: 0 | V180: 11054.29 | W180: 0 | X180: 1 | Y180: 1 | Z180: 14 | AA180: 2 | AB180: 1-30 | AC180: 0.25 | AD180: 0
A181: INV-025696 | B181: C0351 | C181: Ironbridge Components | D181: OEM Manufacturer | E181: Midwest | F181: Hana Sato | G181: High | H181: 450000 | I181: COL-01 | J181: Priya Natarajan | K181: Strategic Accounts | L181: NET45 | M181: 45 | N181: 0 | O181: 45918 | P181: 45963 | Q181: 16942.82 | R181: 10165.69 | S181: 0 | T181: 0 | U181: 0 | V181: 6777.13 | W181: 0 | X181: 1 | Y181: 1 | Z181: 59 | AA181: 3 | AB181: 31-60 | AC181: 0.5 | AD181: 0
A182: INV-025698 | B182: C0361 | C182: Titan University Facilities - Midwest | D182: Institutional | E182: Midwest | F182: Ben Kowalczyk | G182: Low | H182: 165000 | I182: COL-01 | J182: Priya Natarajan | K182: Strategic Accounts | L182: NET90 | M182: 90 | N182: 0 | O182: 45918 | P182: 46008 | Q182: 6000.4 | R182: 0 | S182: 0 | T182: 0 | U182: 0 | V182: 6000.4 | W182: 0 | X182: 1 | Y182: 1 | Z182: 14 | AA182: 2 | AB182: 1-30 | AC182: 0.25 | AD182: 0
A183: INV-025699 | B183: C0366 | C183: Westbrook Industries - West | D183: OEM Manufacturer | E183: West | F183: Owen Price | G183: Medium | H183: 320000 | I183: COL-02 | J183: Marcus Bell | K183: Strategic Accounts | L183: NET60 | M183: 60 | N183: 0 | O183: 45918 | P183: 45978 | Q183: 13314 | R183: 0 | S183: 0 | T183: 0 | U183: 0 | V183: 13314 | W183: 0 | X183: 1 | Y183: 1 | Z183: 44 | AA183: 3 | AB183: 31-60 | AC183: 0.5 | AD183: 0
A184: INV-025714 | B184: C0066 | C184: Summit Industries | D184: OEM Manufacturer | E184: Midwest | F184: Ben Kowalczyk | G184: Medium | H184: 385000 | I184: COL-02 | J184: Marcus Bell | K184: Strategic Accounts | L184: NET60 | M184: 60 | N184: 0 | O184: 45919 | P184: 45979 | Q184: 3672.29 | R184: 0 | S184: 0 | T184: 0 | U184: 0 | V184: 3672.29 | W184: 0 | X184: 1 | Y184: 1 | Z184: 43 | AA184: 3 | AB184: 31-60 | AC184: 0.5 | AD184: 0
A185: INV-025732 | B185: C0185 | C185: Harbor Supply Co. | D185: MRO Reseller | E185: Southwest | F185: Rosa Delgado | G185: Low | H185: 60000 | I185: COL-06 | J185: Sam Horowitz | K185: Small Business | L185: NET30 | M185: 30 | N185: 0 | O185: 45919 | P185: 45949 | Q185: 2808.25 | R185: 0 | S185: 0 | T185: 421.24 | U185: 0 | V185: 2387.01 | W185: 0 | X185: 1 | Y185: 1 | Z185: 73 | AA185: 4 | AB185: 61-90 | AC185: 0.75 | AD185: 0 | AE185: Damaged Goods
A186: INV-025759 | B186: C0386 | C186: Bluewater Electric | D186: Contractor | E186: West | F186: Maya Brennan | G186: High | H186: 100000 | I186: COL-03 | J186: Elena Ruiz | K186: Commercial | L186: NET60 | M186: 60 | N186: 0 | O186: 45919 | P186: 45979 | Q186: 800.84 | R186: 0 | S186: 0 | T186: 0 | U186: 0 | V186: 800.84 | W186: 0 | X186: 1 | Y186: 1 | Z186: 43 | AA186: 3 | AB186: 31-60 | AC186: 0.5 | AD186: 0
A187: INV-025766 | B187: C0031 | C187: Stonegate Machine Works | D187: OEM Manufacturer | E187: Northeast | F187: Adrian Cole | G187: Low | H187: 515000 | I187: COL-02 | J187: Marcus Bell | K187: Strategic Accounts | L187: NET60 | M187: 60 | N187: 0 | O187: 45922 | P187: 45982 | Q187: 6104.26 | R187: 0 | S187: 0 | T187: 0 | U187: 0 | V187: 6104.26 | W187: 0 | X187: 1 | Y187: 1 | Z187: 40 | AA187: 3 | AB187: 31-60 | AC187: 0.5 | AD187: 0
A188: INV-025798 | B188: C0226 | C188: Lakeshore Industries | D188: OEM Manufacturer | E188: Midwest | F188: Hana Sato | G188: Medium | H188: 410000 | I188: COL-01 | J188: Priya Natarajan | K188: Strategic Accounts | L188: NET60 | M188: 60 | N188: 0 | O188: 45922 | P188: 45982 | Q188: 1664.8 | R188: 998.88 | S188: 0 | T188: 0 | U188: 0 | V188: 665.92 | W188: 0 | X188: 1 | Y188: 1 | Z188: 40 | AA188: 3 | AB188: 31-60 | AC188: 0.5 | AD188: 0
A189: INV-025819 | B189: C0327 | C189: Ironbridge Water Authority | D189: Institutional | E189: Midwest | F189: Ben Kowalczyk | G189: Low | H189: 195000 | I189: COL-01 | J189: Priya Natarajan | K189: Strategic Accounts | L189: NET90 | M189: 90 | N189: 0 | O189: 45922 | P189: 46012 | Q189: 6421.52 | R189: 0 | S189: 0 | T189: 0 | U189: 0 | V189: 6421.52 | W189: 0 | X189: 1 | Y189: 1 | Z189: 10 | AA189: 2 | AB189: 1-30 | AC189: 0.25 | AD189: 0
A190: INV-025823 | B190: C0349 | C190: Granite Manufacturing | D190: OEM Manufacturer | E190: Northeast | F190: Nadia Farouk | G190: High | H190: 490000 | I190: COL-02 | J190: Marcus Bell | K190: Strategic Accounts | L190: NET60 | M190: 60 | N190: 0 | O190: 45922 | P190: 45982 | Q190: 2481.33 | R190: 1488.8 | S190: 0 | T190: 0 | U190: 0 | V190: 992.53 | W190: 0 | X190: 1 | Y190: 1 | Z190: 40 | AA190: 3 | AB190: 31-60 | AC190: 0.5 | AD190: 0
A191: INV-025825 | B191: C0366 | C191: Westbrook Industries - West | D191: OEM Manufacturer | E191: West | F191: Owen Price | G191: Medium | H191: 320000 | I191: COL-02 | J191: Marcus Bell | K191: Strategic Accounts | L191: NET60 | M191: 60 | N191: 0 | O191: 45922 | P191: 45982 | Q191: 11721.89 | R191: 0 | S191: 0 | T191: 0 | U191: 0 | V191: 11721.89 | W191: 0 | X191: 1 | Y191: 1 | Z191: 40 | AA191: 3 | AB191: 31-60 | AC191: 0.5 | AD191: 0
A192: INV-025828 | B192: C0386 | C192: Bluewater Electric | D192: Contractor | E192: West | F192: Maya Brennan | G192: High | H192: 100000 | I192: COL-03 | J192: Elena Ruiz | K192: Commercial | L192: NET60 | M192: 60 | N192: 0 | O192: 45922 | P192: 45982 | Q192: 4365.41 | R192: 0 | S192: 0 | T192: 0 | U192: 0 | V192: 4365.41 | W192: 0 | X192: 1 | Y192: 1 | Z192: 40 | AA192: 3 | AB192: 31-60 | AC192: 0.5 | AD192: 0
A193: INV-025835 | B193: C0059 | C193: Apex Mechanical | D193: Contractor | E193: Midwest | F193: Ben Kowalczyk | G193: High | H193: 150000 | I193: COL-02 | J193: Marcus Bell | K193: Strategic Accounts | L193: NET30 | M193: 30 | N193: 0 | O193: 45923 | P193: 45953 | Q193: 6178.24 | R193: 0 | S193: 0 | T193: 0 | U193: 0 | V193: 6178.24 | W193: 0 | X193: 1 | Y193: 1 | Z193: 69 | AA193: 4 | AB193: 61-90 | AC193: 0.75 | AD193: 0
A194: INV-025836 | B194: C0063 | C194: Oakmont Medical Center | D194: Institutional | E194: Midwest | F194: Hana Sato | G194: Low | H194: 210000 | I194: COL-01 | J194: Priya Natarajan | K194: Strategic Accounts | L194: NET90 | M194: 90 | N194: 0 | O194: 45923 | P194: 46013 | Q194: 10069.76 | R194: 0 | S194: 0 | T194: 0 | U194: 0 | V194: 10069.76 | W194: 0 | X194: 1 | Y194: 1 | Z194: 9 | AA194: 2 | AB194: 1-30 | AC194: 0.25 | AD194: 0
A195: INV-025849 | B195: C0128 | C195: Summit Builders | D195: Contractor | E195: Southwest | F195: Kevin Ames | G195: Low | H195: 125000 | I195: COL-03 | J195: Elena Ruiz | K195: Commercial | L195: NET60 | M195: 60 | N195: 0 | O195: 45923 | P195: 45983 | Q195: 852.14 | R195: 511.28 | S195: 0 | T195: 0 | U195: 0 | V195: 340.86 | W195: 0 | X195: 1 | Y195: 1 | Z195: 39 | AA195: 3 | AB195: 31-60 | AC195: 0.5 | AD195: 0
A196: INV-025854 | B196: C0180 | C196: Titan Contracting | D196: Contractor | E196: Southwest | F196: Kevin Ames | G196: Low | H196: 25000 | I196: COL-03 | J196: Elena Ruiz | K196: Commercial | L196: NET60 | M196: 60 | N196: 0 | O196: 45923 | P196: 45983 | Q196: 2126.2 | R196: 0 | S196: 0 | T196: 0 | U196: 0 | V196: 2126.2 | W196: 0 | X196: 1 | Y196: 1 | Z196: 39 | AA196: 3 | AB196: 31-60 | AC196: 0.5 | AD196: 0
A197: INV-025868 | B197: C0306 | C197: Apex Builders - Southwest 3 | D197: Contractor | E197: Southwest | F197: Rosa Delgado | G197: Low | H197: 90000 | I197: COL-04 | J197: Tomas Okafor | K197: Commercial | L197: NET60 | M197: 60 | N197: 0 | O197: 45923 | P197: 45983 | Q197: 6533.8 | R197: 3920.28 | S197: 0 | T197: 0 | U197: 0 | V197: 2613.52 | W197: 0 | X197: 1 | Y197: 1 | Z197: 39 | AA197: 3 | AB197: 31-60 | AC197: 0.5 | AD197: 0
... A203: INV-025931 | B203: C0279 | C203: Ironbridge Medical Center - Northeast | D203: Institutional | E203: Northeast | F203: Nadia Farouk | G203: Low | H203: 155000 | I203: COL-02 | J203: Marcus Bell | K203: Strategic Accounts | L203: NET90 | M203: 90 | N203: 0 | O203: 45924 | P203: 46014 | Q203: 9182.14 | R203: 0 | S203: 0 | T203: 0 | U203: 0 | V203: 9182.14 | W203: 0 | X203: 1 | Y203: 1 | Z203: 8 | AA203: 2 | AB203: 1-30 | AC203: 0.25 | AD203: 0
A204: INV-025941 | B204: C0329 | C204: Northfield School District - Midwest | D204: Institutional | E204: Midwest | F204: Hana Sato | G204: Low | H204: 230000 | I204: COL-01 | J204: Priya Natarajan | K204: Strategic Accounts | L204: NET90 | M204: 90 | N204: 0 | O204: 45924 | P204: 46014 | Q204: 4835.31 | R204: 0 | S204: 0 | T204: 1208.83 | U204: 0 | V204: 3626.48 | W204: 0 | X204: 1 | Y204: 1 | Z204: 8 | AA204: 2 | AB204: 1-30 | AC204: 0.25 | AD204: 0 | AE204: Pricing
A205: INV-025944 | B205: C0351 | C205: Ironbridge Components | D205: OEM Manufacturer | E205: Midwest | F205: Hana Sato | G205: High | H205: 450000 | I205: COL-01 | J205: Priya Natarajan | K205: Strategic Accounts | L205: NET45 | M205: 45 | N205: 0 | O205: 45924 | P205: 45969 | Q205: 12356 | R205: 0 | S205: 0 | T205: 0 | U205: 0 | V205: 12356 | W205: 0 | X205: 1 | Y205: 1 | Z205: 53 | AA205: 3 | AB205: 31-60 | AC205: 0.5 | AD205: 0
A206: INV-025948 | B206: C0386 | C206: Bluewater Electric | D206: Contractor | E206: West | F206: Maya Brennan | G206: High | H206: 100000 | I206: COL-03 | J206: Elena Ruiz | K206: Commercial | L206: NET60 | M206: 60 | N206: 0 | O206: 45924 | P206: 45984 | Q206: 3090.81 | R206: 0 | S206: 0 | T206: 0 | U206: 0 | V206: 3090.81 | W206: 0 | X206: 1 | Y206: 1 | Z206: 38 | AA206: 3 | AB206: 31-60 | AC206: 0.5 | AD206: 0
A207: INV-025956 | B207: C0063 | C207: Oakmont Medical Center | D207: Institutional | E207: Midwest | F207: Hana Sato | G207: Low | H207: 210000 | I207: COL-01 | J207: Priya Natarajan | K207: Strategic Accounts | L207: NET90 | M207: 90 | N207: 0 | O207: 45925 | P207: 46015 | Q207: 1055.34 | R207: 0 | S207: 0 | T207: 0 | U207: 0 | V207: 1055.34 | W207: 0 | X207: 1 | Y207: 1 | Z207: 7 | AA207: 2 | AB207: 1-30 | AC207: 0.25 | AD207: 0
A208: INV-025959 | B208: C0079 | C208: Cedar Ridge Machine Works | D208: OEM Manufacturer | E208: West | F208: Owen Price | G208: Low | H208: 555000 | I208: COL-01 | J208: Priya Natarajan | K208: Strategic Accounts | L208: NET60 | M208: 60 | N208: 0 | O208: 45925 | P208: 45985 | Q208: 10004.97 | R208: 6002.98 | S208: 0 | T208: 0 | U208: 0 | V208: 4001.99 | W208: 0 | X208: 1 | Y208: 1 | Z208: 37 | AA208: 3 | AB208: 31-60 | AC208: 0.5 | AD208: 0
A209: INV-025968 | B209: C0132 | C209: Keystone Contracting | D209: Contractor | E209: West | F209: Maya Brennan | G209: High | H209: 105000 | I209: COL-04 | J209: Tomas Okafor | K209: Commercial | L209: NET60 | M209: 60 | N209: 0 | O209: 45925 | P209: 45985 | Q209: 2305.33 | R209: 0 | S209: 0 | T209: 0 | U209: 0 | V209: 2305.33 | W209: 0 | X209: 1 | Y209: 1 | Z209: 37 | AA209: 3 | AB209: 31-60 | AC209: 0.5 | AD209: 0
A210: INV-025981 | B210: C0231 | C210: Silverline Components - Northeast | D210: OEM Manufacturer | E210: Northeast | F210: Adrian Cole | G210: Medium | H210: 305000 | I210: COL-01 | J210: Priya Natarajan | K210: Strategic Accounts | L210: NET60 | M210: 60 | N210: 0 | O210: 45925 | P210: 45985 | Q210: 6751.98 | R210: 4051.19 | S210: 0 | T210: 0 | U210: 0 | V210: 2700.79 | W210: 0 | X210: 1 | Y210: 1 | Z210: 37 | AA210: 3 | AB210: 31-60 | AC210: 0.5 | AD210: 0
A211: INV-025992 | B211: C0302 | C211: Crestview Contracting - Northeast 3 | D211: Contractor | E211: Northeast | F211: Nadia Farouk | G211: High | H211: 125000 | I211: COL-04 | J211: Tomas Okafor | K211: Commercial | L211: 2/10NET30 | M211: 30 | N211: 2 | O211: 45925 | P211: 45955 | Q211: 1356.15 | R211: 0 | S211: 0 | T211: 0 | U211: 0 | V211: 1356.15 | W211: 0 | X211: 1 | Y211: 1 | Z211: 67 | AA211: 4 | AB211: 61-90 | AC211: 0.75 | AD211: 0
A212: INV-026006 | B212: C0025 | C212: Oakmont County Facilities | D212: Institutional | E212: West | F212: Owen Price | G212: Low | H212: 65000 | I212: COL-03 | J212: Elena Ruiz | K212: Commercial | L212: NET90 | M212: 90 | N212: 0 | O212: 45926 | P212: 46016 | Q212: 1228.27 | R212: 0 | S212: 0 | T212: 0 | U212: 0 | V212: 1228.27 | W212: 0 | X212: 1 | Y212: 1 | Z212: 6 | AA212: 2 | AB212: 1-30 | AC212: 0.25 | AD212: 0
A213: INV-026022 | B213: C0135 | C213: Oakmont Medical Center - Midwest | D213: Institutional | E213: Midwest | F213: Hana Sato | G213: Low | H213: 155000 | I213: COL-02 | J213: Marcus Bell | K213: Strategic Accounts | L213: NET90 | M213: 90 | N213: 0 | O213: 45926 | P213: 46016 | Q213: 1612.17 | R213: 0 | S213: 0 | T213: 0 | U213: 0 | V213: 1612.17 | W213: 0 | X213: 1 | Y213: 1 | Z213: 6 | AA213: 2 | AB213: 1-30 | AC213: 0.25 | AD213: 0
A214: INV-026025 | B214: C0145 | C214: Crestview Medical Center | D214: Institutional | E214: West | F214: Maya Brennan | G214: Low | H214: 120000 | I214: COL-04 | J214: Tomas Okafor | K214: Commercial | L214: NET90 | M214: 90 | N214: 0 | O214: 45926 | P214: 46016 | Q214: 3947.92 | R214: 0 | S214: 0 | T214: 0 | U214: 0 | V214: 3947.92 | W214: 0 | X214: 1 | Y214: 1 | Z214: 6 | AA214: 2 | AB214: 1-30 | AC214: 0.25 | AD214: 0
A215: INV-026034 | B215: C0208 | C215: Keystone University Facilities | D215: Institutional | E215: Southwest | F215: Rosa Delgado | G215: Low | H215: 95000 | I215: COL-04 | J215: Tomas Okafor | K215: Commercial | L215: NET90 | M215: 90 | N215: 0 | O215: 45926 | P215: 46016 | Q215: 6497.77 | R215: 0 | S215: 0 | T215: 0 | U215: 0 | V215: 6497.77 | W215: 0 | X215: 1 | Y215: 1 | Z215: 6 | AA215: 2 | AB215: 1-30 | AC215: 0.25 | AD215: 0
A216: INV-026036 | B216: C0216 | C216: Bluewater Construction - West | D216: Contractor | E216: West | F216: Maya Brennan | G216: Medium | H216: 40000 | I216: COL-04 | J216: Tomas Okafor | K216: Commercial | L216: NET60 | M216: 60 | N216: 0 | O216: 45926 | P216: 45986 | Q216: 1215.62 | R216: 729.37 | S216: 0 | T216: 0 | U216: 0 | V216: 486.25 | W216: 0 | X216: 1 | Y216: 1 | Z216: 36 | AA216: 3 | AB216: 31-60 | AC216: 0.5 | AD216: 0
... A229: INV-026148 | B229: C0059 | C229: Apex Mechanical | D229: Contractor | E229: Midwest | F229: Ben Kowalczyk | G229: High | H229: 150000 | I229: COL-02 | J229: Marcus Bell | K229: Strategic Accounts | L229: NET30 | M229: 30 | N229: 0 | O229: 45930 | P229: 45960 | Q229: 2813.2 | R229: 0 | S229: 0 | T229: 0 | U229: 0 | V229: 2813.2 | W229: 0 | X229: 1 | Y229: 1 | Z229: 62 | AA229: 4 | AB229: 61-90 | AC229: 0.75 | AD229: 0
A230: INV-026160 | B230: C0118 | C230: Granite MRO Services | D230: MRO Reseller | E230: Southeast | F230: Dana Whitfield | G230: Low | H230: 60000 | I230: COL-05 | J230: Grace Lindqvist | K230: Small Business | L230: 2/10NET30 | M230: 30 | N230: 2 | O230: 45930 | P230: 45960 | Q230: 824.24 | R230: 0 | S230: 0 | T230: 0 | U230: 0 | V230: 824.24 | W230: 0 | X230: 1 | Y230: 1 | Z230: 62 | AA230: 4 | AB230: 61-90 | AC230: 0.75 | AD230: 1 | AE230: Pricing
A231: INV-026163 | B231: C0129 | C231: Northfield Builders | D231: Contractor | E231: Northeast | F231: Adrian Cole | G231: Medium | H231: 115000 | I231: COL-03 | J231: Elena Ruiz | K231: Commercial | L231: NET30 | M231: 30 | N231: 0 | O231: 45930 | P231: 45960 | Q231: 5244.45 | R231: 0 | S231: 0 | T231: 1206.22 | U231: 0 | V231: 4038.23 | W231: 0 | X231: 1 | Y231: 1 | Z231: 62 | AA231: 4 | AB231: 61-90 | AC231: 0.75 | AD231: 0 | AE231: Damaged Goods
A232: INV-026169 | B232: C0164 | C232: Lakeshore Fabrication | D232: OEM Manufacturer | E232: Southwest | F232: Rosa Delgado | G232: Medium | H232: 240000 | I232: COL-01 | J232: Priya Natarajan | K232: Strategic Accounts | L232: NET45 | M232: 45 | N232: 0 | O232: 45930 | P232: 45975 | Q232: 2211.83 | R232: 0 | S232: 0 | T232: 0 | U232: 0 | V232: 2211.83 | W232: 0 | X232: 1 | Y232: 1 | Z232: 47 | AA232: 3 | AB232: 31-60 | AC232: 0.5 | AD232: 0
A233: INV-026193 | B233: C0287 | C233: Redline University Facilities - Southwest 4 | D233: Institutional | E233: Southwest | F233: Kevin Ames | G233: Low | H233: 155000 | I233: COL-02 | J233: Marcus Bell | K233: Strategic Accounts | L233: NET90 | M233: 90 | N233: 0 | O233: 45930 | P233: 46020 | Q233: 1872.16 | R233: 0 | S233: 0 | T233: 0 | U233: 0 | V233: 1872.16 | W233: 0 | X233: 1 | Y233: 1 | Z233: 2 | AA233: 2 | AB233: 1-30 | AC233: 0.25 | AD233: 0
A234: INV-026195 | B234: C0302 | C234: Crestview Contracting - Northeast 3 | D234: Contractor | E234: Northeast | F234: Nadia Farouk | G234: High | H234: 125000 | I234: COL-04 | J234: Tomas Okafor | K234: Commercial | L234: 2/10NET30 | M234: 30 | N234: 2 | O234: 45930 | P234: 45960 | Q234: 5225.67 | R234: 0 | S234: 0 | T234: 0 | U234: 0 | V234: 5225.67 | W234: 0 | X234: 1 | Y234: 1 | Z234: 62 | AA234: 4 | AB234: 61-90 | AC234: 0.75 | AD234: 0
A235: INV-026205 | B235: C0356 | C235: Stonegate University Facilities - Midwest 3 | D235: Institutional | E235: Midwest | F235: Ben Kowalczyk | G235: Low | H235: 145000 | I235: COL-03 | J235: Elena Ruiz | K235: Commercial | L235: NET90 | M235: 90 | N235: 0 | O235: 45930 | P235: 46020 | Q235: 3961.04 | R235: 0 | S235: 0 | T235: 0 | U235: 0 | V235: 3961.04 | W235: 0 | X235: 1 | Y235: 1 | Z235: 2 | AA235: 2 | AB235: 1-30 | AC235: 0.25 | AD235: 0
A236: INV-026210 | B236: C0005 | C236: Lakeshore Medical Center | D236: Institutional | E236: West | F236: Owen Price | G236: Low | H236: 195000 | I236: COL-01 | J236: Priya Natarajan | K236: Strategic Accounts | L236: NET90 | M236: 90 | N236: 0 | O236: 45931 | P236: 46021 | Q236: 5721.77 | R236: 0 | S236: 0 | T236: 0 | U236: 0 | V236: 5721.77 | W236: 0 | X236: 1 | Y236: 1 | Z236: 1 | AA236: 2 | AB236: 1-30 | AC236: 0.25 | AD236: 0
A237: INV-026229 | B237: C0135 | C237: Oakmont Medical Center - Midwest | D237: Institutional | E237: Midwest | F237: Hana Sato | G237: Low | H237: 155000 | I237: COL-02 | J237: Marcus Bell | K237: Strategic Accounts | L237: NET90 | M237: 90 | N237: 0 | O237: 45931 | P237: 46021 | Q237: 1064.33 | R237: 0 | S237: 0 | T237: 0 | U237: 0 | V237: 1064.33 | W237: 0 | X237: 1 | Y237: 1 | Z237: 1 | AA237: 2 | AB237: 1-30 | AC237: 0.25 | AD237: 0
A238: INV-026230 | B238: C0139 | C238: Harbor Machine Works | D238: OEM Manufacturer | E238: Midwest | F238: Ben Kowalczyk | G238: Medium | H238: 570000 | I238: COL-01 | J238: Priya Natarajan | K238: Strategic Accounts | L238: NET45 | M238: 45 | N238: 0 | O238: 45931 | P238: 45976 | Q238: 3983.18 | R238: 2389.91 | S238: 0 | T238: 0 | U238: 0 | V238: 1593.27 | W238: 0 | X238: 1 | Y238: 1 | Z238: 46 | AA238: 3 | AB238: 31-60 | AC238: 0.5 | AD238: 0
A239: INV-026235 | B239: C0164 | C239: Lakeshore Fabrication | D239: OEM Manufacturer | E239: Southwest | F239: Rosa Delgado | G239: Medium | H239: 240000 | I239: COL-01 | J239: Priya Natarajan | K239: Strategic Accounts | L239: NET45 | M239: 45 | N239: 0 | O239: 45931 | P239: 45976 | Q239: 5675.19 | R239: 0 | S239: 0 | T239: 0 | U239: 0 | V239: 5675.19 | W239: 0 | X239: 1 | Y239: 1 | Z239: 46 | AA239: 3 | AB239: 31-60 | AC239: 0.5 | AD239: 0
A240: INV-026244 | B240: C0234 | C240: Redline University Facilities - Midwest 3 | D240: Institutional | E240: Midwest | F240: Ben Kowalczyk | G240: Low | H240: 145000 | I240: COL-04 | J240: Tomas Okafor | K240: Commercial | L240: NET90 | M240: 90 | N240: 0 | O240: 45931 | P240: 46021 | Q240: 9901.96 | R240: 0 | S240: 0 | T240: 0 | U240: 0 | V240: 9901.96 | W240: 0 | X240: 1 | Y240: 1 | Z240: 1 | AA240: 2 | AB240: 1-30 | AC240: 0.25 | AD240: 0
A241: INV-026248 | B241: C0279 | C241: Ironbridge Medical Center - Northeast | D241: Institutional | E241: Northeast | F241: Nadia Farouk | G241: Low | H241: 155000 | I241: COL-02 | J241: Marcus Bell | K241: Strategic Accounts | L241: NET90 | M241: 90 | N241: 0 | O241: 45931 | P241: 46021 | Q241: 3334.98 | R241: 0 | S241: 0 | T241: 0 | U241: 0 | V241: 3334.98 | W241: 0 | X241: 1 | Y241: 1 | Z241: 1 | AA241: 2 | AB241: 1-30 | AC241: 0.25 | AD241: 0
A242: INV-026255 | B242: C0329 | C242: Northfield School District - Midwest | D242: Institutional | E242: Midwest | F242: Hana Sato | G242: Low | H242: 230000 | I242: COL-01 | J242: Priya Natarajan | K242: Strategic Accounts | L242: NET90 | M242: 90 | N242: 0 | O242: 45931 | P242: 46021 | Q242: 2169.71 | R242: 0 | S242: 0 | T242: 0 | U242: 0 | V242: 2169.71 | W242: 0 | X242: 1 | Y242: 1 | Z242: 1 | AA242: 2 | AB242: 1-30 | AC242: 0.25 | AD242: 0
A243: INV-026261 | B243: C0360 | C243: Bluewater Medical Center - Northeast | D243: Institutional | E243: Northeast | F243: Nadia Farouk | G243: Medium | H243: 160000 | I243: COL-02 | J243: Marcus Bell | K243: Strategic Accounts | L243: NET90 | M243: 90 | N243: 0 | O243: 45931 | P243: 46021 | Q243: 8463.43 | R243: 0 | S243: 0 | T243: 0 | U243: 0 | V243: 8463.43 | W243: 0 | X243: 1 | Y243: 1 | Z243: 1 | AA243: 2 | AB243: 1-30 | AC243: 0.25 | AD243: 0
... A245: INV-026263 | B245: C0369 | C245: Lakeshore Components | D245: OEM Manufacturer | E245: Midwest | F245: Hana Sato | G245: High | H245: 545000 | I245: COL-02 | J245: Marcus Bell | K245: Strategic Accounts | L245: NET60 | M245: 60 | N245: 0 | O245: 45931 | P245: 45991 | Q245: 15782.24 | R245: 0 | S245: 0 | T245: 0 | U245: 0 | V245: 15782.24 | W245: 0 | X245: 1 | Y245: 1 | Z245: 31 | AA245: 3 | AB245: 31-60 | AC245: 0.5 | AD245: 0
A246: INV-026274 | B246: C0031 | C246: Stonegate Machine Works | D246: OEM Manufacturer | E246: Northeast | F246: Adrian Cole | G246: Low | H246: 515000 | I246: COL-02 | J246: Marcus Bell | K246: Strategic Accounts | L246: NET60 | M246: 60 | N246: 0 | O246: 45932 | P246: 45992 | Q246: 9348.84 | R246: 0 | S246: 0 | T246: 0 | U246: 0 | V246: 9348.84 | W246: 0 | X246: 1 | Y246: 1 | Z246: 30 | AA246: 2 | AB246: 1-30 | AC246: 0.25 | AD246: 0 | AE246: PO Mismatch
A247: INV-026277 | B247: C0063 | C247: Oakmont Medical Center | D247: Institutional | E247: Midwest | F247: Hana Sato | G247: Low | H247: 210000 | I247: COL-01 | J247: Priya Natarajan | K247: Strategic Accounts | L247: NET90 | M247: 90 | N247: 0 | O247: 45932 | P247: 46022 | Q247: 11144.61 | R247: 0 | S247: 0 | T247: 0 | U247: 0 | V247: 11144.61 | W247: 0 | X247: 1 | Y247: 0 | Z247: 0 | AA247: 1 | AB247: Current | AC247: 0 | AD247: 0
A248: INV-026280 | B248: C0094 | C248: Bluewater Industries - Southeast | D248: OEM Manufacturer | E248: Southeast | F248: Dana Whitfield | G248: Low | H248: 535000 | I248: COL-02 | J248: Marcus Bell | K248: Strategic Accounts | L248: NET45 | M248: 45 | N248: 0 | O248: 45932 | P248: 45977 | Q248: 7379.9 | R248: 0 | S248: 0 | T248: 516.59 | U248: 0 | V248: 6863.31 | W248: 0 | X248: 1 | Y248: 1 | Z248: 45 | AA248: 3 | AB248: 31-60 | AC248: 0.5 | AD248: 0 | AE248: Damaged Goods
A249: INV-026296 | B249: C0219 | C249: Titan Construction - Southwest 3 | D249: Contractor | E249: Southwest | F249: Rosa Delgado | G249: Low | H249: 115000 | I249: COL-03 | J249: Elena Ruiz | K249: Commercial | L249: NET60 | M249: 60 | N249: 0 | O249: 45932 | P249: 45992 | Q249: 6397.83 | R249: 0 | S249: 0 | T249: 0 | U249: 0 | V249: 6397.83 | W249: 0 | X249: 1 | Y249: 1 | Z249: 30 | AA249: 2 | AB249: 1-30 | AC249: 0.25 | AD249: 0
...

Sheet Data_Queue
A1: PriorityRank | B1: CollectorRank | C1: CustomerID | D1: CustomerName | E1: Segment | F1: Region | G1: RiskTier | H1: CollectorID | I1: CollectorName | J1: Team | K1: TermsCode | L1: OpenBalance | M1: PastDueBalance | N1: Balance90Plus | O1: DisputedBalance | P1: WeightedExposure | Q1: DisputedWeightedExposure | R1: CollectableExposure | S1: NetCollectablePosition | T1: IsFullyOffsetByCash | U1: OldestDaysPastDue | V1: CreditUtilizationPct | W1: AvgDaysLateHistoric | X1: UnappliedCash | Y1: NetExposure | Z1: BrokenPromises90d | AA1: ActionCode | AB1: CreditHoldFlag | AC1: IsTodaysWorklist | AD1: RecommendedAction
A2: 1 | B2: 1 | C2: C0351 | D2: Ironbridge Components | E2: OEM Manufacturer | F2: Midwest | G2: High | H2: COL-01 | I2: Priya Natarajan | J2: Strategic Accounts | K2: NET45 | L2: 171140.07 | M2: 132293.14 | N2: 0 | O2: 15640.04 | P2: 64535.33 | Q2: 606.04 | R2: 57024.44 | S2: 57024.44 | T2: 0 | U2: 90 | V2: 38.03 | W2: 79.4 | X2: 7056.36 | Y2: 164083.71 | Z2: 2 | AA2: ESCALATE | AB2: 0 | AC2: 1 | AD2: Escalate: high-risk account carrying a 90+ balance. Hold further shipments and agree a payment plan or refer for recovery.
A3: 2 | B3: 1 | C3: C0366 | D3: Westbrook Industries - West | E3: OEM Manufacturer | F3: West | G3: Medium | H3: COL-02 | I3: Marcus Bell | J3: Strategic Accounts | K3: NET60 | L3: 122327.81 | M3: 82857.53 | N3: 0 | O3: 0 | P3: 37750.08 | Q3: 0 | R3: 37750.08 | S3: 37750.08 | T3: 0 | U3: 68 | V3: 38.23 | W3: 65.1 | X3: 0 | Y3: 122327.81 | Z3: 0 | AA3: COLLECTION_CALL | AB3: 0 | AC3: 1 | AD3: Collection call: oldest item is more than 30 days past due.
A4: 3 | B4: 1 | C4: C0302 | D4: Crestview Contracting - Northeast 3 | E4: Contractor | F4: Northeast | G4: High | H4: COL-04 | I4: Tomas Okafor | J4: Commercial | K4: 2/10NET30 | L4: 60651.51 | M4: 52023.36 | N4: 19027.82 | O4: 0 | P4: 37672.1 | Q4: 0 | R4: 37672.1 | S4: 37672.1 | T4: 0 | U4: 139 | V4: 48.52 | W4: 8.2 | X4: 0 | Y4: 60651.51 | Z4: 8 | AA4: ESCALATE | AB4: 0 | AC4: 1 | AD4: Escalate: high-risk account carrying a 90+ balance. Hold further shipments and agree a payment plan or refer for recovery.
A5: 4 | B5: 2 | C5: C0232 | D5: Titan Builders - Southwest | E5: Contractor | F5: Southwest | G5: High | H5: COL-04 | I5: Tomas Okafor | J5: Commercial | K5: 2/10NET30 | L5: 60280.9 | M5: 48278 | N5: 24426.9 | O5: 0 | P5: 35663.13 | Q5: 0 | R5: 35663.13 | S5: 35663.13 | T5: 0 | U5: 147 | V5: 57.41 | W5: 8.4 | X5: 0 | Y5: 60280.9 | Z5: 7 | AA5: ESCALATE | AB5: 0 | AC5: 1 | AD5: Escalate: high-risk account carrying a 90+ balance. Hold further shipments and agree a payment plan or refer for recovery.
A6: 5 | B6: 1 | C6: C0386 | D6: Bluewater Electric | E6: Contractor | F6: West | G6: High | H6: COL-03 | I6: Elena Ruiz | J6: Commercial | K6: NET60 | L6: 76941.41 | M6: 46413.57 | N6: 10287.08 | O6: 0 | P6: 32793.73 | Q6: 0 | R6: 32793.73 | S6: 32793.73 | T6: 0 | U6: 120 | V6: 76.94 | W6: 27.5 | X6: 0 | Y6: 76941.41 | Z6: 8 | AA6: ESCALATE | AB6: 0 | AC6: 1 | AD6: Escalate: high-risk account carrying a 90+ balance. Hold further shipments and agree a payment plan or refer for recovery.
A7: 6 | B7: 2 | C7: C0324 | D7: Pioneer Construction | E7: Contractor | F7: Southeast | G7: High | H7: COL-03 | I7: Elena Ruiz | J7: Commercial | K7: 2/10NET30 | L7: 65460.37 | M7: 51420.43 | N7: 18333.73 | O7: 7692.27 | P7: 32505.02 | Q7: 0 | R7: 32505.02 | S7: 32505.02 | T7: 0 | U7: 140 | V7: 45.15 | W7: 17.1 | X7: 0 | Y7: 65460.37 | Z7: 7 | AA7: ESCALATE | AB7: 0 | AC7: 1 | AD7: Escalate: high-risk account carrying a 90+ balance. Hold further shipments and agree a payment plan or refer for recovery.
A8: 7 | B8: 2 | C8: C0059 | D8: Apex Mechanical | E8: Contractor | F8: Midwest | G8: High | H8: COL-02 | I8: Marcus Bell | J8: Strategic Accounts | K8: NET30 | L8: 53593.68 | M8: 45881.37 | N8: 16968.16 | O8: 0 | P8: 31940.25 | Q8: 0 | R8: 31940.25 | S8: 31940.25 | T8: 0 | U8: 143 | V8: 35.73 | W8: 26 | X8: 0 | Y8: 53593.68 | Z8: 8 | AA8: ESCALATE | AB8: 0 | AC8: 1 | AD8: Escalate: high-risk account carrying a 90+ balance. Hold further shipments and agree a payment plan or refer for recovery.
A9: 8 | B9: 3 | C9: C0031 | D9: Stonegate Machine Works | E9: OEM Manufacturer | F9: Northeast | G9: Low | H9: COL-02 | I9: Marcus Bell | J9: Strategic Accounts | K9: NET60 | L9: 150926.78 | M9: 85720.95 | N9: 1675.15 | O9: 0 | P9: 33193.06 | Q9: 0 | R9: 31517.91 | S9: 31517.91 | T9: 0 | U9: 274 | V9: 29.31 | W9: 59.3 | X9: 1675.15 | Y9: 149251.63 | Z9: 0 | AA9: FINAL_NOTICE | AB9: 0 | AC9: 1 | AD9: Issue a final notice on the 90+ balance and confirm a payment date in writing.
A10: 9 | B10: 3 | C10: C0271 | D10: Riverbend Electric - Midwest 3 | E10: Contractor | F10: Midwest | G10: High | H10: COL-03 | I10: Elena Ruiz | J10: Commercial | K10: 2/10NET30 | L10: 59342.1 | M10: 46818.72 | N10: 14609.63 | O10: 0 | P10: 27084.27 | Q10: 0 | R10: 27084.27 | S10: 27084.27 | T10: 0 | U10: 140 | V10: 42.39 | W10: 10.9 | X10: 0 | Y10: 59342.1 | Z10: 7 | AA10: ESCALATE | AB10: 0 | AC10: 1 | AD10: Escalate: high-risk account carrying a 90+ balance. Hold further shipments and agree a payment plan or refer for recovery.
A11: 10 | B11: 3 | C11: C0297 | D11: Apex Mechanical - Southeast 3 | E11: Contractor | F11: Southeast | G11: High | H11: COL-04 | I11: Tomas Okafor | J11: Commercial | K11: NET30 | L11: 31830.69 | M11: 28601.28 | N11: 26001.78 | O11: 0 | P11: 27073.54 | Q11: 0 | R11: 27073.54 | S11: 27073.54 | T11: 0 | U11: 138 | V11: 106.1 | W11: 32.3 | X11: 0 | Y11: 31830.69 | Z11: 5 | AA11: ESCALATE | AB11: 1 | AC11: 1 | AD11: Escalate: high-risk account carrying a 90+ balance. Hold further shipments and agree a payment plan or refer for recovery. Also place a credit hold: the account is at or over its credit limit.
A12: 11 | B12: 4 | C12: C0132 | D12: Keystone Contracting | E12: Contractor | F12: West | G12: High | H12: COL-04 | I12: Tomas Okafor | J12: Commercial | K12: NET60 | L12: 84970.22 | M12: 41199.26 | N12: 9337.53 | O12: 0 | P12: 25099.35 | Q12: 0 | R12: 25099.35 | S12: 25099.35 | T12: 0 | U12: 122 | V12: 80.92 | W12: 24.2 | X12: 0 | Y12: 84970.22 | Z12: 10 | AA12: ESCALATE | AB12: 0 | AC12: 1 | AD12: Escalate: high-risk account carrying a 90+ balance. Hold further shipments and agree a payment plan or refer for recovery.
A13: 12 | B13: 4 | C13: C0094 | D13: Bluewater Industries - Southeast | E13: OEM Manufacturer | F13: Southeast | G13: Low | H13: COL-02 | I13: Marcus Bell | J13: Strategic Accounts | K13: NET45 | L13: 125485.34 | M13: 87648.64 | N13: 0 | O13: 17811.56 | P13: 27862.93 | Q13: 4216.65 | R13: 24700.44 | S13: 24700.44 | T13: 0 | U13: 69 | V13: 23.46 | W13: 58.6 | X13: 0 | Y13: 125485.34 | Z13: 0 | AA13: COLLECTION_CALL | AB13: 0 | AC13: 1 | AD13: Collection call: oldest item is more than 30 days past due.
... A273: 272 | B273: 32 | C273: C0385 | D273: Cedar Ridge Maintenance Supply - Southeast | E273: MRO Reseller | F273: Southeast | G273: Medium | H273: COL-05 | I273: Grace Lindqvist | J273: Small Business | K273: NET30 | L273: 9077.63 | M273: 3231.7 | N273: 0 | O273: 0 | P273: 807.93 | Q273: 0 | R273: 0 | S273: -113.77 | T273: 1 | U273: 27 | V273: 36.31 | W273: 14 | X273: 921.7 | Y273: 8155.93 | Z273: 0 | AA273: STANDARD_DUNNING | AB273: 0 | AC273: 0 | AD273: Standard dunning letter and follow-up call.

Sheet Data_KPI
A1: YearMonth | B1: AsOfDate | C1: BeginAR | D1: MonthSales | E1: EndAR | F1: EndCurrentAR | G1: PastDueAR | H1: AR90Plus | I1: DisputedAR | J1: OpenInvoices | K1: PastDueInvoices | L1: Invoices90Plus | M1: CashApplied | N1: CashReceived | O1: CashAppliedLessReceived | P1: UnappliedCash | Q1: UnappliedCashPct | R1: WriteOffs | S1: CreditMemos | T1: DSO_Countback | U1: DSO_Simple | V1: BPDSO_Countback | W1: AvgDaysDelinquent | X1: DSO_MethodGap | Y1: CollectableBase | Z1: CEI_Book | AA1: CEI_Cash | AB1: PaperCollectionsGap | AC1: PctPastDue | AD1: Pct90Plus | AE1: PctDisputed | AF1: PctPastDueByCount | AG1: Pct90PlusByCount | AH1: IsComparablePeriod
A2: 2024-02 | B2: 45351 | C2: 4759740.7 | D2: 4650317.3 | E2: 7708695 | F2: 6995522.6 | G2: 713172.39 | H2: 0 | I2: 332653.12 | J2: 1562 | K2: 189 | L2: 0 | M2: 1668455.2 | N2: 1693087.7 | O2: -24632.51 | P2: 50367.02 | Q2: 0.65 | R2: 0 | S2: 34378.39 | T2: 48.03 | U2: 48.01 | V2: 43.59 | W2: 4.44 | X2: 0.02 | Y2: 2414535.4 | Z2: 70.46 | AA2: 69.1 | AB2: 1.36 | AC2: 9.25 | AD2: 0 | AE2: 4.32 | AF2: 12.1 | AG2: 0 | AH2: 0
A3: 2024-03 | B3: 45382 | C3: 7708695 | D3: 4985626.5 | E3: 9161279.8 | F3: 7454278.3 | G3: 1707001.4 | H3: 0 | I3: 477125.84 | J3: 1888 | K3: 396 | L3: 0 | M3: 3492498.7 | N3: 3531440.7 | O3: -38942.02 | P3: 94695.34 | Q3: 1.03 | R3: 0 | S3: 44487.76 | T3: 57.04 | U3: 57.03 | V3: 46.39 | W3: 10.65 | X3: 0.01 | Y3: 5240043.1 | Z3: 67.42 | AA3: 66.65 | AB3: 0.77 | AC3: 18.63 | AD3: 0 | AE3: 5.21 | AF3: 20.97 | AG3: 0 | AH3: 0
A4: 2024-04 | B4: 45412 | C4: 9161279.8 | D4: 5818772.5 | E4: 10031154 | F4: 7950377.4 | G4: 2080776.3 | H4: 0 | I4: 486298.26 | J4: 2101 | K4: 492 | L4: 0 | M4: 4919479.4 | N4: 4967591.6 | O4: -48112.13 | P4: 152004.07 | Q4: 1.52 | R4: 0 | S4: 42951.89 | T4: 56.19 | U4: 59.39 | V4: 43.25 | W4: 12.94 | X4: -3.2 | Y4: 7029674.9 | Z4: 70.4 | AA4: 69.98 | AB4: 0.42 | AC4: 20.74 | AD4: 0 | AE4: 4.85 | AF4: 23.42 | AG4: 0 | AH4: 0
